Workbook

Sheet STT Report
A1: Date | B1: Month | C1: Invoice Number | D1: Customer Code | E1: City | F1: Shop Type | G1: Shops Name | H1: Sales Person | I1: Address | K1: Indomie 70GM | O1: Indomie 120GM | S1: QTY | T1: FOC Indomie 70GM | X1: FOC Indomie 120GM | AB1: Rate 60GM | AC1: Rate 70GM | AD1: Rate 120GM | AE1: T.P Amount | AF1: Disc % | AG1: Disc Amt | AH1: 0.035 | AI1: Amount | AJ1: GST % | AK1: GST Amount | AL1: Net Amount | AM1: Cash Received | AN1: Oth Disc | AO1: Cash Receivable | AP1: Remarks
I2: Address | J2: Chicken 60gm | K2: Meat 70gr | L2: Lemon 70gr | M2: Chicken 70gr | N2: Total 70gr | O2: Meat 120g | P2: Lemon 120gr | Q2: Chicken 120gr | R2: Total 120gr | T2: Meat 70gr FOC | U2: Lemon 70gr FOC | V2: Chicken 70gr FOC | W2: Total 70gr FOC | X2: Meat 120g FOC | Y2: Lemon 120gr FOC | Z2: Chicken 120gr FOC | AA2: Total 120gr FOC | AH2: Trade offer (amount)
A3: 46204 | B3: July | C3: 123156 | D3: 5643 | E3: LHR | F3: LMT | G3: Gourmet Food | H3: Shakoor | I3: Awan Town | K3: 80 | L3: 80 | N3: =K3+L3+M3 -> 160 | O3: 80 | P3: 80 | Q3: 80 | R3: =SUM(O3:Q3) -> 240 | S3: =R3+N3+J3 -> 400 | U3: 79950 | AB3: 39.27 | AC3: 52.4625 | AD3: 72.64 | AE3: =(J3*AB3)+(N3*AC3)+(AD3*S3) -> 37450 | AF3: 0.08 | AG3: =AE3*AF3 -> 2996 | AH3: =(AB3*J3)*$AH$1 -> 0 | AI3: =AE3-AG3-AH3 -> 34454 | AJ3: 0.18 | AK3: =AI3*AJ3 -> 6201.72 | AL3: =AI3+AK3 -> 40655.72
A4: 46204 | B4: July | C4: 12313212 | D4: 5464 | E4: LHR | F4: LMT | G4: Gourmet Food | H4: Shakoor | I4: Canal view | K4: 80 | L4: 80 | N4: =K4+L4+M4 -> 160 | O4: 80 | P4: 80 | Q4: 80 | R4: =SUM(O4:Q4) -> 240 | S4: =R4+N4+J4 -> 400 | U4: =U3/40 -> 1998.75 | AB4: 39.27 | AC4: 52.4625 | AD4: 72.64 | AE4: =(J4*AB4)+(N4*AC4)+(AD4*S4) -> 37450 | AF4: 0.065 | AG4: =AE4*AF4 -> 2434.25 | AH4: =(AB4*J4)*$AH$1 -> 0 | AI4: =AE4-AG4 -> 35015.75 | AJ4: 0.18 | AK4: =AI4*AJ4 -> 6302.835 | AL4: =AI4+AK4 -> 41318.585
A5: 46204 | B5: July | C5: 156165 | D5: 1523 | E5: LHR | F5: LMT | G5: Gourmet Food | H5: Shakoor | I5: Liyaqat chowk | K5: 80 | L5: 80 | N5: =K5+L5+M5 -> 160 | O5: 80 | P5: 80 | Q5: 80 | R5: =SUM(O5:Q5) -> 240 | S5: =R5+N5+J5 -> 400 | AB5: 39.27 | AC5: 52.4625 | AD5: 72.64 | AE5: =(J5*AB5)+(N5*AC5)+(AD5*S5) -> 37450 | AF5: 0.065 | AG5: =AE5*AF5 -> 2434.25 | AH5: =(AB5*J5)*$AH$1 -> 0 | AI5: =AE5-AG5 -> 35015.75 | AJ5: 0.18 | AK5: =AI5*AJ5 -> 6302.835 | AL5: =AI5+AK5 -> 41318.585
A6: 46204 | B6: July | C6: 1561531 | D6: 5461 | E6: LHR | F6: LMT | G6: Gourmet Food | H6: Shakoor | I6: Gulshan Ravi | K6: 80 | L6: 80 | N6: =K6+L6+M6 -> 160 | O6: 40 | P6: 40 | Q6: 40 | R6: =SUM(O6:Q6) -> 120 | S6: =R6+N6+J6 -> 280 | AB6: 39.27 | AC6: 52.4625 | AD6: 72.64 | AE6: =(J6*AB6)+(N6*AC6)+(AD6*S6) -> 28733.2 | AF6: 0.065 | AG6: =AE6*AF6 -> 1867.658 | AH6: =(AB6*J6)*$AH$1 -> 0 | AI6: =AE6-AG6 -> 26865.542 | AJ6: 0.18 | AK6: =AI6*AJ6 -> 4835.7976 | AL6: =AI6+AK6 -> 31701.34
A7: 46204 | B7: July | C7: 1561561 | D7: 2316 | E7: LHR | F7: LMT | G7: Gourmet Food | H7: Shakoor | I7: Multan Road | K7: 40 | L7: 40 | N7: =K7+L7+M7 -> 80 | O7: 40 | P7: 40 | Q7: 40 | R7: =SUM(O7:Q7) -> 120 | S7: =R7+N7+J7 -> 200 | AB7: 39.27 | AC7: 52.4625 | AD7: 72.64 | AE7: =(J7*AB7)+(N7*AC7)+(AD7*S7) -> 18725 | AF7: 0.065 | AG7: =AE7*AF7 -> 1217.125 | AH7: =(AB7*J7)*$AH$1 -> 0 | AI7: =AE7-AG7 -> 17507.875 | AJ7: 0.18 | AK7: =AI7*AJ7 -> 3151.4175 | AL7: =AI7+AK7 -> 20659.292 | AM7: =SUM(#REF!) -> #REF! | AN7: =SUM(#REF!) -> #REF! | AO7: =SUM(#REF!) -> #REF!
A8: 46204 | B8: July | C8: 1561561 | D8: 2084.3 | E8: LHR | F8: LMT | G8: Gourmet Food | H8: Shakoor | I8: Nadeem Shaheed | K8: 40 | L8: 40 | N8: =K8+L8+M8 -> 80 | O8: 40 | P8: 80 | Q8: 80 | R8: =SUM(O8:Q8) -> 200 | S8: =R8+N8+J8 -> 280 | AB8: 39.27 | AC8: 52.4625 | AD8: 72.64 | AE8: =(J8*AB8)+(N8*AC8)+(AD8*S8) -> 24536.2 | AF8: 0.065 | AG8: =AE8*AF8 -> 1594.853 | AH8: =(AB8*J8)*$AH$1 -> 0 | AI8: =AE8-AG8 -> 22941.347 | AJ8: 0.18 | AK8: =AI8*AJ8 -> 4129.4425 | AL8: =AI8+AK8 -> 27070.789
A9: 46204 | B9: July | C9: 1561561 | D9: 1418.6 | E9: LHR | F9: LMT | G9: Gourmet Food | H9: Shakoor | I9: Poonch Road | K9: 80 | L9: 80 | N9: =K9+L9+M9 -> 160 | O9: 40 | P9: 40 | Q9: 40 | R9: =SUM(O9:Q9) -> 120 | S9: =R9+N9+J9 -> 280 | AB9: 39.27 | AC9: 52.4625 | AD9: 72.64 | AE9: =(J9*AB9)+(N9*AC9)+(AD9*S9) -> 28733.2 | AF9: 0.1 | AG9: =AE9*AF9 -> 2873.32 | AH9: =(AB9*J9)*$AH$1 -> 0 | AI9: =AE9-AG9 -> 25859.88 | AJ9: 0.18 | AK9: =AI9*AJ9 -> 4654.7784 | AL9: =AI9+AK9 -> 30514.658
A10: 46204 | B10: July | C10: 1561561 | D10: 752.9 | E10: LHR | F10: LMT | G10: Gourmet Food | H10: Shakoor | I10: Rehman pura | K10: 40 | L10: 40 | N10: =K10+L10+M10 -> 80 | O10: 40 | P10: 40 | Q10: 40 | R10: =SUM(O10:Q10) -> 120 | S10: =R10+N10+J10 -> 200 | AB10: 39.27 | AC10: 52.4625 | AD10: 72.64 | AE10: =(J10*AB10)+(N10*AC10)+(AD10*S10) -> 18725 | AF10: 0.065 | AG10: =AE10*AF10 -> 1217.125 | AH10: =(AB10*J10)*$AH$1 -> 0 | AI10: =AE10-AG10 -> 17507.875 | AJ10: 0.18 | AK10: =AI10*AJ10 -> 3151.4175 | AL10: =AI10+AK10 -> 20659.292
A11: 46204 | B11: July | C11: 435402.68 | D11: 87.2 | E11: LHR | F11: LMT | G11: Gourmet Food | H11: Shakoor | I11: Rewaz Garden | K11: 40 | L11: 40 | N11: =K11+L11+M11 -> 80 | O11: 40 | P11: 40 | Q11: 40 | R11: =SUM(O11:Q11) -> 120 | S11: =R11+N11+J11 -> 200 | AB11: 39.27 | AC11: 52.4625 | AD11: 72.64 | AE11: =(J11*AB11)+(N11*AC11)+(AD11*S11) -> 18725 | AF11: 0.065 | AG11: =AE11*AF11 -> 1217.125 | AH11: =(AB11*J11)*$AH$1 -> 0 | AI11: =AE11-AG11 -> 17507.875 | AJ11: 0.18 | AK11: =AI11*AJ11 -> 3151.4175 | AL11: =AI11+AK11 -> 20659.292
A12: 46204 | B12: July | C12: 34516.393 | D12: 578.5 | E12: LHR | F12: LMT | G12: Gourmet Food | H12: Shakoor | I12: Rustam Park | K12: 40 | L12: 40 | N12: =K12+L12+M12 -> 80 | O12: 40 | P12: 40 | Q12: 40 | R12: =SUM(O12:Q12) -> 120 | S12: =R12+N12+J12 -> 200 | AB12: 39.27 | AC12: 52.4625 | AD12: 72.64 | AE12: =(J12*AB12)+(N12*AC12)+(AD12*S12) -> 18725 | AF12: 0.065 | AG12: =AE12*AF12 -> 1217.125 | AH12: =(AB12*J12)*$AH$1 -> 0 | AI12: =AE12-AG12 -> 17507.875 | AJ12: 0.18 | AK12: =AI12*AJ12 -> 3151.4175 | AL12: =AI12+AK12 -> 20659.292
A13: 46204 | B13: July | C13: 504435.46 | D13: 1244.2 | E13: LHR | F13: LMT | G13: Gourmet Food | H13: Shakoor | I13: Samanaabd lhr | K13: 80 | L13: 80 | N13: =K13+L13+M13 -> 160 | O13: 40 | P13: 40 | Q13: 40 | R13: =SUM(O13:Q13) -> 120 | S13: =R13+N13+J13 -> 280 | AB13: 39.27 | AC13: 52.4625 | AD13: 72.64 | AE13: =(J13*AB13)+(N13*AC13)+(AD13*S13) -> 28733.2 | AF13: 0.065 | AG13: =AE13*AF13 -> 1867.658 | AH13: =(AB13*J13)*$AH$1 -> 0 | AI13: =AE13-AG13 -> 26865.542 | AJ13: 0.18 | AK13: =AI13*AJ13 -> 4835.7976 | AL13: =AI13+AK13 -> 31701.34
A14: 46204 | B14: July | C14: 974354.54 | D14: 1909.9 | E14: LHR | F14: LMT | G14: Gourmet Food | H14: Shakoor | I14: Wahdat Road | K14: 80 | L14: 80 | N14: =K14+L14+M14 -> 160 | O14: 40 | P14: 40 | Q14: 40 | R14: =SUM(O14:Q14) -> 120 | S14: =R14+N14+J14 -> 280 | AB14: 39.27 | AC14: 52.4625 | AD14: 72.64 | AE14: =(J14*AB14)+(N14*AC14)+(AD14*S14) -> 28733.2 | AF14: 0.065 | AG14: =AE14*AF14 -> 1867.658 | AH14: =(AB14*J14)*$AH$1 -> 0 | AI14: =AE14-AG14 -> 26865.542 | AJ14: 0.18 | AK14: =AI14*AJ14 -> 4835.7976 | AL14: =AI14+AK14 -> 31701.34
A15: 46204 | B15: July | C15: 1444273.6 | D15: 2575.6 | E15: LHR | F15: LMT | G15: Gourmet Food | H15: Shakoor | I15: Kareem Block | K15: 80 | L15: 80 | N15: =K15+L15+M15 -> 160 | O15: 40 | P15: 40 | Q15: 40 | R15: =SUM(O15:Q15) -> 120 | S15: =R15+N15+J15 -> 280 | AB15: 39.27 | AC15: 52.4625 | AD15: 72.64 | AE15: =(J15*AB15)+(N15*AC15)+(AD15*S15) -> 28733.2 | AF15: 0.065 | AG15: =AE15*AF15 -> 1867.658 | AH15: =(AB15*J15)*$AH$1 -> 0 | AI15: =AE15-AG15 -> 26865.542 | AJ15: 0.18 | AK15: =AI15*AJ15 -> 4835.7976 | AL15: =AI15+AK15 -> 31701.34
A16: 46204 | B16: July | C16: 1914192.7 | D16: 3241.3 | E16: LHR | F16: General Store | G16: Awan Store | H16: Furqan | I16: Lawrance Road | J16: 12 | N16: =K16+L16+M16 -> 0 | R16: =SUM(O16:Q16) -> 0 | S16: =R16+N16+J16 -> 12 | AB16: 39.27 | AC16: 52.4625 | AD16: 72.64 | AE16: =(J16*AB16)+(N16*AC16)+(AD16*S16) -> 1342.92 | AF16: 0.065 | AG16: =AE16*AF16 -> 87.2898 | AH16: =(AB16*J16)*$AH$1 -> 16.4934 | AI16: =AE16-AG16 -> 1255.6302 | AJ16: 0.18 | AK16: =AI16*AJ16 -> 226.01344 | AL16: =AI16+AK16 -> 1481.6436
A17: 46204 | B17: July | C17: 2384111.8 | D17: 3907 | E17: LHR | F17: General Store | G17: Ch General Store | H17: Furqan | I17: Lawrance Road | J17: 12 | N17: =K17+L17+M17 -> 0 | R17: =SUM(O17:Q17) -> 0 | S17: =R17+N17+J17 -> 12 | AB17: 39.27 | AC17: 52.4625 | AD17: 72.64 | AE17: =(J17*AB17)+(N17*AC17)+(AD17*S17) -> 1342.92 | AF17: 0.065 | AG17: =AE17*AF17 -> 87.2898 | AH17: =(AB17*J17)*$AH$1 -> 16.4934 | AI17: =AE17-AG17 -> 1255.6302 | AJ17: 0.18 | AK17: =AI17*AJ17 -> 226.01344 | AL17: =AI17+AK17 -> 1481.6436
A18: 46204 | B18: July | C18: 2854030.8 | D18: 4572.7 | E18: LHR | F18: General Store | G18: Shahid Bakery | H18: Furqan | I18: Lawrance Road | N18: =K18+L18+M18 -> 0 | O18: 15 | P18: 15 | Q18: 10 | R18: =SUM(O18:Q18) -> 40 | S18: =R18+N18+J18 -> 40 | AB18: 39.27 | AC18: 52.4625 | AD18: 72.64 | AE18: =(J18*AB18)+(N18*AC18)+(AD18*S18) -> 2905.6 | AF18: 0.065 | AG18: =AE18*AF18 -> 188.864 | AH18: =(AB18*J18)*$AH$1 -> 0 | AI18: =AE18-AG18 -> 2716.736 | AJ18: 0.18 | AK18: =AI18*AJ18 -> 489.01248 | AL18: =AI18+AK18 -> 3205.7485
A19: 46204 | B19: July | C19: 3323949.9 | D19: 5238.4 | E19: LHR | F19: General Store | G19: Khan Nimko | H19: Furqan | I19: Lawrance Road | N19: =K19+L19+M19 -> 0 | O19: 8 | P19: 4 | Q19: 8 | R19: =SUM(O19:Q19) -> 20 | S19: =R19+N19+J19 -> 20 | AB19: 39.27 | AC19: 52.4625 | AD19: 72.64 | AE19: =(J19*AB19)+(N19*AC19)+(AD19*S19) -> 1452.8 | AF19: 0.065 | AG19: =AE19*AF19 -> 94.432 | AH19: =(AB19*J19)*$AH$1 -> 0 | AI19: =AE19-AG19 -> 1358.368 | AJ19: 0.18 | AK19: =AI19*AJ19 -> 244.50624 | AL19: =AI19+AK19 -> 1602.8742
A20: 46204 | B20: July | C20: 3793869 | D20: 5904.1 | E20: LHR | F20: Mart | G20: Shell Petrol Mart | H20: Furqan | I20: Lawrance Road | K20: 40 | L20: 40 | N20: =K20+L20+M20 -> 80 | O20: 40 | P20: 40 | Q20: 40 | R20: =SUM(O20:Q20) -> 120 | S20: =R20+N20+J20 -> 200 | AB20: 39.27 | AC20: 52.4625 | AD20: 72.64 | AE20: =(J20*AB20)+(N20*AC20)+(AD20*S20) -> 18725 | AF20: 0.065 | AG20: =AE20*AF20 -> 1217.125 | AH20: =(AB20*J20)*$AH$1 -> 0 | AI20: =AE20-AG20 -> 17507.875 | AJ20: 0.18 | AK20: =AI20*AJ20 -> 3151.4175 | AL20: =AI20+AK20 -> 20659.292
A21: 46204 | B21: July | C21: 4263788 | D21: 6569.8 | E21: LHR | F21: General Store | G21: Lala G Super Store | H21: Salman | I21: Falcon Society | K21: 12 | L21: 12 | N21: =K21+L21+M21 -> 24 | R21: =SUM(O21:Q21) -> 0 | S21: =R21+N21+J21 -> 24 | AB21: 39.27 | AC21: 52.4625 | AD21: 72.64 | AE21: =(J21*AB21)+(N21*AC21)+(AD21*S21) -> 3002.46 | AF21: 0.065 | AG21: =AE21*AF21 -> 195.1599 | AH21: =(AB21*J21)*$AH$1 -> 0 | AI21: =AE21-AG21 -> 2807.3001 | AJ21: 0.18 | AK21: =AI21*AJ21 -> 505.31402 | AL21: =AI21+AK21 -> 3312.6141
A22: 46204 | B22: July | C22: 4733707.1 | D22: 7235.5 | E22: LHR | F22: General Store | G22: Ajwa Bakers | H22: Salman | I22: Falcon Society | N22: =K22+L22+M22 -> 0 | O22: 10 | P22: 15 | Q22: 15 | R22: =SUM(O22:Q22) -> 40 | S22: =R22+N22+J22 -> 40 | AB22: 39.27 | AC22: 52.4625 | AD22: 72.64 | AE22: =(J22*AB22)+(N22*AC22)+(AD22*S22) -> 2905.6 | AF22: 0.065 | AG22: =AE22*AF22 -> 188.864 | AH22: =(AB22*J22)*$AH$1 -> 0 | AI22: =AE22-AG22 -> 2716.736 | AJ22: 0.18 | AK22: =AI22*AJ22 -> 489.01248 | AL22: =AI22+AK22 -> 3205.7485
A23: 46204 | B23: July | C23: 5203626.2 | D23: 7901.2 | E23: LHR | F23: General Store | G23: New Way Store | H23: Salman | I23: Falcon Society | J23: 200 | N23: =K23+L23+M23 -> 0 | R23: =SUM(O23:Q23) -> 0 | S23: =R23+N23+J23 -> 200 | AB23: 39.27 | AC23: 52.4625 | AD23: 72.64 | AE23: =(J23*AB23)+(N23*AC23)+(AD23*S23) -> 22382 | AF23: 0.065 | AG23: =AE23*AF23 -> 1454.83 | AH23: =(AB23*J23)*$AH$1 -> 274.89 | AI23: =AE23-AG23 -> 20927.17 | AJ23: 0.18 | AK23: =AI23*AJ23 -> 3766.8906 | AL23: =AI23+AK23 -> 24694.061
A24: 46204 | B24: July | C24: 5673545.2 | D24: 8566.9 | E24: LHR | F24: General Store | G24: Sulshan bakery | H24: Umair | I24: Awan Market | J24: 40 | K24: 20 | L24: 20 | N24: =K24+L24+M24 -> 40 | R24: =SUM(O24:Q24) -> 0 | S24: =R24+N24+J24 -> 80 | AB24: 39.27 | AC24: 52.4625 | AD24: 72.64 | AE24: =(J24*AB24)+(N24*AC24)+(AD24*S24) -> 9480.5 | AF24: 0.065 | AG24: =AE24*AF24 -> 616.2325 | AH24: =(AB24*J24)*$AH$1 -> 54.978 | AI24: =AE24-AG24 -> 8864.2675 | AJ24: 0.18 | AK24: =AI24*AJ24 -> 1595.5681 | AL24: =AI24+AK24 -> 10459.836
A25: 46204 | B25: July | C25: 6143464.3 | D25: 9232.6 | E25: LHR | F25: General Store | G25: Ali Super GS | H25: Umair | I25: Awan Market | J25: 20 | N25: =K25+L25+M25 -> 0 | R25: =SUM(O25:Q25) -> 0 | S25: =R25+N25+J25 -> 20 | AB25: 39.27 | AC25: 52.4625 | AD25: 72.64 | AE25: =(J25*AB25)+(N25*AC25)+(AD25*S25) -> 2238.2 | AF25: 0.1 | AG25: =AE25*AF25 -> 223.82 | AH25: =(AB25*J25)*$AH$1 -> 27.489 | AI25: =AE25-AG25 -> 2014.38 | AJ25: 0.18 | AK25: =AI25*AJ25 -> 362.5884 | AL25: =AI25+AK25 -> 2376.9684
A26: 46204 | B26: July | C26: 6613383.4 | D26: 9898.3 | E26: LHR | F26: Mart | G26: Fareedia Bakery | H26: Umair | I26: Awan Market | J26: 12 | N26: =K26+L26+M26 -> 0 | O26: 20 | R26: =SUM(O26:Q26) -> 20 | S26: =R26+N26+J26 -> 32 | AB26: 39.27 | AC26: 52.4625 | AD26: 72.64 | AE26: =(J26*AB26)+(N26*AC26)+(AD26*S26) -> 2795.72 | AF26: 0.065 | AG26: =AE26*AF26 -> 181.7218 | AH26: =(AB26*J26)*$AH$1 -> 16.4934 | AI26: =AE26-AG26 -> 2613.9982 | AJ26: 0.18 | AK26: =AI26*AJ26 -> 470.51968 | AL26: =AI26+AK26 -> 3084.5179
A27: 46204 | B27: July | C27: 7083302.5 | D27: 10564 | E27: LHR | F27: General Store | G27: hanif Store | H27: Umair | I27: Awan Market | J27: 12 | N27: =K27+L27+M27 -> 0 | R27: =SUM(O27:Q27) -> 0 | S27: =R27+N27+J27 -> 12 | AB27: 39.27 | AC27: 52.4625 | AD27: 72.64 | AE27: =(J27*AB27)+(N27*AC27)+(AD27*S27) -> 1342.92 | AF27: 0.065 | AG27: =AE27*AF27 -> 87.2898 | AH27: =(AB27*J27)*$AH$1 -> 16.4934 | AI27: =AE27-AG27 -> 1255.6302 | AJ27: 0.18 | AK27: =AI27*AJ27 -> 226.01344 | AL27: =AI27+AK27 -> 1481.6436
A28: 46204 | B28: July | C28: 7553221.5 | D28: 11229.7 | E28: LHR | F28: General Store | G28: Khubaib Mart | H28: Umair | I28: Awan Market | N28: =K28+L28+M28 -> 0 | O28: 26 | P28: 26 | Q28: 28 | R28: =SUM(O28:Q28) -> 80 | S28: =R28+N28+J28 -> 80 | AB28: 39.27 | AC28: 52.4625 | AD28: 72.64 | AE28: =(J28*AB28)+(N28*AC28)+(AD28*S28) -> 5811.2 | AF28: 0.065 | AG28: =AE28*AF28 -> 377.728 | AH28: =(AB28*J28)*$AH$1 -> 0 | AI28: =AE28-AG28 -> 5433.472 | AJ28: 0.18 | AK28: =AI28*AJ28 -> 978.02496 | AL28: =AI28+AK28 -> 6411.497
A29: 46204 | B29: July | C29: 8023140.6 | D29: 11895.4 | E29: LHR | F29: General Store | G29: Chanda Mart | H29: Umair | I29: Awan Market | N29: =K29+L29+M29 -> 0 | P29: 20 | Q29: 20 | R29: =SUM(O29:Q29) -> 40 | S29: =R29+N29+J29 -> 40 | AB29: 39.27 | AC29: 52.4625 | AD29: 72.64 | AE29: =(J29*AB29)+(N29*AC29)+(AD29*S29) -> 2905.6 | AF29: 0.065 | AG29: =AE29*AF29 -> 188.864 | AH29: =(AB29*J29)*$AH$1 -> 0 | AI29: =AE29-AG29 -> 2716.736 | AJ29: 0.18 | AK29: =AI29*AJ29 -> 489.01248 | AL29: =AI29+AK29 -> 3205.7485
A30: 46204 | B30: July | C30: 8493059.7 | D30: 12561.1 | E30: LHR | F30: General Store | G30: DVA Store | H30: Umair | I30: Awan Market | J30: 40 | N30: =K30+L30+M30 -> 0 | R30: =SUM(O30:Q30) -> 0 | S30: =R30+N30+J30 -> 40 | AB30: 39.27 | AC30: 52.4625 | AD30: 72.64 | AE30: =(J30*AB30)+(N30*AC30)+(AD30*S30) -> 4476.4 | AF30: 0.065 | AG30: =AE30*AF30 -> 290.966 | AH30: =(AB30*J30)*$AH$1 -> 54.978 | AI30: =AE30-AG30 -> 4185.434 | AJ30: 0.18 | AK30: =AI30*AJ30 -> 753.37812 | AL30: =AI30+AK30 -> 4938.8121
A31: 46204 | B31: July | C31: 8962978.8 | D31: 13226.8 | E31: LHR | F31: General Store | G31: Palaece Sweet | H31: Umair | I31: Awan Market | J31: 40 | N31: =K31+L31+M31 -> 0 | R31: =SUM(O31:Q31) -> 0 | S31: =R31+N31+J31 -> 40 | AB31: 39.27 | AC31: 52.4625 | AD31: 72.64 | AE31: =(J31*AB31)+(N31*AC31)+(AD31*S31) -> 4476.4 | AF31: 0.065 | AG31: =AE31*AF31 -> 290.966 | AH31: =(AB31*J31)*$AH$1 -> 54.978 | AI31: =AE31-AG31 -> 4185.434 | AJ31: 0.18 | AK31: =AI31*AJ31 -> 753.37812 | AL31: =AI31+AK31 -> 4938.8121
A32: 46204 | B32: July | C32: 9432897.8 | D32: 13892.5 | E32: LHR | F32: Mart | G32: Ghosia Store | H32: Umair | I32: Awan Market | J32: 80 | N32: =K32+L32+M32 -> 0 | R32: =SUM(O32:Q32) -> 0 | S32: =R32+N32+J32 -> 80 | AB32: 39.27 | AC32: 52.4625 | AD32: 72.64 | AE32: =(J32*AB32)+(N32*AC32)+(AD32*S32) -> 8952.8 | AF32: 0.065 | AG32: =AE32*AF32 -> 581.932 | AH32: =(AB32*J32)*$AH$1 -> 109.956 | AI32: =AE32-AG32 -> 8370.868 | AJ32: 0.18 | AK32: =AI32*AJ32 -> 1506.7562 | AL32: =AI32+AK32 -> 9877.6242
A33: 46204 | B33: July | C33: 9902816.9 | D33: 14558.2 | E33: LHR | F33: General Store | G33: NM Mart | H33: Umair | I33: Awan Market | J33: 40 | K33: 20 | L33: 20 | N33: =K33+L33+M33 -> 40 | O33: 20 | P33: 20 | Q33: 20 | R33: =SUM(O33:Q33) -> 60 | S33: =R33+N33+J33 -> 140 | AB33: 39.27 | AC33: 52.4625 | AD33: 72.64 | AE33: =(J33*AB33)+(N33*AC33)+(AD33*S33) -> 13838.9 | AF33: 0.065 | AG33: =AE33*AF33 -> 899.5285 | AH33: =(AB33*J33)*$AH$1 -> 54.978 | AI33: =AE33-AG33 -> 12939.372 | AJ33: 0.18 | AK33: =AI33*AJ33 -> 2329.0869 | AL33: =AI33+AK33 -> 15268.458
A34: 46204 | B34: July | C34: 10372736 | D34: 15223.9 | E34: LHR | F34: General Store | G34: Qadri Store | H34: Zeshan | I34: Nishat | N34: =K34+L34+M34 -> 0 | Q34: 6 | R34: =SUM(O34:Q34) -> 6 | S34: =R34+N34+J34 -> 6 | AB34: 39.27 | AC34: 52.4625 | AD34: 72.64 | AE34: =(J34*AB34)+(N34*AC34)+(AD34*S34) -> 435.84 | AF34: 0.065 | AG34: =AE34*AF34 -> 28.3296 | AH34: =(AB34*J34)*$AH$1 -> 0 | AI34: =AE34-AG34 -> 407.5104 | AJ34: 0.18 | AK34: =AI34*AJ34 -> 73.351872 | AL34: =AI34+AK34 -> 480.86227
A35: 46204 | B35: July | C35: 10842655 | D35: 15889.6 | E35: LHR | F35: General Store | G35: Ahmad Store | H35: Zeshan | I35: Nishat | J35: 6 | N35: =K35+L35+M35 -> 0 | R35: =SUM(O35:Q35) -> 0 | S35: =R35+N35+J35 -> 6 | AB35: 39.27 | AC35: 52.4625 | AD35: 72.64 | AE35: =(J35*AB35)+(N35*AC35)+(AD35*S35) -> 671.46 | AF35: 0.065 | AG35: =AE35*AF35 -> 43.6449 | AH35: =(AB35*J35)*$AH$1 -> 8.2467 | AI35: =AE35-AG35 -> 627.8151 | AJ35: 0.18 | AK35: =AI35*AJ35 -> 113.00672 | AL35: =AI35+AK35 -> 740.82182
A36: 46204 | B36: July | C36: 11312574 | D36: 16555.3 | E36: LHR | F36: General Store | G36: Green Mart | H36: Zeshan | I36: Nishat | J36: 80 | N36: =K36+L36+M36 -> 0 | O36: 40 | P36: 40 | Q36: 80 | R36: =SUM(O36:Q36) -> 160 | S36: =R36+N36+J36 -> 240 | AB36: 39.27 | AC36: 52.4625 | AD36: 72.64 | AE36: =(J36*AB36)+(N36*AC36)+(AD36*S36) -> 20575.2 | AF36: 0.065 | AG36: =AE36*AF36 -> 1337.388 | AH36: =(AB36*J36)*$AH$1 -> 109.956 | AI36: =AE36-AG36 -> 19237.812 | AJ36: 0.18 | AK36: =AI36*AJ36 -> 3462.8062 | AL36: =AI36+AK36 -> 22700.618
A37: 46204 | B37: July | C37: 11782493 | D37: 17221 | E37: LHR | F37: General Store | G37: 786 Store | H37: Zeshan | I37: Nishat | N37: =K37+L37+M37 -> 0 | O37: 15 | P37: 15 | Q37: 10 | R37: =SUM(O37:Q37) -> 40 | S37: =R37+N37+J37 -> 40 | AB37: 39.27 | AC37: 52.4625 | AD37: 72.64 | AE37: =(J37*AB37)+(N37*AC37)+(AD37*S37) -> 2905.6 | AF37: 0.065 | AG37: =AE37*AF37 -> 188.864 | AH37: =(AB37*J37)*$AH$1 -> 0 | AI37: =AE37-AG37 -> 2716.736 | AJ37: 0.18 | AK37: =AI37*AJ37 -> 489.01248 | AL37: =AI37+AK37 -> 3205.7485
A38: 46204 | B38: July | C38: 12252412 | D38: 17886.7 | E38: LHR | F38: Mart | G38: Shreef Mart | H38: Zeshan | I38: Nishat | N38: =K38+L38+M38 -> 0 | O38: 10 | P38: 10 | Q38: 10 | R38: =SUM(O38:Q38) -> 30 | S38: =R38+N38+J38 -> 30 | AB38: 39.27 | AC38: 52.4625 | AD38: 72.64 | AE38: =(J38*AB38)+(N38*AC38)+(AD38*S38) -> 2179.2 | AF38: 0.065 | AG38: =AE38*AF38 -> 141.648 | AH38: =(AB38*J38)*$AH$1 -> 0 | AI38: =AE38-AG38 -> 2037.552 | AJ38: 0.18 | AK38: =AI38*AJ38 -> 366.75936 | AL38: =AI38+AK38 -> 2404.3114
A39: 46205 | B39: July | C39: 12722331 | D39: 18552.4 | E39: LHR | F39: LMT | G39: Native | H39: Asif Shb | I39: Origin Main | J39: 40 | K39: 20 | L39: 20 | N39: =K39+L39+M39 -> 40 | O39: 13 | P39: 13 | Q39: 14 | R39: =SUM(O39:Q39) -> 40 | S39: =R39+N39+J39 -> 120 | AB39: 39.27 | AC39: 52.4625 | AD39: 72.64 | AE39: =(J39*AB39)+(N39*AC39)+(AD39*S39) -> 12386.1 | AF39: 0.065 | AG39: =AE39*AF39 -> 805.0965 | AH39: =(AB39*J39)*$AH$1 -> 54.978 | AI39: =AE39-AG39 -> 11581.003 | AJ39: 0.18 | AK39: =AI39*AJ39 -> 2084.5806 | AL39: =AI39+AK39 -> 13665.584
A40: 46205 | B40: July | C40: 13192250 | D40: 19218.1 | E40: LHR | F40: General Store | G40: Bismillah GS | H40: Furqan | I40: Shadman Market | J40: 12 | N40: =K40+L40+M40 -> 0 | O40: 12 | P40: 0 | Q40: 12 | R40: =SUM(O40:Q40) -> 24 | S40: =R40+N40+J40 -> 36 | AB40: 39.27 | AC40: 52.4625 | AD40: 72.64 | AE40: =(J40*AB40)+(N40*AC40)+(AD40*S40) -> 3086.28 | AF40: 0.065 | AG40: =AE40*AF40 -> 200.6082 | AH40: =(AB40*J40)*$AH$1 -> 16.4934 | AI40: =AE40-AG40 -> 2885.6718 | AJ40: 0.18 | AK40: =AI40*AJ40 -> 519.42092 | AL40: =AI40+AK40 -> 3405.0927
A41: 46205 | B41: July | C41: 13662169 | D41: 19883.8 | E41: LHR | F41: General Store | G41: Bilal Store | H41: Furqan | I41: Shadman Market | N41: =K41+L41+M41 -> 0 | O41: 7 | P41: 6 | Q41: 7 | R41: =SUM(O41:Q41) -> 20 | S41: =R41+N41+J41 -> 20 | AB41: 39.27 | AC41: 52.4625 | AD41: 72.64 | AE41: =(J41*AB41)+(N41*AC41)+(AD41*S41) -> 1452.8 | AF41: 0.065 | AG41: =AE41*AF41 -> 94.432 | AH41: =(AB41*J41)*$AH$1 -> 0 | AI41: =AE41-AG41 -> 1358.368 | AJ41: 0.18 | AK41: =AI41*AJ41 -> 244.50624 | AL41: =AI41+AK41 -> 1602.8742
A42: 46205 | B42: July | C42: 14132089 | D42: 20549.5 | E42: LHR | F42: General Store | G42: New Data Store | H42: Furqan | I42: Shadman Market | J42: 12 | N42: =K42+L42+M42 -> 0 | Q42: 12 | R42: =SUM(O42:Q42) -> 12 | S42: =R42+N42+J42 -> 24 | T42: 3412 | AB42: 39.27 | AC42: 52.4625 | AD42: 72.64 | AE42: =(J42*AB42)+(N42*AC42)+(AD42*S42) -> 2214.6 | AF42: 0.065 | AG42: =AE42*AF42 -> 143.949 | AH42: =(AB42*J42)*$AH$1 -> 16.4934 | AI42: =AE42-AG42 -> 2070.651 | AJ42: 0.18 | AK42: =AI42*AJ42 -> 372.71718 | AL42: =AI42+AK42 -> 2443.3682
A43: 46205 | B43: July | C43: 14602008 | D43: 21215.2 | E43: LHR | F43: General Store | G43: Sohna Departmental | H43: Furqan | I43: Shadman Market | L43: 40 | N43: =K43+L43+M43 -> 40 | R43: =SUM(O43:Q43) -> 0 | S43: =R43+N43+J43 -> 40 | T43: =T42/40 -> 85.3 | AB43: 39.27 | AC43: 52.4625 | AD43: 72.64 | AE43: =(J43*AB43)+(N43*AC43)+(AD43*S43) -> 5004.1 | AF43: 0.065 | AG43: =AE43*AF43 -> 325.2665 | AH43: =(AB43*J43)*$AH$1 -> 0 | AI43: =AE43-AG43 -> 4678.8335 | AJ43: 0.18 | AK43: =AI43*AJ43 -> 842.19003 | AL43: =AI43+AK43 -> 5521.0235
A44: 46205 | B44: July | C44: 15071927 | D44: 21880.9 | E44: LHR | F44: General Store | G44: Hafiz Store | H44: Furqan | I44: Shadman Market | J44: 6 | K44: 6 | L44: 12 | N44: =K44+L44+M44 -> 18 | O44: 3 | P44: 12 | Q44: 6 | R44: =SUM(O44:Q44) -> 21 | S44: =R44+N44+J44 -> 45 | AB44: 39.27 | AC44: 52.4625 | AD44: 72.64 | AE44: =(J44*AB44)+(N44*AC44)+(AD44*S44) -> 4448.745 | AF44: 0.065 | AG44: =AE44*AF44 -> 289.16843 | AH44: =(AB44*J44)*$AH$1 -> 8.2467 | AI44: =AE44-AG44 -> 4159.5766 | AJ44: 0.18 | AK44: =AI44*AJ44 -> 748.72378 | AL44: =AI44+AK44 -> 4908.3004
A45: 46205 | B45: July | C45: 15541846 | D45: 22546.6 | E45: LHR | F45: General Store | G45: Shell Petrol Mart | H45: Furqan | I45: Shadman Market | L45: 20 | N45: =K45+L45+M45 -> 20 | P45: 20 | Q45: 20 | R45: =SUM(O45:Q45) -> 40 | S45: =R45+N45+J45 -> 60 | AB45: 39.27 | AC45: 52.4625 | AD45: 72.64 | AE45: =(J45*AB45)+(N45*AC45)+(AD45*S45) -> 5407.65 | AF45: 0.065 | AG45: =AE45*AF45 -> 351.49725 | AH45: =(AB45*J45)*$AH$1 -> 0 | AI45: =AE45-AG45 -> 5056.1527 | AJ45: 0.18 | AK45: =AI45*AJ45 -> 910.10749 | AL45: =AI45+AK45 -> 5966.2602
A46: 46205 | B46: July | C46: 16011765 | D46: 23212.3 | E46: LHR | F46: General Store | G46: Madina GS | H46: Furqan | I46: Shadman Market | N46: =K46+L46+M46 -> 0 | O46: 12 | P46: 12 | Q46: 12 | R46: =SUM(O46:Q46) -> 36 | S46: =R46+N46+J46 -> 36 | AB46: 39.27 | AC46: 52.4625 | AD46: 72.64 | AE46: =(J46*AB46)+(N46*AC46)+(AD46*S46) -> 2615.04 | AF46: 0.065 | AG46: =AE46*AF46 -> 169.9776 | AH46: =(AB46*J46)*$AH$1 -> 0 | AI46: =AE46-AG46 -> 2445.0624 | AJ46: 0.18 | AK46: =AI46*AJ46 -> 440.11123 | AL46: =AI46+AK46 -> 2885.1736
A47: 46205 | B47: July | C47: 16481684 | D47: 23878 | E47: LHR | F47: General Store | G47: Hafiz Store | H47: Furqan | I47: Shadman Market | N47: =K47+L47+M47 -> 0 | P47: 20 | Q47: 20 | R47: =SUM(O47:Q47) -> 40 | S47: =R47+N47+J47 -> 40 | AB47: 39.27 | AC47: 52.4625 | AD47: 72.64 | AE47: =(J47*AB47)+(N47*AC47)+(AD47*S47) -> 2905.6 | AF47: 0.065 | AG47: =AE47*AF47 -> 188.864 | AH47: =(AB47*J47)*$AH$1 -> 0 | AI47: =AE47-AG47 -> 2716.736 | AJ47: 0.18 | AK47: =AI47*AJ47 -> 489.01248 | AL47: =AI47+AK47 -> 3205.7485
A48: 46205 | B48: July | C48: 16951603 | D48: 24543.7 | E48: LHR | F48: General Store | G48: Data Store | H48: Furqan | I48: Shadman Market | N48: =K48+L48+M48 -> 0 | O48: 20 | P48: 20 | Q48: 20 | R48: =SUM(O48:Q48) -> 60 | S48: =R48+N48+J48 -> 60 | AB48: 39.27 | AC48: 52.4625 | AD48: 72.64 | AE48: =(J48*AB48)+(N48*AC48)+(AD48*S48) -> 4358.4 | AF48: 0.065 | AG48: =AE48*AF48 -> 283.296 | AH48: =(AB48*J48)*$AH$1 -> 0 | AI48: =AE48-AG48 -> 4075.104 | AJ48: 0.18 | AK48: =AI48*AJ48 -> 733.51872 | AL48: =AI48+AK48 -> 4808.6227
A49: 46205 | B49: July | C49: 17421522 | D49: 25209.4 | E49: LHR | F49: General Store | G49: Data Store | H49: Furqan | I49: Shadman Market | J49: 24 | N49: =K49+L49+M49 -> 0 | R49: =SUM(O49:Q49) -> 0 | S49: =R49+N49+J49 -> 24 | AB49: 39.27 | AC49: 52.4625 | AD49: 72.64 | AE49: =(J49*AB49)+(N49*AC49)+(AD49*S49) -> 2685.84 | AF49: 0.065 | AG49: =AE49*AF49 -> 174.5796 | AH49: =(AB49*J49)*$AH$1 -> 32.9868 | AI49: =AE49-AG49 -> 2511.2604 | AJ49: 0.18 | AK49: =AI49*AJ49 -> 452.02687 | AL49: =AI49+AK49 -> 2963.2873
A50: 46205 | B50: July | C50: 17891441 | D50: 25875.1 | E50: LHR | F50: General Store | G50: Daim Store | H50: Salman | I50: Rifal Range Road | J50: 12 | K50: 10 | L50: 10 | N50: =K50+L50+M50 -> 20 | R50: =SUM(O50:Q50) -> 0 | S50: =R50+N50+J50 -> 32 | AB50: 39.27 | AC50: 52.4625 | AD50: 72.64 | AE50: =(J50*AB50)+(N50*AC50)+(AD50*S50) -> 3844.97 | AF50: 0.065 | AG50: =AE50*AF50 -> 249.92305 | AH50: =(AB50*J50)*$AH$1 -> 16.4934 | AI50: =AE50-AG50 -> 3595.047 | AJ50: 0.18 | AK50: =AI50*AJ50 -> 647.10845 | AL50: =AI50+AK50 -> 4242.1554
A51: 46205 | B51: July | C51: 18361360 | D51: 26540.8 | E51: LHR | F51: General Store | G51: Bread & Bakers | H51: Salman | I51: Rifal Range Road | J51: 40 | K51: 10 | L51: 10 | N51: =K51+L51+M51 -> 20 | O51: 10 | P51: 10 | Q51: 20 | R51: =SUM(O51:Q51) -> 40 | S51: =R51+N51+J51 -> 100 | AB51: 39.27 | AC51: 52.4625 | AD51: 72.64 | AE51: =(J51*AB51)+(N51*AC51)+(AD51*S51) -> 9884.05 | AF51: 0.065 | AG51: =AE51*AF51 -> 642.46325 | AH51: =(AB51*J51)*$AH$1 -> 54.978 | AI51: =AE51-AG51 -> 9241.5867 | AJ51: 0.18 | AK51: =AI51*AJ51 -> 1663.4856 | AL51: =AI51+AK51 -> 10905.072
A52: 46205 | B52: July | C52: 18831279 | D52: 27206.5 | E52: LHR | F52: General Store | G52: Ahmad Pharmacy Mart | H52: Salman | I52: Rifal Range Road | J52: 40 | N52: =K52+L52+M52 -> 0 | O52: 13 | P52: 13 | Q52: 14 | R52: =SUM(O52:Q52) -> 40 | S52: =R52+N52+J52 -> 80 | AB52: 39.27 | AC52: 52.4625 | AD52: 72.64 | AE52: =(J52*AB52)+(N52*AC52)+(AD52*S52) -> 7382 | AF52: 0.14 | AG52: =AE52*AF52 -> 1033.48 | AH52: =(AB52*J52)*$AH$1 -> 54.978 | AI52: =AE52-AG52 -> 6348.52 | AJ52: 0.18 | AK52: =AI52*AJ52 -> 1142.7336 | AL52: =AI52+AK52 -> 7491.2536
A53: 46205 | B53: July | C53: 19301198 | D53: 27872.2 | E53: LHR | F53: General Store | G53: Imtiaz Mart | H53: Salman | I53: Rifal Range Road | J53: 6 | K53: 10 | N53: =K53+L53+M53 -> 10 | O53: 10 | P53: 10 | Q53: 10 | R53: =SUM(O53:Q53) -> 30 | S53: =R53+N53+J53 -> 46 | AB53: 39.27 | AC53: 52.4625 | AD53: 72.64 | AE53: =(J53*AB53)+(N53*AC53)+(AD53*S53) -> 4101.685 | AF53: 0.065 | AG53: =AE53*AF53 -> 266.60953 | AH53: =(AB53*J53)*$AH$1 -> 8.2467 | AI53: =AE53-AG53 -> 3835.0755 | AJ53: 0.18 | AK53: =AI53*AJ53 -> 690.31359 | AL53: =AI53+AK53 -> 4525.3891
A54: 46205 | B54: July | C54: 19771117 | D54: 28537.9 | E54: LHR | F54: General Store | G54: Shamza Store | H54: Salman | I54: Rifal Range Road | J54: 6 | K54: 2 | L54: 2 | N54: =K54+L54+M54 -> 4 | O54: 2 | P54: 2 | Q54: 2 | R54: =SUM(O54:Q54) -> 6 | S54: =R54+N54+J54 -> 16 | AB54: 39.27 | AC54: 52.4625 | AD54: 72.64 | AE54: =(J54*AB54)+(N54*AC54)+(AD54*S54) -> 1607.71 | AF54: 0.065 | AG54: =AE54*AF54 -> 104.50115 | AH54: =(AB54*J54)*$AH$1 -> 8.2467 | AI54: =AE54-AG54 -> 1503.2088 | AJ54: 0.18 | AK54: =AI54*AJ54 -> 270.57759 | AL54: =AI54+AK54 -> 1773.7864
A55: 46205 | B55: July | C55: 20241036 | D55: 29203.6 | E55: LHR | F55: General Store | G55: Al Makkah Store | H55: Salman | I55: Rifal Range Road | J55: 24 | K55: 12 | L55: 12 | N55: =K55+L55+M55 -> 24 | O55: 20 | P55: 10 | Q55: 10 | R55: =SUM(O55:Q55) -> 40 | S55: =R55+N55+J55 -> 88 | AB55: 39.27 | AC55: 52.4625 | AD55: 72.64 | AE55: =(J55*AB55)+(N55*AC55)+(AD55*S55) -> 8593.9 | AF55: 0.065 | AG55: =AE55*AF55 -> 558.6035 | AH55: =(AB55*J55)*$AH$1 -> 32.9868 | AI55: =AE55-AG55 -> 8035.2965 | AJ55: 0.18 | AK55: =AI55*AJ55 -> 1446.3534 | AL55: =AI55+AK55 -> 9481.6499
A56: 46205 | B56: July | C56: 20710956 | D56: 29869.3 | E56: LHR | F56: General Store | G56: Mozzam Mart | H56: Umair | I56: Youna Abad | J56: 40 | K56: 39 | L56: 40 | N56: =K56+L56+M56 -> 79 | O56: 40 | P56: 40 | Q56: 40 | R56: =SUM(O56:Q56) -> 120 | S56: =R56+N56+J56 -> 239 | AB56: 39.27 | AC56: 52.4625 | AD56: 72.64 | AE56: =(J56*AB56)+(N56*AC56)+(AD56*S56) -> 23076.298 | AF56: 0.065 | AG56: =AE56*AF56 -> 1499.9593 | AH56: =(AB56*J56)*$AH$1 -> 54.978 | AI56: =AE56-AG56 -> 21576.338 | AJ56: 0.18 | AK56: =AI56*AJ56 -> 3883.7409 | AL56: =AI56+AK56 -> 25460.079
A57: 46205 | B57: July | C57: 21180875 | D57: 30535 | E57: LHR | F57: General Store | G57: Azan Traders | H57: Umair | I57: Youna Abad | J57: 40 | N57: =K57+L57+M57 -> 0 | R57: =SUM(O57:Q57) -> 0 | S57: =R57+N57+J57 -> 40 | AB57: 39.27 | AC57: 52.4625 | AD57: 72.64 | AE57: =(J57*AB57)+(N57*AC57)+(AD57*S57) -> 4476.4 | AF57: 0.1 | AG57: =AE57*AF57 -> 447.64 | AH57: =(AB57*J57)*$AH$1 -> 54.978 | AI57: =AE57-AG57 -> 4028.76 | AJ57: 0.18 | AK57: =AI57*AJ57 -> 725.1768 | AL57: =AI57+AK57 -> 4753.9368
A58: 46205 | B58: July | C58: 21650794 | D58: 31200.7 | E58: LHR | F58: General Store | G58: Grace Land Mart | H58: Umair | I58: Youna Abad | J58: 40 | N58: =K58+L58+M58 -> 0 | O58: 40 | R58: =SUM(O58:Q58) -> 40 | S58: =R58+N58+J58 -> 80 | AB58: 39.27 | AC58: 52.4625 | AD58: 72.64 | AE58: =(J58*AB58)+(N58*AC58)+(AD58*S58) -> 7382 | AF58: 0.1 | AG58: =AE58*AF58 -> 738.2 | AH58: =(AB58*J58)*$AH$1 -> 54.978 | AI58: =AE58-AG58 -> 6643.8 | AJ58: 0.18 | AK58: =AI58*AJ58 -> 1195.884 | AL58: =AI58+AK58 -> 7839.684
A59: 46205 | B59: July | C59: 22120713 | D59: 31866.4 | E59: LHR | F59: General Store | G59: Bhai Bhai GS | H59: Umair | I59: Youna Abad | J59: 40 | N59: =K59+L59+M59 -> 0 | R59: =SUM(O59:Q59) -> 0 | S59: =R59+N59+J59 -> 40 | AB59: 39.27 | AC59: 52.4625 | AD59: 72.64 | AE59: =(J59*AB59)+(N59*AC59)+(AD59*S59) -> 4476.4 | AF59: 0.065 | AG59: =AE59*AF59 -> 290.966 | AH59: =(AB59*J59)*$AH$1 -> 54.978 | AI59: =AE59-AG59 -> 4185.434 | AJ59: 0.18 | AK59: =AI59*AJ59 -> 753.37812 | AL59: =AI59+AK59 -> 4938.8121
A60: 46205 | B60: July | C60: 22590632 | D60: 32532.1 | E60: LHR | F60: General Store | G60: Tayaab Store | H60: Umair | I60: Youna Abad | J60: 40 | N60: =K60+L60+M60 -> 0 | R60: =SUM(O60:Q60) -> 0 | S60: =R60+N60+J60 -> 40 | AB60: 39.27 | AC60: 52.4625 | AD60: 72.64 | AE60: =(J60*AB60)+(N60*AC60)+(AD60*S60) -> 4476.4 | AF60: 0.065 | AG60: =AE60*AF60 -> 290.966 | AH60: =(AB60*J60)*$AH$1 -> 54.978 | AI60: =AE60-AG60 -> 4185.434 | AJ60: 0.18 | AK60: =AI60*AJ60 -> 753.37812 | AL60: =AI60+AK60 -> 4938.8121
A61: 46205 | B61: July | C61: 23060551 | D61: 33197.8 | E61: LHR | F61: General Store | G61: Shehriyar Store | H61: Umair | I61: Youna Abad | J61: 6 | N61: =K61+L61+M61 -> 0 | R61: =SUM(O61:Q61) -> 0 | S61: =R61+N61+J61 -> 6 | AB61: 39.27 | AC61: 52.4625 | AD61: 72.64 | AE61: =(J61*AB61)+(N61*AC61)+(AD61*S61) -> 671.46 | AF61: 0.065 | AG61: =AE61*AF61 -> 43.6449 | AH61: =(AB61*J61)*$AH$1 -> 8.2467 | AI61: =AE61-AG61 -> 627.8151 | AJ61: 0.18 | AK61: =AI61*AJ61 -> 113.00672 | AL61: =AI61+AK61 -> 740.82182
A62: 46205 | B62: July | C62: 23530470 | D62: 33863.5 | E62: LHR | F62: General Store | G62: Bhati GS | H62: Umair | I62: Youna Abad | J62: 10 | N62: =K62+L62+M62 -> 0 | R62: =SUM(O62:Q62) -> 0 | S62: =R62+N62+J62 -> 10 | AB62: 39.27 | AC62: 52.4625 | AD62: 72.64 | AE62: =(J62*AB62)+(N62*AC62)+(AD62*S62) -> 1119.1 | AF62: 0.065 | AG62: =AE62*AF62 -> 72.7415 | AH62: =(AB62*J62)*$AH$1 -> 13.7445 | AI62: =AE62-AG62 -> 1046.3585 | AJ62: 0.18 | AK62: =AI62*AJ62 -> 188.34453 | AL62: =AI62+AK62 -> 1234.703
A63: 46205 | B63: July | C63: 24000389 | D63: 34529.2 | E63: LHR | F63: General Store | G63: Malik Ijaz | H63: Umair | I63: Youna Abad | J63: 10 | N63: =K63+L63+M63 -> 0 | R63: =SUM(O63:Q63) -> 0 | S63: =R63+N63+J63 -> 10 | AB63: 39.27 | AC63: 52.4625 | AD63: 72.64 | AE63: =(J63*AB63)+(N63*AC63)+(AD63*S63) -> 1119.1 | AF63: 0.065 | AG63: =AE63*AF63 -> 72.7415 | AH63: =(AB63*J63)*$AH$1 -> 13.7445 | AI63: =AE63-AG63 -> 1046.3585 | AJ63: 0.18 | AK63: =AI63*AJ63 -> 188.34453 | AL63: =AI63+AK63 -> 1234.703
A64: 46205 | B64: July | C64: 24470308 | D64: 35194.9 | E64: LHR | F64: General Store | G64: Nadeem Bakers | H64: Umair | I64: Youna Abad | J64: 10 | N64: =K64+L64+M64 -> 0 | R64: =SUM(O64:Q64) -> 0 | S64: =R64+N64+J64 -> 10 | AB64: 39.27 | AC64: 52.4625 | AD64: 72.64 | AE64: =(J64*AB64)+(N64*AC64)+(AD64*S64) -> 1119.1 | AF64: 0.065 | AG64: =AE64*AF64 -> 72.7415 | AH64: =(AB64*J64)*$AH$1 -> 13.7445 | AI64: =AE64-AG64 -> 1046.3585 | AJ64: 0.18 | AK64: =AI64*AJ64 -> 188.34453 | AL64: =AI64+AK64 -> 1234.703
A65: 46205 | B65: July | C65: 24940227 | D65: 35860.6 | E65: LHR | F65: General Store | G65: MA Bakers | H65: Umair | I65: Youna Abad | J65: 40 | N65: =K65+L65+M65 -> 0 | R65: =SUM(O65:Q65) -> 0 | S65: =R65+N65+J65 -> 40 | AB65: 39.27 | AC65: 52.4625 | AD65: 72.64 | AE65: =(J65*AB65)+(N65*AC65)+(AD65*S65) -> 4476.4 | AF65: 0.065 | AG65: =AE65*AF65 -> 290.966 | AH65: =(AB65*J65)*$AH$1 -> 54.978 | AI65: =AE65-AG65 -> 4185.434 | AJ65: 0.18 | AK65: =AI65*AJ65 -> 753.37812 | AL65: =AI65+AK65 -> 4938.8121
A66: 46205 | B66: July | C66: 25410146 | D66: 36526.3 | E66: LHR | F66: General Store | G66: Ali Store | H66: Zeshan | I66: Ali Park | N66: =K66+L66+M66 -> 0 | P66: 20 | Q66: 20 | R66: =SUM(O66:Q66) -> 40 | S66: =R66+N66+J66 -> 40 | AB66: 39.27 | AC66: 52.4625 | AD66: 72.64 | AE66: =(J66*AB66)+(N66*AC66)+(AD66*S66) -> 2905.6 | AF66: 0.065 | AG66: =AE66*AF66 -> 188.864 | AH66: =(AB66*J66)*$AH$1 -> 0 | AI66: =AE66-AG66 -> 2716.736 | AJ66: 0.18 | AK66: =AI66*AJ66 -> 489.01248 | AL66: =AI66+AK66 -> 3205.7485
A67: 46205 | B67: July | C67: 25880065 | D67: 37192 | E67: LHR | F67: General Store | G67: Organic Store | H67: Zeshan | I67: Ali Park | N67: =K67+L67+M67 -> 0 | O67: 15 | P67: 15 | Q67: 10 | R67: =SUM(O67:Q67) -> 40 | S67: =R67+N67+J67 -> 40 | AB67: 39.27 | AC67: 52.4625 | AD67: 72.64 | AE67: =(J67*AB67)+(N67*AC67)+(AD67*S67) -> 2905.6 | AF67: 0.065 | AG67: =AE67*AF67 -> 188.864 | AH67: =(AB67*J67)*$AH$1 -> 0 | AI67: =AE67-AG67 -> 2716.736 | AJ67: 0.18 | AK67: =AI67*AJ67 -> 489.01248 | AL67: =AI67+AK67 -> 3205.7485
A68: 46205 | B68: July | C68: 26349984 | D68: 37857.7 | E68: LHR | F68: General Store | G68: Moon Mart | H68: Zeshan | I68: Ali Park | N68: =K68+L68+M68 -> 0 | O68: 15 | P68: 15 | Q68: 10 | R68: =SUM(O68:Q68) -> 40 | S68: =R68+N68+J68 -> 40 | AB68: 39.27 | AC68: 52.4625 | AD68: 72.64 | AE68: =(J68*AB68)+(N68*AC68)+(AD68*S68) -> 2905.6 | AF68: 0.065 | AG68: =AE68*AF68 -> 188.864 | AH68: =(AB68*J68)*$AH$1 -> 0 | AI68: =AE68-AG68 -> 2716.736 | AJ68: 0.18 | AK68: =AI68*AJ68 -> 489.01248 | AL68: =AI68+AK68 -> 3205.7485
A69: 46205 | B69: July | C69: 26819903 | D69: 38523.4 | E69: LHR | F69: General Store | G69: Raza Mart | H69: Zeshan | I69: Ali Park | J69: 40 | K69: 20 | L69: 20 | N69: =K69+L69+M69 -> 40 | O69: 15 | P69: 15 | Q69: 10 | R69: =SUM(O69:Q69) -> 40 | S69: =R69+N69+J69 -> 120 | AB69: 39.27 | AC69: 52.4625 | AD69: 72.64 | AE69: =(J69*AB69)+(N69*AC69)+(AD69*S69) -> 12386.1 | AF69: 0.065 | AG69: =AE69*AF69 -> 805.0965 | AH69: =(AB69*J69)*$AH$1 -> 54.978 | AI69: =AE69-AG69 -> 11581.003 | AJ69: 0.18 | AK69: =AI69*AJ69 -> 2084.5806 | AL69: =AI69+AK69 -> 13665.584
A70: 46205 | B70: July | C70: 27289823 | D70: 39189.1 | E70: LHR | F70: General Store | G70: HR Mart | H70: Zeshan | I70: Ali Park | K70: 20 | L70: 20 | N70: =K70+L70+M70 -> 40 | O70: 15 | P70: 15 | Q70: 10 | R70: =SUM(O70:Q70) -> 40 | S70: =R70+N70+J70 -> 80 | AB70: 39.27 | AC70: 52.4625 | AD70: 72.64 | AE70: =(J70*AB70)+(N70*AC70)+(AD70*S70) -> 7909.7 | AF70: 0.065 | AG70: =AE70*AF70 -> 514.1305 | AH70: =(AB70*J70)*$AH$1 -> 0 | AI70: =AE70-AG70 -> 7395.5695 | AJ70: 0.18 | AK70: =AI70*AJ70 -> 1331.2025 | AL70: =AI70+AK70 -> 8726.772
A71: 46205 | B71: July | C71: 27759742 | D71: 39854.8 | E71: LHR | F71: General Store | G71: Khan Store | H71: Zeshan | I71: Ali Park | J71: 10 | N71: =K71+L71+M71 -> 0 | R71: =SUM(O71:Q71) -> 0 | S71: =R71+N71+J71 -> 10 | AB71: 39.27 | AC71: 52.4625 | AD71: 72.64 | AE71: =(J71*AB71)+(N71*AC71)+(AD71*S71) -> 1119.1 | AF71: 0.065 | AG71: =AE71*AF71 -> 72.7415 | AH71: =(AB71*J71)*$AH$1 -> 13.7445 | AI71: =AE71-AG71 -> 1046.3585 | AJ71: 0.18 | AK71: =AI71*AJ71 -> 188.34453 | AL71: =AI71+AK71 -> 1234.703
A72: 46205 | B72: July | C72: 28229661 | D72: 40520.5 | E72: LHR | F72: General Store | G72: Awan Store | H72: Zeshan | I72: Ali Park | J72: 10 | N72: =K72+L72+M72 -> 0 | R72: =SUM(O72:Q72) -> 0 | S72: =R72+N72+J72 -> 10 | AB72: 39.27 | AC72: 52.4625 | AD72: 72.64 | AE72: =(J72*AB72)+(N72*AC72)+(AD72*S72) -> 1119.1 | AF72: 0.065 | AG72: =AE72*AF72 -> 72.7415 | AH72: =(AB72*J72)*$AH$1 -> 13.7445 | AI72: =AE72-AG72 -> 1046.3585 | AJ72: 0.18 | AK72: =AI72*AJ72 -> 188.34453 | AL72: =AI72+AK72 -> 1234.703
A73: 46205 | B73: July | C73: 28699580 | D73: 41186.2 | E73: LHR | F73: General Store | G73: Sheri Mart | H73: Zeshan | I73: Ali Park | J73: 10 | N73: =K73+L73+M73 -> 0 | R73: =SUM(O73:Q73) -> 0 | S73: =R73+N73+J73 -> 10 | AB73: 39.27 | AC73: 52.4625 | AD73: 72.64 | AE73: =(J73*AB73)+(N73*AC73)+(AD73*S73) -> 1119.1 | AF73: 0.065 | AG73: =AE73*AF73 -> 72.7415 | AH73: =(AB73*J73)*$AH$1 -> 13.7445 | AI73: =AE73-AG73 -> 1046.3585 | AJ73: 0.18 | AK73: =AI73*AJ73 -> 188.34453 | AL73: =AI73+AK73 -> 1234.703
A74: 46205 | B74: July | C74: 29169499 | D74: 41851.9 | E74: LHR | F74: LMT | G74: Manawan (Risen) | H74: Shakoor | I74: Manawan | K74: 120 | L74: 80 | N74: =K74+L74+M74 -> 200 | O74: 40 | P74: 40 | Q74: 120 | R74: =SUM(O74:Q74) -> 200 | S74: =R74+N74+J74 -> 400 | AB74: 39.27 | AC74: 52.4625 | AD74: 72.64 | AE74: =(J74*AB74)+(N74*AC74)+(AD74*S74) -> 39548.5 | AF74: 0.065 | AG74: =AE74*AF74 -> 2570.6525 | AH74: =(AB74*J74)*$AH$1 -> 0 | AI74: =AE74-AG74 -> 36977.848 | AJ74: 0.18 | AK74: =AI74*AJ74 -> 6656.0126 | AL74: =AI74+AK74 -> 43633.86
A75: 46205 | B75: July | C75: 29639418 | D75: 42517.6 | E75: LHR | F75: LMT | G75: Shadbagh (Risen) | H75: Shakoor | I75: Shadbagh | N75: =K75+L75+M75 -> 0 | O75: 120 | P75: 120 | Q75: 120 | R75: =SUM(O75:Q75) -> 360 | S75: =R75+N75+J75 -> 360 | AB75: 39.27 | AC75: 52.4625 | AD75: 72.64 | AE75: =(J75*AB75)+(N75*AC75)+(AD75*S75) -> 26150.4 | AF75: 0.065 | AG75: =AE75*AF75 -> 1699.776 | AH75: =(AB75*J75)*$AH$1 -> 0 | AI75: =AE75-AG75 -> 24450.624 | AJ75: 0.18 | AK75: =AI75*AJ75 -> 4401.1123 | AL75: =AI75+AK75 -> 28851.736
A76: 46205 | B76: July | C76: 30109337 | D76: 43183.3 | E76: LHR | F76: LMT | G76: Vip | H76: Shakoor | I76: Behria Town | N76: =K76+L76+M76 -> 0 | O76: 240 | P76: 240 | Q76: 240 | R76: =SUM(O76:Q76) -> 720 | S76: =R76+N76+J76 -> 720 | AB76: 39.27 | AC76: 52.4625 | AD76: 72.64 | AE76: =(J76*AB76)+(N76*AC76)+(AD76*S76) -> 52300.8 | AF76: 0.065 | AG76: =AE76*AF76 -> 3399.552 | AH76: =(AB76*J76)*$AH$1 -> 0 | AI76: =AE76-AG76 -> 48901.248 | AJ76: 0.18 | AK76: =AI76*AJ76 -> 8802.2246 | AL76: =AI76+AK76 -> 57703.473
A77: 46205 | B77: July | C77: 30579256 | D77: 43849 | E77: LHR | F77: LMT | G77: Umaima paragon City | H77: Shakoor | I77: Paragon City | K77: 40 | L77: 40 | N77: =K77+L77+M77 -> 80 | O77: 40 | P77: 40 | Q77: 40 | R77: =SUM(O77:Q77) -> 120 | S77: =R77+N77+J77 -> 200 | AB77: 39.27 | AC77: 52.4625 | AD77: 72.64 | AE77: =(J77*AB77)+(N77*AC77)+(AD77*S77) -> 18725 | AF77: 0.065 | AG77: =AE77*AF77 -> 1217.125 | AH77: =(AB77*J77)*$AH$1 -> 0 | AI77: =AE77-AG77 -> 17507.875 | AJ77: 0.18 | AK77: =AI77*AJ77 -> 3151.4175 | AL77: =AI77+AK77 -> 20659.292
A78: 46206 | B78: July | C78: 31049175 | D78: 44514.7 | E78: LHR | F78: LMT | G78: Clinix | H78: Shakoor | I78: Mughalpura | K78: 78 | L78: 77 | N78: =K78+L78+M78 -> 155 | O78: 159 | P78: 38 | Q78: 158 | R78: =SUM(O78:Q78) -> 355 | S78: =R78+N78+J78 -> 510 | AB78: 39.27 | AC78: 52.4625 | AD78: 72.64 | AE78: =(J78*AB78)+(N78*AC78)+(AD78*S78) -> 45178.088 | AF78: 0.065 | AG78: =AE78*AF78 -> 2936.5757 | AH78: =(AB78*J78)*$AH$1 -> 0 | AI78: =AE78-AG78 -> 42241.512 | AJ78: 0.18 | AK78: =AI78*AJ78 -> 7603.4721 | AL78: =AI78+AK78 -> 49844.984
A79: 46206 | B79: July | C79: 31519094 | D79: 45180.4 | E79: LHR | F79: LMT | G79: Rainbow Model Town | H79: Shakoor | I79: Model Town | L79: 40 | N79: =K79+L79+M79 -> 40 | O79: 40 | P79: 40 | Q79: 40 | R79: =SUM(O79:Q79) -> 120 | S79: =R79+N79+J79 -> 160 | AB79: 39.27 | AC79: 52.4625 | AD79: 72.64 | AE79: =(J79*AB79)+(N79*AC79)+(AD79*S79) -> 13720.9 | AF79: 0.065 | AG79: =AE79*AF79 -> 891.8585 | AH79: =(AB79*J79)*$AH$1 -> 0 | AI79: =AE79-AG79 -> 12829.041 | AJ79: 0.18 | AK79: =AI79*AJ79 -> 2309.2275 | AL79: =AI79+AK79 -> 15138.269
A80: 46206 | B80: July | C80: 31989013 | D80: 45846.1 | E80: LHR | F80: LMT | G80: Raheem Store | H80: Shakoor | I80: Mughalpura | K80: 120 | L80: 120 | N80: =K80+L80+M80 -> 240 | O80: 160 | P80: 0 | Q80: 160 | R80: =SUM(O80:Q80) -> 320 | S80: =R80+N80+J80 -> 560 | AB80: 39.27 | AC80: 52.4625 | AD80: 72.64 | AE80: =(J80*AB80)+(N80*AC80)+(AD80*S80) -> 53269.4 | AF80: 0.065 | AG80: =AE80*AF80 -> 3462.511 | AH80: =(AB80*J80)*$AH$1 -> 0 | AI80: =AE80-AG80 -> 49806.889 | AJ80: 0.18 | AK80: =AI80*AJ80 -> 8965.24 | AL80: =AI80+AK80 -> 58772.129
A81: 46206 | B81: July | C81: 32458932 | D81: 46511.8 | E81: LHR | F81: General Store | G81: Shell Petrol Mart | H81: Furqan | I81: Habibulah Road | N81: =K81+L81+M81 -> 0 | O81: 20 | P81: 20 | Q81: 40 | R81: =SUM(O81:Q81) -> 80 | S81: =R81+N81+J81 -> 80 | AB81: 39.27 | AC81: 52.4625 | AD81: 72.64 | AE81: =(J81*AB81)+(N81*AC81)+(AD81*S81) -> 5811.2 | AF81: 0.065 | AG81: =AE81*AF81 -> 377.728 | AH81: =(AB81*J81)*$AH$1 -> 0 | AI81: =AE81-AG81 -> 5433.472 | AJ81: 0.18 | AK81: =AI81*AJ81 -> 978.02496 | AL81: =AI81+AK81 -> 6411.497
A82: 46206 | B82: July | C82: 32928851 | D82: 47177.5 | E82: LHR | F82: General Store | G82: Iqbal Mart | H82: Furqan | I82: Habibulah Road | J82: 40 | N82: =K82+L82+M82 -> 0 | R82: =SUM(O82:Q82) -> 0 | S82: =R82+N82+J82 -> 40 | AB82: 39.27 | AC82: 52.4625 | AD82: 72.64 | AE82: =(J82*AB82)+(N82*AC82)+(AD82*S82) -> 4476.4 | AF82: 0.065 | AG82: =AE82*AF82 -> 290.966 | AH82: =(AB82*J82)*$AH$1 -> 54.978 | AI82: =AE82-AG82 -> 4185.434 | AJ82: 0.18 | AK82: =AI82*AJ82 -> 753.37812 | AL82: =AI82+AK82 -> 4938.8121
A83: 46206 | B83: July | C83: 33398770 | D83: 47843.2 | E83: LHR | F83: General Store | G83: Ali Brother | H83: Furqan | I83: Habibulah Road | J83: 20 | K83: 16 | L83: 12 | N83: =K83+L83+M83 -> 28 | R83: =SUM(O83:Q83) -> 0 | S83: =R83+N83+J83 -> 48 | AB83: 39.27 | AC83: 52.4625 | AD83: 72.64 | AE83: =(J83*AB83)+(N83*AC83)+(AD83*S83) -> 5741.07 | AF83: 0.065 | AG83: =AE83*AF83 -> 373.16955 | AH83: =(AB83*J83)*$AH$1 -> 27.489 | AI83: =AE83-AG83 -> 5367.9005 | AJ83: 0.18 | AK83: =AI83*AJ83 -> 966.22208 | AL83: =AI83+AK83 -> 6334.1225
A84: 46206 | B84: July | C84: 33868690 | D84: 48508.9 | E84: LHR | F84: General Store | G84: Tofail Store | H84: Furqan | I84: Habibulah Road | K84: 20 | L84: 20 | N84: =K84+L84+M84 -> 40 | R84: =SUM(O84:Q84) -> 0 | S84: =R84+N84+J84 -> 40 | AB84: 39.27 | AC84: 52.4625 | AD84: 72.64 | AE84: =(J84*AB84)+(N84*AC84)+(AD84*S84) -> 5004.1 | AF84: 0.065 | AG84: =AE84*AF84 -> 325.2665 | AH84: =(AB84*J84)*$AH$1 -> 0 | AI84: =AE84-AG84 -> 4678.8335 | AJ84: 0.18 | AK84: =AI84*AJ84 -> 842.19003 | AL84: =AI84+AK84 -> 5521.0235
A85: 46206 | B85: July | C85: 34338609 | D85: 49174.6 | E85: LHR | F85: General Store | G85: Rehman Store | H85: Mubeen | I85: Al Kareem Society 60ft Road | N85: =K85+L85+M85 -> 0 | O85: 40 | P85: 40 | Q85: 40 | R85: =SUM(O85:Q85) -> 120 | S85: =R85+N85+J85 -> 120 | AB85: 39.27 | AC85: 52.4625 | AD85: 72.64 | AE85: =(J85*AB85)+(N85*AC85)+(AD85*S85) -> 8716.8 | AF85: 0.065 | AG85: =AE85*AF85 -> 566.592 | AH85: =(AB85*J85)*$AH$1 -> 0 | AI85: =AE85-AG85 -> 8150.208 | AJ85: 0.18 | AK85: =AI85*AJ85 -> 1467.0374 | AL85: =AI85+AK85 -> 9617.2454
A86: 46206 | B86: July | C86: 34808528 | D86: 49840.3 | E86: LHR | F86: Mart | G86: Al Falah Mart | H86: Salman | I86: Gullberg 2 | N86: =K86+L86+M86 -> 0 | O86: 10 | P86: 10 | Q86: 12 | R86: =SUM(O86:Q86) -> 32 | S86: =R86+N86+J86 -> 32 | AB86: 39.27 | AC86: 52.4625 | AD86: 72.64 | AE86: =(J86*AB86)+(N86*AC86)+(AD86*S86) -> 2324.48 | AF86: 0.065 | AG86: =AE86*AF86 -> 151.0912 | AH86: =(AB86*J86)*$AH$1 -> 0 | AI86: =AE86-AG86 -> 2173.3888 | AJ86: 0.18 | AK86: =AI86*AJ86 -> 391.20998 | AL86: =AI86+AK86 -> 2564.5988
A87: 46206 | B87: July | C87: 35278447 | D87: 50506 | E87: LHR | F87: Mart | G87: H Mart | H87: Salman | I87: Gullberg 2 | N87: =K87+L87+M87 -> 0 | P87: 13 | Q87: 14 | R87: =SUM(O87:Q87) -> 27 | S87: =R87+N87+J87 -> 27 | AB87: 39.27 | AC87: 52.4625 | AD87: 72.64 | AE87: =(J87*AB87)+(N87*AC87)+(AD87*S87) -> 1961.28 | AF87: 0.065 | AG87: =AE87*AF87 -> 127.4832 | AH87: =(AB87*J87)*$AH$1 -> 0 | AI87: =AE87-AG87 -> 1833.7968 | AJ87: 0.18 | AK87: =AI87*AJ87 -> 330.08342 | AL87: =AI87+AK87 -> 2163.8802
A88: 46206 | B88: July | C88: 35748366 | D88: 51171.7 | E88: LHR | F88: Mart | G88: Sk Mart | H88: Salman | I88: Gullberg 2 | J88: 12 | K88: 6 | L88: 6 | N88: =K88+L88+M88 -> 12 | R88: =SUM(O88:Q88) -> 0 | S88: =R88+N88+J88 -> 24 | AB88: 39.27 | AC88: 52.4625 | AD88: 72.64 | AE88: =(J88*AB88)+(N88*AC88)+(AD88*S88) -> 2844.15 | AF88: 0.065 | AG88: =AE88*AF88 -> 184.86975 | AH88: =(AB88*J88)*$AH$1 -> 16.4934 | AI88: =AE88-AG88 -> 2659.2803 | AJ88: 0.18 | AK88: =AI88*AJ88 -> 478.67045 | AL88: =AI88+AK88 -> 3137.9507
A89: 46206 | B89: July | C89: 36218285 | D89: 51837.4 | E89: LHR | F89: General Store | G89: Shera Store | H89: Salman | I89: Gullberg 2 | J89: 6 | K89: 20 | L89: 20 | N89: =K89+L89+M89 -> 40 | R89: =SUM(O89:Q89) -> 0 | S89: =R89+N89+J89 -> 46 | AB89: 39.27 | AC89: 52.4625 | AD89: 72.64 | AE89: =(J89*AB89)+(N89*AC89)+(AD89*S89) -> 5675.56 | AF89: 0.065 | AG89: =AE89*AF89 -> 368.9114 | AH89: =(AB89*J89)*$AH$1 -> 8.2467 | AI89: =AE89-AG89 -> 5306.6486 | AJ89: 0.18 | AK89: =AI89*AJ89 -> 955.19675 | AL89: =AI89+AK89 -> 6261.8453
A90: 46206 | B90: July | C90: 36688204 | D90: 52503.1 | E90: LHR | F90: General Store | G90: Murad GS | H90: Salman | I90: Gullberg 2 | J90: 12 | N90: =K90+L90+M90 -> 0 | R90: =SUM(O90:Q90) -> 0 | S90: =R90+N90+J90 -> 12 | AB90: 39.27 | AC90: 52.4625 | AD90: 72.64 | AE90: =(J90*AB90)+(N90*AC90)+(AD90*S90) -> 1342.92 | AF90: 0.065 | AG90: =AE90*AF90 -> 87.2898 | AH90: =(AB90*J90)*$AH$1 -> 16.4934 | AI90: =AE90-AG90 -> 1255.6302 | AJ90: 0.18 | AK90: =AI90*AJ90 -> 226.01344 | AL90: =AI90+AK90 -> 1481.6436
A91: 46206 | B91: July | C91: 37158123 | D91: 53168.8 | E91: LHR | F91: General Store | G91: Kamal Store | H91: Salman | I91: Gullberg 2 | J91: 10 | N91: =K91+L91+M91 -> 0 | O91: 6 | Q91: 6 | R91: =SUM(O91:Q91) -> 12 | S91: =R91+N91+J91 -> 22 | AB91: 39.27 | AC91: 52.4625 | AD91: 72.64 | AE91: =(J91*AB91)+(N91*AC91)+(AD91*S91) -> 1990.78 | AF91: 0.065 | AG91: =AE91*AF91 -> 129.4007 | AH91: =(AB91*J91)*$AH$1 -> 13.7445 | AI91: =AE91-AG91 -> 1861.3793 | AJ91: 0.18 | AK91: =AI91*AJ91 -> 335.04827 | AL91: =AI91+AK91 -> 2196.4276
A92: 46206 | B92: July | C92: 37628042 | D92: 53834.5 | E92: LHR | F92: General Store | G92: Umair Store | H92: Salman | I92: Gullberg 2 | N92: =K92+L92+M92 -> 0 | O92: 13 | P92: 13 | Q92: 14 | R92: =SUM(O92:Q92) -> 40 | S92: =R92+N92+J92 -> 40 | AB92: 39.27 | AC92: 52.4625 | AD92: 72.64 | AE92: =(J92*AB92)+(N92*AC92)+(AD92*S92) -> 2905.6 | AF92: 0.065 | AG92: =AE92*AF92 -> 188.864 | AH92: =(AB92*J92)*$AH$1 -> 0 | AI92: =AE92-AG92 -> 2716.736 | AJ92: 0.18 | AK92: =AI92*AJ92 -> 489.01248 | AL92: =AI92+AK92 -> 3205.7485
A93: 46206 | B93: July | C93: 38097961 | D93: 54500.2 | E93: LHR | F93: Mart | G93: MS Mart | H93: Umair | I93: Shahdab Colony | J93: 40 | N93: =K93+L93+M93 -> 0 | O93: 15 | P93: 15 | Q93: 10 | R93: =SUM(O93:Q93) -> 40 | S93: =R93+N93+J93 -> 80 | AB93: 39.27 | AC93: 52.4625 | AD93: 72.64 | AE93: =(J93*AB93)+(N93*AC93)+(AD93*S93) -> 7382 | AF93: 0.14 | AG93: =AE93*AF93 -> 1033.48 | AH93: =(AB93*J93)*$AH$1 -> 54.978 | AI93: =AE93-AG93 -> 6348.52 | AJ93: 0.18 | AK93: =AI93*AJ93 -> 1142.7336 | AL93: =AI93+AK93 -> 7491.2536
A94: 46206 | B94: July | C94: 38567880 | D94: 55165.9 | E94: LHR | F94: General Store | G94: MF Chanda Store | H94: Umair | I94: Shahdab Colony | J94: 12 | N94: =K94+L94+M94 -> 0 | R94: =SUM(O94:Q94) -> 0 | S94: =R94+N94+J94 -> 12 | AB94: 39.27 | AC94: 52.4625 | AD94: 72.64 | AE94: =(J94*AB94)+(N94*AC94)+(AD94*S94) -> 1342.92 | AF94: 0.14 | AG94: =AE94*AF94 -> 188.0088 | AH94: =(AB94*J94)*$AH$1 -> 16.4934 | AI94: =AE94-AG94 -> 1154.9112 | AJ94: 0.18 | AK94: =AI94*AJ94 -> 207.88402 | AL94: =AI94+AK94 -> 1362.7952
A95: 46206 | B95: July | C95: 39037799 | D95: 55831.6 | E95: LHR | F95: General Store | G95: Bhati GS | H95: Umair | I95: Shahdab Colony | J95: 40 | K95: 20 | L95: 20 | N95: =K95+L95+M95 -> 40 | O95: 40 | P95: 40 | Q95: 40 | R95: =SUM(O95:Q95) -> 120 | S95: =R95+N95+J95 -> 200 | AB95: 39.27 | AC95: 52.4625 | AD95: 72.64 | AE95: =(J95*AB95)+(N95*AC95)+(AD95*S95) -> 18197.3 | AF95: 0.065 | AG95: =AE95*AF95 -> 1182.8245 | AH95: =(AB95*J95)*$AH$1 -> 54.978 | AI95: =AE95-AG95 -> 17014.476 | AJ95: 0.18 | AK95: =AI95*AJ95 -> 3062.6056 | AL95: =AI95+AK95 -> 20077.081
A96: 46206 | B96: July | C96: 39507718 | D96: 56497.3 | E96: LHR | F96: Mart | G96: Us Mart | H96: Umair | I96: Shahdab Colony | J96: 40 | N96: =K96+L96+M96 -> 0 | O96: 10 | P96: 10 | Q96: 20 | R96: =SUM(O96:Q96) -> 40 | S96: =R96+N96+J96 -> 80 | AB96: 39.27 | AC96: 52.4625 | AD96: 72.64 | AE96: =(J96*AB96)+(N96*AC96)+(AD96*S96) -> 7382 | AF96: 0.065 | AG96: =AE96*AF96 -> 479.83 | AH96: =(AB96*J96)*$AH$1 -> 54.978 | AI96: =AE96-AG96 -> 6902.17 | AJ96: 0.18 | AK96: =AI96*AJ96 -> 1242.3906 | AL96: =AI96+AK96 -> 8144.5606
A97: 46206 | B97: July | C97: 39977637 | D97: 57163 | E97: LHR | F97: General Store | G97: Shahdab Super Store | H97: Umair | I97: Shahdab Colony | J97: 400 | N97: =K97+L97+M97 -> 0 | O97: 80 | P97: 80 | Q97: 40 | R97: =SUM(O97:Q97) -> 200 | S97: =R97+N97+J97 -> 600 | AB97: 39.27 | AC97: 52.4625 | AD97: 72.64 | AE97: =(J97*AB97)+(N97*AC97)+(AD97*S97) -> 59292 | AF97: 0.065 | AG97: =AE97*AF97 -> 3853.98 | AH97: =(AB97*J97)*$AH$1 -> 549.78 | AI97: =AE97-AG97 -> 55438.02 | AJ97: 0.18 | AK97: =AI97*AJ97 -> 9978.8436 | AL97: =AI97+AK97 -> 65416.864
A98: 46206 | B98: July | C98: 40447557 | D98: 57828.7 | E98: LHR | F98: Mart | G98: Al Karam Smart Mart | H98: Umair | I98: Shahdab Colony | J98: 40 | N98: =K98+L98+M98 -> 0 | R98: =SUM(O98:Q98) -> 0 | S98: =R98+N98+J98 -> 40 | AB98: 39.27 | AC98: 52.4625 | AD98: 72.64 | AE98: =(J98*AB98)+(N98*AC98)+(AD98*S98) -> 4476.4 | AF98: 0.065 | AG98: =AE98*AF98 -> 290.966 | AH98: =(AB98*J98)*$AH$1 -> 54.978 | AI98: =AE98-AG98 -> 4185.434 | AJ98: 0.18 | AK98: =AI98*AJ98 -> 753.37812 | AL98: =AI98+AK98 -> 4938.8121
A99: 46206 | B99: July | C99: 40917476 | D99: 58494.4 | E99: LHR | F99: General Store | G99: Trust Store | H99: Zeshan | I99: DHA | J99: 10 | K99: 10 | N99: =K99+L99+M99 -> 10 | R99: =SUM(O99:Q99) -> 0 | S99: =R99+N99+J99 -> 20 | AB99: 39.27 | AC99: 52.4625 | AD99: 72.64 | AE99: =(J99*AB99)+(N99*AC99)+(AD99*S99) -> 2370.125 | AF99: 0.065 | AG99: =AE99*AF99 -> 154.05813 | AH99: =(AB99*J99)*$AH$1 -> 13.7445 | AI99: =AE99-AG99 -> 2216.0669 | AJ99: 0.18 | AK99: =AI99*AJ99 -> 398.89204 | AL99: =AI99+AK99 -> 2614.9589
A100: 46206 | B100: July | C100: 41387395 | D100: 59160.1 | E100: LHR | F100: General Store | G100: Bilal Store | H100: Zeshan | I100: DHA | N100: =K100+L100+M100 -> 0 | Q100: 10 | R100: =SUM(O100:Q100) -> 10 | S100: =R100+N100+J100 -> 10 | AB100: 39.27 | AC100: 52.4625 | AD100: 72.64 | AE100: =(J100*AB100)+(N100*AC100)+(AD100*S100) -> 726.4 | AF100: 0.065 | AG100: =AE100*AF100 -> 47.216 | AH100: =(AB100*J100)*$AH$1 -> 0 | AI100: =AE100-AG100 -> 679.184 | AJ100: 0.18 | AK100: =AI100*AJ100 -> 122.25312 | AL100: =AI100+AK100 -> 801.43712
...

Sheet Inventory
D4: STOCK REPORT
D5: Periode : 01 to 11July,2026
D6: SKU Name | E6: Opening Stock | F6: Stock In | G6: Stock Out | H6: Balance
D7: Indomie Chicken Chatkhara 120gm | E7: 273 | F7: 1047 | G7: ='STT Report'!Q864+'STT Report'!Z864 -> 913.5 | H7: =E7+F7-G7 -> 406.5
D8: Indomie Lemon Tarka 120gm | E8: 140 | F8: 203 | G8: ='STT Report'!P864+'STT Report'!Y864 -> 634.5 | H8: =E8+F8-G8 -> -291.5
D9: Indomie Meet Masala 120gm | E9: 178 | F9: 750 | G9: ='STT Report'!O864+'STT Report'!X864 -> 769.85 | H9: =E9+F9-G9 -> 158.15
D10: Sub Total | E10: =SUM(E7:E9) -> 591 | F10: =SUM(F7:F9) -> 2000 | G10: =SUM(G7:G9) -> 2317.85 | H10: =SUM(H7:H9) -> 273.15
D11: Indomie Chicken Chatkhara 60gm | E11: 1653 | G11: ='STT Report'!J864 -> 752.275 | H11: =(E11+F11)-G11 -> 900.725
H12: =(E12+F12)-G12 -> 0
H13: =(E13+F13)-G13 -> 0
D14: Sub Total | E14: =SUM(E11:E13) -> 1653 | F14: =SUM(F11:F13) -> 0 | G14: =SUM(G11:G13) -> 752.275 | H14: =SUM(H11:H13) -> 900.725
D15: Indomie Chicken Chatkhara 70gm | E15: 0 | G15: ='STT Report'!M864+'STT Report'!V864 -> 70 | H15: =E15+F15-G15 -> -70
D16: Indomie Lemon Tarka 70gm | E16: 267 | G16: ='STT Report'!L864+'STT Report'!U864 -> 401.675 | H16: =E16+F16-G16 -> -134.675
D17: Indomie Meet Masala 70gm | E17: 240 | G17: ='STT Report'!K864+'STT Report'!T864 -> 394.125 | H17: =E17+F17-G17 -> -154.125
D18: Sub Total | E18: =SUM(E15+E16+E17) -> 507 | F18: =SUM(F15:F17) -> 0 | G18: =SUM(G15:G17) -> 865.8 | H18: =SUM(H15:H17) -> -358.8
D19: Total | E19: =E10+E14+E18 -> 2751 | F19: =F10+F14+F18 -> 2000 | G19: =G10+G14+G18 -> 3935.925 | H19: =H10+H14+H18 -> 815.075
C23: SR NAME | D23: DISTRIBUTION NAME | E23: SR Target JUNE-2026 | F23: Totel CTN Order | G23: FOC 120g 20+1 | H23: FOC 70g10+1 | I23: Totel CTN 120g Sale | J23: Totel CTN 70g Sale | K23: Totel CTN 60g Sale | L23: Totel CTN Sale | M23: Achvid Target %
C24: Zeeshan Meharban | D24: ELITE MARKETING | E24: 500 | F24: =I24+J24+K24 -> 0 | G24: =I24/10 -> 0 | H24: =J24/10 -> 0 | L24: =I24+J24+G24+H24+K24 -> 0 | M24: =L24/E24 -> 0
C25: Salman Butt | D25: ELITE MARKETING | E25: 500 | F25: =I25+J25+K25 -> 0 | G25: =I25/10 -> 0 | H25: =J25/10 -> 0 | L25: =I25+J25+G25+H25+K25 -> 0 | M25: =L25/E25 -> 0
C26: Furqan Ali | D26: ELITE MARKETING | E26: 500 | F26: =I26+J26+K26 -> 0 | G26: =I26/10 -> 0 | H26: =J26/10 -> 0 | L26: =I26+J26+G26+H26+K26 -> 0 | M26: =L26/E26 -> 0
C27: Mobeen Ahmad | D27: ELITE MARKETING | E27: 500 | F27: =I27+J27+K27 -> 0 | G27: =I27/10 -> 0 | H27: =J27/10 -> 0 | L27: =I27+J27+G27+H27+K27 -> 0 | M27: =L27/E27 -> 0
C28: Umair Rehman | D28: ELITE MARKETING | E28: 500 | F28: =I28+J28+K28 -> 0 | G28: =I28/10 -> 0 | H28: =J28/10 -> 0 | L28: =I28+J28+G28+H28+K28 -> 0 | M28: =L28/E28 -> 0
C29: vacant | D29: ELITE MARKETING | E29: 500 | F29: =I29+J29+K29 -> 0 | G29: =I29/10 -> 0 | H29: =J29/10 -> 0 | L29: =I29+J29+G29+H29+K29 -> 0 | M29: =L29/E29 -> 0
C30: Shakoor (LMT) | D30: ELITE MARKETING | E30: 5000 | F30: =I30+J30+K30 -> 0 | G30: =I30/10 -> 0 | H30: =J30/10 -> 0 | L30: =I30+J30+G30+H30+K30 -> 0 | M30: =L30/E30 -> 0
C31: Total | E31: =SUM(E24:E30) -> 8000 | F31: =SUM(F24:F27) -> 0 | G31: =SUM(G24:G27) -> 0 | H31: =SUM(H24:H27) -> 0 | I31: =SUM(I24:I27) -> 0 | J31: =SUM(J24:J27) -> 0 | K31: =SUM(K24:K27) -> 0 | L31: =SUM(L24:L27) -> 0 | M31: =L31/E31 -> 0
