Workbook

Sheet Sheet2
B5: OB Name
A6: 1 | B6: Salman Butt
A7: 2 | B7: Qasim Khan
A8: 3 | B8: Mobeen Ahmad
A9: 4 | B9: Zahid Rafique
A10: 5 | B10: Zeeshan Meharban
A11: 6 | B11: Furqan
A12: 7 | B12: Rana Bilal Tso
A13: 8 | B13: Shakoor
A14: 9
A15: 10
A16: 11
A17: 12
A18: 13

Sheet Cust. Price List
V2: 0.18
A4: S# | B4: Code | D4: SKU | E4: SKUs Description | F4: Unit | H4: Retail Price | J4: TP Incl. | L4: TP Excl. | N4: Dist Margin | P4: Trade Offre | R4: Stale | T4: Ex-Fac | V4: S.Tax | X4: Dist. Price
B5: Bar | C5: SKU | F5: Gm | G5: CTN | H5: Ctn | I5: Pk | J5: Ctn | K5: Pk | L5: Ctn | M5: Pk | N5: 0.19 | O5: Amount | P5: 0.04 | Q5: Amount | R5: 0.005 | S5: Amount | T5: Ctn | U5: Pk | V5: Ctn | W5: Pk | X5: Ctn | Y5: Pk | AA5: Weight/ctn
A6: 1 | C6: BCN | D6: BCN | E6: Meat Masala | F6: 70 | G6: 40 | H6: =I6*G6 -> 2600 | I6: 65 | J6: =K6*G6 -> 2560.17 | K6: =M6*1.22 -> 64.00425 | L6: 2098.5 | M6: =L6/G6 -> 52.4625 | N6: 0.19 | O6: =N6*M6 -> 9.967875 | Q6: =P6*M6 -> 0 | S6: =R6*M6 -> 0 | T6: =U6*G6 -> 1699.785 | U6: =M6-O6-Q6-S6 -> 42.494625 | V6: =T6*$V$2 -> 305.9613 | W6: =U6*$V$2 -> 7.6490325 | X6: =T6+V6 -> 2005.7463 | Y6: =U6+W6 -> 50.143657 | AA6: =(F6*G6)/1000 -> 2.8
A7: =+A6+1 -> 2 | C7: VTN | D7: VTN | E7: Lemon Tarka | F7: 70 | G7: 40 | H7: =I7*G7 -> 2600 | I7: 65 | J7: =K7*G7 -> 2560.17 | K7: =M7*1.22 -> 64.00425 | L7: 2098.5 | M7: =L7/G7 -> 52.4625 | N7: =+N6 -> 0.19 | O7: =N7*M7 -> 9.967875 | Q7: =P7*M7 -> 0 | S7: =R7*M7 -> 0 | T7: =U7*G7 -> 1699.785 | U7: =M7-O7-Q7-S7 -> 42.494625 | V7: =T7*$V$2 -> 305.9613 | W7: =U7*$V$2 -> 7.6490325 | X7: =T7+V7 -> 2005.7463 | Y7: =U7+W7 -> 50.143657 | AA7: =(F7*G7)/1000 -> 2.8
A8: =+A7+1 -> 3 | C8: CCN | D8: CCN | E8: Chicken Chatkhara | F8: 70 | G8: 40 | H8: =I8*G8 -> 2600 | I8: 65 | J8: =K8*G8 -> 2560.17 | K8: =M8*1.22 -> 64.00425 | L8: 2098.5 | M8: =L8/G8 -> 52.4625 | N8: =+N7 -> 0.19 | O8: =N8*M8 -> 9.967875 | Q8: =P8*M8 -> 0 | S8: =R8*M8 -> 0 | T8: =U8*G8 -> 1699.785 | U8: =M8-O8-Q8-S8 -> 42.494625 | V8: =T8*$V$2 -> 305.9613 | W8: =U8*$V$2 -> 7.6490325 | X8: =T8+V8 -> 2005.7463 | Y8: =U8+W8 -> 50.143657 | AA8: =(F8*G8)/1000 -> 2.8
A9: =+A8+1 -> 4 | C9: BCNJ | D9: BCNJ | E9: Meat Masala (Jumbo) | F9: 120 | G9: 40 | H9: =I9*G9 -> 3600 | I9: 90 | J9: =K9*G9 -> 3544.832 | K9: =M9*1.22 -> 88.6208 | L9: 2905.6 | M9: =L9/G9 -> 72.64 | N9: =+N8 -> 0.19 | O9: =N9*M9 -> 13.8016 | Q9: =P9*M9 -> 0 | S9: =R9*M9 -> 0 | T9: =U9*G9 -> 2353.536 | U9: =M9-O9-Q9-S9 -> 58.8384 | V9: =T9*$V$2 -> 423.63648 | W9: =U9*$V$2 -> 10.590912 | X9: =T9+V9 -> 2777.1725 | Y9: =U9+W9 -> 69.429312 | AA9: =(F9*G9)/1000 -> 4.8
A10: =+A9+1 -> 5 | C10: VTNJ | D10: VTNJ | E10: Lemon Tarka (Jumbo) | F10: 120 | G10: 40 | H10: =I10*G10 -> 3600 | I10: 90 | J10: =K10*G10 -> 3544.832 | K10: =M10*1.22 -> 88.6208 | L10: 2905.6 | M10: =L10/G10 -> 72.64 | N10: =+N9 -> 0.19 | O10: =N10*M10 -> 13.8016 | Q10: =P10*M10 -> 0 | S10: =R10*M10 -> 0 | T10: =U10*G10 -> 2353.536 | U10: =M10-O10-Q10-S10 -> 58.8384 | V10: =T10*$V$2 -> 423.63648 | W10: =U10*$V$2 -> 10.590912 | X10: =T10+V10 -> 2777.1725 | Y10: =U10+W10 -> 69.429312 | AA10: =(F10*G10)/1000 -> 4.8
A11: =+A10+1 -> 6 | C11: CCNJ | D11: CCNJ | E11: Chicken Chatkhara (Jumbo) | F11: 120 | G11: 40 | H11: =I11*G11 -> 3600 | I11: 90 | J11: =K11*G11 -> 3544.832 | K11: =M11*1.22 -> 88.6208 | L11: 2905.6 | M11: =L11/G11 -> 72.64 | N11: =+N10 -> 0.19 | O11: =N11*M11 -> 13.8016 | Q11: =P11*M11 -> 0 | S11: =R11*M11 -> 0 | T11: =U11*G11 -> 2353.536 | U11: =M11-O11-Q11-S11 -> 58.8384 | V11: =T11*$V$2 -> 423.63648 | W11: =U11*$V$2 -> 10.590912 | X11: =T11+V11 -> 2777.1725 | Y11: =U11+W11 -> 69.429312 | AA11: =(F11*G11)/1000 -> 4.8
A12: =+A11+1 -> 7 | C12: CCE | D12: CCE | E12: Chicken Chatkhara (ECO) | F12: 60 | G12: 40 | H12: =I12*G12 -> 2000 | I12: 50 | J12: =K12*G12 -> 1914.424 | K12: =M12*1.22 -> 47.8606 | L12: 1569.2 | M12: =L12/G12 -> 39.23 | N12: =+N11 -> 0.19 | O12: =N12*M12 -> 7.4537 | Q12: =P12*M12 -> 0 | S12: =R12*M12 -> 0 | T12: =U12*G12 -> 1271.052 | U12: =M12-O12-Q12-S12 -> 31.7763 | V12: =T12*$V$2 -> 228.78936 | W12: =U12*$V$2 -> 5.719734 | X12: =T12+V12 -> 1499.8414 | Y12: =U12+W12 -> 37.496034 | AA12: =(F12*G12)/1000 -> 2.4
A13: =+A12+1 -> 8 | C13: VTE | D13: VTE | E13: Lemon Tarka (ECO) | F13: 60 | G13: 40 | H13: =I13*G13 -> 2000 | I13: 50 | J13: =K13*G13 -> 1914.424 | K13: =M13*1.22 -> 47.8606 | L13: 1569.2 | M13: =L13/G13 -> 39.23 | N13: =+N12 -> 0.19 | O13: =N13*M13 -> 7.4537 | Q13: =P13*M13 -> 0 | S13: =R13*M13 -> 0 | T13: =U13*G13 -> 1271.052 | U13: =M13-O13-Q13-S13 -> 31.7763 | V13: =T13*$V$2 -> 228.78936 | W13: =U13*$V$2 -> 5.719734 | X13: =T13+V13 -> 1499.8414 | Y13: =U13+W13 -> 37.496034 | AA13: =(F13*G13)/1000 -> 2.4
A14: =+A13+1 -> 9 | C14: BCE | D14: BCE | E14: Meat Masala (ECO) | F14: 60 | G14: 40 | H14: =I14*G14 -> 2000 | I14: 50 | J14: =K14*G14 -> 1914.424 | K14: =M14*1.22 -> 47.8606 | L14: 1569.2 | M14: =L14/G14 -> 39.23 | N14: =+N13 -> 0.19 | O14: =N14*M14 -> 7.4537 | Q14: =P14*M14 -> 0 | S14: =R14*M14 -> 0 | T14: =U14*G14 -> 1271.052 | U14: =M14-O14-Q14-S14 -> 31.7763 | V14: =T14*$V$2 -> 228.78936 | W14: =U14*$V$2 -> 5.719734 | X14: =T14+V14 -> 1499.8414 | Y14: =U14+W14 -> 37.496034 | AA14: =(F14*G14)/1000 -> 2.4
A15: =+A14+1 -> 10
A16: =+A15+1 -> 11
A17: =+A16+1 -> 12
A18: =+A17+1 -> 13
A19: =+A18+1 -> 14
A20: =+A19+1 -> 15
A22: =+A20+1 -> 16
A23: =+A22+1 -> 17
A24: =+A23+1 -> 18
A25: =+A24+1 -> 19
A26: =+A25+1 -> 20
A27: =+A26+1 -> 21
A28: =+A27+1 -> 22
A29: =+A28+1 -> 23
A30: =+A29+1 -> 24
A31: =+A30+1 -> 25
A32: =+A31+1 -> 26
A33: =+A32+1 -> 27
A34: =+A33+1 -> 28
A36: =+A34+1 -> 29
A37: =+A36+1 -> 30
A38: =+A37+1 -> 31
A39: =+A38+1 -> 32
A40: =+A39+1 -> 33
A41: =+A40+1 -> 34
A42: =+A41+1 -> 35
A43: =+A42+1 -> 36
A44: =+A43+1 -> 37
A45: =+A44+1 -> 38
A47: =+A45+1 -> 39
A48: =+A47+1 -> 40
A50: =+A48+1 -> 41
A51: =+A50+1 -> 42
A52: =+A51+1 -> 43
A54: =+A52+1 -> 44
A55: =+A54+1 -> 45
A56: =+A55+1 -> 46
A57: =+A56+1 -> 47
A58: =+A57+1 -> 48
A60: =+A58+1 -> 49
A61: =+A60+1 -> 50
A62: =+A61+1 -> 51
A63: =+A62+1 -> 52
A64: =+A63+1 -> 53
A65: =+A64+1 -> 54
A66: =+A65+1 -> 55
A68: =+A66+1 -> 56
A69: =+A68+1 -> 57
A70: =+A69+1 -> 58

Sheet Format
A2: Elite MARKETING
A3: 44A- Gulberg Lahore | K3: Invoice No # : | N3: 1 | XFC3: Filer | XFD3: 0.005
A4: STRN / NTN :3808207-1 | K4: Date/Day : | N4: =TODAY() -> 46219 | XFC4: Non-filer | XFD4: 0.025
A5: Vacant_01 | K5: Order Date : | N5: =N4-1 -> 46218
K6: Order Name : | N6: Salman Aslam | XFC6: Registered | XFD6: 0.18
XFC7: Un-registered | XFD7: 0.22
XFD9: Yes
K10: Invoice Status : | N10: Serviced | XFD10: No
K11: Order at Original Location : | N11: Yes
K12: Reference Invoice : | T12: Shop Bill Summary (Vacant_01) | XFD12: Monday/Tuesday
L13: 0.05 | XFD13: Tuesday / Wednesday
A14: Product Code/Description | C14: GM/ Pack | D14: CTN | E14: R.P Per | F14: T.P Per | G14: Sale QTY | I14: Gross Amount Excl. Taxes | J14: Trade Offer & Discount | M14: After Discount Amount | N14: GST | O14: Adv. Tax 236H | P14: Invoice | T14: =+'1'!A5 -> Customer Name : Jalal Sons Izmir Town | U14: =+'1'!P35 -> 12481.297 | XFD14: Wednesday/Thursday
D15: SIZE | E15: Unit | F15: Unit | G15: CTN | H15: Pack | J15: FOC Qty | K15: Trade Offer | L15: Pass On | N15: =IF(B12="Registered",18%,22%) -> 0.22 | O15: =IF(B11="Filer",0.5%,2.5%) -> 0.025 | P15: Amount | T15: =+'2'!A5 -> Customer Name : Jalal Sons Izmir Town | U15: =+'2'!P35 -> 0 | XFD15: Thursday /Friday
A16: BCN | B16: =VLOOKUP($A16,'[1]Cust. Price List'!$D$6:$O$14,2,0) -> Meat Masala | C16: =VLOOKUP(A16,'[1]Cust. Price List'!D6:M14,3,0) -> 70 | D16: =VLOOKUP(A16,'[1]Cust. Price List'!D6:M14,4,0) -> 40 | E16: =VLOOKUP(A16,'[1]Cust. Price List'!D6:M14,6,0) -> 65 | F16: =VLOOKUP(A16,'[1]Cust. Price List'!D6:M14,10,0) -> 52.4625 | H16: =+'1'!H16+'2'!H16+'4'!H16+'3'!H16+'5'!H16+'6'!H16+'7'!H16+'8'!H16+'9'!H16+'10'!H16+'11'!H16+'12'!H16+'13'!H16+'14'!H16+'15'!H16+'16'!H16 -> 40 | I16: =(G16*D16)*F16+H16*F16 -> 2098.5 | J16: =+'1'!J16+'2'!J16+'4'!J16+'3'!J16+'5'!J16+'6'!J16+'7'!J16+'8'!J16+'9'!J16+'10'!J16+'11'!J16+'12'!J16+'13'!J16+'14'!J16+'15'!J16+'16'!J16+'17'!J16+'18'!J16 -> 0 | K16: =+'1'!K16+'2'!K16+'4'!K16+'3'!K16+'5'!K16+'6'!K16+'7'!K16+'8'!K16+'9'!K16+'10'!K16 -> 73.4475 | L16: =+'1'!L16+'2'!L16+'4'!L16+'3'!L16+'5'!L16+'6'!L16+'7'!L16+'8'!L16+'9'!L16+'10'!L16 -> 314.775 | M16: =I16-K16-L16 -> 1710.2775 | N16: =+'1'!N16+'2'!N16+'4'!N16+'3'!N16+'5'!N16+'6'!N16+'7'!N16+'8'!N16+'9'!N16+'10'!N16 -> 307.84995 | O16: =+'1'!O16+'2'!O16+'4'!O16+'3'!O16+'5'!O16+'6'!O16+'7'!O16+'8'!O16+'9'!O16+'10'!O16 -> 10.090637 | P16: =M16+N16+O16 -> 2028.2181 | T16: =+'4'!A5 -> Customer Name : Jalal Sons Izmir Town | U16: =+'4'!P35 -> 0 | XFD16: Friday / Saturday
A17: VTN | B17: =VLOOKUP($A17,'[1]Cust. Price List'!$D$6:$O$14,2,0) -> Lemon Tarka | C17: =VLOOKUP(B17,'[1]Cust. Price List'!E7:P15,2,0) -> 70 | D17: =VLOOKUP(A17,'[1]Cust. Price List'!D7:M15,4,0) -> 40 | E17: =VLOOKUP(A17,'[1]Cust. Price List'!D7:M15,6,0) -> 65 | F17: =VLOOKUP(A17,'[1]Cust. Price List'!D7:M15,10,0) -> 52.4625 | H17: =+'1'!H17+'2'!H17+'4'!H17+'3'!H17+'5'!H17+'6'!H17+'7'!H17+'8'!H17+'9'!H17+'10'!H17+'11'!H17+'12'!H17+'13'!H17+'14'!H17+'15'!H17+'16'!H17 -> 40 | I17: =(G17*D17)*F17+H17*F17 -> 2098.5 | J17: =+'1'!J17+'2'!J17+'4'!J17+'3'!J17+'5'!J17+'6'!J17+'7'!J17+'8'!J17+'9'!J17+'10'!J17+'11'!J17+'12'!J17+'13'!J17+'14'!J17+'15'!J17+'16'!J17+'17'!J17+'18'!J17 -> 0 | K17: =+'1'!K17+'2'!K17+'4'!K17+'3'!K17+'5'!K17+'6'!K17+'7'!K17+'8'!K17+'9'!K17+'10'!K17 -> 73.4475 | L17: =+'1'!L17+'2'!L17+'4'!L17+'3'!L17+'5'!L17+'6'!L17+'7'!L17+'8'!L17+'9'!L17+'10'!L17 -> 314.775 | M17: =I17-K17-L17 -> 1710.2775 | N17: =+'1'!N17+'2'!N17+'4'!N17+'3'!N17+'5'!N17+'6'!N17+'7'!N17+'8'!N17+'9'!N17+'10'!N17 -> 307.84995 | O17: =+'1'!O17+'2'!O17+'4'!O17+'3'!O17+'5'!O17+'6'!O17+'7'!O17+'8'!O17+'9'!O17+'10'!O17 -> 10.090637 | P17: =M17+N17+O17 -> 2028.2181 | T17: =+'3'!A5 -> Customer Name : Jalal Sons Izmir Town | U17: =+'3'!P35 -> 0 | XFD17: Saturday /Monday
A18: CCN | B18: =VLOOKUP($A18,'[1]Cust. Price List'!$D$6:$O$14,2,0) -> Chicken Chatkhara | C18: =VLOOKUP(B18,'[1]Cust. Price List'!E8:P16,2,0) -> 70 | D18: =VLOOKUP(A18,'[1]Cust. Price List'!D8:M16,4,0) -> 40 | E18: =VLOOKUP(A18,'[1]Cust. Price List'!D8:M16,6,0) -> 65 | F18: =VLOOKUP(A18,'[1]Cust. Price List'!D8:M16,10,0) -> 52.4625 | H18: =+'1'!H18+'2'!H18+'4'!H18+'3'!H18+'5'!H18+'6'!H18+'7'!H18+'8'!H18+'9'!H18+'10'!H18+'11'!H18+'12'!H18+'13'!H18+'14'!H18+'15'!H18+'16'!H18 -> 0 | I18: =(G18*D18)*F18+H18*F18 -> 0 | J18: =+'1'!J18+'2'!J18+'4'!J18+'3'!J18+'5'!J18+'6'!J18+'7'!J18+'8'!J18+'9'!J18+'10'!J18+'11'!J18+'12'!J18+'13'!J18+'14'!J18+'15'!J18+'16'!J18+'17'!J18+'18'!J18 -> 0 | K18: =+'1'!K18+'2'!K18+'4'!K18+'3'!K18+'5'!K18+'6'!K18+'7'!K18+'8'!K18+'9'!K18+'10'!K18 -> 0 | L18: =+'1'!L18+'2'!L18+'4'!L18+'3'!L18+'5'!L18+'6'!L18+'7'!L18+'8'!L18+'9'!L18+'10'!L18 -> 0 | M18: =I18-K18-L18 -> 0 | N18: =+'1'!N18+'2'!N18+'4'!N18+'3'!N18+'5'!N18+'6'!N18+'7'!N18+'8'!N18+'9'!N18+'10'!N18 -> 0 | O18: =+'1'!O18+'2'!O18+'4'!O18+'3'!O18+'5'!O18+'6'!O18+'7'!O18+'8'!O18+'9'!O18+'10'!O18 -> 0 | P18: =M18+N18+O18 -> 0 | T18: =+'5'!A5 -> Customer Name : Jalal Sons Izmir Town | U18: =+'5'!P35 -> 0
A19: BCNJ | B19: =VLOOKUP($A19,'[1]Cust. Price List'!$D$6:$O$14,2,0) -> Meat Masala (Jumbo) | C19: =VLOOKUP(B19,'[1]Cust. Price List'!E9:P17,2,0) -> 120 | D19: =VLOOKUP(A19,'[1]Cust. Price List'!D9:M17,4,0) -> 40 | E19: =VLOOKUP(A19,'[1]Cust. Price List'!D9:M17,6,0) -> 90 | F19: =VLOOKUP(A19,'[1]Cust. Price List'!D9:M17,10,0) -> 72.64 | H19: =+'1'!H19+'2'!H19+'4'!H19+'3'!H19+'5'!H19+'6'!H19+'7'!H19+'8'!H19+'9'!H19+'10'!H19+'11'!H19+'12'!H19+'13'!H19+'14'!H19+'15'!H19+'16'!H19 -> 40 | I19: =(G19*D19)*F19+H19*F19 -> 2905.6 | J19: =+'1'!J19+'2'!J19+'4'!J19+'3'!J19+'5'!J19+'6'!J19+'7'!J19+'8'!J19+'9'!J19+'10'!J19+'11'!J19+'12'!J19+'13'!J19+'14'!J19+'15'!J19+'16'!J19+'17'!J19+'18'!J19 -> 0 | K19: =+'1'!K19+'2'!K19+'4'!K19+'3'!K19+'5'!K19+'6'!K19+'7'!K19+'8'!K19+'9'!K19+'10'!K19 -> 101.696 | L19: =+'1'!L19+'2'!L19+'4'!L19+'3'!L19+'5'!L19+'6'!L19+'7'!L19+'8'!L19+'9'!L19+'10'!L19 -> 435.84 | M19: =I19-K19-L19 -> 2368.064 | N19: =+'1'!N19+'2'!N19+'4'!N19+'3'!N19+'5'!N19+'6'!N19+'7'!N19+'8'!N19+'9'!N19+'10'!N19 -> 426.25152 | O19: =+'1'!O19+'2'!O19+'4'!O19+'3'!O19+'5'!O19+'6'!O19+'7'!O19+'8'!O19+'9'!O19+'10'!O19 -> 13.971578 | P19: =M19+N19+O19 -> 2808.2871 | T19: =+'6'!A5 -> Customer Name : Jalal Sons Izmir Town | U19: =+'6'!P35 -> 0
A20: VTNJ | B20: =VLOOKUP($A20,'[1]Cust. Price List'!$D$6:$O$14,2,0) -> Lemon Tarka (Jumbo) | C20: =VLOOKUP(B20,'[1]Cust. Price List'!E10:P18,2,0) -> 120 | D20: =VLOOKUP(A20,'[1]Cust. Price List'!D10:M18,4,0) -> 40 | E20: =VLOOKUP(A20,'[1]Cust. Price List'!D10:M18,6,0) -> 90 | F20: =VLOOKUP(A20,'[1]Cust. Price List'!D10:M18,10,0) -> 72.64 | H20: =+'1'!H20+'2'!H20+'4'!H20+'3'!H20+'5'!H20+'6'!H20+'7'!H20+'8'!H20+'9'!H20+'10'!H20+'11'!H20+'12'!H20+'13'!H20+'14'!H20+'15'!H20+'16'!H20 -> 40 | I20: =(G20*D20)*F20+H20*F20 -> 2905.6 | J20: =+'1'!J20+'2'!J20+'4'!J20+'3'!J20+'5'!J20+'6'!J20+'7'!J20+'8'!J20+'9'!J20+'10'!J20+'11'!J20+'12'!J20+'13'!J20+'14'!J20+'15'!J20+'16'!J20+'17'!J20+'18'!J20 -> 0 | K20: =+'1'!K20+'2'!K20+'4'!K20+'3'!K20+'5'!K20+'6'!K20+'7'!K20+'8'!K20+'9'!K20+'10'!K20 -> 101.696 | L20: =+'1'!L20+'2'!L20+'4'!L20+'3'!L20+'5'!L20+'6'!L20+'7'!L20+'8'!L20+'9'!L20+'10'!L20 -> 435.84 | M20: =I20-K20-L20 -> 2368.064 | N20: =+'1'!N20+'2'!N20+'4'!N20+'3'!N20+'5'!N20+'6'!N20+'7'!N20+'8'!N20+'9'!N20+'10'!N20 -> 426.25152 | O20: =+'1'!O20+'2'!O20+'4'!O20+'3'!O20+'5'!O20+'6'!O20+'7'!O20+'8'!O20+'9'!O20+'10'!O20 -> 13.971578 | P20: =M20+N20+O20 -> 2808.2871 | T20: =+'7'!A5 -> Customer Name : Jalal Sons Izmir Town | U20: =+'7'!P35 -> 0
A21: CCNJ | B21: =VLOOKUP($A21,'[1]Cust. Price List'!$D$6:$O$14,2,0) -> Chicken Chatkhara (Jumbo) | C21: =VLOOKUP(B21,'[1]Cust. Price List'!E11:P19,2,0) -> 120 | D21: =VLOOKUP(A21,'[1]Cust. Price List'!D11:M19,4,0) -> 40 | E21: =VLOOKUP(A21,'[1]Cust. Price List'!D11:M19,6,0) -> 90 | F21: =VLOOKUP(A21,'[1]Cust. Price List'!D11:M19,10,0) -> 72.64 | H21: =+'1'!H21+'2'!H21+'4'!H21+'3'!H21+'5'!H21+'6'!H21+'7'!H21+'8'!H21+'9'!H21+'10'!H21+'11'!H21+'12'!H21+'13'!H21+'14'!H21+'15'!H21+'16'!H21 -> 40 | I21: =(G21*D21)*F21+H21*F21 -> 2905.6 | J21: =+'1'!J21+'2'!J21+'4'!J21+'3'!J21+'5'!J21+'6'!J21+'7'!J21+'8'!J21+'9'!J21+'10'!J21+'11'!J21+'12'!J21+'13'!J21+'14'!J21+'15'!J21+'16'!J21+'17'!J21+'18'!J21 -> 0 | K21: =+'1'!K21+'2'!K21+'4'!K21+'3'!K21+'5'!K21+'6'!K21+'7'!K21+'8'!K21+'9'!K21+'10'!K21 -> 101.696 | L21: =+'1'!L21+'2'!L21+'4'!L21+'3'!L21+'5'!L21+'6'!L21+'7'!L21+'8'!L21+'9'!L21+'10'!L21 -> 435.84 | M21: =I21-K21-L21 -> 2368.064 | N21: =+'1'!N21+'2'!N21+'4'!N21+'3'!N21+'5'!N21+'6'!N21+'7'!N21+'8'!N21+'9'!N21+'10'!N21 -> 426.25152 | O21: =+'1'!O21+'2'!O21+'4'!O21+'3'!O21+'5'!O21+'6'!O21+'7'!O21+'8'!O21+'9'!O21+'10'!O21 -> 13.971578 | P21: =M21+N21+O21 -> 2808.2871 | T21: =+'8'!A5 -> Customer Name : Jalal Sons Izmir Town | U21: =+'8'!P35 -> 0
A22: CCE | B22: =VLOOKUP($A22,'[1]Cust. Price List'!$D$6:$O$14,2,0) -> Chicken Chatkhara (ECO) | C22: =VLOOKUP(B22,'[1]Cust. Price List'!E12:P20,2,0) -> 60 | D22: =VLOOKUP(A22,'[1]Cust. Price List'!D12:M20,4,0) -> 40 | E22: =VLOOKUP(A22,'[1]Cust. Price List'!D12:M20,6,0) -> 50 | F22: =VLOOKUP(A22,'[1]Cust. Price List'!D12:M20,10,0) -> 39.23 | H22: =+'1'!H22+'2'!H22+'4'!H22+'3'!H22+'5'!H22+'6'!H22+'7'!H22+'8'!H22+'9'!H22+'10'!H22+'11'!H22+'12'!H22+'13'!H22+'14'!H22+'15'!H22+'16'!H22 -> 0 | I22: =(G22*D22)*F22+H22*F22 -> 0 | J22: =+'1'!J22+'2'!J22+'4'!J22+'3'!J22+'5'!J22+'6'!J22+'7'!J22+'8'!J22+'9'!J22+'10'!J22+'11'!J22+'12'!J22+'13'!J22+'14'!J22+'15'!J22+'16'!J22+'17'!J22+'18'!J22 -> 0 | K22: =+'1'!K22+'2'!K22+'4'!K22+'3'!K22+'5'!K22+'6'!K22+'7'!K22+'8'!K22+'9'!K22+'10'!K22 -> 0 | L22: =+'1'!L22+'2'!L22+'4'!L22+'3'!L22+'5'!L22+'6'!L22+'7'!L22+'8'!L22+'9'!L22+'10'!L22 -> 0 | M22: =I22-K22-L22 -> 0 | N22: =+'1'!N22+'2'!N22+'4'!N22+'3'!N22+'5'!N22+'6'!N22+'7'!N22+'8'!N22+'9'!N22+'10'!N22 -> 0 | O22: =+'1'!O22+'2'!O22+'4'!O22+'3'!O22+'5'!O22+'6'!O22+'7'!O22+'8'!O22+'9'!O22+'10'!O22 -> 0 | P22: =M22+N22+O22 -> 0 | T22: =+'9'!A5 -> Customer Name : Jalal Sons Izmir Town | U22: =+'9'!P35 -> 0
A23: VTE | B23: =VLOOKUP($A23,'[1]Cust. Price List'!$D$6:$O$14,2,0) -> Lemon Tarka (ECO) | C23: =VLOOKUP(B23,'[1]Cust. Price List'!E13:P21,2,0) -> 60 | D23: =VLOOKUP(A23,'[1]Cust. Price List'!D13:M21,4,0) -> 40 | E23: =VLOOKUP(A23,'[1]Cust. Price List'!D13:M21,6,0) -> 50 | F23: =VLOOKUP(A23,'[1]Cust. Price List'!D13:M21,10,0) -> 39.23 | H23: =+'1'!H23+'2'!H23+'4'!H23+'3'!H23+'5'!H23+'6'!H23+'7'!H23+'8'!H23+'9'!H23+'10'!H23+'11'!H23+'12'!H23+'13'!H23+'14'!H23+'15'!H23+'16'!H23 -> 0 | I23: =(G23*D23)*F23+H23*F23 -> 0 | J23: =+'1'!J23+'2'!J23+'4'!J23+'3'!J23+'5'!J23+'6'!J23+'7'!J23+'8'!J23+'9'!J23+'10'!J23+'11'!J23+'12'!J23+'13'!J23+'14'!J23+'15'!J23+'16'!J23+'17'!J23+'18'!J23 -> 0 | K23: =+'1'!K23+'2'!K23+'4'!K23+'3'!K23+'5'!K23+'6'!K23+'7'!K23+'8'!K23+'9'!K23+'10'!K23 -> 0 | L23: =+'1'!L23+'2'!L23+'4'!L23+'3'!L23+'5'!L23+'6'!L23+'7'!L23+'8'!L23+'9'!L23+'10'!L23 -> 0 | M23: =I23-K23-L23 -> 0 | N23: =+'1'!N23+'2'!N23+'4'!N23+'3'!N23+'5'!N23+'6'!N23+'7'!N23+'8'!N23+'9'!N23+'10'!N23 -> 0 | O23: =+'1'!O23+'2'!O23+'4'!O23+'3'!O23+'5'!O23+'6'!O23+'7'!O23+'8'!O23+'9'!O23+'10'!O23 -> 0 | P23: =M23+N23+O23 -> 0 | T23: =+'10'!A5 -> Customer Name : Jalal Sons Izmir Town | U23: =+'10'!P35 -> 0
A24: BCE | B24: =VLOOKUP($A24,'[1]Cust. Price List'!$D$6:$O$14,2,0) -> Meat Masala (ECO) | C24: =VLOOKUP(B24,'[1]Cust. Price List'!E14:P22,2,0) -> 60 | D24: =VLOOKUP(A24,'[1]Cust. Price List'!D14:M22,4,0) -> 40 | E24: =VLOOKUP(A24,'[1]Cust. Price List'!D14:M22,6,0) -> 50 | F24: =VLOOKUP(A24,'[1]Cust. Price List'!D14:M22,10,0) -> 39.23 | H24: =+'1'!H24+'2'!H24+'4'!H24+'3'!H24+'5'!H24+'6'!H24+'7'!H24+'8'!H24+'9'!H24+'10'!H24+'11'!H24+'12'!H24+'13'!H24+'14'!H24+'15'!H24+'16'!H24 -> 0 | I24: =(G24*D24)*F24+H24*F24 -> 0 | J24: =+'1'!J24+'2'!J24+'4'!J24+'3'!J24+'5'!J24+'6'!J24+'7'!J24+'8'!J24+'9'!J24+'10'!J24+'11'!J24+'12'!J24+'13'!J24+'14'!J24+'15'!J24+'16'!J24+'17'!J24+'18'!J24 -> 0 | K24: =+'1'!K24+'2'!K24+'4'!K24+'3'!K24+'5'!K24+'6'!K24+'7'!K24+'8'!K24+'9'!K24+'10'!K24 -> 0 | L24: =+'1'!L24+'2'!L24+'4'!L24+'3'!L24+'5'!L24+'6'!L24+'7'!L24+'8'!L24+'9'!L24+'10'!L24 -> 0 | M24: =I24-K24-L24 -> 0 | N24: =+'1'!N24+'2'!N24+'4'!N24+'3'!N24+'5'!N24+'6'!N24+'7'!N24+'8'!N24+'9'!N24+'10'!N24 -> 0 | O24: =+'1'!O24+'2'!O24+'4'!O24+'3'!O24+'5'!O24+'6'!O24+'7'!O24+'8'!O24+'9'!O24+'10'!O24 -> 0 | P24: =M24+N24+O24 -> 0 | T24: =+'11'!A5 -> Customer Name : Jalal Sons Izmir Town | U24: =+'11'!P35 -> 0
A25: Total | C25: =H25/40 -> 5 | G25: =SUM(G16:G24) -> 0 | H25: =SUM(H16:H24) -> 200 | I25: =SUM(I16:I24) -> 12913.8 | J25: =SUM(J16:J24) -> 0 | K25: =SUM(K16:K24) -> 451.983 | L25: =SUM(L16:L24) -> 1937.07 | M25: =SUM(M16:M24) -> 10524.747 | N25: =SUM(N16:N24) -> 1894.4545 | ... P25: =SUM(P16:P24) -> 12481.297 | T25: =+'12'!A5 -> Customer Name : Jalal Sons Izmir Town | U25: =+'12'!P35 -> 0
T26: =+'13'!A5 -> Customer Name : Jalal Sons Izmir Town | U26: =+'13'!P35 -> 0
T27: =+'14'!A5 -> Customer Name : Jalal Sons Izmir Town | U27: =+'14'!P35 -> 0
T28: =+'15'!A5 -> Customer Name : Jalal Sons Izmir Town | U28: =+'15'!P35 -> 0
T30: Total | U30: =SUM(U14:U28) -> 12481.297
B32: یکم جولائی 2024سے نئی ٹیکس ترمیم کے مطابق، ایف بی آر سیکشن 236 ایچ کے مطابق، فائلرز کے لیے ہر سیل انوائس پر 0.5% اور نان فائلرز کے لیے 2.5% ایڈوانس ود ہولڈنگ ٹیکس وصول کیا جائے گا۔ | N32: Gross Amount: | P32: =I25 -> 12913.8
N33: Regular Discount | P33: =L25 -> 1937.07
N34: Trade Offre | P34: =K25 -> 451.983
N35: After Dis. Amount | P35: =P32-P33-P34 -> 10524.747
N36: Total GST: | O36: =IF(B12="Registered",18%,22%) -> 0.22 | P36: =N25 -> 1894.4545
N37: Net Amount: | P37: =P35+P36 -> 12419.201
N38: Ad.Tax | O38: =IF(B11="Filer",0.5%,2.5%) -> 0.025 | P38: =O38*P37 -> 310.48004
N39: Net Amount with Ad.Tax | P39: =P37+P38 -> 12729.681
B40: Delivered By

Sheet 1
A1: pr
A2: Elite MARKETING
A3: 44A- Gulberg Lahore | K3: Invoice No # : | N3: 1001 | XFC3: Filer | XFD3: 0.005
A4: STRN / NTN :3808207-1 | K4: Date/Day : | N4: 46213 | XFC4: Non-filer | XFD4: 0.025
A5: Customer Name : Jalal Sons Izmir Town | K5: Order Date : | N5: 46212
A6: Address: Izmir Town Canal | K6: Order Name : | N6: Shakoor | XFC6: Registered | XFD6: 0.18
XFC7: Un-registered | XFD7: 0.22
XFD9: Yes
A10: NTN/CNIC Number: | B10: 1010737-1 | K10: Invoice Status : | N10: Serviced | XFD10: No
B11: Filer | C11: =IF($O34>2.49%,"No","Yes") -> Yes | K11: Order at Original Location : | N11: Yes
A12: STRN Number: | B12: Registered | C12: =IF($O32>21.99%,"No","Yes") -> Yes | K12: Reference Invoice : | XFD12: Monday/Tuesday
B13: 3520255124113 | L13: 0.05 | XFD13: Tuesday / Wednesday
A14: Product Code/Description | C14: GM/ Pack | D14: CTN | E14: R.P Per | F14: T.P Per | G14: Sale QTY | I14: Gross Amount Excl. Taxes | J14: Trade Offer & Discount | M14: After Discount Amount | N14: GST | O14: Adv. Tax 236H | P14: Invoice | XFD14: Wednesday/Thursday
D15: SIZE | E15: Unit | F15: Unit | G15: CTN | H15: Pack | J15: FOC Qty | K15: Trade Offer | L15: 0.15 | N15: =IF(B12="Registered",18%,22%) -> 0.18 | O15: =IF(B11="Filer",0.5%,2.5%) -> 0.005 | P15: Amount | XFD15: Thursday /Friday
A16: BCN | B16: =VLOOKUP($A16,'[1]Cust. Price List'!$D$6:$O$14,2,0) -> Meat Masala | C16: =VLOOKUP(A16,'[1]Cust. Price List'!D6:M14,3,0) -> 70 | D16: =VLOOKUP(A16,'[1]Cust. Price List'!D6:M14,4,0) -> 40 | E16: =VLOOKUP(A16,'[1]Cust. Price List'!D6:M14,6,0) -> 65 | F16: =VLOOKUP(A16,'[1]Cust. Price List'!D6:M14,10,0) -> 52.4625 | H16: 40 | I16: =(G16*D16)*F16+H16*F16 -> 2098.5 | K16: =I16*3.5% -> 73.4475 | L16: =I16*15% -> 314.775 | M16: =I16-K16-L16 -> 1710.2775 | N16: =(M16*$N$15)+(J16*F16)*$N$15 -> 307.84995 | O16: =(N16+M16)*$O$15 -> 10.090637 | P16: =M16+N16+O16 -> 2028.2181 | XFD16: Friday / Saturday
A17: VTN | B17: =VLOOKUP($A17,'[1]Cust. Price List'!$D$6:$O$14,2,0) -> Lemon Tarka | C17: =VLOOKUP(B17,'[1]Cust. Price List'!E7:P15,2,0) -> 70 | D17: =VLOOKUP(A17,'[1]Cust. Price List'!D7:M15,4,0) -> 40 | E17: =VLOOKUP(A17,'[1]Cust. Price List'!D7:M15,6,0) -> 65 | F17: =VLOOKUP(A17,'[1]Cust. Price List'!D7:M15,10,0) -> 52.4625 | H17: 40 | I17: =(G17*D17)*F17+H17*F17 -> 2098.5 | K17: =I17*3.5% -> 73.4475 | L17: =I17*15% -> 314.775 | M17: =I17-K17-L17 -> 1710.2775 | N17: =(M17*$N$15)+(J17*F17)*$N$15 -> 307.84995 | O17: =(N17+M17)*$O$15 -> 10.090637 | P17: =M17+N17+O17 -> 2028.2181 | XFD17: Saturday /Monday
A18: CCN | B18: =VLOOKUP($A18,'[1]Cust. Price List'!$D$6:$O$14,2,0) -> Chicken Chatkhara | C18: =VLOOKUP(B18,'[1]Cust. Price List'!E8:P16,2,0) -> 70 | D18: =VLOOKUP(A18,'[1]Cust. Price List'!D8:M16,4,0) -> 40 | E18: =VLOOKUP(A18,'[1]Cust. Price List'!D8:M16,6,0) -> 65 | F18: =VLOOKUP(A18,'[1]Cust. Price List'!D8:M16,10,0) -> 52.4625 | I18: =(G18*D18)*F18+H18*F18 -> 0 | K18: =I18*3.5% -> 0 | L18: =I18*15% -> 0 | M18: =I18-K18-L18 -> 0 | N18: =(M18*$N$15)+(J18*F18)*$N$15 -> 0 | O18: =(N18+M18)*$O$15 -> 0 | P18: =M18+N18+O18 -> 0
A19: BCNJ | B19: =VLOOKUP($A19,'[1]Cust. Price List'!$D$6:$O$14,2,0) -> Meat Masala (Jumbo) | C19: =VLOOKUP(B19,'[1]Cust. Price List'!E9:P17,2,0) -> 120 | D19: =VLOOKUP(A19,'[1]Cust. Price List'!D9:M17,4,0) -> 40 | E19: =VLOOKUP(A19,'[1]Cust. Price List'!D9:M17,6,0) -> 90 | F19: =VLOOKUP(A19,'[1]Cust. Price List'!D9:M17,10,0) -> 72.64 | H19: 40 | I19: =(G19*D19)*F19+H19*F19 -> 2905.6 | K19: =I19*3.5% -> 101.696 | L19: =I19*15% -> 435.84 | M19: =I19-K19-L19 -> 2368.064 | N19: =(M19*$N$15)+(J19*F19)*$N$15 -> 426.25152 | O19: =(N19+M19)*$O$15 -> 13.971578 | P19: =M19+N19+O19 -> 2808.2871
A20: VTNJ | B20: =VLOOKUP($A20,'[1]Cust. Price List'!$D$6:$O$14,2,0) -> Lemon Tarka (Jumbo) | C20: =VLOOKUP(B20,'[1]Cust. Price List'!E10:P18,2,0) -> 120 | D20: =VLOOKUP(A20,'[1]Cust. Price List'!D10:M18,4,0) -> 40 | E20: =VLOOKUP(A20,'[1]Cust. Price List'!D10:M18,6,0) -> 90 | F20: =VLOOKUP(A20,'[1]Cust. Price List'!D10:M18,10,0) -> 72.64 | H20: 40 | I20: =(G20*D20)*F20+H20*F20 -> 2905.6 | K20: =I20*3.5% -> 101.696 | L20: =I20*15% -> 435.84 | M20: =I20-K20-L20 -> 2368.064 | N20: =(M20*$N$15)+(J20*F20)*$N$15 -> 426.25152 | O20: =(N20+M20)*$O$15 -> 13.971578 | P20: =M20+N20+O20 -> 2808.2871
A21: CCNJ | B21: =VLOOKUP($A21,'[1]Cust. Price List'!$D$6:$O$14,2,0) -> Chicken Chatkhara (Jumbo) | C21: =VLOOKUP(B21,'[1]Cust. Price List'!E11:P19,2,0) -> 120 | D21: =VLOOKUP(A21,'[1]Cust. Price List'!D11:M19,4,0) -> 40 | E21: =VLOOKUP(A21,'[1]Cust. Price List'!D11:M19,6,0) -> 90 | F21: =VLOOKUP(A21,'[1]Cust. Price List'!D11:M19,10,0) -> 72.64 | H21: 40 | I21: =(G21*D21)*F21+H21*F21 -> 2905.6 | K21: =I21*3.5% -> 101.696 | L21: =I21*15% -> 435.84 | M21: =I21-K21-L21 -> 2368.064 | N21: =(M21*$N$15)+(J21*F21)*$N$15 -> 426.25152 | O21: =(N21+M21)*$O$15 -> 13.971578 | P21: =M21+N21+O21 -> 2808.2871
A22: CCE | B22: =VLOOKUP($A22,'[1]Cust. Price List'!$D$6:$O$14,2,0) -> Chicken Chatkhara (ECO) | C22: =VLOOKUP(B22,'[1]Cust. Price List'!E12:P20,2,0) -> 60 | D22: =VLOOKUP(A22,'[1]Cust. Price List'!D12:M20,4,0) -> 40 | E22: =VLOOKUP(A22,'[1]Cust. Price List'!D12:M20,6,0) -> 50 | F22: =VLOOKUP(A22,'[1]Cust. Price List'!D12:M20,10,0) -> 39.23 | I22: =(G22*D22)*F22+H22*F22 -> 0 | K22: =I22*8.6% -> 0 | L22: =I22*5% -> 0 | M22: =I22-K22-L22 -> 0 | N22: =(M22*$N$15)+(J22*F22)*$N$15 -> 0 | O22: =(N22+M22)*$O$15 -> 0 | P22: =M22+N22+O22 -> 0
A23: VTE | B23: =VLOOKUP($A23,'[1]Cust. Price List'!$D$6:$O$14,2,0) -> Lemon Tarka (ECO) | C23: =VLOOKUP(B23,'[1]Cust. Price List'!E13:P21,2,0) -> 60 | D23: =VLOOKUP(A23,'[1]Cust. Price List'!D13:M21,4,0) -> 40 | E23: =VLOOKUP(A23,'[1]Cust. Price List'!D13:M21,6,0) -> 50 | F23: =VLOOKUP(A23,'[1]Cust. Price List'!D13:M21,10,0) -> 39.23 | I23: =(G23*D23)*F23+H23*F23 -> 0 | K23: =I23*3.5% -> 0 | L23: =I23*$L$13 -> 0 | M23: =I23-K23-L23 -> 0 | N23: =(M23*$N$15)+(J23*F23)*$N$15 -> 0 | O23: =(N23+M23)*$O$15 -> 0 | P23: =M23+N23+O23 -> 0
A24: BCE | B24: =VLOOKUP($A24,'[1]Cust. Price List'!$D$6:$O$14,2,0) -> Meat Masala (ECO) | C24: =VLOOKUP(B24,'[1]Cust. Price List'!E14:P22,2,0) -> 60 | D24: =VLOOKUP(A24,'[1]Cust. Price List'!D14:M22,4,0) -> 40 | E24: =VLOOKUP(A24,'[1]Cust. Price List'!D14:M22,6,0) -> 50 | F24: =VLOOKUP(A24,'[1]Cust. Price List'!D14:M22,10,0) -> 39.23 | I24: =(G24*D24)*F24+H24*F24 -> 0 | K24: =I24*3.5% -> 0 | L24: =I24*$L$13 -> 0 | M24: =I24-K24-L24 -> 0 | N24: =(M24*$N$15)+(J24*F24)*$N$15 -> 0 | O24: =(N24+M24)*$O$15 -> 0 | P24: =M24+N24+O24 -> 0
A25: Total | G25: =SUM(G16:G24) -> 0 | H25: =SUM(H16:H24) -> 200 | I25: =SUM(I16:I24) -> 12913.8 | K25: =SUM(K16:K24) -> 451.983 | L25: =SUM(L16:L24) -> 1937.07 | M25: =SUM(M16:M24) -> 10524.747 | N25: =SUM(N16:N24) -> 1894.4545 | O25: =SUM(O16:O24) -> 62.096007 | P25: =SUM(P16:P24) -> 12481.297
B28: یکم جولائی 2024سے نئی ٹیکس ترمیم کے مطابق، ایف بی آر سیکشن 236 ایچ کے مطابق، فائلرز کے لیے ہر سیل انوائس پر 0.5% اور نان فائلرز کے لیے 2.5% ایڈوانس ود ہولڈنگ ٹیکس وصول کیا جائے گا۔ | N28: Gross Amount: | P28: =I25 -> 12913.8
N29: Regular Discount | P29: =L25 -> 1937.07
N30: Trade Offre | P30: =K25 -> 451.983
N31: After Dis. Amount | P31: =P28-P29-P30 -> 10524.747
N32: Total GST: | O32: =IF(B12="Registered",18%,22%) -> 0.18 | P32: =N25 -> 1894.4545
N33: Net Amount: | P33: =P31+P32 -> 12419.201
N34: Ad.Tax | O34: =IF(B11="Filer",0.5%,2.5%) -> 0.005 | P34: =O34*P33 -> 62.096007
N35: Net Amount with Ad.Tax | P35: =P33+P34 -> 12481.297
B36: Delivered By

Sheet Sheet1
B2: 40
B3: 16.3 | C3: 9.025 | D3: 8.1 | E3: 41.375 | F3: 0 | G3: 6.55 | H3: 3.45 | I3: 3.5 | J3: 4.925 | K3: 10.35 | L3: 18.6 | M3: 0 | N3: 5.975 | O3: 8.975 | P3: 0 | Q3: 0 | R3: 0 | S3: 0 | T3: 0 | U3: 0 | V3: 0 | W3: 0 | X3: 0 | Y3: 0 | Z3: 0 | AA3: 0 | AB3: 0 | AC3: 0 | AD3: 0 | AE3: 0 | AF3: 0 | AG3: 0 | AH3: 0 | AI3: 0 | AJ3: 0 | AK3: 0 | AL3: 0 | AM3: 0 | AN3: 0 | AO3: 0 | AP3: 0 | AQ3: 0 | AR3: 0 | AS3: 0 | AT3: 0 | AU3: 0 | AV3: 0 | AW3: 0 | AX3: 0 | AY3: 0 | AZ3: 0 | BA3: 0 | BB3: 0 | BC3: 0 | BD3: 0 | BE3: 0 | BF3: 0 | BG3: 0 | BH3: 0 | BI3: 0 | BJ3: 0 | BK3: 0 | BL3: 0 | BM3: 0 | BN3: 0 | BO3: 0 | BP3: 0 | BQ3: 0 | BR3: 0 | BS3: 0 | BT3: 0 | BU3: 0 | BV3: 0 | BW3: 0 | BX3: 0 | BY3: 0 | BZ3: 0 | CA3: 0 | CB3: 0 | CC3: 0 | CD3: 0 | CE3: 0 | CF3: 0 | CG3: 0 | CH3: 0 | CI3: 0 | CJ3: 0 | CK3: 0 | CL3: 0 | CM3: 0 | CN3: 0 | CO3: 0 | CP3: 0 | CQ3: 0 | CR3: 0 | CS3: 0 | CT3: 0 | CU3: 0 | CV3: 0 | CW3: 0 | CX3: 0 | CY3: 0 | CZ3: 0 | DA3: 0 | DB3: 0 | DC3: 0 | DD3: 0 | DE3: 0 | DF3: 0 | DG3: 0 | DH3: 0 | DI3: 0 | DJ3: 0 | DK3: 0 | DL3: 0 | DM3: 0 | DN3: 0 | DO3: 0 | DP3: 0 | DQ3: 0 | DR3: 0 | DS3: 0 | DT3: 0 | DU3: 0 | DV3: 0 | DW3: 0 | DX3: 0 | DY3: 0 | DZ3: 0 | EA3: 0 | EB3: 0 | EC3: 0 | ED3: 0 | EE3: 0 | EF3: 0 | EG3: 0 | EH3: 0 | EI3: 0 | EJ3: 0 | EK3: 0 | EL3: 0 | EM3: 0 | EN3: 0 | EO3: 0 | EP3: 0 | EQ3: 0 | ER3: 0 | ES3: 0 | ET3: 0 | EU3: 0 | EV3: 0 | EW3: 0 | EX3: 0 | EY3: 0 | EZ3: 0 | FA3: 0 | FB3: 0 | FC3: 0 | FD3: 0 | FE3: 0 | FF3: 0 | FG3: 0 | FH3: 0 | FI3: 0 | FJ3: 0 | FK3: 0 | FL3: 0 | FM3: 0 | FN3: 0 | FO3: 0 | FP3: 0 | FQ3: 0 | FR3: 0 | FS3: 0 | FT3: 0 | FU3: 0 | FV3: 0 | FW3: 0 | FX3: 0 | FY3: 0 | FZ3: 0 | GA3: 0 | GB3: 0 | GC3: 0 | GD3: 0 | GE3: 0 | GF3: 0 | GG3: 0 | GH3: 0 | GI3: 0 | GJ3: 0 | GK3: 0 | GL3: 0 | GM3: 0 | GN3: 0 | GO3: 0 | GP3: 0 | GQ3: 0 | GR3: 0 | GS3: 0 | GT3: 0 | GU3: 0 | GV3: 0 | GW3: 0 | GX3: 0 | GY3: 0 | GZ3: 0 | HA3: 0 | HB3: 0 | HC3: 0 | HD3: 0 | HE3: 0 | HF3: 0 | HG3: 0 | HH3: 0 | HI3: 0 | HJ3: 0 | HK3: 0 | HL3: 0 | HM3: 0 | HN3: 0 | HO3: 0 | HP3: 0 | HQ3: 0 | HR3: 0 | HS3: 0 | HT3: 0 | HU3: 0 | HV3: 0 | HW3: 0 | HX3: 0 | HY3: 0 | HZ3: 0 | IA3: 0 | IB3: 0 | IC3: 0 | ID3: 0 | IE3: 0 | IF3: 0 | IG3: 0 | IH3: 0 | II3: 0 | IJ3: 0 | IK3: 0 | IL3: 0 | IM3: 0 | IN3: 0 | IO3: 0 | IP3: 0 | IQ3: 0 | IR3: 0 | IS3: 0 | IT3: 0 | IU3: 0 | IV3: 0 | IW3: 0 | IX3: 0 | IY3: 0 | IZ3: 0 | JA3: 0 | JB3: 0 | JC3: 0 | JD3: 0 | JE3: 0 | JF3: 0 | JG3: 0 | JH3: 0 | JI3: 0 | JJ3: 0 | JK3: 0 | JL3: 0 | JM3: 0 | JN3: 0 | JO3: 0 | JP3: 0 | JQ3: 0 | JR3: 0 | JS3: 0 | JT3: 0 | JU3: 0 | JV3: 0 | JW3: 0 | JX3: 0 | JY3: 0 | JZ3: 0 | KA3: 0 | KB3: 0 | KC3: 0 | KD3: 0 | KE3: 0 | KF3: 0 | KG3: 0 | KH3: 0 | KI3: 0 | KJ3: 0 | KK3: 0 | KL3: 0 | KM3: 0 | KN3: 0 | KO3: 0 | KP3: 0 | KQ3: 0 | KR3: 0 | KS3: 0 | KT3: 0 | KU3: 0 | KV3: 0 | KW3: 0 | KX3: 0 | KY3: 0 | KZ3: 0 | LA3: 0 | LB3: 0 | LC3: 0 | LD3: 0 | LE3: 0 | LF3: 0 | LG3: 0 | LH3: 0 | LI3: 0 | LJ3: 0 | LK3: 0 | LL3: 0 | LM3: 0 | LN3: 0 | LO3: 0 | LP3: 0 | LQ3: 0 | LR3: 0 | LS3: 0 | LT3: 0 | LU3: 0 | LV3: 0 | LW3: 0 | LX3: 0 | LY3: 0 | LZ3: 0 | MA3: 0 | MB3: 0 | MC3: 0 | MD3: 0 | ME3: 0 | MF3: 0 | MG3: 0 | MH3: 0 | MI3: 0 | MJ3: 0 | MK3: 0 | ML3: 0 | MM3: 0 | MN3: 0 | MO3: 0 | MP3: 0 | MQ3: 0 | MR3: 0 | MS3: 0 | MT3: 0 | MU3: 0 | MV3: 0 | MW3: 0 | MX3: 0 | MY3: 0 | MZ3: 0 | NA3: 0 | NB3: 0 | NC3: 0 | ND3: 0 | NE3: 0 | NF3: 0 | NG3: 0 | NH3: 0 | NI3: 0 | NJ3: 0 | NK3: 0 | NL3: 0 | NM3: 0 | NN3: 0 | NO3: 0 | NP3: 0 | NQ3: 0 | NR3: 0 | NS3: 0 | NT3: 0 | NU3: 0 | NV3: 0 | NW3: 0 | NX3: 0 | NY3: 0 | NZ3: 0 | OA3: 0 | OB3: 0 | OC3: 0 | OD3: 0 | OE3: 0 | OF3: 0 | OG3: 0 | OH3: 0 | OI3: 0 | OJ3: 0 | OK3: 0 | OL3: 0 | OM3: 0 | ON3: 0 | OO3: 0 | OP3: 0 | OQ3: 0 | OR3: 0 | OS3: 0 | OT3: 0 | OU3: 0 | OV3: 0 | OW3: 0 | OX3: 0 | OY3: 0 | OZ3: 0 | PA3: 0 | PB3: 0 | PC3: 0 | PD3: 0 | PE3: 0 | PF3: 0 | PG3: 0 | PH3: 0 | PI3: 0 | PJ3: 0 | PK3: 0 | PL3: 0 | PM3: 0 | PN3: 0 | PO3: 0 | PP3: 0 | PQ3: 0 | PR3: 0 | PS3: 0 | PT3: 0 | PU3: 0 | PV3: 0 | PW3: 0 | PX3: 0 | PY3: 0 | PZ3: 0 | QA3: 0 | QB3: 0 | QC3: 0 | QD3: 0 | QE3: 0 | QF3: 0 | QG3: 0 | QH3: 0 | QI3: 0 | QJ3: 0 | QK3: 0 | QL3: 0 | QM3: 0 | QN3: 0 | QO3: 0 | QP3: 0 | QQ3: 0 | QR3: 0 | QS3: 0 | QT3: 0 | QU3: 0 | QV3: 0 | QW3: 0 | QX3: 0 | QY3: 0 | QZ3: 0 | RA3: 0 | RB3: 0 | RC3: 0 | RD3: 0 | RE3: 0 | RF3: 0 | RG3: 0 | RH3: 0 | RI3: 0 | RJ3: 0 | RK3: 0 | RL3: 0 | RM3: 0 | RN3: 0 | RO3: 0 | RP3: 0 | RQ3: 0 | RR3: 0 | RS3: 0 | RT3: 0 | RU3: 0 | RV3: 0 | RW3: 0 | RX3: 0 | RY3: 0 | RZ3: 0 | SA3: 0 | SB3: 0 | SC3: 0 | SD3: 0 | SE3: 0 | SF3: 0 | SG3: 0 | SH3: 0 | SI3: 0 | SJ3: 0 | SK3: 0 | SL3: 0 | SM3: 0 | SN3: 0 | SO3: 0 | SP3: 0 | SQ3: 0 | SR3: 0 | SS3: 0 | ST3: 0 | SU3: 0 | SV3: 0 | SW3: 0 | SX3: 0 | SY3: 0 | SZ3: 0 | TA3: 0 | TB3: 0 | TC3: 0 | TD3: 0 | TE3: 0 | TF3: 0 | TG3: 0 | TH3: 0 | TI3: 0 | TJ3: 0 | TK3: 0 | TL3: 0 | TM3: 0 | TN3: 0 | TO3: 0 | TP3: 0 | TQ3: 0 | TR3: 0 | TS3: 0 | TT3: 0 | TU3: 0 | TV3: 0 | TW3: 0 | TX3: 0 | TY3: 0 | TZ3: 0 | UA3: 0 | UB3: 0 | UC3: 0 | UD3: 0 | UE3: 0 | UF3: 0 | UG3: 0 | UH3: 0 | UI3: 0 | UJ3: 0 | UK3: 0 | UL3: 0 | UM3: 0 | UN3: 0 | UO3: 0 | UP3: 0 | UQ3: 0 | UR3: 0 | US3: 0 | UT3: 0 | UU3: 0 | UV3: 0 | UW3: 0 | UX3: 0 | UY3: 0 | UZ3: 0 | VA3: 0 | VB3: 0 | VC3: 0 | VD3: 0 | VE3: 0 | VF3: 0 | VG3: 0 | VH3: 0 | VI3: 0 | VJ3: 0 | VK3: 0 | VL3: 0 | VM3: 0 | VN3: 0 | VO3: 0 | VP3: 0 | VQ3: 0 | VR3: 0 | VS3: 0 | VT3: 0 | VU3: 0 | VV3: 0 | VW3: 0 | VX3: 0 | VY3: 0 | VZ3: 0 | WA3: 0 | WB3: 0 | WC3: 0 | WD3: 0 | WE3: 0 | WF3: 0 | WG3: 0 | WH3: 0 | WI3: 0 | WJ3: 0 | WK3: 0 | WL3: 0 | WM3: 0 | WN3: 0 | WO3: 0 | WP3: 0 | WQ3: 0 | WR3: 0 | WS3: 0 | WT3: 0 | WU3: 0 | WV3: 0 | WW3: 0 | WX3: 0 | WY3: 0 | WZ3: 0 | XA3: 0 | XB3: 0 | XC3: 0 | XD3: 0 | XE3: 0 | XF3: 0 | XG3: 0 | XH3: 0 | XI3: 0 | XJ3: 0 | XK3: 0 | XL3: 0 | XM3: 0 | XN3: 0 | XO3: 0 | XP3: 0 | XQ3: 0 | XR3: 0 | XS3: 0 | XT3: 0 | XU3: 0 | XV3: 0 | XW3: 0 | XX3: 0 | XY3: 0 | XZ3: 0 | YA3: 0 | YB3: 0 | YC3: 0 | YD3: 0 | YE3: 0 | YF3: 0 | YG3: 0 | YH3: 0 | YI3: 0 | YJ3: 0 | YK3: 0 | YL3: 0 | YM3: 0 | YN3: 0 | YO3: 0 | YP3: 0 | YQ3: 0 | YR3: 0 | YS3: 0 | YT3: 0 | YU3: 0 | YV3: 0 | YW3: 0 | YX3: 0 | YY3: 0 | YZ3: 0 | ZA3: 0 | ZB3: 0 | ZC3: 0 | ZD3: 0 | ZE3: 0 | ZF3: 0 | ZG3: 0 | ZH3: 0 | ZI3: 0 | ZJ3: 0 | ZK3: 0 | ZL3: 0 | ZM3: 0 | ZN3: 0 | ZO3: 0 | ZP3: 0 | ZQ3: 0 | ZR3: 0 | ZS3: 0 | ZT3: 0 | ZU3: 0 | ZV3: 0 | ZW3: 0 | ZX3: 0 | ZY3: 0 | ZZ3: 0 | AAA3: 0 | AAB3: 0 | AAC3: 0 | AAD3: 0 | AAE3: 0 | AAF3: 0 | AAG3: 0 | AAH3: 0 | AAI3: 0 | AAJ3: 0 | AAK3: 0 | AAL3: 0 | AAM3: 0 | AAN3: 0 | AAO3: 0 | AAP3: 0 | AAQ3: 0 | AAR3: 0 | AAS3: 0 | AAT3: 0 | AAU3: 0 | AAV3: 0 | AAW3: 0 | AAX3: 0 | AAY3: 0 | AAZ3: 0 | ABA3: 0 | ABB3: 0 | ABC3: 0 | ABD3: 0 | ABE3: 0 | ABF3: 0 | ABG3: 0 | ABH3: 0 | ABI3: 0 | ABJ3: 0 | ABK3: 0 | ABL3: 0 | ABM3: 0 | ABN3: 0 | ABO3: 0 | ABP3: 0 | ABQ3: 0 | ABR3: 0 | ABS3: 0 | ABT3: 0 | ABU3: 0 | ABV3: 0 | ABW3: 0 | ABX3: 0 | ABY3: 0 | ABZ3: 0 | ACA3: 0 | ACB3: 0 | ACC3: 0 | ACD3: 0 | ACE3: 0 | ACF3: 0 | ACG3: 0 | ACH3: 0 | ACI3: 0 | ACJ3: 0 | ACK3: 0 | ACL3: 0 | ACM3: 0 | ACN3: 0 | ACO3: 0 | ACP3: 0 | ACQ3: 0 | ACR3: 0 | ACS3: 0 | ACT3: 0 | ACU3: 0 | ACV3: 0 | ACW3: 0 | ACX3: 0 | ACY3: 0 | ACZ3: 0 | ADA3: 0 | ADB3: 0 | ADC3: 0 | ADD3: 0 | ADE3: 0 | ADF3: 0 | ADG3: 0 | ADH3: 0 | ADI3: 0 | ADJ3: 0 | ADK3: 0 | ADL3: 0 | ADM3: 0 | ADN3: 0 | ADO3: 0 | ADP3: 0 | ADQ3: 0 | ADR3: 0 | ADS3: 0 | ADT3: 0 | ADU3: 0 | ADV3: 0 | ADW3: 0 | ADX3: 0 | ADY3: 0 | ADZ3: 0 | AEA3: 0 | AEB3: 0 | AEC3: 0 | AED3: 0 | AEE3: 0 | AEF3: 0 | AEG3: 0 | AEH3: 0 | AEI3: 0 | AEJ3: 0 | AEK3: 0 | AEL3: 0 | AEM3: 0 | AEN3: 0 | AEO3: 0 | AEP3: 0 | AEQ3: 0 | AER3: 0 | AES3: 0 | AET3: 0 | AEU3: 0 | AEV3: 0 | AEW3: 0 | AEX3: 0 | AEY3: 0 | AEZ3: 0 | AFA3: 0 | AFB3: 0 | AFC3: 0 | AFD3: 0 | AFE3: 0 | AFF3: 0 | AFG3: 0 | AFH3: 0 | AFI3: 0 | AFJ3: 0 | AFK3: 0 | AFL3: 0 | AFM3: 0 | AFN3: 0 | AFO3: 0 | AFP3: 0 | AFQ3: 0 | AFR3: 0 | AFS3: 0 | AFT3: 0 | AFU3: 0 | AFV3: 0 | AFW3: 0 | AFX3: 0 | AFY3: 0 | AFZ3: 0 | AGA3: 0 | AGB3: 0 | AGC3: 0 | AGD3: 0 | AGE3: 0 | AGF3: 0 | AGG3: 0 | AGH3: 0 | AGI3: 0 | AGJ3: 0 | AGK3: 0 | AGL3: 0 | AGM3: 0 | AGN3: 0 | AGO3: 0 | AGP3: 0 | AGQ3: 0 | AGR3: 0 | AGS3: 0 | AGT3: 0 | AGU3: 0 | AGV3: 0 | AGW3: 0 | AGX3: 0 | AGY3: 0 | AGZ3: 0 | AHA3: 0 | AHB3: 0 | AHC3: 0 | AHD3: 0 | AHE3: 0 | AHF3: 0 | AHG3: 0 | AHH3: 0 | AHI3: 0 | AHJ3: 0 | AHK3: 0 | AHL3: 0 | AHM3: 0 | AHN3: 0 | AHO3: 0 | AHP3: 0 | AHQ3: 0 | AHR3: 0 | AHS3: 0 | AHT3: 0 | AHU3: 0 | AHV3: 0 | AHW3: 0 | AHX3: 0 | AHY3: 0 | AHZ3: 0 | AIA3: 0 | AIB3: 0 | AIC3: 0 | AID3: 0 | AIE3: 0 | AIF3: 0 | AIG3: 0 | AIH3: 0 | AII3: 0 | AIJ3: 0 | AIK3: 0 | AIL3: 0 | AIM3: 0 | AIN3: 0 | AIO3: 0 | AIP3: 0 | AIQ3: 0 | AIR3: 0 | AIS3: 0 | AIT3: 0 | AIU3: 0 | AIV3: 0 | AIW3: 0 | AIX3: 0 | AIY3: 0 | AIZ3: 0 | AJA3: 0 | AJB3: 0 | AJC3: 0 | AJD3: 0 | AJE3: 0 | AJF3: 0 | AJG3: 0 | AJH3: 0 | AJI3: 0 | AJJ3: 0 | AJK3: 0 | AJL3: 0 | AJM3: 0 | AJN3: 0 | AJO3: 0 | AJP3: 0 | AJQ3: 0 | AJR3: 0 | AJS3: 0 | AJT3: 0 | AJU3: 0 | AJV3: 0 | AJW3: 0 | AJX3: 0 | AJY3: 0 | AJZ3: 0 | AKA3: 0 | AKB3: 0 | AKC3: 0 | AKD3: 0 | AKE3: 0 | AKF3: 0 | AKG3: 0 | AKH3: 0 | AKI3: 0 | AKJ3: 0 | AKK3: 0 | AKL3: 0 | AKM3: 0 | AKN3: 0 | AKO3: 0 | AKP3: 0 | AKQ3: 0 | AKR3: 0 | AKS3: 0 | AKT3: 0 | AKU3: 0 | AKV3: 0 | AKW3: 0 | AKX3: 0 | AKY3: 0 | AKZ3: 0 | ALA3: 0 | ALB3: 0 | ALC3: 0 | ALD3: 0 | ALE3: 0 | ALF3: 0 | ALG3: 0 | ALH3: 0 | ALI3: 0 | ALJ3: 0 | ALK3: 0 | ALL3: 0 | ALM3: 0 | ALN3: 0 | ALO3: 0 | ALP3: 0 | ALQ3: 0 | ALR3: 0 | ALS3: 0 | ALT3: 0 | ALU3: 0 | ALV3: 0 | ALW3: 0 | ALX3: 0 | ALY3: 0 | ALZ3: 0 | AMA3: 0 | AMB3: 0 | AMC3: 0 | AMD3: 0 | AME3: 0 | AMF3: 0 | AMG3: 0 | AMH3: 0 | AMI3: 0 | AMJ3: 0 | AMK3: 0 | AML3: 0 | AMM3: 0 | AMN3: 0 | AMO3: 0 | AMP3: 0 | AMQ3: 0 | AMR3: 0 | AMS3: 0 | AMT3: 0 | AMU3: 0 | AMV3: 0 | AMW3: 0 | AMX3: 0 | AMY3: 0 | AMZ3: 0 | ANA3: 0 | ANB3: 0 | ANC3: 0 | AND3: 0 | ANE3: 0 | ANF3: 0 | ANG3: 0 | ANH3: 0 | ANI3: 0 | ANJ3: 0 | ANK3: 0 | ANL3: 0 | ANM3: 0 | ANN3: 0 | ANO3: 0 | ANP3: 0 | ANQ3: 0 | ANR3: 0 | ANS3: 0 | ANT3: 0 | ANU3: 0 | ANV3: 0 | ANW3: 0 | ANX3: 0 | ANY3: 0 | ANZ3: 0 | AOA3: 0 | AOB3: 0 | AOC3: 0 | AOD3: 0 | AOE3: 0 | AOF3: 0 | AOG3: 0 | AOH3: 0 | AOI3: 0 | AOJ3: 0 | AOK3: 0 | AOL3: 0 | AOM3: 0 | AON3: 0 | AOO3: 0 | AOP3: 0 | AOQ3: 0 | AOR3: 0 | AOS3: 0 | AOT3: 0 | AOU3: 0 | AOV3: 0 | AOW3: 0 | AOX3: 0 | AOY3: 0 | AOZ3: 0 | APA3: 0 | APB3: 0 | APC3: 0 | APD3: 0 | APE3: 0 | APF3: 0 | APG3: 0 | APH3: 0 | API3: 0 | APJ3: 0 | APK3: 0 | APL3: 0 | APM3: 0 | APN3: 0 | APO3: 0 | APP3: 0 | APQ3: 0 | APR3: 0 | APS3: 0 | APT3: 0 | APU3: 0 | APV3: 0 | APW3: 0 | APX3: 0 | APY3: 0 | APZ3: 0 | AQA3: 0 | AQB3: 0 | AQC3: 0 | AQD3: 0 | AQE3: 0 | AQF3: 0 | AQG3: 0 | AQH3: 0 | AQI3: 0 | AQJ3: 0 | AQK3: 0 | AQL3: 0 | AQM3: 0 | AQN3: 0 | AQO3: 0 | AQP3: 0 | AQQ3: 0 | AQR3: 0 | AQS3: 0 | AQT3: 0 | AQU3: 0 | AQV3: 0 | AQW3: 0 | AQX3: 0 | AQY3: 0 | AQZ3: 0 | ARA3: 0 | ARB3: 0 | ARC3: 0 | ARD3: 0 | ARE3: 0 | ARF3: 0 | ARG3: 0 | ARH3: 0 | ARI3: 0 | ARJ3: 0 | ARK3: 0 | ARL3: 0 | ARM3: 0 | ARN3: 0 | ARO3: 0 | ARP3: 0 | ARQ3: 0 | ARR3: 0 | ARS3: 0 | ART3: 0 | ARU3: 0 | ARV3: 0 | ARW3: 0 | ARX3: 0 | ARY3: 0 | ARZ3: 0 | ASA3: 0 | ASB3: 0 | ASC3: 0 | ASD3: 0 | ASE3: 0 | ASF3: 0 | ASG3: 0 | ASH3: 0 | ASI3: 0 | ASJ3: 0 | ASK3: 0 | ASL3: 0 | ASM3: 0 | ASN3: 0 | ASO3: 0 | ASP3: 0 | ASQ3: 0 | ASR3: 0 | ASS3: 0 | AST3: 0 | ASU3: 0 | ASV3: 0 | ASW3: 0 | ASX3: 0 | ASY3: 0 | ASZ3: 0 | ATA3: 0 | ATB3: 0 | ATC3: 0 | ATD3: 0 | ATE3: 0 | ATF3: 0 | ATG3: 0 | ATH3: 0 | ATI3: 0 | ATJ3: 0 | ATK3: 0 | ATL3: 0 | ATM3: 0 | ATN3: 0 | ATO3: 0 | ATP3: 0 | ATQ3: 0 | ATR3: 0 | ATS3: 0 | ATT3: 0 | ATU3: 0 | ATV3: 0 | ATW3: 0 | ATX3: 0 | ATY3: 0 | ATZ3: 0 | AUA3: 0 | AUB3: 0 | AUC3: 0 | AUD3: 0 | AUE3: 0 | AUF3: 0 | AUG3: 0 | AUH3: 0 | AUI3: 0 | AUJ3: 0 | AUK3: 0 | AUL3: 0 | AUM3: 0 | AUN3: 0 | AUO3: 0 | AUP3: 0 | AUQ3: 0 | AUR3: 0 | AUS3: 0 | AUT3: 0 | AUU3: 0 | AUV3: 0 | AUW3: 0 | AUX3: 0 | AUY3: 0 | AUZ3: 0 | AVA3: 0 | AVB3: 0 | AVC3: 0 | AVD3: 0 | AVE3: 0 | AVF3: 0 | AVG3: 0 | AVH3: 0 | AVI3: 0 | AVJ3: 0 | AVK3: 0 | AVL3: 0 | AVM3: 0 | AVN3: 0 | AVO3: 0 | AVP3: 0 | AVQ3: 0 | AVR3: 0 | AVS3: 0 | AVT3: 0 | AVU3: 0 | AVV3: 0 | AVW3: 0 | AVX3: 0 | AVY3: 0 | AVZ3: 0 | AWA3: 0 | AWB3: 0 | AWC3: 0 | AWD3: 0 | AWE3: 0 | AWF3: 0 | AWG3: 0 | AWH3: 0 | AWI3: 0 | AWJ3: 0 | AWK3: 0 | AWL3: 0 | AWM3: 0 | AWN3: 0 | AWO3: 0 | AWP3: 0 | AWQ3: 0 | AWR3: 0 | AWS3: 0 | AWT3: 0 | AWU3: 0 | AWV3: 0 | AWW3: 0 | AWX3: 0 | AWY3: 0 | AWZ3: 0 | AXA3: 0 | AXB3: 0 | AXC3: 0 | AXD3: 0 | AXE3: 0 | AXF3: 0 | AXG3: 0 | AXH3: 0 | AXI3: 0 | AXJ3: 0 | AXK3: 0 | AXL3: 0 | AXM3: 0 | AXN3: 0 | AXO3: 0 | AXP3: 0 | AXQ3: 0 | AXR3: 0 | AXS3: 0 | AXT3: 0 | AXU3: 0 | AXV3: 0 | AXW3: 0 | AXX3: 0 | AXY3: 0 | AXZ3: 0 | AYA3: 0 | AYB3: 0 | AYC3: 0 | AYD3: 0 | AYE3: 0 | AYF3: 0 | AYG3: 0 | AYH3: 0 | AYI3: 0 | AYJ3: 0 | AYK3: 0 | AYL3: 0 | AYM3: 0 | AYN3: 0 | AYO3: 0 | AYP3: 0 | AYQ3: 0 | AYR3: 0 | AYS3: 0 | AYT3: 0 | AYU3: 0 | AYV3: 0 | AYW3: 0 | AYX3: 0 | AYY3: 0 | AYZ3: 0 | AZA3: 0 | AZB3: 0 | AZC3: 0 | AZD3: 0 | AZE3: 0 | AZF3: 0 | AZG3: 0 | AZH3: 0 | AZI3: 0 | AZJ3: 0 | AZK3: 0 | AZL3: 0 | AZM3: 0 | AZN3: 0 | AZO3: 0 | AZP3: 0 | AZQ3: 0 | AZR3: 0 | AZS3: 0 | AZT3: 0 | AZU3: 0 | AZV3: 0 | AZW3: 0 | AZX3: 0 | AZY3: 0 | AZZ3: 0 | BAA3: 0 | BAB3: 0 | BAC3: 0 | BAD3: 0 | BAE3: 0 | BAF3: 0 | BAG3: 0 | BAH3: 0 | BAI3: 0 | BAJ3: 0 | BAK3: 0 | BAL3: 0 | BAM3: 0 | BAN3: 0 | BAO3: 0 | BAP3: 0 | BAQ3: 0 | BAR3: 0 | BAS3: 0 | BAT3: 0 | BAU3: 0 | BAV3: 0 | BAW3: 0 | BAX3: 0 | BAY3: 0 | BAZ3: 0 | BBA3: 0 | BBB3: 0 | BBC3: 0 | BBD3: 0 | BBE3: 0 | BBF3: 0 | BBG3: 0 | BBH3: 0 | BBI3: 0 | BBJ3: 0 | BBK3: 0 | BBL3: 0 | BBM3: 0 | BBN3: 0 | BBO3: 0 | BBP3: 0 | BBQ3: 0 | BBR3: 0 | BBS3: 0 | BBT3: 0 | BBU3: 0 | BBV3: 0 | BBW3: 0 | BBX3: 0 | BBY3: 0 | BBZ3: 0 | BCA3: 0 | BCB3: 0 | BCC3: 0 | BCD3: 0 | BCE3: 0 | BCF3: 0 | BCG3: 0 | BCH3: 0 | BCI3: 0 | BCJ3: 0 | BCK3: 0 | BCL3: 0 | BCM3: 0 | BCN3: 0 | BCO3: 0 | BCP3: 0 | BCQ3: 0 | BCR3: 0 | BCS3: 0 | BCT3: 0 | BCU3: 0 | BCV3: 0 | BCW3: 0 | BCX3: 0 | BCY3: 0 | BCZ3: 0 | BDA3: 0 | BDB3: 0 | BDC3: 0 | BDD3: 0 | BDE3: 0 | BDF3: 0 | BDG3: 0 | BDH3: 0 | BDI3: 0 | BDJ3: 0 | BDK3: 0 | BDL3: 0 | BDM3: 0 | BDN3: 0 | BDO3: 0 | BDP3: 0 | BDQ3: 0 | BDR3: 0 | BDS3: 0 | BDT3: 0 | BDU3: 0 | BDV3: 0 | BDW3: 0 | BDX3: 0 | BDY3: 0 | BDZ3: 0 | BEA3: 0 | BEB3: 0 | BEC3: 0 | BED3: 0 | BEE3: 0 | BEF3: 0 | BEG3: 0 | BEH3: 0 | BEI3: 0 | BEJ3: 0 | BEK3: 0 | BEL3: 0 | BEM3: 0 | BEN3: 0 | BEO3: 0 | BEP3: 0 | BEQ3: 0 | BER3: 0 | BES3: 0 | BET3: 0 | BEU3: 0 | BEV3: 0 | BEW3: 0 | BEX3: 0 | BEY3: 0 | BEZ3: 0 | BFA3: 0 | BFB3: 0 | BFC3: 0 | BFD3: 0 | BFE3: 0 | BFF3: 0 | BFG3: 0 | BFH3: 0 | BFI3: 0 | BFJ3: 0 | BFK3: 0 | BFL3: 0 | BFM3: 0 | BFN3: 0 | BFO3: 0 | BFP3: 0 | BFQ3: 0 | BFR3: 0 | BFS3: 0 | BFT3: 0 | BFU3: 0 | BFV3: 0 | BFW3: 0 | BFX3: 0 | BFY3: 0 | BFZ3: 0 | BGA3: 0 | BGB3: 0 | BGC3: 0 | BGD3: 0 | BGE3: 0 | BGF3: 0 | BGG3: 0 | BGH3: 0 | BGI3: 0 | BGJ3: 0 | BGK3: 0 | BGL3: 0 | BGM3: 0 | BGN3: 0 | BGO3: 0 | BGP3: 0 | BGQ3: 0 | BGR3: 0 | BGS3: 0 | BGT3: 0 | BGU3: 0 | BGV3: 0 | BGW3: 0 | BGX3: 0 | BGY3: 0 | BGZ3: 0 | BHA3: 0 | BHB3: 0 | BHC3: 0 | BHD3: 0 | BHE3: 0 | BHF3: 0 | BHG3: 0 | BHH3: 0 | BHI3: 0 | BHJ3: 0 | BHK3: 0 | BHL3: 0 | BHM3: 0 | BHN3: 0 | BHO3: 0 | BHP3: 0 | BHQ3: 0 | BHR3: 0 | BHS3: 0 | BHT3: 0 | BHU3: 0 | BHV3: 0 | BHW3: 0 | BHX3: 0 | BHY3: 0 | BHZ3: 0 | BIA3: 0 | BIB3: 0 | BIC3: 0 | BID3: 0 | BIE3: 0 | BIF3: 0 | BIG3: 0 | BIH3: 0 | BII3: 0 | BIJ3: 0 | BIK3: 0 | BIL3: 0 | BIM3: 0 | BIN3: 0 | BIO3: 0 | BIP3: 0 | BIQ3: 0 | BIR3: 0 | BIS3: 0 | BIT3: 0 | BIU3: 0 | BIV3: 0 | BIW3: 0 | BIX3: 0 | BIY3: 0 | BIZ3: 0 | BJA3: 0 | BJB3: 0 | BJC3: 0 | BJD3: 0 | BJE3: 0 | BJF3: 0 | BJG3: 0 | BJH3: 0 | BJI3: 0 | BJJ3: 0 | BJK3: 0 | BJL3: 0 | BJM3: 0 | BJN3: 0 | BJO3: 0 | BJP3: 0 | BJQ3: 0 | BJR3: 0 | BJS3: 0 | BJT3: 0 | BJU3: 0 | BJV3: 0 | BJW3: 0 | BJX3: 0 | BJY3: 0 | BJZ3: 0 | BKA3: 0 | BKB3: 0 | BKC3: 0 | BKD3: 0 | BKE3: 0 | BKF3: 0 | BKG3: 0 | BKH3: 0 | BKI3: 0 | BKJ3: 0 | BKK3: 0 | BKL3: 0 | BKM3: 0 | BKN3: 0 | BKO3: 0 | BKP3: 0 | BKQ3: 0 | BKR3: 0 | BKS3: 0 | BKT3: 0 | BKU3: 0 | BKV3: 0 | BKW3: 0 | BKX3: 0 | BKY3: 0 | BKZ3: 0 | BLA3: 0 | BLB3: 0 | BLC3: 0 | BLD3: 0 | BLE3: 0 | BLF3: 0 | BLG3: 0 | BLH3: 0 | BLI3: 0 | BLJ3: 0 | BLK3: 0 | BLL3: 0 | BLM3: 0 | BLN3: 0 | BLO3: 0 | BLP3: 0 | BLQ3: 0 | BLR3: 0 | BLS3: 0 | BLT3: 0 | BLU3: 0 | BLV3: 0 | BLW3: 0 | BLX3: 0 | BLY3: 0 | BLZ3: 0 | BMA3: 0 | BMB3: 0 | BMC3: 0 | BMD3: 0 | BME3: 0 | BMF3: 0 | BMG3: 0 | BMH3: 0 | BMI3: 0 | BMJ3: 0 | BMK3: 0 | BML3: 0 | BMM3: 0 | BMN3: 0 | BMO3: 0 | BMP3: 0 | BMQ3: 0 | BMR3: 0 | BMS3: 0 | BMT3: 0 | BMU3: 0 | BMV3: 0 | BMW3: 0 | BMX3: 0 | BMY3: 0 | BMZ3: 0 | BNA3: 0 | BNB3: 0 | BNC3: 0 | BND3: 0 | BNE3: 0 | BNF3: 0 | BNG3: 0 | BNH3: 0 | BNI3: 0 | BNJ3: 0 | BNK3: 0 | BNL3: 0 | BNM3: 0 | BNN3: 0 | BNO3: 0 | BNP3: 0 | BNQ3: 0 | BNR3: 0 | BNS3: 0 | BNT3: 0 | BNU3: 0 | BNV3: 0 | BNW3: 0 | BNX3: 0 | BNY3: 0 | BNZ3: 0 | BOA3: 0 | BOB3: 0 | BOC3: 0 | BOD3: 0 | BOE3: 0 | BOF3: 0 | BOG3: 0 | BOH3: 0 | BOI3: 0 | BOJ3: 0 | BOK3: 0 | BOL3: 0 | BOM3: 0 | BON3: 0 | BOO3: 0 | BOP3: 0 | BOQ3: 0 | BOR3: 0 | BOS3: 0 | BOT3: 0 | BOU3: 0 | BOV3: 0 | BOW3: 0 | BOX3: 0 | BOY3: 0 | BOZ3: 0 | BPA3: 0 | BPB3: 0 | BPC3: 0 | BPD3: 0 | BPE3: 0 | BPF3: 0 | BPG3: 0 | BPH3: 0 | BPI3: 0 | BPJ3: 0 | BPK3: 0 | BPL3: 0 | BPM3: 0 | BPN3: 0 | BPO3: 0 | BPP3: 0 | BPQ3: 0 | BPR3: 0 | BPS3: 0 | BPT3: 0 | BPU3: 0 | BPV3: 0 | BPW3: 0 | BPX3: 0 | BPY3: 0 | BPZ3: 0 | BQA3: 0 | BQB3: 0 | BQC3: 0 | BQD3: 0 | BQE3: 0 | BQF3: 0 | BQG3: 0 | BQH3: 0 | BQI3: 0 | BQJ3: 0 | BQK3: 0 | BQL3: 0 | BQM3: 0 | BQN3: 0 | BQO3: 0 | BQP3: 0 | BQQ3: 0 | BQR3: 0 | BQS3: 0 | BQT3: 0 | BQU3: 0 | BQV3: 0 | BQW3: 0 | BQX3: 0 | BQY3: 0 | BQZ3: 0 | BRA3: 0 | BRB3: 0 | BRC3: 0 | BRD3: 0 | BRE3: 0 | BRF3: 0 | BRG3: 0 | BRH3: 0 | BRI3: 0 | BRJ3: 0 | BRK3: 0 | BRL3: 0 | BRM3: 0 | BRN3: 0 | BRO3: 0 | BRP3: 0 | BRQ3: 0 | BRR3: 0 | BRS3: 0 | BRT3: 0 | BRU3: 0 | BRV3: 0 | BRW3: 0 | BRX3: 0 | BRY3: 0 | BRZ3: 0 | BSA3: 0 | BSB3: 0 | BSC3: 0 | BSD3: 0 | BSE3: 0 | BSF3: 0 | BSG3: 0 | BSH3: 0 | BSI3: 0 | BSJ3: 0 | BSK3: 0 | BSL3: 0 | BSM3: 0 | BSN3: 0 | BSO3: 0 | BSP3: 0 | BSQ3: 0 | BSR3: 0 | BSS3: 0 | BST3: 0 | BSU3: 0 | BSV3: 0 | BSW3: 0 | BSX3: 0 | BSY3: 0 | BSZ3: 0 | BTA3: 0 | BTB3: 0 | BTC3: 0 | BTD3: 0 | BTE3: 0 | BTF3: 0 | BTG3: 0 | BTH3: 0 | BTI3: 0 | BTJ3: 0 | BTK3: 0 | BTL3: 0 | BTM3: 0 | BTN3: 0 | BTO3: 0 | BTP3: 0 | BTQ3: 0 | BTR3: 0 | BTS3: 0 | BTT3: 0 | BTU3: 0 | BTV3: 0 | BTW3: 0 | BTX3: 0 | BTY3: 0 | BTZ3: 0 | BUA3: 0 | BUB3: 0 | BUC3: 0 | BUD3: 0 | BUE3: 0 | BUF3: 0 | BUG3: 0 | BUH3: 0 | BUI3: 0 | BUJ3: 0 | BUK3: 0 | BUL3: 0 | BUM3: 0 | BUN3: 0 | BUO3: 0 | BUP3: 0 | BUQ3: 0 | BUR3: 0 | BUS3: 0 | BUT3: 0 | BUU3: 0 | BUV3: 0 | BUW3: 0 | BUX3: 0 | BUY3: 0 | BUZ3: 0 | BVA3: 0 | BVB3: 0 | BVC3: 0 | BVD3: 0 | BVE3: 0 | BVF3: 0 | BVG3: 0 | BVH3: 0 | BVI3: 0 | BVJ3: 0 | BVK3: 0 | BVL3: 0 | BVM3: 0 | BVN3: 0 | BVO3: 0 | BVP3: 0 | BVQ3: 0 | BVR3: 0 | BVS3: 0 | BVT3: 0 | BVU3: 0 | BVV3: 0 | BVW3: 0 | BVX3: 0 | BVY3: 0 | BVZ3: 0 | BWA3: 0 | BWB3: 0 | BWC3: 0 | BWD3: 0 | BWE3: 0 | BWF3: 0 | BWG3: 0 | BWH3: 0 | BWI3: 0 | BWJ3: 0 | BWK3: 0 | BWL3: 0 | BWM3: 0 | BWN3: 0 | BWO3: 0 | BWP3: 0 | BWQ3: 0 | BWR3: 0 | BWS3: 0 | BWT3: 0 | BWU3: 0 | BWV3: 0 | BWW3: 0 | BWX3: 0 | BWY3: 0 | BWZ3: 0 | BXA3: 0 | BXB3: 0 | BXC3: 0 | BXD3: 0 | BXE3: 0 | BXF3: 0 | BXG3: 0 | BXH3: 0 | BXI3: 0 | BXJ3: 0 | BXK3: 0 | BXL3: 0 | BXM3: 0 | BXN3: 0 | BXO3: 0 | BXP3: 0 | BXQ3: 0 | BXR3: 0 | BXS3: 0 | BXT3: 0 | BXU3: 0 | BXV3: 0 | BXW3: 0 | BXX3: 0 | BXY3: 0 | BXZ3: 0 | BYA3: 0 | BYB3: 0 | BYC3: 0 | BYD3: 0 | BYE3: 0 | BYF3: 0 | BYG3: 0 | BYH3: 0 | BYI3: 0 | BYJ3: 0 | BYK3: 0 | BYL3: 0 | BYM3: 0 | BYN3: 0 | BYO3: 0 | BYP3: 0 | BYQ3: 0 | BYR3: 0 | BYS3: 0 | BYT3: 0 | BYU3: 0 | BYV3: 0 | BYW3: 0 | BYX3: 0 | BYY3: 0 | BYZ3: 0 | BZA3: 0 | BZB3: 0 | BZC3: 0 | BZD3: 0 | BZE3: 0 | BZF3: 0 | BZG3: 0 | BZH3: 0 | BZI3: 0 | BZJ3: 0 | BZK3: 0 | BZL3: 0 | BZM3: 0 | BZN3: 0 | BZO3: 0 | BZP3: 0 | BZQ3: 0 | BZR3: 0 | BZS3: 0 | BZT3: 0 | BZU3: 0 | BZV3: 0 | BZW3: 0 | BZX3: 0 | BZY3: 0 | BZZ3: 0 | CAA3: 0 | CAB3: 0 | CAC3: 0 | CAD3: 0 | CAE3: 0 | CAF3: 0 | CAG3: 0 | CAH3: 0 | CAI3: 0 | CAJ3: 0 | CAK3: 0 | CAL3: 0 | CAM3: 0 | CAN3: 0 | CAO3: 0 | CAP3: 0 | CAQ3: 0 | CAR3: 0 | CAS3: 0 | CAT3: 0 | CAU3: 0 | CAV3: 0 | CAW3: 0 | CAX3: 0 | CAY3: 0 | CAZ3: 0 | CBA3: 0 | CBB3: 0 | CBC3: 0 | CBD3: 0 | CBE3: 0 | CBF3: 0 | CBG3: 0 | CBH3: 0 | CBI3: 0 | CBJ3: 0 | CBK3: 0 | CBL3: 0 | CBM3: 0 | CBN3: 0 | CBO3: 0 | CBP3: 0 | CBQ3: 0 | CBR3: 0 | CBS3: 0 | CBT3: 0 | CBU3: 0 | CBV3: 0 | CBW3: 0 | CBX3: 0 | CBY3: 0 | CBZ3: 0 | CCA3: 0 | CCB3: 0 | CCC3: 0 | CCD3: 0 | CCE3: 0 | CCF3: 0 | CCG3: 0 | CCH3: 0 | CCI3: 0 | CCJ3: 0 | CCK3: 0 | CCL3: 0 | CCM3: 0 | CCN3: 0 | CCO3: 0 | CCP3: 0 | CCQ3: 0 | CCR3: 0 | CCS3: 0 | CCT3: 0 | CCU3: 0 | CCV3: 0 | CCW3: 0 | CCX3: 0 | CCY3: 0 | CCZ3: 0 | CDA3: 0 | CDB3: 0 | CDC3: 0 | CDD3: 0 | CDE3: 0 | CDF3: 0 | CDG3: 0 | CDH3: 0 | CDI3: 0 | CDJ3: 0 | CDK3: 0 | CDL3: 0 | CDM3: 0 | CDN3: 0 | CDO3: 0 | CDP3: 0 | CDQ3: 0 | CDR3: 0 | CDS3: 0 | CDT3: 0 | CDU3: 0 | CDV3: 0 | CDW3: 0 | CDX3: 0 | CDY3: 0 | CDZ3: 0 | CEA3: 0 | CEB3: 0 | CEC3: 0 | CED3: 0 | CEE3: 0 | CEF3: 0 | CEG3: 0 | CEH3: 0 | CEI3: 0 | CEJ3: 0 | CEK3: 0 | CEL3: 0 | CEM3: 0 | CEN3: 0 | CEO3: 0 | CEP3: 0 | CEQ3: 0 | CER3: 0 | CES3: 0 | CET3: 0 | CEU3: 0 | CEV3: 0 | CEW3: 0 | CEX3: 0 | CEY3: 0 | CEZ3: 0 | CFA3: 0 | CFB3: 0 | CFC3: 0 | CFD3: 0 | CFE3: 0 | CFF3: 0 | CFG3: 0 | CFH3: 0 | CFI3: 0 | CFJ3: 0 | CFK3: 0 | CFL3: 0 | CFM3: 0 | CFN3: 0 | CFO3: 0 | CFP3: 0 | CFQ3: 0 | CFR3: 0 | CFS3: 0 | CFT3: 0 | CFU3: 0 | CFV3: 0 | CFW3: 0 | CFX3: 0 | CFY3: 0 | CFZ3: 0 | CGA3: 0 | CGB3: 0 | CGC3: 0 | CGD3: 0 | CGE3: 0 | CGF3: 0 | CGG3: 0 | CGH3: 0 | CGI3: 0 | CGJ3: 0 | CGK3: 0 | CGL3: 0 | CGM3: 0 | CGN3: 0 | CGO3: 0 | CGP3: 0 | CGQ3: 0 | CGR3: 0 | CGS3: 0 | CGT3: 0 | CGU3: 0 | CGV3: 0 | CGW3: 0 | CGX3: 0 | CGY3: 0 | CGZ3: 0 | CHA3: 0 | CHB3: 0 | CHC3: 0 | CHD3: 0 | CHE3: 0 | CHF3: 0 | CHG3: 0 | CHH3: 0 | CHI3: 0 | CHJ3: 0 | CHK3: 0 | CHL3: 0 | CHM3: 0 | CHN3: 0 | CHO3: 0 | CHP3: 0 | CHQ3: 0 | CHR3: 0 | CHS3: 0 | CHT3: 0 | CHU3: 0 | CHV3: 0 | CHW3: 0 | CHX3: 0 | CHY3: 0 | CHZ3: 0 | CIA3: 0 | CIB3: 0 | CIC3: 0 | CID3: 0 | CIE3: 0 | CIF3: 0 | CIG3: 0 | CIH3: 0 | CII3: 0 | CIJ3: 0 | CIK3: 0 | CIL3: 0 | CIM3: 0 | CIN3: 0 | CIO3: 0 | CIP3: 0 | CIQ3: 0 | CIR3: 0 | CIS3: 0 | CIT3: 0 | CIU3: 0 | CIV3: 0 | CIW3: 0 | CIX3: 0 | CIY3: 0 | CIZ3: 0 | CJA3: 0 | CJB3: 0 | CJC3: 0 | CJD3: 0 | CJE3: 0 | CJF3: 0 | CJG3: 0 | CJH3: 0 | CJI3: 0 | CJJ3: 0 | CJK3: 0 | CJL3: 0 | CJM3: 0 | CJN3: 0 | CJO3: 0 | CJP3: 0 | CJQ3: 0 | CJR3: 0 | CJS3: 0 | CJT3: 0 | CJU3: 0 | CJV3: 0 | CJW3: 0 | CJX3: 0 | CJY3: 0 | CJZ3: 0 | CKA3: 0 | CKB3: 0 | CKC3: 0 | CKD3: 0 | CKE3: 0 | CKF3: 0 | CKG3: 0 | CKH3: 0 | CKI3: 0 | CKJ3: 0 | CKK3: 0 | CKL3: 0 | CKM3: 0 | CKN3: 0 | CKO3: 0 | CKP3: 0 | CKQ3: 0 | CKR3: 0 | CKS3: 0 | CKT3: 0 | CKU3: 0 | CKV3: 0 | CKW3: 0 | CKX3: 0 | CKY3: 0 | CKZ3: 0 | CLA3: 0 | CLB3: 0 | CLC3: 0 | CLD3: 0 | CLE3: 0 | CLF3: 0 | CLG3: 0 | CLH3: 0 | CLI3: 0 | CLJ3: 0 | CLK3: 0 | CLL3: 0 | CLM3: 0 | CLN3: 0 | CLO3: 0 | CLP3: 0 | CLQ3: 0 | CLR3: 0 | CLS3: 0 | CLT3: 0 | CLU3: 0 | CLV3: 0 | CLW3: 0 | CLX3: 0 | CLY3: 0 | CLZ3: 0 | CMA3: 0 | CMB3: 0 | CMC3: 0 | CMD3: 0 | CME3: 0 | CMF3: 0 | CMG3: 0 | CMH3: 0 | CMI3: 0 | CMJ3: 0 | CMK3: 0 | CML3: 0 | CMM3: 0 | CMN3: 0 | CMO3: 0 | CMP3: 0 | CMQ3: 0 | CMR3: 0 | CMS3: 0 | CMT3: 0 | CMU3: 0 | CMV3: 0 | CMW3: 0 | CMX3: 0 | CMY3: 0 | CMZ3: 0 | CNA3: 0 | CNB3: 0 | CNC3: 0 | CND3: 0 | CNE3: 0 | CNF3: 0 | CNG3: 0 | CNH3: 0 | CNI3: 0 | CNJ3: 0 | CNK3: 0 | CNL3: 0 | CNM3: 0 | CNN3: 0 | CNO3: 0 | CNP3: 0 | CNQ3: 0 | CNR3: 0 | CNS3: 0 | CNT3: 0 | CNU3: 0 | CNV3: 0 | CNW3: 0 | CNX3: 0 | CNY3: 0 | CNZ3: 0 | COA3: 0 | COB3: 0 | COC3: 0 | COD3: 0 | COE3: 0 | COF3: 0 | COG3: 0 | COH3: 0 | COI3: 0 | COJ3: 0 | COK3: 0 | COL3: 0 | COM3: 0 | CON3: 0 | COO3: 0 | COP3: 0 | COQ3: 0 | COR3: 0 | COS3: 0 | COT3: 0 | COU3: 0 | COV3: 0 | COW3: 0 | COX3: 0 | COY3: 0 | COZ3: 0 | CPA3: 0 | CPB3: 0 | CPC3: 0 | CPD3: 0 | CPE3: 0 | CPF3: 0 | CPG3: 0 | CPH3: 0 | CPI3: 0 | CPJ3: 0 | CPK3: 0 | CPL3: 0 | CPM3: 0 | CPN3: 0 | CPO3: 0 | CPP3: 0 | CPQ3: 0 | CPR3: 0 | CPS3: 0 | CPT3: 0 | CPU3: 0 | CPV3: 0 | CPW3: 0 | CPX3: 0 | CPY3: 0 | CPZ3: 0 | CQA3: 0 | CQB3: 0 | CQC3: 0 | CQD3: 0 | CQE3: 0 | CQF3: 0 | CQG3: 0 | CQH3: 0 | CQI3: 0 | CQJ3: 0 | CQK3: 0 | CQL3: 0 | CQM3: 0 | CQN3: 0 | CQO3: 0 | CQP3: 0 | CQQ3: 0 | CQR3: 0 | CQS3: 0 | CQT3: 0 | CQU3: 0 | CQV3: 0 | CQW3: 0 | CQX3: 0 | CQY3: 0 | CQZ3: 0 | CRA3: 0 | CRB3: 0 | CRC3: 0 | CRD3: 0 | CRE3: 0 | CRF3: 0 | CRG3: 0 | CRH3: 0 | CRI3: 0 | CRJ3: 0 | CRK3: 0 | CRL3: 0 | CRM3: 0 | CRN3: 0 | CRO3: 0 | CRP3: 0 | CRQ3: 0 | CRR3: 0 | CRS3: 0 | CRT3: 0 | CRU3: 0 | CRV3: 0 | CRW3: 0 | CRX3: 0 | CRY3: 0 | CRZ3: 0 | CSA3: 0 | CSB3: 0 | CSC3: 0 | CSD3: 0 | CSE3: 0 | CSF3: 0 | CSG3: 0 | CSH3: 0 | CSI3: 0 | CSJ3: 0 | CSK3: 0 | CSL3: 0 | CSM3: 0 | CSN3: 0 | CSO3: 0 | CSP3: 0 | CSQ3: 0 | CSR3: 0 | CSS3: 0 | CST3: 0 | CSU3: 0 | CSV3: 0 | CSW3: 0 | CSX3: 0 | CSY3: 0 | CSZ3: 0 | CTA3: 0 | CTB3: 0 | CTC3: 0 | CTD3: 0 | CTE3: 0 | CTF3: 0 | CTG3: 0 | CTH3: 0 | CTI3: 0 | CTJ3: 0 | CTK3: 0 | CTL3: 0 | CTM3: 0 | CTN3: 0 | CTO3: 0 | CTP3: 0 | CTQ3: 0 | CTR3: 0 | CTS3: 0 | CTT3: 0 | CTU3: 0 | CTV3: 0 | CTW3: 0 | CTX3: 0 | CTY3: 0 | CTZ3: 0 | CUA3: 0 | CUB3: 0 | CUC3: 0 | CUD3: 0 | CUE3: 0 | CUF3: 0 | CUG3: 0 | CUH3: 0 | CUI3: 0 | CUJ3: 0 | CUK3: 0 | CUL3: 0 | CUM3: 0 | CUN3: 0 | CUO3: 0 | CUP3: 0 | CUQ3: 0 | CUR3: 0 | CUS3: 0 | CUT3: 0 | CUU3: 0 | CUV3: 0 | CUW3: 0 | CUX3: 0 | CUY3: 0 | CUZ3: 0 | CVA3: 0 | CVB3: 0 | CVC3: 0 | CVD3: 0 | CVE3: 0 | CVF3: 0 | CVG3: 0 | CVH3: 0 | CVI3: 0 | CVJ3: 0 | CVK3: 0 | CVL3: 0 | CVM3: 0 | CVN3: 0 | CVO3: 0 | CVP3: 0 | CVQ3: 0 | CVR3: 0 | CVS3: 0 | CVT3: 0 | CVU3: 0 | CVV3: 0 | CVW3: 0 | CVX3: 0 | CVY3: 0 | CVZ3: 0 | CWA3: 0 | CWB3: 0 | CWC3: 0 | CWD3: 0 | CWE3: 0 | CWF3: 0 | CWG3: 0 | CWH3: 0 | CWI3: 0 | CWJ3: 0 | CWK3: 0 | CWL3: 0 | CWM3: 0 | CWN3: 0 | CWO3: 0 | CWP3: 0 | CWQ3: 0 | CWR3: 0 | CWS3: 0 | CWT3: 0 | CWU3: 0 | CWV3: 0 | CWW3: 0 | CWX3: 0 | CWY3: 0 | CWZ3: 0 | CXA3: 0 | CXB3: 0 | CXC3: 0 | CXD3: 0 | CXE3: 0 | CXF3: 0 | CXG3: 0 | CXH3: 0 | CXI3: 0 | CXJ3: 0 | CXK3: 0 | CXL3: 0 | CXM3: 0 | CXN3: 0 | CXO3: 0 | CXP3: 0 | CXQ3: 0 | CXR3: 0 | CXS3: 0 | CXT3: 0 | CXU3: 0 | CXV3: 0 | CXW3: 0 | CXX3: 0 | CXY3: 0 | CXZ3: 0 | CYA3: 0 | CYB3: 0 | CYC3: 0 | CYD3: 0 | CYE3: 0 | CYF3: 0 | CYG3: 0 | CYH3: 0 | CYI3: 0 | CYJ3: 0 | CYK3: 0 | CYL3: 0 | CYM3: 0 | CYN3: 0 | CYO3: 0 | CYP3: 0 | CYQ3: 0 | CYR3: 0 | CYS3: 0 | CYT3: 0 | CYU3: 0 | CYV3: 0 | CYW3: 0 | CYX3: 0 | CYY3: 0 | CYZ3: 0 | CZA3: 0 | CZB3: 0 | CZC3: 0 | CZD3: 0 | CZE3: 0 | CZF3: 0 | CZG3: 0 | CZH3: 0 | CZI3: 0 | CZJ3: 0 | CZK3: 0 | CZL3: 0 | CZM3: 0 | CZN3: 0 | CZO3: 0 | CZP3: 0 | CZQ3: 0 | CZR3: 0 | CZS3: 0 | CZT3: 0 | CZU3: 0 | CZV3: 0 | CZW3: 0 | CZX3: 0 | CZY3: 0 | CZZ3: 0 | DAA3: 0 | DAB3: 0 | DAC3: 0 | DAD3: 0 | DAE3: 0 | DAF3: 0 | DAG3: 0 | DAH3: 0 | DAI3: 0 | DAJ3: 0 | DAK3: 0 | DAL3: 0 | DAM3: 0 | DAN3: 0 | DAO3: 0 | DAP3: 0 | DAQ3: 0 | DAR3: 0 | DAS3: 0 | DAT3: 0 | DAU3: 0 | DAV3: 0 | DAW3: 0 | DAX3: 0 | DAY3: 0 | DAZ3: 0 | DBA3: 0 | DBB3: 0 | DBC3: 0 | DBD3: 0 | DBE3: 0 | DBF3: 0 | DBG3: 0 | DBH3: 0 | DBI3: 0 | DBJ3: 0 | DBK3: 0 | DBL3: 0 | DBM3: 0 | DBN3: 0 | DBO3: 0 | DBP3: 0 | DBQ3: 0 | DBR3: 0 | DBS3: 0 | DBT3: 0 | DBU3: 0 | DBV3: 0 | DBW3: 0 | DBX3: 0 | DBY3: 0 | DBZ3: 0 | DCA3: 0 | DCB3: 0 | DCC3: 0 | DCD3: 0 | DCE3: 0 | DCF3: 0 | DCG3: 0 | DCH3: 0 | DCI3: 0 | DCJ3: 0 | DCK3: 0 | DCL3: 0 | DCM3: 0 | DCN3: 0 | DCO3: 0 | DCP3: 0 | DCQ3: 0 | DCR3: 0 | DCS3: 0 | DCT3: 0 | DCU3: 0 | DCV3: 0 | DCW3: 0 | DCX3: 0 | DCY3: 0 | DCZ3: 0 | DDA3: 0 | DDB3: 0 | DDC3: 0 | DDD3: 0 | DDE3: 0 | DDF3: 0 | DDG3: 0 | DDH3: 0 | DDI3: 0 | DDJ3: 0 | DDK3: 0 | DDL3: 0 | DDM3: 0 | DDN3: 0 | DDO3: 0 | DDP3: 0 | DDQ3: 0 | DDR3: 0 | DDS3: 0 | DDT3: 0 | DDU3: 0 | DDV3: 0 | DDW3: 0 | DDX3: 0 | DDY3: 0 | DDZ3: 0 | DEA3: 0 | DEB3: 0 | DEC3: 0 | DED3: 0 | DEE3: 0 | DEF3: 0 | DEG3: 0 | DEH3: 0 | DEI3: 0 | DEJ3: 0 | DEK3: 0 | DEL3: 0 | DEM3: 0 | DEN3: 0 | DEO3: 0 | DEP3: 0 | DEQ3: 0 | DER3: 0 | DES3: 0 | DET3: 0 | DEU3: 0 | DEV3: 0 | DEW3: 0 | DEX3: 0 | DEY3: 0 | DEZ3: 0 | DFA3: 0 | DFB3: 0 | DFC3: 0 | DFD3: 0 | DFE3: 0 | DFF3: 0 | DFG3: 0 | DFH3: 0 | DFI3: 0 | DFJ3: 0 | DFK3: 0 | DFL3: 0 | DFM3: 0 | DFN3: 0 | DFO3: 0 | DFP3: 0 | DFQ3: 0 | DFR3: 0 | DFS3: 0 | DFT3: 0 | DFU3: 0 | DFV3: 0 | DFW3: 0 | DFX3: 0 | DFY3: 0 | DFZ3: 0 | DGA3: 0 | DGB3: 0 | DGC3: 0 | DGD3: 0 | DGE3: 0 | DGF3: 0 | DGG3: 0 | DGH3: 0 | DGI3: 0 | DGJ3: 0 | DGK3: 0 | DGL3: 0 | DGM3: 0 | DGN3: 0 | DGO3: 0 | DGP3: 0 | DGQ3: 0 | DGR3: 0 | DGS3: 0 | DGT3: 0 | DGU3: 0 | DGV3: 0 | DGW3: 0 | DGX3: 0 | DGY3: 0 | DGZ3: 0 | DHA3: 0 | DHB3: 0 | DHC3: 0 | DHD3: 0 | DHE3: 0 | DHF3: 0 | DHG3: 0 | DHH3: 0 | DHI3: 0 | DHJ3: 0 | DHK3: 0 | DHL3: 0 | DHM3: 0 | DHN3: 0 | DHO3: 0 | DHP3: 0 | DHQ3: 0 | DHR3: 0 | DHS3: 0 | DHT3: 0 | DHU3: 0 | DHV3: 0 | DHW3: 0 | DHX3: 0 | DHY3: 0 | DHZ3: 0 | DIA3: 0 | DIB3: 0 | DIC3: 0 | DID3: 0 | DIE3: 0 | DIF3: 0 | DIG3: 0 | DIH3: 0 | DII3: 0 | DIJ3: 0 | DIK3: 0 | DIL3: 0 | DIM3: 0 | DIN3: 0 | DIO3: 0 | DIP3: 0 | DIQ3: 0 | DIR3: 0 | DIS3: 0 | DIT3: 0 | DIU3: 0 | DIV3: 0 | DIW3: 0 | DIX3: 0 | DIY3: 0 | DIZ3: 0 | DJA3: 0 | DJB3: 0 | DJC3: 0 | DJD3: 0 | DJE3: 0 | DJF3: 0 | DJG3: 0 | DJH3: 0 | DJI3: 0 | DJJ3: 0 | DJK3: 0 | DJL3: 0 | DJM3: 0 | DJN3: 0 | DJO3: 0 | DJP3: 0 | DJQ3: 0 | DJR3: 0 | DJS3: 0 | DJT3: 0 | DJU3: 0 | DJV3: 0 | DJW3: 0 | DJX3: 0 | DJY3: 0 | DJZ3: 0 | DKA3: 0 | DKB3: 0 | DKC3: 0 | DKD3: 0 | DKE3: 0 | DKF3: 0 | DKG3: 0 | DKH3: 0 | DKI3: 0 | DKJ3: 0 | DKK3: 0 | DKL3: 0 | DKM3: 0 | DKN3: 0 | DKO3: 0 | DKP3: 0 | DKQ3: 0 | DKR3: 0 | DKS3: 0 | DKT3: 0 | DKU3: 0 | DKV3: 0 | DKW3: 0 | DKX3: 0 | DKY3: 0 | DKZ3: 0 | DLA3: 0 | DLB3: 0 | DLC3: 0 | DLD3: 0 | DLE3: 0 | DLF3: 0 | DLG3: 0 | DLH3: 0 | DLI3: 0 | DLJ3: 0 | DLK3: 0 | DLL3: 0 | DLM3: 0 | DLN3: 0 | DLO3: 0 | DLP3: 0 | DLQ3: 0 | DLR3: 0 | DLS3: 0 | DLT3: 0 | DLU3: 0 | DLV3: 0 | DLW3: 0 | DLX3: 0 | DLY3: 0 | DLZ3: 0 | DMA3: 0 | DMB3: 0 | DMC3: 0 | DMD3: 0 | DME3: 0 | DMF3: 0 | DMG3: 0 | DMH3: 0 | DMI3: 0 | DMJ3: 0 | DMK3: 0 | DML3: 0 | DMM3: 0 | DMN3: 0 | DMO3: 0 | DMP3: 0 | DMQ3: 0 | DMR3: 0 | DMS3: 0 | DMT3: 0 | DMU3: 0 | DMV3: 0 | DMW3: 0 | DMX3: 0 | DMY3: 0 | DMZ3: 0 | DNA3: 0 | DNB3: 0 | DNC3: 0 | DND3: 0 | DNE3: 0 | DNF3: 0 | DNG3: 0 | DNH3: 0 | DNI3: 0 | DNJ3: 0 | DNK3: 0 | DNL3: 0 | DNM3: 0 | DNN3: 0 | DNO3: 0 | DNP3: 0 | DNQ3: 0 | DNR3: 0 | DNS3: 0 | DNT3: 0 | DNU3: 0 | DNV3: 0 | DNW3: 0 | DNX3: 0 | DNY3: 0 | DNZ3: 0 | DOA3: 0 | DOB3: 0 | DOC3: 0 | DOD3: 0 | DOE3: 0 | DOF3: 0 | DOG3: 0 | DOH3: 0 | DOI3: 0 | DOJ3: 0 | DOK3: 0 | DOL3: 0 | DOM3: 0 | DON3: 0 | DOO3: 0 | DOP3: 0 | DOQ3: 0 | DOR3: 0 | DOS3: 0 | DOT3: 0 | DOU3: 0 | DOV3: 0 | DOW3: 0 | DOX3: 0 | DOY3: 0 | DOZ3: 0 | DPA3: 0 | DPB3: 0 | DPC3: 0 | DPD3: 0 | DPE3: 0 | DPF3: 0 | DPG3: 0 | DPH3: 0 | DPI3: 0 | DPJ3: 0 | DPK3: 0 | DPL3: 0 | DPM3: 0 | DPN3: 0 | DPO3: 0 | DPP3: 0 | DPQ3: 0 | DPR3: 0 | DPS3: 0 | DPT3: 0 | DPU3: 0 | DPV3: 0 | DPW3: 0 | DPX3: 0 | DPY3: 0 | DPZ3: 0 | DQA3: 0 | DQB3: 0 | DQC3: 0 | DQD3: 0 | DQE3: 0 | DQF3: 0 | DQG3: 0 | DQH3: 0 | DQI3: 0 | DQJ3: 0 | DQK3: 0 | DQL3: 0 | DQM3: 0 | DQN3: 0 | DQO3: 0 | DQP3: 0 | DQQ3: 0 | DQR3: 0 | DQS3: 0 | DQT3: 0 | DQU3: 0 | DQV3: 0 | DQW3: 0 | DQX3: 0 | DQY3: 0 | DQZ3: 0 | DRA3: 0 | DRB3: 0 | DRC3: 0 | DRD3: 0 | DRE3: 0 | DRF3: 0 | DRG3: 0 | DRH3: 0 | DRI3: 0 | DRJ3: 0 | DRK3: 0 | DRL3: 0 | DRM3: 0 | DRN3: 0 | DRO3: 0 | DRP3: 0 | DRQ3: 0 | DRR3: 0 | DRS3: 0 | DRT3: 0 | DRU3: 0 | DRV3: 0 | DRW3: 0 | DRX3: 0 | DRY3: 0 | DRZ3: 0 | DSA3: 0 | DSB3: 0 | DSC3: 0 | DSD3: 0 | DSE3: 0 | DSF3: 0 | DSG3: 0 | DSH3: 0 | DSI3: 0 | DSJ3: 0 | DSK3: 0 | DSL3: 0 | DSM3: 0 | DSN3: 0 | DSO3: 0 | DSP3: 0 | DSQ3: 0 | DSR3: 0 | DSS3: 0 | DST3: 0 | DSU3: 0 | DSV3: 0 | DSW3: 0 | DSX3: 0 | DSY3: 0 | DSZ3: 0 | DTA3: 0 | DTB3: 0 | DTC3: 0 | DTD3: 0 | DTE3: 0 | DTF3: 0 | DTG3: 0 | DTH3: 0 | DTI3: 0 | DTJ3: 0 | DTK3: 0 | DTL3: 0 | DTM3: 0 | DTN3: 0 | DTO3: 0 | DTP3: 0 | DTQ3: 0 | DTR3: 0 | DTS3: 0 | DTT3: 0 | DTU3: 0 | DTV3: 0 | DTW3: 0 | DTX3: 0 | DTY3: 0 | DTZ3: 0 | DUA3: 0 | DUB3: 0 | DUC3: 0 | DUD3: 0 | DUE3: 0 | DUF3: 0 | DUG3: 0 | DUH3: 0 | DUI3: 0 | DUJ3: 0 | DUK3: 0 | DUL3: 0 | DUM3: 0 | DUN3: 0 | DUO3: 0 | DUP3: 0 | DUQ3: 0 | DUR3: 0 | DUS3: 0 | DUT3: 0 | DUU3: 0 | DUV3: 0 | DUW3: 0 | DUX3: 0 | DUY3: 0 | DUZ3: 0 | DVA3: 0 | DVB3: 0 | DVC3: 0 | DVD3: 0 | DVE3: 0 | DVF3: 0 | DVG3: 0 | DVH3: 0 | DVI3: 0 | DVJ3: 0 | DVK3: 0 | DVL3: 0 | DVM3: 0 | DVN3: 0 | DVO3: 0 | DVP3: 0 | DVQ3: 0 | DVR3: 0 | DVS3: 0 | DVT3: 0 | DVU3: 0 | DVV3: 0 | DVW3: 0 | DVX3: 0 | DVY3: 0 | DVZ3: 0 | DWA3: 0 | DWB3: 0 | DWC3: 0 | DWD3: 0 | DWE3: 0 | DWF3: 0 | DWG3: 0 | DWH3: 0 | DWI3: 0 | DWJ3: 0 | DWK3: 0 | DWL3: 0 | DWM3: 0 | DWN3: 0 | DWO3: 0 | DWP3: 0 | DWQ3: 0 | DWR3: 0 | DWS3: 0 | DWT3: 0 | DWU3: 0 | DWV3: 0 | DWW3: 0 | DWX3: 0 | DWY3: 0 | DWZ3: 0 | DXA3: 0 | DXB3: 0 | DXC3: 0 | DXD3: 0 | DXE3: 0 | DXF3: 0 | DXG3: 0 | DXH3: 0 | DXI3: 0 | DXJ3: 0 | DXK3: 0 | DXL3: 0 | DXM3: 0 | DXN3: 0 | DXO3: 0 | DXP3: 0 | DXQ3: 0 | DXR3: 0 | DXS3: 0 | DXT3: 0 | DXU3: 0 | DXV3: 0 | DXW3: 0 | DXX3: 0 | DXY3: 0 | DXZ3: 0 | DYA3: 0 | DYB3: 0 | DYC3: 0 | DYD3: 0 | DYE3: 0 | DYF3: 0 | DYG3: 0 | DYH3: 0 | DYI3: 0 | DYJ3: 0 | DYK3: 0 | DYL3: 0 | DYM3: 0 | DYN3: 0 | DYO3: 0 | DYP3: 0 | DYQ3: 0 | DYR3: 0 | DYS3: 0 | DYT3: 0 | DYU3: 0 | DYV3: 0 | DYW3: 0 | DYX3: 0 | DYY3: 0 | DYZ3: 0 | DZA3: 0 | DZB3: 0 | DZC3: 0 | DZD3: 0 | DZE3: 0 | DZF3: 0 | DZG3: 0 | DZH3: 0 | DZI3: 0 | DZJ3: 0 | DZK3: 0 | DZL3: 0 | DZM3: 0 | DZN3: 0 | DZO3: 0 | DZP3: 0 | DZQ3: 0 | DZR3: 0 | DZS3: 0 | DZT3: 0 | DZU3: 0 | DZV3: 0 | DZW3: 0 | DZX3: 0 | DZY3: 0 | DZZ3: 0 | EAA3: 0 | EAB3: 0 | EAC3: 0 | EAD3: 0 | EAE3: 0 | EAF3: 0 | EAG3: 0 | EAH3: 0 | EAI3: 0 | EAJ3: 0 | EAK3: 0 | EAL3: 0 | EAM3: 0 | EAN3: 0 | EAO3: 0 | EAP3: 0 | EAQ3: 0 | EAR3: 0 | EAS3: 0 | EAT3: 0 | EAU3: 0 | EAV3: 0 | EAW3: 0 | EAX3: 0 | EAY3: 0 | EAZ3: 0 | EBA3: 0 | EBB3: 0 | EBC3: 0 | EBD3: 0 | EBE3: 0 | EBF3: 0 | EBG3: 0 | EBH3: 0 | EBI3: 0 | EBJ3: 0 | EBK3: 0 | EBL3: 0 | EBM3: 0 | EBN3: 0 | EBO3: 0 | EBP3: 0 | EBQ3: 0 | EBR3: 0 | EBS3: 0 | EBT3: 0 | EBU3: 0 | EBV3: 0 | EBW3: 0 | EBX3: 0 | EBY3: 0 | EBZ3: 0 | ECA3: 0 | ECB3: 0 | ECC3: 0 | ECD3: 0 | ECE3: 0 | ECF3: 0 | ECG3: 0 | ECH3: 0 | ECI3: 0 | ECJ3: 0 | ECK3: 0 | ECL3: 0 | ECM3: 0 | ECN3: 0 | ECO3: 0 | ECP3: 0 | ECQ3: 0 | ECR3: 0 | ECS3: 0 | ECT3: 0 | ECU3: 0 | ECV3: 0 | ECW3: 0 | ECX3: 0 | ECY3: 0 | ECZ3: 0 | EDA3: 0 | EDB3: 0 | EDC3: 0 | EDD3: 0 | EDE3: 0 | EDF3: 0 | EDG3: 0 | EDH3: 0 | EDI3: 0 | EDJ3: 0 | EDK3: 0 | EDL3: 0 | EDM3: 0 | EDN3: 0 | EDO3: 0 | EDP3: 0 | EDQ3: 0 | EDR3: 0 | EDS3: 0 | EDT3: 0 | EDU3: 0 | EDV3: 0 | EDW3: 0 | EDX3: 0 | EDY3: 0 | EDZ3: 0 | EEA3: 0 | EEB3: 0 | EEC3: 0 | EED3: 0 | EEE3: 0 | EEF3: 0 | EEG3: 0 | EEH3: 0 | EEI3: 0 | EEJ3: 0 | EEK3: 0 | EEL3: 0 | EEM3: 0 | EEN3: 0 | EEO3: 0 | EEP3: 0 | EEQ3: 0 | EER3: 0 | EES3: 0 | EET3: 0 | EEU3: 0 | EEV3: 0 | EEW3: 0 | EEX3: 0 | EEY3: 0 | EEZ3: 0 | EFA3: 0 | EFB3: 0 | EFC3: 0 | EFD3: 0 | EFE3: 0 | EFF3: 0 | EFG3: 0 | EFH3: 0 | EFI3: 0 | EFJ3: 0 | EFK3: 0 | EFL3: 0 | EFM3: 0 | EFN3: 0 | EFO3: 0 | EFP3: 0 | EFQ3: 0 | EFR3: 0 | EFS3: 0 | EFT3: 0 | EFU3: 0 | EFV3: 0 | EFW3: 0 | EFX3: 0 | EFY3: 0 | EFZ3: 0 | EGA3: 0 | EGB3: 0 | EGC3: 0 | EGD3: 0 | EGE3: 0 | EGF3: 0 | EGG3: 0 | EGH3: 0 | EGI3: 0 | EGJ3: 0 | EGK3: 0 | EGL3: 0 | EGM3: 0 | EGN3: 0 | EGO3: 0 | EGP3: 0 | EGQ3: 0 | EGR3: 0 | EGS3: 0 | EGT3: 0 | EGU3: 0 | EGV3: 0 | EGW3: 0 | EGX3: 0 | EGY3: 0 | EGZ3: 0 | EHA3: 0 | EHB3: 0 | EHC3: 0 | EHD3: 0 | EHE3: 0 | EHF3: 0 | EHG3: 0 | EHH3: 0 | EHI3: 0 | EHJ3: 0 | EHK3: 0 | EHL3: 0 | EHM3: 0 | EHN3: 0 | EHO3: 0 | EHP3: 0 | EHQ3: 0 | EHR3: 0 | EHS3: 0 | EHT3: 0 | EHU3: 0 | EHV3: 0 | EHW3: 0 | EHX3: 0 | EHY3: 0 | EHZ3: 0 | EIA3: 0 | EIB3: 0 | EIC3: 0 | EID3: 0 | EIE3: 0 | EIF3: 0 | EIG3: 0 | EIH3: 0 | EII3: 0 | EIJ3: 0 | EIK3: 0 | EIL3: 0 | EIM3: 0 | EIN3: 0 | EIO3: 0 | EIP3: 0 | EIQ3: 0 | EIR3: 0 | EIS3: 0 | EIT3: 0 | EIU3: 0 | EIV3: 0 | EIW3: 0 | EIX3: 0 | EIY3: 0 | EIZ3: 0 | EJA3: 0 | EJB3: 0 | EJC3: 0 | EJD3: 0 | EJE3: 0 | EJF3: 0 | EJG3: 0 | EJH3: 0 | EJI3: 0 | EJJ3: 0 | EJK3: 0 | EJL3: 0 | EJM3: 0 | EJN3: 0 | EJO3: 0 | EJP3: 0 | EJQ3: 0 | EJR3: 0 | EJS3: 0 | EJT3: 0 | EJU3: 0 | EJV3: 0 | EJW3: 0 | EJX3: 0 | EJY3: 0 | EJZ3: 0 | EKA3: 0 | EKB3: 0 | EKC3: 0 | EKD3: 0 | EKE3: 0 | EKF3: 0 | EKG3: 0 | EKH3: 0 | EKI3: 0 | EKJ3: 0 | EKK3: 0 | EKL3: 0 | EKM3: 0 | EKN3: 0 | EKO3: 0 | EKP3: 0 | EKQ3: 0 | EKR3: 0 | EKS3: 0 | EKT3: 0 | EKU3: 0 | EKV3: 0 | EKW3: 0 | EKX3: 0 | EKY3: 0 | EKZ3: 0 | ELA3: 0 | ELB3: 0 | ELC3: 0 | ELD3: 0 | ELE3: 0 | ELF3: 0 | ELG3: 0 | ELH3: 0 | ELI3: 0 | ELJ3: 0 | ELK3: 0 | ELL3: 0 | ELM3: 0 | ELN3: 0 | ELO3: 0 | ELP3: 0 | ELQ3: 0 | ELR3: 0 | ELS3: 0 | ELT3: 0 | ELU3: 0 | ELV3: 0 | ELW3: 0 | ELX3: 0 | ELY3: 0 | ELZ3: 0 | EMA3: 0 | EMB3: 0 | EMC3: 0 | EMD3: 0 | EME3: 0 | EMF3: 0 | EMG3: 0 | EMH3: 0 | EMI3: 0 | EMJ3: 0 | EMK3: 0 | EML3: 0 | EMM3: 0 | EMN3: 0 | EMO3: 0 | EMP3: 0 | EMQ3: 0 | EMR3: 0 | EMS3: 0 | EMT3: 0 | EMU3: 0 | EMV3: 0 | EMW3: 0 | EMX3: 0 | EMY3: 0 | EMZ3: 0 | ENA3: 0 | ENB3: 0 | ENC3: 0 | END3: 0 | ENE3: 0 | ENF3: 0 | ENG3: 0 | ENH3: 0 | ENI3: 0 | ENJ3: 0 | ENK3: 0 | ENL3: 0 | ENM3: 0 | ENN3: 0 | ENO3: 0 | ENP3: 0 | ENQ3: 0 | ENR3: 0 | ENS3: 0 | ENT3: 0 | ENU3: 0 | ENV3: 0 | ENW3: 0 | ENX3: 0 | ENY3: 0 | ENZ3: 0 | EOA3: 0 | EOB3: 0 | EOC3: 0 | EOD3: 0 | EOE3: 0 | EOF3: 0 | EOG3: 0 | EOH3: 0 | EOI3: 0 | EOJ3: 0 | EOK3: 0 | EOL3: 0 | EOM3: 0 | EON3: 0 | EOO3: 0 | EOP3: 0 | EOQ3: 0 | EOR3: 0 | EOS3: 0 | EOT3: 0 | EOU3: 0 | EOV3: 0 | EOW3: 0 | EOX3: 0 | EOY3: 0 | EOZ3: 0 | EPA3: 0 | EPB3: 0 | EPC3: 0 | EPD3: 0 | EPE3: 0 | EPF3: 0 | EPG3: 0 | EPH3: 0 | EPI3: 0 | EPJ3: 0 | EPK3: 0 | EPL3: 0 | EPM3: 0 | EPN3: 0 | EPO3: 0 | EPP3: 0 | EPQ3: 0 | EPR3: 0 | EPS3: 0 | EPT3: 0 | EPU3: 0 | EPV3: 0 | EPW3: 0 | EPX3: 0 | EPY3: 0 | EPZ3: 0 | EQA3: 0 | EQB3: 0 | EQC3: 0 | EQD3: 0 | EQE3: 0 | EQF3: 0 | EQG3: 0 | EQH3: 0 | EQI3: 0 | EQJ3: 0 | EQK3: 0 | EQL3: 0 | EQM3: 0 | EQN3: 0 | EQO3: 0 | EQP3: 0 | EQQ3: 0 | EQR3: 0 | EQS3: 0 | EQT3: 0 | EQU3: 0 | EQV3: 0 | EQW3: 0 | EQX3: 0 | EQY3: 0 | EQZ3: 0 | ERA3: 0 | ERB3: 0 | ERC3: 0 | ERD3: 0 | ERE3: 0 | ERF3: 0 | ERG3: 0 | ERH3: 0 | ERI3: 0 | ERJ3: 0 | ERK3: 0 | ERL3: 0 | ERM3: 0 | ERN3: 0 | ERO3: 0 | ERP3: 0 | ERQ3: 0 | ERR3: 0 | ERS3: 0 | ERT3: 0 | ERU3: 0 | ERV3: 0 | ERW3: 0 | ERX3: 0 | ERY3: 0 | ERZ3: 0 | ESA3: 0 | ESB3: 0 | ESC3: 0 | ESD3: 0 | ESE3: 0 | ESF3: 0 | ESG3: 0 | ESH3: 0 | ESI3: 0 | ESJ3: 0 | ESK3: 0 | ESL3: 0 | ESM3: 0 | ESN3: 0 | ESO3: 0 | ESP3: 0 | ESQ3: 0 | ESR3: 0 | ESS3: 0 | EST3: 0 | ESU3: 0 | ESV3: 0 | ESW3: 0 | ESX3: 0 | ESY3: 0 | ESZ3: 0 | ETA3: 0 | ETB3: 0 | ETC3: 0 | ETD3: 0 | ETE3: 0 | ETF3: 0 | ETG3: 0 | ETH3: 0 | ETI3: 0 | ETJ3: 0 | ETK3: 0 | ETL3: 0 | ETM3: 0 | ETN3: 0 | ETO3: 0 | ETP3: 0 | ETQ3: 0 | ETR3: 0 | ETS3: 0 | ETT3: 0 | ETU3: 0 | ETV3: 0 | ETW3: 0 | ETX3: 0 | ETY3: 0 | ETZ3: 0 | EUA3: 0 | EUB3: 0 | EUC3: 0 | EUD3: 0 | EUE3: 0 | EUF3: 0 | EUG3: 0 | EUH3: 0 | EUI3: 0 | EUJ3: 0 | EUK3: 0 | EUL3: 0 | EUM3: 0 | EUN3: 0 | EUO3: 0 | EUP3: 0 | EUQ3: 0 | EUR3: 0 | EUS3: 0 | EUT3: 0 | EUU3: 0 | EUV3: 0 | EUW3: 0 | EUX3: 0 | EUY3: 0 | EUZ3: 0 | EVA3: 0 | EVB3: 0 | EVC3: 0 | EVD3: 0 | EVE3: 0 | EVF3: 0 | EVG3: 0 | EVH3: 0 | EVI3: 0 | EVJ3: 0 | EVK3: 0 | EVL3: 0 | EVM3: 0 | EVN3: 0 | EVO3: 0 | EVP3: 0 | EVQ3: 0 | EVR3: 0 | EVS3: 0 | EVT3: 0 | EVU3: 0 | EVV3: 0 | EVW3: 0 | EVX3: 0 | EVY3: 0 | EVZ3: 0 | EWA3: 0 | EWB3: 0 | EWC3: 0 | EWD3: 0 | EWE3: 0 | EWF3: 0 | EWG3: 0 | EWH3: 0 | EWI3: 0 | EWJ3: 0 | EWK3: 0 | EWL3: 0 | EWM3: 0 | EWN3: 0 | EWO3: 0 | EWP3: 0 | EWQ3: 0 | EWR3: 0 | EWS3: 0 | EWT3: 0 | EWU3: 0 | EWV3: 0 | EWW3: 0 | EWX3: 0 | EWY3: 0 | EWZ3: 0 | EXA3: 0 | EXB3: 0 | EXC3: 0 | EXD3: 0 | EXE3: 0 | EXF3: 0 | EXG3: 0 | EXH3: 0 | EXI3: 0 | EXJ3: 0 | EXK3: 0 | EXL3: 0 | EXM3: 0 | EXN3: 0 | EXO3: 0 | EXP3: 0 | EXQ3: 0 | EXR3: 0 | EXS3: 0 | EXT3: 0 | EXU3: 0 | EXV3: 0 | EXW3: 0 | EXX3: 0 | EXY3: 0 | EXZ3: 0 | EYA3: 0 | EYB3: 0 | EYC3: 0 | EYD3: 0 | EYE3: 0 | EYF3: 0 | EYG3: 0 | EYH3: 0 | EYI3: 0 | EYJ3: 0 | EYK3: 0 | EYL3: 0 | EYM3: 0 | EYN3: 0 | EYO3: 0 | EYP3: 0 | EYQ3: 0 | EYR3: 0 | EYS3: 0 | EYT3: 0 | EYU3: 0 | EYV3: 0 | EYW3: 0 | EYX3: 0 | EYY3: 0 | EYZ3: 0 | EZA3: 0 | EZB3: 0 | EZC3: 0 | EZD3: 0 | EZE3: 0 | EZF3: 0 | EZG3: 0 | EZH3: 0 | EZI3: 0 | EZJ3: 0 | EZK3: 0 | EZL3: 0 | EZM3: 0 | EZN3: 0 | EZO3: 0 | EZP3: 0 | EZQ3: 0 | EZR3: 0 | EZS3: 0 | EZT3: 0 | EZU3: 0 | EZV3: 0 | EZW3: 0 | EZX3: 0 | EZY3: 0 | EZZ3: 0 | FAA3: 0 | FAB3: 0 | FAC3: 0 | FAD3: 0 | FAE3: 0 | FAF3: 0 | FAG3: 0 | FAH3: 0 | FAI3: 0 | FAJ3: 0 | FAK3: 0 | FAL3: 0 | FAM3: 0 | FAN3: 0 | FAO3: 0 | FAP3: 0 | FAQ3: 0 | FAR3: 0 | FAS3: 0 | FAT3: 0 | FAU3: 0 | FAV3: 0 | FAW3: 0 | FAX3: 0 | FAY3: 0 | FAZ3: 0 | FBA3: 0 | FBB3: 0 | FBC3: 0 | FBD3: 0 | FBE3: 0 | FBF3: 0 | FBG3: 0 | FBH3: 0 | FBI3: 0 | FBJ3: 0 | FBK3: 0 | FBL3: 0 | FBM3: 0 | FBN3: 0 | FBO3: 0 | FBP3: 0 | FBQ3: 0 | FBR3: 0 | FBS3: 0 | FBT3: 0 | FBU3: 0 | FBV3: 0 | FBW3: 0 | FBX3: 0 | FBY3: 0 | FBZ3: 0 | FCA3: 0 | FCB3: 0 | FCC3: 0 | FCD3: 0 | FCE3: 0 | FCF3: 0 | FCG3: 0 | FCH3: 0 | FCI3: 0 | FCJ3: 0 | FCK3: 0 | FCL3: 0 | FCM3: 0 | FCN3: 0 | FCO3: 0 | FCP3: 0 | FCQ3: 0 | FCR3: 0 | FCS3: 0 | FCT3: 0 | FCU3: 0 | FCV3: 0 | FCW3: 0 | FCX3: 0 | FCY3: 0 | FCZ3: 0 | FDA3: 0 | FDB3: 0 | FDC3: 0 | FDD3: 0 | FDE3: 0 | FDF3: 0 | FDG3: 0 | FDH3: 0 | FDI3: 0 | FDJ3: 0 | FDK3: 0 | FDL3: 0 | FDM3: 0 | FDN3: 0 | FDO3: 0 | FDP3: 0 | FDQ3: 0 | FDR3: 0 | FDS3: 0 | FDT3: 0 | FDU3: 0 | FDV3: 0 | FDW3: 0 | FDX3: 0 | FDY3: 0 | FDZ3: 0 | FEA3: 0 | FEB3: 0 | FEC3: 0 | FED3: 0 | FEE3: 0 | FEF3: 0 | FEG3: 0 | FEH3: 0 | FEI3: 0 | FEJ3: 0 | FEK3: 0 | FEL3: 0 | FEM3: 0 | FEN3: 0 | FEO3: 0 | FEP3: 0 | FEQ3: 0 | FER3: 0 | FES3: 0 | FET3: 0 | FEU3: 0 | FEV3: 0 | FEW3: 0 | FEX3: 0 | FEY3: 0 | FEZ3: 0 | FFA3: 0 | FFB3: 0 | FFC3: 0 | FFD3: 0 | FFE3: 0 | FFF3: 0 | FFG3: 0 | FFH3: 0 | FFI3: 0 | FFJ3: 0 | FFK3: 0 | FFL3: 0 | FFM3: 0 | FFN3: 0 | FFO3: 0 | FFP3: 0 | FFQ3: 0 | FFR3: 0 | FFS3: 0 | FFT3: 0 | FFU3: 0 | FFV3: 0 | FFW3: 0 | FFX3: 0 | FFY3: 0 | FFZ3: 0 | FGA3: 0 | FGB3: 0 | FGC3: 0 | FGD3: 0 | FGE3: 0 | FGF3: 0 | FGG3: 0 | FGH3: 0 | FGI3: 0 | FGJ3: 0 | FGK3: 0 | FGL3: 0 | FGM3: 0 | FGN3: 0 | FGO3: 0 | FGP3: 0 | FGQ3: 0 | FGR3: 0 | FGS3: 0 | FGT3: 0 | FGU3: 0 | FGV3: 0 | FGW3: 0 | FGX3: 0 | FGY3: 0 | FGZ3: 0 | FHA3: 0 | FHB3: 0 | FHC3: 0 | FHD3: 0 | FHE3: 0 | FHF3: 0 | FHG3: 0 | FHH3: 0 | FHI3: 0 | FHJ3: 0 | FHK3: 0 | FHL3: 0 | FHM3: 0 | FHN3: 0 | FHO3: 0 | FHP3: 0 | FHQ3: 0 | FHR3: 0 | FHS3: 0 | FHT3: 0 | FHU3: 0 | FHV3: 0 | FHW3: 0 | FHX3: 0 | FHY3: 0 | FHZ3: 0 | FIA3: 0 | FIB3: 0 | FIC3: 0 | FID3: 0 | FIE3: 0 | FIF3: 0 | FIG3: 0 | FIH3: 0 | FII3: 0 | FIJ3: 0 | FIK3: 0 | FIL3: 0 | FIM3: 0 | FIN3: 0 | FIO3: 0 | FIP3: 0 | FIQ3: 0 | FIR3: 0 | FIS3: 0 | FIT3: 0 | FIU3: 0 | FIV3: 0 | FIW3: 0 | FIX3: 0 | FIY3: 0 | FIZ3: 0 | FJA3: 0 | FJB3: 0 | FJC3: 0 | FJD3: 0 | FJE3: 0 | FJF3: 0 | FJG3: 0 | FJH3: 0 | FJI3: 0 | FJJ3: 0 | FJK3: 0 | FJL3: 0 | FJM3: 0 | FJN3: 0 | FJO3: 0 | FJP3: 0 | FJQ3: 0 | FJR3: 0 | FJS3: 0 | FJT3: 0 | FJU3: 0 | FJV3: 0 | FJW3: 0 | FJX3: 0 | FJY3: 0 | FJZ3: 0 | FKA3: 0 | FKB3: 0 | FKC3: 0 | FKD3: 0 | FKE3: 0 | FKF3: 0 | FKG3: 0 | FKH3: 0 | FKI3: 0 | FKJ3: 0 | FKK3: 0 | FKL3: 0 | FKM3: 0 | FKN3: 0 | FKO3: 0 | FKP3: 0 | FKQ3: 0 | FKR3: 0 | FKS3: 0 | FKT3: 0 | FKU3: 0 | FKV3: 0 | FKW3: 0 | FKX3: 0 | FKY3: 0 | FKZ3: 0 | FLA3: 0 | FLB3: 0 | FLC3: 0 | FLD3: 0 | FLE3: 0 | FLF3: 0 | FLG3: 0 | FLH3: 0 | FLI3: 0 | FLJ3: 0 | FLK3: 0 | FLL3: 0 | FLM3: 0 | FLN3: 0 | FLO3: 0 | FLP3: 0 | FLQ3: 0 | FLR3: 0 | FLS3: 0 | FLT3: 0 | FLU3: 0 | FLV3: 0 | FLW3: 0 | FLX3: 0 | FLY3: 0 | FLZ3: 0 | FMA3: 0 | FMB3: 0 | FMC3: 0 | FMD3: 0 | FME3: 0 | FMF3: 0 | FMG3: 0 | FMH3: 0 | FMI3: 0 | FMJ3: 0 | FMK3: 0 | FML3: 0 | FMM3: 0 | FMN3: 0 | FMO3: 0 | FMP3: 0 | FMQ3: 0 | FMR3: 0 | FMS3: 0 | FMT3: 0 | FMU3: 0 | FMV3: 0 | FMW3: 0 | FMX3: 0 | FMY3: 0 | FMZ3: 0 | FNA3: 0 | FNB3: 0 | FNC3: 0 | FND3: 0 | FNE3: 0 | FNF3: 0 | FNG3: 0 | FNH3: 0 | FNI3: 0 | FNJ3: 0 | FNK3: 0 | FNL3: 0 | FNM3: 0 | FNN3: 0 | FNO3: 0 | FNP3: 0 | FNQ3: 0 | FNR3: 0 | FNS3: 0 | FNT3: 0 | FNU3: 0 | FNV3: 0 | FNW3: 0 | FNX3: 0 | FNY3: 0 | FNZ3: 0 | FOA3: 0 | FOB3: 0 | FOC3: 0 | FOD3: 0 | FOE3: 0 | FOF3: 0 | FOG3: 0 | FOH3: 0 | FOI3: 0 | FOJ3: 0 | FOK3: 0 | FOL3: 0 | FOM3: 0 | FON3: 0 | FOO3: 0 | FOP3: 0 | FOQ3: 0 | FOR3: 0 | FOS3: 0 | FOT3: 0 | FOU3: 0 | FOV3: 0 | FOW3: 0 | FOX3: 0 | FOY3: 0 | FOZ3: 0 | FPA3: 0 | FPB3: 0 | FPC3: 0 | FPD3: 0 | FPE3: 0 | FPF3: 0 | FPG3: 0 | FPH3: 0 | FPI3: 0 | FPJ3: 0 | FPK3: 0 | FPL3: 0 | FPM3: 0 | FPN3: 0 | FPO3: 0 | FPP3: 0 | FPQ3: 0 | FPR3: 0 | FPS3: 0 | FPT3: 0 | FPU3: 0 | FPV3: 0 | FPW3: 0 | FPX3: 0 | FPY3: 0 | FPZ3: 0 | FQA3: 0 | FQB3: 0 | FQC3: 0 | FQD3: 0 | FQE3: 0 | FQF3: 0 | FQG3: 0 | FQH3: 0 | FQI3: 0 | FQJ3: 0 | FQK3: 0 | FQL3: 0 | FQM3: 0 | FQN3: 0 | FQO3: 0 | FQP3: 0 | FQQ3: 0 | FQR3: 0 | FQS3: 0 | FQT3: 0 | FQU3: 0 | FQV3: 0 | FQW3: 0 | FQX3: 0 | FQY3: 0 | FQZ3: 0 | FRA3: 0 | FRB3: 0 | FRC3: 0 | FRD3: 0 | FRE3: 0 | FRF3: 0 | FRG3: 0 | FRH3: 0 | FRI3: 0 | FRJ3: 0 | FRK3: 0 | FRL3: 0 | FRM3: 0 | FRN3: 0 | FRO3: 0 | FRP3: 0 | FRQ3: 0 | FRR3: 0 | FRS3: 0 | FRT3: 0 | FRU3: 0 | FRV3: 0 | FRW3: 0 | FRX3: 0 | FRY3: 0 | FRZ3: 0 | FSA3: 0 | FSB3: 0 | FSC3: 0 | FSD3: 0 | FSE3: 0 | FSF3: 0 | FSG3: 0 | FSH3: 0 | FSI3: 0 | FSJ3: 0 | FSK3: 0 | FSL3: 0 | FSM3: 0 | FSN3: 0 | FSO3: 0 | FSP3: 0 | FSQ3: 0 | FSR3: 0 | FSS3: 0 | FST3: 0 | FSU3: 0 | FSV3: 0 | FSW3: 0 | FSX3: 0 | FSY3: 0 | FSZ3: 0 | FTA3: 0 | FTB3: 0 | FTC3: 0 | FTD3: 0 | FTE3: 0 | FTF3: 0 | FTG3: 0 | FTH3: 0 | FTI3: 0 | FTJ3: 0 | FTK3: 0 | FTL3: 0 | FTM3: 0 | FTN3: 0 | FTO3: 0 | FTP3: 0 | FTQ3: 0 | FTR3: 0 | FTS3: 0 | FTT3: 0 | FTU3: 0 | FTV3: 0 | FTW3: 0 | FTX3: 0 | FTY3: 0 | FTZ3: 0 | FUA3: 0 | FUB3: 0 | FUC3: 0 | FUD3: 0 | FUE3: 0 | FUF3: 0 | FUG3: 0 | FUH3: 0 | FUI3: 0 | FUJ3: 0 | FUK3: 0 | FUL3: 0 | FUM3: 0 | FUN3: 0 | FUO3: 0 | FUP3: 0 | FUQ3: 0 | FUR3: 0 | FUS3: 0 | FUT3: 0 | FUU3: 0 | FUV3: 0 | FUW3: 0 | FUX3: 0 | FUY3: 0 | FUZ3: 0 | FVA3: 0 | FVB3: 0 | FVC3: 0 | FVD3: 0 | FVE3: 0 | FVF3: 0 | FVG3: 0 | FVH3: 0 | FVI3: 0 | FVJ3: 0 | FVK3: 0 | FVL3: 0 | FVM3: 0 | FVN3: 0 | FVO3: 0 | FVP3: 0 | FVQ3: 0 | FVR3: 0 | FVS3: 0 | FVT3: 0 | FVU3: 0 | FVV3: 0 | FVW3: 0 | FVX3: 0 | FVY3: 0 | FVZ3: 0 | FWA3: 0 | FWB3: 0 | FWC3: 0 | FWD3: 0 | FWE3: 0 | FWF3: 0 | FWG3: 0 | FWH3: 0 | FWI3: 0 | FWJ3: 0 | FWK3: 0 | FWL3: 0 | FWM3: 0 | FWN3: 0 | FWO3: 0 | FWP3: 0 | FWQ3: 0 | FWR3: 0 | FWS3: 0 | FWT3: 0 | FWU3: 0 | FWV3: 0 | FWW3: 0 | FWX3: 0 | FWY3: 0 | FWZ3: 0 | FXA3: 0 | FXB3: 0 | FXC3: 0 | FXD3: 0 | FXE3: 0 | FXF3: 0 | FXG3: 0 | FXH3: 0 | FXI3: 0 | FXJ3: 0 | FXK3: 0 | FXL3: 0 | FXM3: 0 | FXN3: 0 | FXO3: 0 | FXP3: 0 | FXQ3: 0 | FXR3: 0 | FXS3: 0 | FXT3: 0 | FXU3: 0 | FXV3: 0 | FXW3: 0 | FXX3: 0 | FXY3: 0 | FXZ3: 0 | FYA3: 0 | FYB3: 0 | FYC3: 0 | FYD3: 0 | FYE3: 0 | FYF3: 0 | FYG3: 0 | FYH3: 0 | FYI3: 0 | FYJ3: 0 | FYK3: 0 | FYL3: 0 | FYM3: 0 | FYN3: 0 | FYO3: 0 | FYP3: 0 | FYQ3: 0 | FYR3: 0 | FYS3: 0 | FYT3: 0 | FYU3: 0 | FYV3: 0 | FYW3: 0 | FYX3: 0 | FYY3: 0 | FYZ3: 0 | FZA3: 0 | FZB3: 0 | FZC3: 0 | FZD3: 0 | FZE3: 0 | FZF3: 0 | FZG3: 0 | FZH3: 0 | FZI3: 0 | FZJ3: 0 | FZK3: 0 | FZL3: 0 | FZM3: 0 | FZN3: 0 | FZO3: 0 | FZP3: 0 | FZQ3: 0 | FZR3: 0 | FZS3: 0 | FZT3: 0 | FZU3: 0 | FZV3: 0 | FZW3: 0 | FZX3: 0 | FZY3: 0 | FZZ3: 0 | GAA3: 0 | GAB3: 0 | GAC3: 0 | GAD3: 0 | GAE3: 0 | GAF3: 0 | GAG3: 0 | GAH3: 0 | GAI3: 0 | GAJ3: 0 | GAK3: 0 | GAL3: 0 | GAM3: 0 | GAN3: 0 | GAO3: 0 | GAP3: 0 | GAQ3: 0 | GAR3: 0 | GAS3: 0 | GAT3: 0 | GAU3: 0 | GAV3: 0 | GAW3: 0 | GAX3: 0 | GAY3: 0 | GAZ3: 0 | GBA3: 0 | GBB3: 0 | GBC3: 0 | GBD3: 0 | GBE3: 0 | GBF3: 0 | GBG3: 0 | GBH3: 0 | GBI3: 0 | GBJ3: 0 | GBK3: 0 | GBL3: 0 | GBM3: 0 | GBN3: 0 | GBO3: 0 | GBP3: 0 | GBQ3: 0 | GBR3: 0 | GBS3: 0 | GBT3: 0 | GBU3: 0 | GBV3: 0 | GBW3: 0 | GBX3: 0 | GBY3: 0 | GBZ3: 0 | GCA3: 0 | GCB3: 0 | GCC3: 0 | GCD3: 0 | GCE3: 0 | GCF3: 0 | GCG3: 0 | GCH3: 0 | GCI3: 0 | GCJ3: 0 | GCK3: 0 | GCL3: 0 | GCM3: 0 | GCN3: 0 | GCO3: 0 | GCP3: 0 | GCQ3: 0 | GCR3: 0 | GCS3: 0 | GCT3: 0 | GCU3: 0 | GCV3: 0 | GCW3: 0 | GCX3: 0 | GCY3: 0 | GCZ3: 0 | GDA3: 0 | GDB3: 0 | GDC3: 0 | GDD3: 0 | GDE3: 0 | GDF3: 0 | GDG3: 0 | GDH3: 0 | GDI3: 0 | GDJ3: 0 | GDK3: 0 | GDL3: 0 | GDM3: 0 | GDN3: 0 | GDO3: 0 | GDP3: 0 | GDQ3: 0 | GDR3: 0 | GDS3: 0 | GDT3: 0 | GDU3: 0 | GDV3: 0 | GDW3: 0 | GDX3: 0 | GDY3: 0 | GDZ3: 0 | GEA3: 0 | GEB3: 0 | GEC3: 0 | GED3: 0 | GEE3: 0 | GEF3: 0 | GEG3: 0 | GEH3: 0 | GEI3: 0 | GEJ3: 0 | GEK3: 0 | GEL3: 0 | GEM3: 0 | GEN3: 0 | GEO3: 0 | GEP3: 0 | GEQ3: 0 | GER3: 0 | GES3: 0 | GET3: 0 | GEU3: 0 | GEV3: 0 | GEW3: 0 | GEX3: 0 | GEY3: 0 | GEZ3: 0 | GFA3: 0 | GFB3: 0 | GFC3: 0 | GFD3: 0 | GFE3: 0 | GFF3: 0 | GFG3: 0 | GFH3: 0 | GFI3: 0 | GFJ3: 0 | GFK3: 0 | GFL3: 0 | GFM3: 0 | GFN3: 0 | GFO3: 0 | GFP3: 0 | GFQ3: 0 | GFR3: 0 | GFS3: 0 | GFT3: 0 | GFU3: 0 | GFV3: 0 | GFW3: 0 | GFX3: 0 | GFY3: 0 | GFZ3: 0 | GGA3: 0 | GGB3: 0 | GGC3: 0 | GGD3: 0 | GGE3: 0 | GGF3: 0 | GGG3: 0 | GGH3: 0 | GGI3: 0 | GGJ3: 0 | GGK3: 0 | GGL3: 0 | GGM3: 0 | GGN3: 0 | GGO3: 0 | GGP3: 0 | GGQ3: 0 | GGR3: 0 | GGS3: 0 | GGT3: 0 | GGU3: 0 | GGV3: 0 | GGW3: 0 | GGX3: 0 | GGY3: 0 | GGZ3: 0 | GHA3: 0 | GHB3: 0 | GHC3: 0 | GHD3: 0 | GHE3: 0 | GHF3: 0 | GHG3: 0 | GHH3: 0 | GHI3: 0 | GHJ3: 0 | GHK3: 0 | GHL3: 0 | GHM3: 0 | GHN3: 0 | GHO3: 0 | GHP3: 0 | GHQ3: 0 | GHR3: 0 | GHS3: 0 | GHT3: 0 | GHU3: 0 | GHV3: 0 | GHW3: 0 | GHX3: 0 | GHY3: 0 | GHZ3: 0 | GIA3: 0 | GIB3: 0 | GIC3: 0 | GID3: 0 | GIE3: 0 | GIF3: 0 | GIG3: 0 | GIH3: 0 | GII3: 0 | GIJ3: 0 | GIK3: 0 | GIL3: 0 | GIM3: 0 | GIN3: 0 | GIO3: 0 | GIP3: 0 | GIQ3: 0 | GIR3: 0 | GIS3: 0 | GIT3: 0 | GIU3: 0 | GIV3: 0 | GIW3: 0 | GIX3: 0 | GIY3: 0 | GIZ3: 0 | GJA3: 0 | GJB3: 0 | GJC3: 0 | GJD3: 0 | GJE3: 0 | GJF3: 0 | GJG3: 0 | GJH3: 0 | GJI3: 0 | GJJ3: 0 | GJK3: 0 | GJL3: 0 | GJM3: 0 | GJN3: 0 | GJO3: 0 | GJP3: 0 | GJQ3: 0 | GJR3: 0 | GJS3: 0 | GJT3: 0 | GJU3: 0 | GJV3: 0 | GJW3: 0 | GJX3: 0 | GJY3: 0 | GJZ3: 0 | GKA3: 0 | GKB3: 0 | GKC3: 0 | GKD3: 0 | GKE3: 0 | GKF3: 0 | GKG3: 0 | GKH3: 0 | GKI3: 0 | GKJ3: 0 | GKK3: 0 | GKL3: 0 | GKM3: 0 | GKN3: 0 | GKO3: 0 | GKP3: 0 | GKQ3: 0 | GKR3: 0 | GKS3: 0 | GKT3: 0 | GKU3: 0 | GKV3: 0 | GKW3: 0 | GKX3: 0 | GKY3: 0 | GKZ3: 0 | GLA3: 0 | GLB3: 0 | GLC3: 0 | GLD3: 0 | GLE3: 0 | GLF3: 0 | GLG3: 0 | GLH3: 0 | GLI3: 0 | GLJ3: 0 | GLK3: 0 | GLL3: 0 | GLM3: 0 | GLN3: 0 | GLO3: 0 | GLP3: 0 | GLQ3: 0 | GLR3: 0 | GLS3: 0 | GLT3: 0 | GLU3: 0 | GLV3: 0 | GLW3: 0 | GLX3: 0 | GLY3: 0 | GLZ3: 0 | GMA3: 0 | GMB3: 0 | GMC3: 0 | GMD3: 0 | GME3: 0 | GMF3: 0 | GMG3: 0 | GMH3: 0 | GMI3: 0 | GMJ3: 0 | GMK3: 0 | GML3: 0 | GMM3: 0 | GMN3: 0 | GMO3: 0 | GMP3: 0 | GMQ3: 0 | GMR3: 0 | GMS3: 0 | GMT3: 0 | GMU3: 0 | GMV3: 0 | GMW3: 0 | GMX3: 0 | GMY3: 0 | GMZ3: 0 | GNA3: 0 | GNB3: 0 | GNC3: 0 | GND3: 0 | GNE3: 0 | GNF3: 0 | GNG3: 0 | GNH3: 0 | GNI3: 0 | GNJ3: 0 | GNK3: 0 | GNL3: 0 | GNM3: 0 | GNN3: 0 | GNO3: 0 | GNP3: 0 | GNQ3: 0 | GNR3: 0 | GNS3: 0 | GNT3: 0 | GNU3: 0 | GNV3: 0 | GNW3: 0 | GNX3: 0 | GNY3: 0 | GNZ3: 0 | GOA3: 0 | GOB3: 0 | GOC3: 0 | GOD3: 0 | GOE3: 0 | GOF3: 0 | GOG3: 0 | GOH3: 0 | GOI3: 0 | GOJ3: 0 | GOK3: 0 | GOL3: 0 | GOM3: 0 | GON3: 0 | GOO3: 0 | GOP3: 0 | GOQ3: 0 | GOR3: 0 | GOS3: 0 | GOT3: 0 | GOU3: 0 | GOV3: 0 | GOW3: 0 | GOX3: 0 | GOY3: 0 | GOZ3: 0 | GPA3: 0 | GPB3: 0 | GPC3: 0 | GPD3: 0 | GPE3: 0 | GPF3: 0 | GPG3: 0 | GPH3: 0 | GPI3: 0 | GPJ3: 0 | GPK3: 0 | GPL3: 0 | GPM3: 0 | GPN3: 0 | GPO3: 0 | GPP3: 0 | GPQ3: 0 | GPR3: 0 | GPS3: 0 | GPT3: 0 | GPU3: 0 | GPV3: 0 | GPW3: 0 | GPX3: 0 | GPY3: 0 | GPZ3: 0 | GQA3: 0 | GQB3: 0 | GQC3: 0 | GQD3: 0 | GQE3: 0 | GQF3: 0 | GQG3: 0 | GQH3: 0 | GQI3: 0 | GQJ3: 0 | GQK3: 0 | GQL3: 0 | GQM3: 0 | GQN3: 0 | GQO3: 0 | GQP3: 0 | GQQ3: 0 | GQR3: 0 | GQS3: 0 | GQT3: 0 | GQU3: 0 | GQV3: 0 | GQW3: 0 | GQX3: 0 | GQY3: 0 | GQZ3: 0 | GRA3: 0 | GRB3: 0 | GRC3: 0 | GRD3: 0 | GRE3: 0 | GRF3: 0 | GRG3: 0 | GRH3: 0 | GRI3: 0 | GRJ3: 0 | GRK3: 0 | GRL3: 0 | GRM3: 0 | GRN3: 0 | GRO3: 0 | GRP3: 0 | GRQ3: 0 | GRR3: 0 | GRS3: 0 | GRT3: 0 | GRU3: 0 | GRV3: 0 | GRW3: 0 | GRX3: 0 | GRY3: 0 | GRZ3: 0 | GSA3: 0 | GSB3: 0 | GSC3: 0 | GSD3: 0 | GSE3: 0 | GSF3: 0 | GSG3: 0 | GSH3: 0 | GSI3: 0 | GSJ3: 0 | GSK3: 0 | GSL3: 0 | GSM3: 0 | GSN3: 0 | GSO3: 0 | GSP3: 0 | GSQ3: 0 | GSR3: 0 | GSS3: 0 | GST3: 0 | GSU3: 0 | GSV3: 0 | GSW3: 0 | GSX3: 0 | GSY3: 0 | GSZ3: 0 | GTA3: 0 | GTB3: 0 | GTC3: 0 | GTD3: 0 | GTE3: 0 | GTF3: 0 | GTG3: 0 | GTH3: 0 | GTI3: 0 | GTJ3: 0 | GTK3: 0 | GTL3: 0 | GTM3: 0 | GTN3: 0 | GTO3: 0 | GTP3: 0 | GTQ3: 0 | GTR3: 0 | GTS3: 0 | GTT3: 0 | GTU3: 0 | GTV3: 0 | GTW3: 0 | GTX3: 0 | GTY3: 0 | GTZ3: 0 | GUA3: 0 | GUB3: 0 | GUC3: 0 | GUD3: 0 | GUE3: 0 | GUF3: 0 | GUG3: 0 | GUH3: 0 | GUI3: 0 | GUJ3: 0 | GUK3: 0 | GUL3: 0 | GUM3: 0 | GUN3: 0 | GUO3: 0 | GUP3: 0 | GUQ3: 0 | GUR3: 0 | GUS3: 0 | GUT3: 0 | GUU3: 0 | GUV3: 0 | GUW3: 0 | GUX3: 0 | GUY3: 0 | GUZ3: 0 | GVA3: 0 | GVB3: 0 | GVC3: 0 | GVD3: 0 | GVE3: 0 | GVF3: 0 | GVG3: 0 | GVH3: 0 | GVI3: 0 | GVJ3: 0 | GVK3: 0 | GVL3: 0 | GVM3: 0 | GVN3: 0 | GVO3: 0 | GVP3: 0 | GVQ3: 0 | GVR3: 0 | GVS3: 0 | GVT3: 0 | GVU3: 0 | GVV3: 0 | GVW3: 0 | GVX3: 0 | GVY3: 0 | GVZ3: 0 | GWA3: 0 | GWB3: 0 | GWC3: 0 | GWD3: 0 | GWE3: 0 | GWF3: 0 | GWG3: 0 | GWH3: 0 | GWI3: 0 | GWJ3: 0 | GWK3: 0 | GWL3: 0 | GWM3: 0 | GWN3: 0 | GWO3: 0 | GWP3: 0 | GWQ3: 0 | GWR3: 0 | GWS3: 0 | GWT3: 0 | GWU3: 0 | GWV3: 0 | GWW3: 0 | GWX3: 0 | GWY3: 0 | GWZ3: 0 | GXA3: 0 | GXB3: 0 | GXC3: 0 | GXD3: 0 | GXE3: 0 | GXF3: 0 | GXG3: 0 | GXH3: 0 | GXI3: 0 | GXJ3: 0 | GXK3: 0 | GXL3: 0 | GXM3: 0 | GXN3: 0 | GXO3: 0 | GXP3: 0 | GXQ3: 0 | GXR3: 0 | GXS3: 0 | GXT3: 0 | GXU3: 0 | GXV3: 0 | GXW3: 0 | GXX3: 0 | GXY3: 0 | GXZ3: 0 | GYA3: 0 | GYB3: 0 | GYC3: 0 | GYD3: 0 | GYE3: 0 | GYF3: 0 | GYG3: 0 | GYH3: 0 | GYI3: 0 | GYJ3: 0 | GYK3: 0 | GYL3: 0 | GYM3: 0 | GYN3: 0 | GYO3: 0 | GYP3: 0 | GYQ3: 0 | GYR3: 0 | GYS3: 0 | GYT3: 0 | GYU3: 0 | GYV3: 0 | GYW3: 0 | GYX3: 0 | GYY3: 0 | GYZ3: 0 | GZA3: 0 | GZB3: 0 | GZC3: 0 | GZD3: 0 | GZE3: 0 | GZF3: 0 | GZG3: 0 | GZH3: 0 | GZI3: 0 | GZJ3: 0 | GZK3: 0 | GZL3: 0 | GZM3: 0 | GZN3: 0 | GZO3: 0 | GZP3: 0 | GZQ3: 0 | GZR3: 0 | GZS3: 0 | GZT3: 0 | GZU3: 0 | GZV3: 0 | GZW3: 0 | GZX3: 0 | GZY3: 0 | GZZ3: 0 | HAA3: 0 | HAB3: 0 | HAC3: 0 | HAD3: 0 | HAE3: 0 | HAF3: 0 | HAG3: 0 | HAH3: 0 | HAI3: 0 | HAJ3: 0 | HAK3: 0 | HAL3: 0 | HAM3: 0 | HAN3: 0 | HAO3: 0 | HAP3: 0 | HAQ3: 0 | HAR3: 0 | HAS3: 0 | HAT3: 0 | HAU3: 0 | HAV3: 0 | HAW3: 0 | HAX3: 0 | HAY3: 0 | HAZ3: 0 | HBA3: 0 | HBB3: 0 | HBC3: 0 | HBD3: 0 | HBE3: 0 | HBF3: 0 | HBG3: 0 | HBH3: 0 | HBI3: 0 | HBJ3: 0 | HBK3: 0 | HBL3: 0 | HBM3: 0 | HBN3: 0 | HBO3: 0 | HBP3: 0 | HBQ3: 0 | HBR3: 0 | HBS3: 0 | HBT3: 0 | HBU3: 0 | HBV3: 0 | HBW3: 0 | HBX3: 0 | HBY3: 0 | HBZ3: 0 | HCA3: 0 | HCB3: 0 | HCC3: 0 | HCD3: 0 | HCE3: 0 | HCF3: 0 | HCG3: 0 | HCH3: 0 | HCI3: 0 | HCJ3: 0 | HCK3: 0 | HCL3: 0 | HCM3: 0 | HCN3: 0 | HCO3: 0 | HCP3: 0 | HCQ3: 0 | HCR3: 0 | HCS3: 0 | HCT3: 0 | HCU3: 0 | HCV3: 0 | HCW3: 0 | HCX3: 0 | HCY3: 0 | HCZ3: 0 | HDA3: 0 | HDB3: 0 | HDC3: 0 | HDD3: 0 | HDE3: 0 | HDF3: 0 | HDG3: 0 | HDH3: 0 | HDI3: 0 | HDJ3: 0 | HDK3: 0 | HDL3: 0 | HDM3: 0 | HDN3: 0 | HDO3: 0 | HDP3: 0 | HDQ3: 0 | HDR3: 0 | HDS3: 0 | HDT3: 0 | HDU3: 0 | HDV3: 0 | HDW3: 0 | HDX3: 0 | HDY3: 0 | HDZ3: 0 | HEA3: 0 | HEB3: 0 | HEC3: 0 | HED3: 0 | HEE3: 0 | HEF3: 0 | HEG3: 0 | HEH3: 0 | HEI3: 0 | HEJ3: 0 | HEK3: 0 | HEL3: 0 | HEM3: 0 | HEN3: 0 | HEO3: 0 | HEP3: 0 | HEQ3: 0 | HER3: 0 | HES3: 0 | HET3: 0 | HEU3: 0 | HEV3: 0 | HEW3: 0 | HEX3: 0 | HEY3: 0 | HEZ3: 0 | HFA3: 0 | HFB3: 0 | HFC3: 0 | HFD3: 0 | HFE3: 0 | HFF3: 0 | HFG3: 0 | HFH3: 0 | HFI3: 0 | HFJ3: 0 | HFK3: 0 | HFL3: 0 | HFM3: 0 | HFN3: 0 | HFO3: 0 | HFP3: 0 | HFQ3: 0 | HFR3: 0 | HFS3: 0 | HFT3: 0 | HFU3: 0 | HFV3: 0 | HFW3: 0 | HFX3: 0 | HFY3: 0 | HFZ3: 0 | HGA3: 0 | HGB3: 0 | HGC3: 0 | HGD3: 0 | HGE3: 0 | HGF3: 0 | HGG3: 0 | HGH3: 0 | HGI3: 0 | HGJ3: 0 | HGK3: 0 | HGL3: 0 | HGM3: 0 | HGN3: 0 | HGO3: 0 | HGP3: 0 | HGQ3: 0 | HGR3: 0 | HGS3: 0 | HGT3: 0 | HGU3: 0 | HGV3: 0 | HGW3: 0 | HGX3: 0 | HGY3: 0 | HGZ3: 0 | HHA3: 0 | HHB3: 0 | HHC3: 0 | HHD3: 0 | HHE3: 0 | HHF3: 0 | HHG3: 0 | HHH3: 0 | HHI3: 0 | HHJ3: 0 | HHK3: 0 | HHL3: 0 | HHM3: 0 | HHN3: 0 | HHO3: 0 | HHP3: 0 | HHQ3: 0 | HHR3: 0 | HHS3: 0 | HHT3: 0 | HHU3: 0 | HHV3: 0 | HHW3: 0 | HHX3: 0 | HHY3: 0 | HHZ3: 0 | HIA3: 0 | HIB3: 0 | HIC3: 0 | HID3: 0 | HIE3: 0 | HIF3: 0 | HIG3: 0 | HIH3: 0 | HII3: 0 | HIJ3: 0 | HIK3: 0 | HIL3: 0 | HIM3: 0 | HIN3: 0 | HIO3: 0 | HIP3: 0 | HIQ3: 0 | HIR3: 0 | HIS3: 0 | HIT3: 0 | HIU3: 0 | HIV3: 0 | HIW3: 0 | HIX3: 0 | HIY3: 0 | HIZ3: 0 | HJA3: 0 | HJB3: 0 | HJC3: 0 | HJD3: 0 | HJE3: 0 | HJF3: 0 | HJG3: 0 | HJH3: 0 | HJI3: 0 | HJJ3: 0 | HJK3: 0 | HJL3: 0 | HJM3: 0 | HJN3: 0 | HJO3: 0 | HJP3: 0 | HJQ3: 0 | HJR3: 0 | HJS3: 0 | HJT3: 0 | HJU3: 0 | HJV3: 0 | HJW3: 0 | HJX3: 0 | HJY3: 0 | HJZ3: 0 | HKA3: 0 | HKB3: 0 | HKC3: 0 | HKD3: 0 | HKE3: 0 | HKF3: 0 | HKG3: 0 | HKH3: 0 | HKI3: 0 | HKJ3: 0 | HKK3: 0 | HKL3: 0 | HKM3: 0 | HKN3: 0 | HKO3: 0 | HKP3: 0 | HKQ3: 0 | HKR3: 0 | HKS3: 0 | HKT3: 0 | HKU3: 0 | HKV3: 0 | HKW3: 0 | HKX3: 0 | HKY3: 0 | HKZ3: 0 | HLA3: 0 | HLB3: 0 | HLC3: 0 | HLD3: 0 | HLE3: 0 | HLF3: 0 | HLG3: 0 | HLH3: 0 | HLI3: 0 | HLJ3: 0 | HLK3: 0 | HLL3: 0 | HLM3: 0 | HLN3: 0 | HLO3: 0 | HLP3: 0 | HLQ3: 0 | HLR3: 0 | HLS3: 0 | HLT3: 0 | HLU3: 0 | HLV3: 0 | HLW3: 0 | HLX3: 0 | HLY3: 0 | HLZ3: 0 | HMA3: 0 | HMB3: 0 | HMC3: 0 | HMD3: 0 | HME3: 0 | HMF3: 0 | HMG3: 0 | HMH3: 0 | HMI3: 0 | HMJ3: 0 | HMK3: 0 | HML3: 0 | HMM3: 0 | HMN3: 0 | HMO3: 0 | HMP3: 0 | HMQ3: 0 | HMR3: 0 | HMS3: 0 | HMT3: 0 | HMU3: 0 | HMV3: 0 | HMW3: 0 | HMX3: 0 | HMY3: 0 | HMZ3: 0 | HNA3: 0 | HNB3: 0 | HNC3: 0 | HND3: 0 | HNE3: 0 | HNF3: 0 | HNG3: 0 | HNH3: 0 | HNI3: 0 | HNJ3: 0 | HNK3: 0 | HNL3: 0 | HNM3: 0 | HNN3: 0 | HNO3: 0 | HNP3: 0 | HNQ3: 0 | HNR3: 0 | HNS3: 0 | HNT3: 0 | HNU3: 0 | HNV3: 0 | HNW3: 0 | HNX3: 0 | HNY3: 0 | HNZ3: 0 | HOA3: 0 | HOB3: 0 | HOC3: 0 | HOD3: 0 | HOE3: 0 | HOF3: 0 | HOG3: 0 | HOH3: 0 | HOI3: 0 | HOJ3: 0 | HOK3: 0 | HOL3: 0 | HOM3: 0 | HON3: 0 | HOO3: 0 | HOP3: 0 | HOQ3: 0 | HOR3: 0 | HOS3: 0 | HOT3: 0 | HOU3: 0 | HOV3: 0 | HOW3: 0 | HOX3: 0 | HOY3: 0 | HOZ3: 0 | HPA3: 0 | HPB3: 0 | HPC3: 0 | HPD3: 0 | HPE3: 0 | HPF3: 0 | HPG3: 0 | HPH3: 0 | HPI3: 0 | HPJ3: 0 | HPK3: 0 | HPL3: 0 | HPM3: 0 | HPN3: 0 | HPO3: 0 | HPP3: 0 | HPQ3: 0 | HPR3: 0 | HPS3: 0 | HPT3: 0 | HPU3: 0 | HPV3: 0 | HPW3: 0 | HPX3: 0 | HPY3: 0 | HPZ3: 0 | HQA3: 0 | HQB3: 0 | HQC3: 0 | HQD3: 0 | HQE3: 0 | HQF3: 0 | HQG3: 0 | HQH3: 0 | HQI3: 0 | HQJ3: 0 | HQK3: 0 | HQL3: 0 | HQM3: 0 | HQN3: 0 | HQO3: 0 | HQP3: 0 | HQQ3: 0 | HQR3: 0 | HQS3: 0 | HQT3: 0 | HQU3: 0 | HQV3: 0 | HQW3: 0 | HQX3: 0 | HQY3: 0 | HQZ3: 0 | HRA3: 0 | HRB3: 0 | HRC3: 0 | HRD3: 0 | HRE3: 0 | HRF3: 0 | HRG3: 0 | HRH3: 0 | HRI3: 0 | HRJ3: 0 | HRK3: 0 | HRL3: 0 | HRM3: 0 | HRN3: 0 | HRO3: 0 | HRP3: 0 | HRQ3: 0 | HRR3: 0 | HRS3: 0 | HRT3: 0 | HRU3: 0 | HRV3: 0 | HRW3: 0 | HRX3: 0 | HRY3: 0 | HRZ3: 0 | HSA3: 0 | HSB3: 0 | HSC3: 0 | HSD3: 0 | HSE3: 0 | HSF3: 0 | HSG3: 0 | HSH3: 0 | HSI3: 0 | HSJ3: 0 | HSK3: 0 | HSL3: 0 | HSM3: 0 | HSN3: 0 | HSO3: 0 | HSP3: 0 | HSQ3: 0 | HSR3: 0 | HSS3: 0 | HST3: 0 | HSU3: 0 | HSV3: 0 | HSW3: 0 | HSX3: 0 | HSY3: 0 | HSZ3: 0 | HTA3: 0 | HTB3: 0 | HTC3: 0 | HTD3: 0 | HTE3: 0 | HTF3: 0 | HTG3: 0 | HTH3: 0 | HTI3: 0 | HTJ3: 0 | HTK3: 0 | HTL3: 0 | HTM3: 0 | HTN3: 0 | HTO3: 0 | HTP3: 0 | HTQ3: 0 | HTR3: 0 | HTS3: 0 | HTT3: 0 | HTU3: 0 | HTV3: 0 | HTW3: 0 | HTX3: 0 | HTY3: 0 | HTZ3: 0 | HUA3: 0 | HUB3: 0 | HUC3: 0 | HUD3: 0 | HUE3: 0 | HUF3: 0 | HUG3: 0 | HUH3: 0 | HUI3: 0 | HUJ3: 0 | HUK3: 0 | HUL3: 0 | HUM3: 0 | HUN3: 0 | HUO3: 0 | HUP3: 0 | HUQ3: 0 | HUR3: 0 | HUS3: 0 | HUT3: 0 | HUU3: 0 | HUV3: 0 | HUW3: 0 | HUX3: 0 | HUY3: 0 | HUZ3: 0 | HVA3: 0 | HVB3: 0 | HVC3: 0 | HVD3: 0 | HVE3: 0 | HVF3: 0 | HVG3: 0 | HVH3: 0 | HVI3: 0 | HVJ3: 0 | HVK3: 0 | HVL3: 0 | HVM3: 0 | HVN3: 0 | HVO3: 0 | HVP3: 0 | HVQ3: 0 | HVR3: 0 | HVS3: 0 | HVT3: 0 | HVU3: 0 | HVV3: 0 | HVW3: 0 | HVX3: 0 | HVY3: 0 | HVZ3: 0 | HWA3: 0 | HWB3: 0 | HWC3: 0 | HWD3: 0 | HWE3: 0 | HWF3: 0 | HWG3: 0 | HWH3: 0 | HWI3: 0 | HWJ3: 0 | HWK3: 0 | HWL3: 0 | HWM3: 0 | HWN3: 0 | HWO3: 0 | HWP3: 0 | HWQ3: 0 | HWR3: 0 | HWS3: 0 | HWT3: 0 | HWU3: 0 | HWV3: 0 | HWW3: 0 | HWX3: 0 | HWY3: 0 | HWZ3: 0 | HXA3: 0 | HXB3: 0 | HXC3: 0 | HXD3: 0 | HXE3: 0 | HXF3: 0 | HXG3: 0 | HXH3: 0 | HXI3: 0 | HXJ3: 0 | HXK3: 0 | HXL3: 0 | HXM3: 0 | HXN3: 0 | HXO3: 0 | HXP3: 0 | HXQ3: 0 | HXR3: 0 | HXS3: 0 | HXT3: 0 | HXU3: 0 | HXV3: 0 | HXW3: 0 | HXX3: 0 | HXY3: 0 | HXZ3: 0 | HYA3: 0 | HYB3: 0 | HYC3: 0 | HYD3: 0 | HYE3: 0 | HYF3: 0 | HYG3: 0 | HYH3: 0 | HYI3: 0 | HYJ3: 0 | HYK3: 0 | HYL3: 0 | HYM3: 0 | HYN3: 0 | HYO3: 0 | HYP3: 0 | HYQ3: 0 | HYR3: 0 | HYS3: 0 | HYT3: 0 | HYU3: 0 | HYV3: 0 | HYW3: 0 | HYX3: 0 | HYY3: 0 | HYZ3: 0 | HZA3: 0 | HZB3: 0 | HZC3: 0 | HZD3: 0 | HZE3: 0 | HZF3: 0 | HZG3: 0 | HZH3: 0 | HZI3: 0 | HZJ3: 0 | HZK3: 0 | HZL3: 0 | HZM3: 0 | HZN3: 0 | HZO3: 0 | HZP3: 0 | HZQ3: 0 | HZR3: 0 | HZS3: 0 | HZT3: 0 | HZU3: 0 | HZV3: 0 | HZW3: 0 | HZX3: 0 | HZY3: 0 | HZZ3: 0 | IAA3: 0 | IAB3: 0 | IAC3: 0 | IAD3: 0 | IAE3: 0 | IAF3: 0 | IAG3: 0 | IAH3: 0 | IAI3: 0 | IAJ3: 0 | IAK3: 0 | IAL3: 0 | IAM3: 0 | IAN3: 0 | IAO3: 0 | IAP3: 0 | IAQ3: 0 | IAR3: 0 | IAS3: 0 | IAT3: 0 | IAU3: 0 | IAV3: 0 | IAW3: 0 | IAX3: 0 | IAY3: 0 | IAZ3: 0 | IBA3: 0 | IBB3: 0 | IBC3: 0 | IBD3: 0 | IBE3: 0 | IBF3: 0 | IBG3: 0 | IBH3: 0 | IBI3: 0 | IBJ3: 0 | IBK3: 0 | IBL3: 0 | IBM3: 0 | IBN3: 0 | IBO3: 0 | IBP3: 0 | IBQ3: 0 | IBR3: 0 | IBS3: 0 | IBT3: 0 | IBU3: 0 | IBV3: 0 | IBW3: 0 | IBX3: 0 | IBY3: 0 | IBZ3: 0 | ICA3: 0 | ICB3: 0 | ICC3: 0 | ICD3: 0 | ICE3: 0 | ICF3: 0 | ICG3: 0 | ICH3: 0 | ICI3: 0 | ICJ3: 0 | ICK3: 0 | ICL3: 0 | ICM3: 0 | ICN3: 0 | ICO3: 0 | ICP3: 0 | ICQ3: 0 | ICR3: 0 | ICS3: 0 | ICT3: 0 | ICU3: 0 | ICV3: 0 | ICW3: 0 | ICX3: 0 | ICY3: 0 | ICZ3: 0 | IDA3: 0 | IDB3: 0 | IDC3: 0 | IDD3: 0 | IDE3: 0 | IDF3: 0 | IDG3: 0 | IDH3: 0 | IDI3: 0 | IDJ3: 0 | IDK3: 0 | IDL3: 0 | IDM3: 0 | IDN3: 0 | IDO3: 0 | IDP3: 0 | IDQ3: 0 | IDR3: 0 | IDS3: 0 | IDT3: 0 | IDU3: 0 | IDV3: 0 | IDW3: 0 | IDX3: 0 | IDY3: 0 | IDZ3: 0 | IEA3: 0 | IEB3: 0 | IEC3: 0 | IED3: 0 | IEE3: 0 | IEF3: 0 | IEG3: 0 | IEH3: 0 | IEI3: 0 | IEJ3: 0 | IEK3: 0 | IEL3: 0 | IEM3: 0 | IEN3: 0 | IEO3: 0 | IEP3: 0 | IEQ3: 0 | IER3: 0 | IES3: 0 | IET3: 0 | IEU3: 0 | IEV3: 0 | IEW3: 0 | IEX3: 0 | IEY3: 0 | IEZ3: 0 | IFA3: 0 | IFB3: 0 | IFC3: 0 | IFD3: 0 | IFE3: 0 | IFF3: 0 | IFG3: 0 | IFH3: 0 | IFI3: 0 | IFJ3: 0 | IFK3: 0 | IFL3: 0 | IFM3: 0 | IFN3: 0 | IFO3: 0 | IFP3: 0 | IFQ3: 0 | IFR3: 0 | IFS3: 0 | IFT3: 0 | IFU3: 0 | IFV3: 0 | IFW3: 0 | IFX3: 0 | IFY3: 0 | IFZ3: 0 | IGA3: 0 | IGB3: 0 | IGC3: 0 | IGD3: 0 | IGE3: 0 | IGF3: 0 | IGG3: 0 | IGH3: 0 | IGI3: 0 | IGJ3: 0 | IGK3: 0 | IGL3: 0 | IGM3: 0 | IGN3: 0 | IGO3: 0 | IGP3: 0 | IGQ3: 0 | IGR3: 0 | IGS3: 0 | IGT3: 0 | IGU3: 0 | IGV3: 0 | IGW3: 0 | IGX3: 0 | IGY3: 0 | IGZ3: 0 | IHA3: 0 | IHB3: 0 | IHC3: 0 | IHD3: 0 | IHE3: 0 | IHF3: 0 | IHG3: 0 | IHH3: 0 | IHI3: 0 | IHJ3: 0 | IHK3: 0 | IHL3: 0 | IHM3: 0 | IHN3: 0 | IHO3: 0 | IHP3: 0 | IHQ3: 0 | IHR3: 0 | IHS3: 0 | IHT3: 0 | IHU3: 0 | IHV3: 0 | IHW3: 0 | IHX3: 0 | IHY3: 0 | IHZ3: 0 | IIA3: 0 | IIB3: 0 | IIC3: 0 | IID3: 0 | IIE3: 0 | IIF3: 0 | IIG3: 0 | IIH3: 0 | III3: 0 | IIJ3: 0 | IIK3: 0 | IIL3: 0 | IIM3: 0 | IIN3: 0 | IIO3: 0 | IIP3: 0 | IIQ3: 0 | IIR3: 0 | IIS3: 0 | IIT3: 0 | IIU3: 0 | IIV3: 0 | IIW3: 0 | IIX3: 0 | IIY3: 0 | IIZ3: 0 | IJA3: 0 | IJB3: 0 | IJC3: 0 | IJD3: 0 | IJE3: 0 | IJF3: 0 | IJG3: 0 | IJH3: 0 | IJI3: 0 | IJJ3: 0 | IJK3: 0 | IJL3: 0 | IJM3: 0 | IJN3: 0 | IJO3: 0 | IJP3: 0 | IJQ3: 0 | IJR3: 0 | IJS3: 0 | IJT3: 0 | IJU3: 0 | IJV3: 0 | IJW3: 0 | IJX3: 0 | IJY3: 0 | IJZ3: 0 | IKA3: 0 | IKB3: 0 | IKC3: 0 | IKD3: 0 | IKE3: 0 | IKF3: 0 | IKG3: 0 | IKH3: 0 | IKI3: 0 | IKJ3: 0 | IKK3: 0 | IKL3: 0 | IKM3: 0 | IKN3: 0 | IKO3: 0 | IKP3: 0 | IKQ3: 0 | IKR3: 0 | IKS3: 0 | IKT3: 0 | IKU3: 0 | IKV3: 0 | IKW3: 0 | IKX3: 0 | IKY3: 0 | IKZ3: 0 | ILA3: 0 | ILB3: 0 | ILC3: 0 | ILD3: 0 | ILE3: 0 | ILF3: 0 | ILG3: 0 | ILH3: 0 | ILI3: 0 | ILJ3: 0 | ILK3: 0 | ILL3: 0 | ILM3: 0 | ILN3: 0 | ILO3: 0 | ILP3: 0 | ILQ3: 0 | ILR3: 0 | ILS3: 0 | ILT3: 0 | ILU3: 0 | ILV3: 0 | ILW3: 0 | ILX3: 0 | ILY3: 0 | ILZ3: 0 | IMA3: 0 | IMB3: 0 | IMC3: 0 | IMD3: 0 | IME3: 0 | IMF3: 0 | IMG3: 0 | IMH3: 0 | IMI3: 0 | IMJ3: 0 | IMK3: 0 | IML3: 0 | IMM3: 0 | IMN3: 0 | IMO3: 0 | IMP3: 0 | IMQ3: 0 | IMR3: 0 | IMS3: 0 | IMT3: 0 | IMU3: 0 | IMV3: 0 | IMW3: 0 | IMX3: 0 | IMY3: 0 | IMZ3: 0 | INA3: 0 | INB3: 0 | INC3: 0 | IND3: 0 | INE3: 0 | INF3: 0 | ING3: 0 | INH3: 0 | INI3: 0 | INJ3: 0 | INK3: 0 | INL3: 0 | INM3: 0 | INN3: 0 | INO3: 0 | INP3: 0 | INQ3: 0 | INR3: 0 | INS3: 0 | INT3: 0 | INU3: 0 | INV3: 0 | INW3: 0 | INX3: 0 | INY3: 0 | INZ3: 0 | IOA3: 0 | IOB3: 0 | IOC3: 0 | IOD3: 0 | IOE3: 0 | IOF3: 0 | IOG3: 0 | IOH3: 0 | IOI3: 0 | IOJ3: 0 | IOK3: 0 | IOL3: 0 | IOM3: 0 | ION3: 0 | IOO3: 0 | IOP3: 0 | IOQ3: 0 | IOR3: 0 | IOS3: 0 | IOT3: 0 | IOU3: 0 | IOV3: 0 | IOW3: 0 | IOX3: 0 | IOY3: 0 | IOZ3: 0 | IPA3: 0 | IPB3: 0 | IPC3: 0 | IPD3: 0 | IPE3: 0 | IPF3: 0 | IPG3: 0 | IPH3: 0 | IPI3: 0 | IPJ3: 0 | IPK3: 0 | IPL3: 0 | IPM3: 0 | IPN3: 0 | IPO3: 0 | IPP3: 0 | IPQ3: 0 | IPR3: 0 | IPS3: 0 | IPT3: 0 | IPU3: 0 | IPV3: 0 | IPW3: 0 | IPX3: 0 | IPY3: 0 | IPZ3: 0 | IQA3: 0 | IQB3: 0 | IQC3: 0 | IQD3: 0 | IQE3: 0 | IQF3: 0 | IQG3: 0 | IQH3: 0 | IQI3: 0 | IQJ3: 0 | IQK3: 0 | IQL3: 0 | IQM3: 0 | IQN3: 0 | IQO3: 0 | IQP3: 0 | IQQ3: 0 | IQR3: 0 | IQS3: 0 | IQT3: 0 | IQU3: 0 | IQV3: 0 | IQW3: 0 | IQX3: 0 | IQY3: 0 | IQZ3: 0 | IRA3: 0 | IRB3: 0 | IRC3: 0 | IRD3: 0 | IRE3: 0 | IRF3: 0 | IRG3: 0 | IRH3: 0 | IRI3: 0 | IRJ3: 0 | IRK3: 0 | IRL3: 0 | IRM3: 0 | IRN3: 0 | IRO3: 0 | IRP3: 0 | IRQ3: 0 | IRR3: 0 | IRS3: 0 | IRT3: 0 | IRU3: 0 | IRV3: 0 | IRW3: 0 | IRX3: 0 | IRY3: 0 | IRZ3: 0 | ISA3: 0 | ISB3: 0 | ISC3: 0 | ISD3: 0 | ISE3: 0 | ISF3: 0 | ISG3: 0 | ISH3: 0 | ISI3: 0 | ISJ3: 0 | ISK3: 0 | ISL3: 0 | ISM3: 0 | ISN3: 0 | ISO3: 0 | ISP3: 0 | ISQ3: 0 | ISR3: 0 | ISS3: 0 | IST3: 0 | ISU3: 0 | ISV3: 0 | ISW3: 0 | ISX3: 0 | ISY3: 0 | ISZ3: 0 | ITA3: 0 | ITB3: 0 | ITC3: 0 | ITD3: 0 | ITE3: 0 | ITF3: 0 | ITG3: 0 | ITH3: 0 | ITI3: 0 | ITJ3: 0 | ITK3: 0 | ITL3: 0 | ITM3: 0 | ITN3: 0 | ITO3: 0 | ITP3: 0 | ITQ3: 0 | ITR3: 0 | ITS3: 0 | ITT3: 0 | ITU3: 0 | ITV3: 0 | ITW3: 0 | ITX3: 0 | ITY3: 0 | ITZ3: 0 | IUA3: 0 | IUB3: 0 | IUC3: 0 | IUD3: 0 | IUE3: 0 | IUF3: 0 | IUG3: 0 | IUH3: 0 | IUI3: 0 | IUJ3: 0 | IUK3: 0 | IUL3: 0 | IUM3: 0 | IUN3: 0 | IUO3: 0 | IUP3: 0 | IUQ3: 0 | IUR3: 0 | IUS3: 0 | IUT3: 0 | IUU3: 0 | IUV3: 0 | IUW3: 0 | IUX3: 0 | IUY3: 0 | IUZ3: 0 | IVA3: 0 | IVB3: 0 | IVC3: 0 | IVD3: 0 | IVE3: 0 | IVF3: 0 | IVG3: 0 | IVH3: 0 | IVI3: 0 | IVJ3: 0 | IVK3: 0 | IVL3: 0 | IVM3: 0 | IVN3: 0 | IVO3: 0 | IVP3: 0 | IVQ3: 0 | IVR3: 0 | IVS3: 0 | IVT3: 0 | IVU3: 0 | IVV3: 0 | IVW3: 0 | IVX3: 0 | IVY3: 0 | IVZ3: 0 | IWA3: 0 | IWB3: 0 | IWC3: 0 | IWD3: 0 | IWE3: 0 | IWF3: 0 | IWG3: 0 | IWH3: 0 | IWI3: 0 | IWJ3: 0 | IWK3: 0 | IWL3: 0 | IWM3: 0 | IWN3: 0 | IWO3: 0 | IWP3: 0 | IWQ3: 0 | IWR3: 0 | IWS3: 0 | IWT3: 0 | IWU3: 0 | IWV3: 0 | IWW3: 0 | IWX3: 0 | IWY3: 0 | IWZ3: 0 | IXA3: 0 | IXB3: 0 | IXC3: 0 | IXD3: 0 | IXE3: 0 | IXF3: 0 | IXG3: 0 | IXH3: 0 | IXI3: 0 | IXJ3: 0 | IXK3: 0 | IXL3: 0 | IXM3: 0 | IXN3: 0 | IXO3: 0 | IXP3: 0 | IXQ3: 0 | IXR3: 0 | IXS3: 0 | IXT3: 0 | IXU3: 0 | IXV3: 0 | IXW3: 0 | IXX3: 0 | IXY3: 0 | IXZ3: 0 | IYA3: 0 | IYB3: 0 | IYC3: 0 | IYD3: 0 | IYE3: 0 | IYF3: 0 | IYG3: 0 | IYH3: 0 | IYI3: 0 | IYJ3: 0 | IYK3: 0 | IYL3: 0 | IYM3: 0 | IYN3: 0 | IYO3: 0 | IYP3: 0 | IYQ3: 0 | IYR3: 0 | IYS3: 0 | IYT3: 0 | IYU3: 0 | IYV3: 0 | IYW3: 0 | IYX3: 0 | IYY3: 0 | IYZ3: 0 | IZA3: 0 | IZB3: 0 | IZC3: 0 | IZD3: 0 | IZE3: 0 | IZF3: 0 | IZG3: 0 | IZH3: 0 | IZI3: 0 | IZJ3: 0 | IZK3: 0 | IZL3: 0 | IZM3: 0 | IZN3: 0 | IZO3: 0 | IZP3: 0 | IZQ3: 0 | IZR3: 0 | IZS3: 0 | IZT3: 0 | IZU3: 0 | IZV3: 0 | IZW3: 0 | IZX3: 0 | IZY3: 0 | IZZ3: 0 | JAA3: 0 | JAB3: 0 | JAC3: 0 | JAD3: 0 | JAE3: 0 | JAF3: 0 | JAG3: 0 | JAH3: 0 | JAI3: 0 | JAJ3: 0 | JAK3: 0 | JAL3: 0 | JAM3: 0 | JAN3: 0 | JAO3: 0 | JAP3: 0 | JAQ3: 0 | JAR3: 0 | JAS3: 0 | JAT3: 0 | JAU3: 0 | JAV3: 0 | JAW3: 0 | JAX3: 0 | JAY3: 0 | JAZ3: 0 | JBA3: 0 | JBB3: 0 | JBC3: 0 | JBD3: 0 | JBE3: 0 | JBF3: 0 | JBG3: 0 | JBH3: 0 | JBI3: 0 | JBJ3: 0 | JBK3: 0 | JBL3: 0 | JBM3: 0 | JBN3: 0 | JBO3: 0 | JBP3: 0 | JBQ3: 0 | JBR3: 0 | JBS3: 0 | JBT3: 0 | JBU3: 0 | JBV3: 0 | JBW3: 0 | JBX3: 0 | JBY3: 0 | JBZ3: 0 | JCA3: 0 | JCB3: 0 | JCC3: 0 | JCD3: 0 | JCE3: 0 | JCF3: 0 | JCG3: 0 | JCH3: 0 | JCI3: 0 | JCJ3: 0 | JCK3: 0 | JCL3: 0 | JCM3: 0 | JCN3: 0 | JCO3: 0 | JCP3: 0 | JCQ3: 0 | JCR3: 0 | JCS3: 0 | JCT3: 0 | JCU3: 0 | JCV3: 0 | JCW3: 0 | JCX3: 0 | JCY3: 0 | JCZ3: 0 | JDA3: 0 | JDB3: 0 | JDC3: 0 | JDD3: 0 | JDE3: 0 | JDF3: 0 | JDG3: 0 | JDH3: 0 | JDI3: 0 | JDJ3: 0 | JDK3: 0 | JDL3: 0 | JDM3: 0 | JDN3: 0 | JDO3: 0 | JDP3: 0 | JDQ3: 0 | JDR3: 0 | JDS3: 0 | JDT3: 0 | JDU3: 0 | JDV3: 0 | JDW3: 0 | JDX3: 0 | JDY3: 0 | JDZ3: 0 | JEA3: 0 | JEB3: 0 | JEC3: 0 | JED3: 0 | JEE3: 0 | JEF3: 0 | JEG3: 0 | JEH3: 0 | JEI3: 0 | JEJ3: 0 | JEK3: 0 | JEL3: 0 | JEM3: 0 | JEN3: 0 | JEO3: 0 | JEP3: 0 | JEQ3: 0 | JER3: 0 | JES3: 0 | JET3: 0 | JEU3: 0 | JEV3: 0 | JEW3: 0 | JEX3: 0 | JEY3: 0 | JEZ3: 0 | JFA3: 0 | JFB3: 0 | JFC3: 0 | JFD3: 0 | JFE3: 0 | JFF3: 0 | JFG3: 0 | JFH3: 0 | JFI3: 0 | JFJ3: 0 | JFK3: 0 | JFL3: 0 | JFM3: 0 | JFN3: 0 | JFO3: 0 | JFP3: 0 | JFQ3: 0 | JFR3: 0 | JFS3: 0 | JFT3: 0 | JFU3: 0 | JFV3: 0 | JFW3: 0 | JFX3: 0 | JFY3: 0 | JFZ3: 0 | JGA3: 0 | JGB3: 0 | JGC3: 0 | JGD3: 0 | JGE3: 0 | JGF3: 0 | JGG3: 0 | JGH3: 0 | JGI3: 0 | JGJ3: 0 | JGK3: 0 | JGL3: 0 | JGM3: 0 | JGN3: 0 | JGO3: 0 | JGP3: 0 | JGQ3: 0 | JGR3: 0 | JGS3: 0 | JGT3: 0 | JGU3: 0 | JGV3: 0 | JGW3: 0 | JGX3: 0 | JGY3: 0 | JGZ3: 0 | JHA3: 0 | JHB3: 0 | JHC3: 0 | JHD3: 0 | JHE3: 0 | JHF3: 0 | JHG3: 0 | JHH3: 0 | JHI3: 0 | JHJ3: 0 | JHK3: 0 | JHL3: 0 | JHM3: 0 | JHN3: 0 | JHO3: 0 | JHP3: 0 | JHQ3: 0 | JHR3: 0 | JHS3: 0 | JHT3: 0 | JHU3: 0 | JHV3: 0 | JHW3: 0 | JHX3: 0 | JHY3: 0 | JHZ3: 0 | JIA3: 0 | JIB3: 0 | JIC3: 0 | JID3: 0 | JIE3: 0 | JIF3: 0 | JIG3: 0 | JIH3: 0 | JII3: 0 | JIJ3: 0 | JIK3: 0 | JIL3: 0 | JIM3: 0 | JIN3: 0 | JIO3: 0 | JIP3: 0 | JIQ3: 0 | JIR3: 0 | JIS3: 0 | JIT3: 0 | JIU3: 0 | JIV3: 0 | JIW3: 0 | JIX3: 0 | JIY3: 0 | JIZ3: 0 | JJA3: 0 | JJB3: 0 | JJC3: 0 | JJD3: 0 | JJE3: 0 | JJF3: 0 | JJG3: 0 | JJH3: 0 | JJI3: 0 | JJJ3: 0 | JJK3: 0 | JJL3: 0 | JJM3: 0 | JJN3: 0 | JJO3: 0 | JJP3: 0 | JJQ3: 0 | JJR3: 0 | JJS3: 0 | JJT3: 0 | JJU3: 0 | JJV3: 0 | JJW3: 0 | JJX3: 0 | JJY3: 0 | JJZ3: 0 | JKA3: 0 | JKB3: 0 | JKC3: 0 | JKD3: 0 | JKE3: 0 | JKF3: 0 | JKG3: 0 | JKH3: 0 | JKI3: 0 | JKJ3: 0 | JKK3: 0 | JKL3: 0 | JKM3: 0 | JKN3: 0 | JKO3: 0 | JKP3: 0 | JKQ3: 0 | JKR3: 0 | JKS3: 0 | JKT3: 0 | JKU3: 0 | JKV3: 0 | JKW3: 0 | JKX3: 0 | JKY3: 0 | JKZ3: 0 | JLA3: 0 | JLB3: 0 | JLC3: 0 | JLD3: 0 | JLE3: 0 | JLF3: 0 | JLG3: 0 | JLH3: 0 | JLI3: 0 | JLJ3: 0 | JLK3: 0 | JLL3: 0 | JLM3: 0 | JLN3: 0 | JLO3: 0 | JLP3: 0 | JLQ3: 0 | JLR3: 0 | JLS3: 0 | JLT3: 0 | JLU3: 0 | JLV3: 0 | JLW3: 0 | JLX3: 0 | JLY3: 0 | JLZ3: 0 | JMA3: 0 | JMB3: 0 | JMC3: 0 | JMD3: 0 | JME3: 0 | JMF3: 0 | JMG3: 0 | JMH3: 0 | JMI3: 0 | JMJ3: 0 | JMK3: 0 | JML3: 0 | JMM3: 0 | JMN3: 0 | JMO3: 0 | JMP3: 0 | JMQ3: 0 | JMR3: 0 | JMS3: 0 | JMT3: 0 | JMU3: 0 | JMV3: 0 | JMW3: 0 | JMX3: 0 | JMY3: 0 | JMZ3: 0 | JNA3: 0 | JNB3: 0 | JNC3: 0 | JND3: 0 | JNE3: 0 | JNF3: 0 | JNG3: 0 | JNH3: 0 | JNI3: 0 | JNJ3: 0 | JNK3: 0 | JNL3: 0 | JNM3: 0 | JNN3: 0 | JNO3: 0 | JNP3: 0 | JNQ3: 0 | JNR3: 0 | JNS3: 0 | JNT3: 0 | JNU3: 0 | JNV3: 0 | JNW3: 0 | JNX3: 0 | JNY3: 0 | JNZ3: 0 | JOA3: 0 | JOB3: 0 | JOC3: 0 | JOD3: 0 | JOE3: 0 | JOF3: 0 | JOG3: 0 | JOH3: 0 | JOI3: 0 | JOJ3: 0 | JOK3: 0 | JOL3: 0 | JOM3: 0 | JON3: 0 | JOO3: 0 | JOP3: 0 | JOQ3: 0 | JOR3: 0 | JOS3: 0 | JOT3: 0 | JOU3: 0 | JOV3: 0 | JOW3: 0 | JOX3: 0 | JOY3: 0 | JOZ3: 0 | JPA3: 0 | JPB3: 0 | JPC3: 0 | JPD3: 0 | JPE3: 0 | JPF3: 0 | JPG3: 0 | JPH3: 0 | JPI3: 0 | JPJ3: 0 | JPK3: 0 | JPL3: 0 | JPM3: 0 | JPN3: 0 | JPO3: 0 | JPP3: 0 | JPQ3: 0 | JPR3: 0 | JPS3: 0 | JPT3: 0 | JPU3: 0 | JPV3: 0 | JPW3: 0 | JPX3: 0 | JPY3: 0 | JPZ3: 0 | JQA3: 0 | JQB3: 0 | JQC3: 0 | JQD3: 0 | JQE3: 0 | JQF3: 0 | JQG3: 0 | JQH3: 0 | JQI3: 0 | JQJ3: 0 | JQK3: 0 | JQL3: 0 | JQM3: 0 | JQN3: 0 | JQO3: 0 | JQP3: 0 | JQQ3: 0 | JQR3: 0 | JQS3: 0 | JQT3: 0 | JQU3: 0 | JQV3: 0 | JQW3: 0 | JQX3: 0 | JQY3: 0 | JQZ3: 0 | JRA3: 0 | JRB3: 0 | JRC3: 0 | JRD3: 0 | JRE3: 0 | JRF3: 0 | JRG3: 0 | JRH3: 0 | JRI3: 0 | JRJ3: 0 | JRK3: 0 | JRL3: 0 | JRM3: 0 | JRN3: 0 | JRO3: 0 | JRP3: 0 | JRQ3: 0 | JRR3: 0 | JRS3: 0 | JRT3: 0 | JRU3: 0 | JRV3: 0 | JRW3: 0 | JRX3: 0 | JRY3: 0 | JRZ3: 0 | JSA3: 0 | JSB3: 0 | JSC3: 0 | JSD3: 0 | JSE3: 0 | JSF3: 0 | JSG3: 0 | JSH3: 0 | JSI3: 0 | JSJ3: 0 | JSK3: 0 | JSL3: 0 | JSM3: 0 | JSN3: 0 | JSO3: 0 | JSP3: 0 | JSQ3: 0 | JSR3: 0 | JSS3: 0 | JST3: 0 | JSU3: 0 | JSV3: 0 | JSW3: 0 | JSX3: 0 | JSY3: 0 | JSZ3: 0 | JTA3: 0 | JTB3: 0 | JTC3: 0 | JTD3: 0 | JTE3: 0 | JTF3: 0 | JTG3: 0 | JTH3: 0 | JTI3: 0 | JTJ3: 0 | JTK3: 0 | JTL3: 0 | JTM3: 0 | JTN3: 0 | JTO3: 0 | JTP3: 0 | JTQ3: 0 | JTR3: 0 | JTS3: 0 | JTT3: 0 | JTU3: 0 | JTV3: 0 | JTW3: 0 | JTX3: 0 | JTY3: 0 | JTZ3: 0 | JUA3: 0 | JUB3: 0 | JUC3: 0 | JUD3: 0 | JUE3: 0 | JUF3: 0 | JUG3: 0 | JUH3: 0 | JUI3: 0 | JUJ3: 0 | JUK3: 0 | JUL3: 0 | JUM3: 0 | JUN3: 0 | JUO3: 0 | JUP3: 0 | JUQ3: 0 | JUR3: 0 | JUS3: 0 | JUT3: 0 | JUU3: 0 | JUV3: 0 | JUW3: 0 | JUX3: 0 | JUY3: 0 | JUZ3: 0 | JVA3: 0 | JVB3: 0 | JVC3: 0 | JVD3: 0 | JVE3: 0 | JVF3: 0 | JVG3: 0 | JVH3: 0 | JVI3: 0 | JVJ3: 0 | JVK3: 0 | JVL3: 0 | JVM3: 0 | JVN3: 0 | JVO3: 0 | JVP3: 0 | JVQ3: 0 | JVR3: 0 | JVS3: 0 | JVT3: 0 | JVU3: 0 | JVV3: 0 | JVW3: 0 | JVX3: 0 | JVY3: 0 | JVZ3: 0 | JWA3: 0 | JWB3: 0 | JWC3: 0 | JWD3: 0 | JWE3: 0 | JWF3: 0 | JWG3: 0 | JWH3: 0 | JWI3: 0 | JWJ3: 0 | JWK3: 0 | JWL3: 0 | JWM3: 0 | JWN3: 0 | JWO3: 0 | JWP3: 0 | JWQ3: 0 | JWR3: 0 | JWS3: 0 | JWT3: 0 | JWU3: 0 | JWV3: 0 | JWW3: 0 | JWX3: 0 | JWY3: 0 | JWZ3: 0 | JXA3: 0 | JXB3: 0 | JXC3: 0 | JXD3: 0 | JXE3: 0 | JXF3: 0 | JXG3: 0 | JXH3: 0 | JXI3: 0 | JXJ3: 0 | JXK3: 0 | JXL3: 0 | JXM3: 0 | JXN3: 0 | JXO3: 0 | JXP3: 0 | JXQ3: 0 | JXR3: 0 | JXS3: 0 | JXT3: 0 | JXU3: 0 | JXV3: 0 | JXW3: 0 | JXX3: 0 | JXY3: 0 | JXZ3: 0 | JYA3: 0 | JYB3: 0 | JYC3: 0 | JYD3: 0 | JYE3: 0 | JYF3: 0 | JYG3: 0 | JYH3: 0 | JYI3: 0 | JYJ3: 0 | JYK3: 0 | JYL3: 0 | JYM3: 0 | JYN3: 0 | JYO3: 0 | JYP3: 0 | JYQ3: 0 | JYR3: 0 | JYS3: 0 | JYT3: 0 | JYU3: 0 | JYV3: 0 | JYW3: 0 | JYX3: 0 | JYY3: 0 | JYZ3: 0 | JZA3: 0 | JZB3: 0 | JZC3: 0 | JZD3: 0 | JZE3: 0 | JZF3: 0 | JZG3: 0 | JZH3: 0 | JZI3: 0 | JZJ3: 0 | JZK3: 0 | JZL3: 0 | JZM3: 0 | JZN3: 0 | JZO3: 0 | JZP3: 0 | JZQ3: 0 | JZR3: 0 | JZS3: 0 | JZT3: 0 | JZU3: 0 | JZV3: 0 | JZW3: 0 | JZX3: 0 | JZY3: 0 | JZZ3: 0 | KAA3: 0 | KAB3: 0 | KAC3: 0 | KAD3: 0 | KAE3: 0 | KAF3: 0 | KAG3: 0 | KAH3: 0 | KAI3: 0 | KAJ3: 0 | KAK3: 0 | KAL3: 0 | KAM3: 0 | KAN3: 0 | KAO3: 0 | KAP3: 0 | KAQ3: 0 | KAR3: 0 | KAS3: 0 | KAT3: 0 | KAU3: 0 | KAV3: 0 | KAW3: 0 | KAX3: 0 | KAY3: 0 | KAZ3: 0 | KBA3: 0 | KBB3: 0 | KBC3: 0 | KBD3: 0 | KBE3: 0 | KBF3: 0 | KBG3: 0 | KBH3: 0 | KBI3: 0 | KBJ3: 0 | KBK3: 0 | KBL3: 0 | KBM3: 0 | KBN3: 0 | KBO3: 0 | KBP3: 0 | KBQ3: 0 | KBR3: 0 | KBS3: 0 | KBT3: 0 | KBU3: 0 | KBV3: 0 | KBW3: 0 | KBX3: 0 | KBY3: 0 | KBZ3: 0 | KCA3: 0 | KCB3: 0 | KCC3: 0 | KCD3: 0 | KCE3: 0 | KCF3: 0 | KCG3: 0 | KCH3: 0 | KCI3: 0 | KCJ3: 0 | KCK3: 0 | KCL3: 0 | KCM3: 0 | KCN3: 0 | KCO3: 0 | KCP3: 0 | KCQ3: 0 | KCR3: 0 | KCS3: 0 | KCT3: 0 | KCU3: 0 | KCV3: 0 | KCW3: 0 | KCX3: 0 | KCY3: 0 | KCZ3: 0 | KDA3: 0 | KDB3: 0 | KDC3: 0 | KDD3: 0 | KDE3: 0 | KDF3: 0 | KDG3: 0 | KDH3: 0 | KDI3: 0 | KDJ3: 0 | KDK3: 0 | KDL3: 0 | KDM3: 0 | KDN3: 0 | KDO3: 0 | KDP3: 0 | KDQ3: 0 | KDR3: 0 | KDS3: 0 | KDT3: 0 | KDU3: 0 | KDV3: 0 | KDW3: 0 | KDX3: 0 | KDY3: 0 | KDZ3: 0 | KEA3: 0 | KEB3: 0 | KEC3: 0 | KED3: 0 | KEE3: 0 | KEF3: 0 | KEG3: 0 | KEH3: 0 | KEI3: 0 | KEJ3: 0 | KEK3: 0 | KEL3: 0 | KEM3: 0 | KEN3: 0 | KEO3: 0 | KEP3: 0 | KEQ3: 0 | KER3: 0 | KES3: 0 | KET3: 0 | KEU3: 0 | KEV3: 0 | KEW3: 0 | KEX3: 0 | KEY3: 0 | KEZ3: 0 | KFA3: 0 | KFB3: 0 | KFC3: 0 | KFD3: 0 | KFE3: 0 | KFF3: 0 | KFG3: 0 | KFH3: 0 | KFI3: 0 | KFJ3: 0 | KFK3: 0 | KFL3: 0 | KFM3: 0 | KFN3: 0 | KFO3: 0 | KFP3: 0 | KFQ3: 0 | KFR3: 0 | KFS3: 0 | KFT3: 0 | KFU3: 0 | KFV3: 0 | KFW3: 0 | KFX3: 0 | KFY3: 0 | KFZ3: 0 | KGA3: 0 | KGB3: 0 | KGC3: 0 | KGD3: 0 | KGE3: 0 | KGF3: 0 | KGG3: 0 | KGH3: 0 | KGI3: 0 | KGJ3: 0 | KGK3: 0 | KGL3: 0 | KGM3: 0 | KGN3: 0 | KGO3: 0 | KGP3: 0 | KGQ3: 0 | KGR3: 0 | KGS3: 0 | KGT3: 0 | KGU3: 0 | KGV3: 0 | KGW3: 0 | KGX3: 0 | KGY3: 0 | KGZ3: 0 | KHA3: 0 | KHB3: 0 | KHC3: 0 | KHD3: 0 | KHE3: 0 | KHF3: 0 | KHG3: 0 | KHH3: 0 | KHI3: 0 | KHJ3: 0 | KHK3: 0 | KHL3: 0 | KHM3: 0 | KHN3: 0 | KHO3: 0 | KHP3: 0 | KHQ3: 0 | KHR3: 0 | KHS3: 0 | KHT3: 0 | KHU3: 0 | KHV3: 0 | KHW3: 0 | KHX3: 0 | KHY3: 0 | KHZ3: 0 | KIA3: 0 | KIB3: 0 | KIC3: 0 | KID3: 0 | KIE3: 0 | KIF3: 0 | KIG3: 0 | KIH3: 0 | KII3: 0 | KIJ3: 0 | KIK3: 0 | KIL3: 0 | KIM3: 0 | KIN3: 0 | KIO3: 0 | KIP3: 0 | KIQ3: 0 | KIR3: 0 | KIS3: 0 | KIT3: 0 | KIU3: 0 | KIV3: 0 | KIW3: 0 | KIX3: 0 | KIY3: 0 | KIZ3: 0 | KJA3: 0 | KJB3: 0 | KJC3: 0 | KJD3: 0 | KJE3: 0 | KJF3: 0 | KJG3: 0 | KJH3: 0 | KJI3: 0 | KJJ3: 0 | KJK3: 0 | KJL3: 0 | KJM3: 0 | KJN3: 0 | KJO3: 0 | KJP3: 0 | KJQ3: 0 | KJR3: 0 | KJS3: 0 | KJT3: 0 | KJU3: 0 | KJV3: 0 | KJW3: 0 | KJX3: 0 | KJY3: 0 | KJZ3: 0 | KKA3: 0 | KKB3: 0 | KKC3: 0 | KKD3: 0 | KKE3: 0 | KKF3: 0 | KKG3: 0 | KKH3: 0 | KKI3: 0 | KKJ3: 0 | KKK3: 0 | KKL3: 0 | KKM3: 0 | KKN3: 0 | KKO3: 0 | KKP3: 0 | KKQ3: 0 | KKR3: 0 | KKS3: 0 | KKT3: 0 | KKU3: 0 | KKV3: 0 | KKW3: 0 | KKX3: 0 | KKY3: 0 | KKZ3: 0 | KLA3: 0 | KLB3: 0 | KLC3: 0 | KLD3: 0 | KLE3: 0 | KLF3: 0 | KLG3: 0 | KLH3: 0 | KLI3: 0 | KLJ3: 0 | KLK3: 0 | KLL3: 0 | KLM3: 0 | KLN3: 0 | KLO3: 0 | KLP3: 0 | KLQ3: 0 | KLR3: 0 | KLS3: 0 | KLT3: 0 | KLU3: 0 | KLV3: 0 | KLW3: 0 | KLX3: 0 | KLY3: 0 | KLZ3: 0 | KMA3: 0 | KMB3: 0 | KMC3: 0 | KMD3: 0 | KME3: 0 | KMF3: 0 | KMG3: 0 | KMH3: 0 | KMI3: 0 | KMJ3: 0 | KMK3: 0 | KML3: 0 | KMM3: 0 | KMN3: 0 | KMO3: 0 | KMP3: 0 | KMQ3: 0 | KMR3: 0 | KMS3: 0 | KMT3: 0 | KMU3: 0 | KMV3: 0 | KMW3: 0 | KMX3: 0 | KMY3: 0 | KMZ3: 0 | KNA3: 0 | KNB3: 0 | KNC3: 0 | KND3: 0 | KNE3: 0 | KNF3: 0 | KNG3: 0 | KNH3: 0 | KNI3: 0 | KNJ3: 0 | KNK3: 0 | KNL3: 0 | KNM3: 0 | KNN3: 0 | KNO3: 0 | KNP3: 0 | KNQ3: 0 | KNR3: 0 | KNS3: 0 | KNT3: 0 | KNU3: 0 | KNV3: 0 | KNW3: 0 | KNX3: 0 | KNY3: 0 | KNZ3: 0 | KOA3: 0 | KOB3: 0 | KOC3: 0 | KOD3: 0 | KOE3: 0 | KOF3: 0 | KOG3: 0 | KOH3: 0 | KOI3: 0 | KOJ3: 0 | KOK3: 0 | KOL3: 0 | KOM3: 0 | KON3: 0 | KOO3: 0 | KOP3: 0 | KOQ3: 0 | KOR3: 0 | KOS3: 0 | KOT3: 0 | KOU3: 0 | KOV3: 0 | KOW3: 0 | KOX3: 0 | KOY3: 0 | KOZ3: 0 | KPA3: 0 | KPB3: 0 | KPC3: 0 | KPD3: 0 | KPE3: 0 | KPF3: 0 | KPG3: 0 | KPH3: 0 | KPI3: 0 | KPJ3: 0 | KPK3: 0 | KPL3: 0 | KPM3: 0 | KPN3: 0 | KPO3: 0 | KPP3: 0 | KPQ3: 0 | KPR3: 0 | KPS3: 0 | KPT3: 0 | KPU3: 0 | KPV3: 0 | KPW3: 0 | KPX3: 0 | KPY3: 0 | KPZ3: 0 | KQA3: 0 | KQB3: 0 | KQC3: 0 | KQD3: 0 | KQE3: 0 | KQF3: 0 | KQG3: 0 | KQH3: 0 | KQI3: 0 | KQJ3: 0 | KQK3: 0 | KQL3: 0 | KQM3: 0 | KQN3: 0 | KQO3: 0 | KQP3: 0 | KQQ3: 0 | KQR3: 0 | KQS3: 0 | KQT3: 0 | KQU3: 0 | KQV3: 0 | KQW3: 0 | KQX3: 0 | KQY3: 0 | KQZ3: 0 | KRA3: 0 | KRB3: 0 | KRC3: 0 | KRD3: 0 | KRE3: 0 | KRF3: 0 | KRG3: 0 | KRH3: 0 | KRI3: 0 | KRJ3: 0 | KRK3: 0 | KRL3: 0 | KRM3: 0 | KRN3: 0 | KRO3: 0 | KRP3: 0 | KRQ3: 0 | KRR3: 0 | KRS3: 0 | KRT3: 0 | KRU3: 0 | KRV3: 0 | KRW3: 0 | KRX3: 0 | KRY3: 0 | KRZ3: 0 | KSA3: 0 | KSB3: 0 | KSC3: 0 | KSD3: 0 | KSE3: 0 | KSF3: 0 | KSG3: 0 | KSH3: 0 | KSI3: 0 | KSJ3: 0 | KSK3: 0 | KSL3: 0 | KSM3: 0 | KSN3: 0 | KSO3: 0 | KSP3: 0 | KSQ3: 0 | KSR3: 0 | KSS3: 0 | KST3: 0 | KSU3: 0 | KSV3: 0 | KSW3: 0 | KSX3: 0 | KSY3: 0 | KSZ3: 0 | KTA3: 0 | KTB3: 0 | KTC3: 0 | KTD3: 0 | KTE3: 0 | KTF3: 0 | KTG3: 0 | KTH3: 0 | KTI3: 0 | KTJ3: 0 | KTK3: 0 | KTL3: 0 | KTM3: 0 | KTN3: 0 | KTO3: 0 | KTP3: 0 | KTQ3: 0 | KTR3: 0 | KTS3: 0 | KTT3: 0 | KTU3: 0 | KTV3: 0 | KTW3: 0 | KTX3: 0 | KTY3: 0 | KTZ3: 0 | KUA3: 0 | KUB3: 0 | KUC3: 0 | KUD3: 0 | KUE3: 0 | KUF3: 0 | KUG3: 0 | KUH3: 0 | KUI3: 0 | KUJ3: 0 | KUK3: 0 | KUL3: 0 | KUM3: 0 | KUN3: 0 | KUO3: 0 | KUP3: 0 | KUQ3: 0 | KUR3: 0 | KUS3: 0 | KUT3: 0 | KUU3: 0 | KUV3: 0 | KUW3: 0 | KUX3: 0 | KUY3: 0 | KUZ3: 0 | KVA3: 0 | KVB3: 0 | KVC3: 0 | KVD3: 0 | KVE3: 0 | KVF3: 0 | KVG3: 0 | KVH3: 0 | KVI3: 0 | KVJ3: 0 | KVK3: 0 | KVL3: 0 | KVM3: 0 | KVN3: 0 | KVO3: 0 | KVP3: 0 | KVQ3: 0 | KVR3: 0 | KVS3: 0 | KVT3: 0 | KVU3: 0 | KVV3: 0 | KVW3: 0 | KVX3: 0 | KVY3: 0 | KVZ3: 0 | KWA3: 0 | KWB3: 0 | KWC3: 0 | KWD3: 0 | KWE3: 0 | KWF3: 0 | KWG3: 0 | KWH3: 0 | KWI3: 0 | KWJ3: 0 | KWK3: 0 | KWL3: 0 | KWM3: 0 | KWN3: 0 | KWO3: 0 | KWP3: 0 | KWQ3: 0 | KWR3: 0 | KWS3: 0 | KWT3: 0 | KWU3: 0 | KWV3: 0 | KWW3: 0 | KWX3: 0 | KWY3: 0 | KWZ3: 0 | KXA3: 0 | KXB3: 0 | KXC3: 0 | KXD3: 0 | KXE3: 0 | KXF3: 0 | KXG3: 0 | KXH3: 0 | KXI3: 0 | KXJ3: 0 | KXK3: 0 | KXL3: 0 | KXM3: 0 | KXN3: 0 | KXO3: 0 | KXP3: 0 | KXQ3: 0 | KXR3: 0 | KXS3: 0 | KXT3: 0 | KXU3: 0 | KXV3: 0 | KXW3: 0 | KXX3: 0 | KXY3: 0 | KXZ3: 0 | KYA3: 0 | KYB3: 0 | KYC3: 0 | KYD3: 0 | KYE3: 0 | KYF3: 0 | KYG3: 0 | KYH3: 0 | KYI3: 0 | KYJ3: 0 | KYK3: 0 | KYL3: 0 | KYM3: 0 | KYN3: 0 | KYO3: 0 | KYP3: 0 | KYQ3: 0 | KYR3: 0 | KYS3: 0 | KYT3: 0 | KYU3: 0 | KYV3: 0 | KYW3: 0 | KYX3: 0 | KYY3: 0 | KYZ3: 0 | KZA3: 0 | KZB3: 0 | KZC3: 0 | KZD3: 0 | KZE3: 0 | KZF3: 0 | KZG3: 0 | KZH3: 0 | KZI3: 0 | KZJ3: 0 | KZK3: 0 | KZL3: 0 | KZM3: 0 | KZN3: 0 | KZO3: 0 | KZP3: 0 | KZQ3: 0 | KZR3: 0 | KZS3: 0 | KZT3: 0 | KZU3: 0 | KZV3: 0 | KZW3: 0 | KZX3: 0 | KZY3: 0 | KZZ3: 0 | LAA3: 0 | LAB3: 0 | LAC3: 0 | LAD3: 0 | LAE3: 0 | LAF3: 0 | LAG3: 0 | LAH3: 0 | LAI3: 0 | LAJ3: 0 | LAK3: 0 | LAL3: 0 | LAM3: 0 | LAN3: 0 | LAO3: 0 | LAP3: 0 | LAQ3: 0 | LAR3: 0 | LAS3: 0 | LAT3: 0 | LAU3: 0 | LAV3: 0 | LAW3: 0 | LAX3: 0 | LAY3: 0 | LAZ3: 0 | LBA3: 0 | LBB3: 0 | LBC3: 0 | LBD3: 0 | LBE3: 0 | LBF3: 0 | LBG3: 0 | LBH3: 0 | LBI3: 0 | LBJ3: 0 | LBK3: 0 | LBL3: 0 | LBM3: 0 | LBN3: 0 | LBO3: 0 | LBP3: 0 | LBQ3: 0 | LBR3: 0 | LBS3: 0 | LBT3: 0 | LBU3: 0 | LBV3: 0 | LBW3: 0 | LBX3: 0 | LBY3: 0 | LBZ3: 0 | LCA3: 0 | LCB3: 0 | LCC3: 0 | LCD3: 0 | LCE3: 0 | LCF3: 0 | LCG3: 0 | LCH3: 0 | LCI3: 0 | LCJ3: 0 | LCK3: 0 | LCL3: 0 | LCM3: 0 | LCN3: 0 | LCO3: 0 | LCP3: 0 | LCQ3: 0 | LCR3: 0 | LCS3: 0 | LCT3: 0 | LCU3: 0 | LCV3: 0 | LCW3: 0 | LCX3: 0 | LCY3: 0 | LCZ3: 0 | LDA3: 0 | LDB3: 0 | LDC3: 0 | LDD3: 0 | LDE3: 0 | LDF3: 0 | LDG3: 0 | LDH3: 0 | LDI3: 0 | LDJ3: 0 | LDK3: 0 | LDL3: 0 | LDM3: 0 | LDN3: 0 | LDO3: 0 | LDP3: 0 | LDQ3: 0 | LDR3: 0 | LDS3: 0 | LDT3: 0 | LDU3: 0 | LDV3: 0 | LDW3: 0 | LDX3: 0 | LDY3: 0 | LDZ3: 0 | LEA3: 0 | LEB3: 0 | LEC3: 0 | LED3: 0 | LEE3: 0 | LEF3: 0 | LEG3: 0 | LEH3: 0 | LEI3: 0 | LEJ3: 0 | LEK3: 0 | LEL3: 0 | LEM3: 0 | LEN3: 0 | LEO3: 0 | LEP3: 0 | LEQ3: 0 | LER3: 0 | LES3: 0 | LET3: 0 | LEU3: 0 | LEV3: 0 | LEW3: 0 | LEX3: 0 | LEY3: 0 | LEZ3: 0 | LFA3: 0 | LFB3: 0 | LFC3: 0 | LFD3: 0 | LFE3: 0 | LFF3: 0 | LFG3: 0 | LFH3: 0 | LFI3: 0 | LFJ3: 0 | LFK3: 0 | LFL3: 0 | LFM3: 0 | LFN3: 0 | LFO3: 0 | LFP3: 0 | LFQ3: 0 | LFR3: 0 | LFS3: 0 | LFT3: 0 | LFU3: 0 | LFV3: 0 | LFW3: 0 | LFX3: 0 | LFY3: 0 | LFZ3: 0 | LGA3: 0 | LGB3: 0 | LGC3: 0 | LGD3: 0 | LGE3: 0 | LGF3: 0 | LGG3: 0 | LGH3: 0 | LGI3: 0 | LGJ3: 0 | LGK3: 0 | LGL3: 0 | LGM3: 0 | LGN3: 0 | LGO3: 0 | LGP3: 0 | LGQ3: 0 | LGR3: 0 | LGS3: 0 | LGT3: 0 | LGU3: 0 | LGV3: 0 | LGW3: 0 | LGX3: 0 | LGY3: 0 | LGZ3: 0 | LHA3: 0 | LHB3: 0 | LHC3: 0 | LHD3: 0 | LHE3: 0 | LHF3: 0 | LHG3: 0 | LHH3: 0 | LHI3: 0 | LHJ3: 0 | LHK3: 0 | LHL3: 0 | LHM3: 0 | LHN3: 0 | LHO3: 0 | LHP3: 0 | LHQ3: 0 | LHR3: 0 | LHS3: 0 | LHT3: 0 | LHU3: 0 | LHV3: 0 | LHW3: 0 | LHX3: 0 | LHY3: 0 | LHZ3: 0 | LIA3: 0 | LIB3: 0 | LIC3: 0 | LID3: 0 | LIE3: 0 | LIF3: 0 | LIG3: 0 | LIH3: 0 | LII3: 0 | LIJ3: 0 | LIK3: 0 | LIL3: 0 | LIM3: 0 | LIN3: 0 | LIO3: 0 | LIP3: 0 | LIQ3: 0 | LIR3: 0 | LIS3: 0 | LIT3: 0 | LIU3: 0 | LIV3: 0 | LIW3: 0 | LIX3: 0 | LIY3: 0 | LIZ3: 0 | LJA3: 0 | LJB3: 0 | LJC3: 0 | LJD3: 0 | LJE3: 0 | LJF3: 0 | LJG3: 0 | LJH3: 0 | LJI3: 0 | LJJ3: 0 | LJK3: 0 | LJL3: 0 | LJM3: 0 | LJN3: 0 | LJO3: 0 | LJP3: 0 | LJQ3: 0 | LJR3: 0 | LJS3: 0 | LJT3: 0 | LJU3: 0 | LJV3: 0 | LJW3: 0 | LJX3: 0 | LJY3: 0 | LJZ3: 0 | LKA3: 0 | LKB3: 0 | LKC3: 0 | LKD3: 0 | LKE3: 0 | LKF3: 0 | LKG3: 0 | LKH3: 0 | LKI3: 0 | LKJ3: 0 | LKK3: 0 | LKL3: 0 | LKM3: 0 | LKN3: 0 | LKO3: 0 | LKP3: 0 | LKQ3: 0 | LKR3: 0 | LKS3: 0 | LKT3: 0 | LKU3: 0 | LKV3: 0 | LKW3: 0 | LKX3: 0 | LKY3: 0 | LKZ3: 0 | LLA3: 0 | LLB3: 0 | LLC3: 0 | LLD3: 0 | LLE3: 0 | LLF3: 0 | LLG3: 0 | LLH3: 0 | LLI3: 0 | LLJ3: 0 | LLK3: 0 | LLL3: 0 | LLM3: 0 | LLN3: 0 | LLO3: 0 | LLP3: 0 | LLQ3: 0 | LLR3: 0 | LLS3: 0 | LLT3: 0 | LLU3: 0 | LLV3: 0 | LLW3: 0 | LLX3: 0 | LLY3: 0 | LLZ3: 0 | LMA3: 0 | LMB3: 0 | LMC3: 0 | LMD3: 0 | LME3: 0 | LMF3: 0 | LMG3: 0 | LMH3: 0 | LMI3: 0 | LMJ3: 0 | LMK3: 0 | LML3: 0 | LMM3: 0 | LMN3: 0 | LMO3: 0 | LMP3: 0 | LMQ3: 0 | LMR3: 0 | LMS3: 0 | LMT3: 0 | LMU3: 0 | LMV3: 0 | LMW3: 0 | LMX3: 0 | LMY3: 0 | LMZ3: 0 | LNA3: 0 | LNB3: 0 | LNC3: 0 | LND3: 0 | LNE3: 0 | LNF3: 0 | LNG3: 0 | LNH3: 0 | LNI3: 0 | LNJ3: 0 | LNK3: 0 | LNL3: 0 | LNM3: 0 | LNN3: 0 | LNO3: 0 | LNP3: 0 | LNQ3: 0 | LNR3: 0 | LNS3: 0 | LNT3: 0 | LNU3: 0 | LNV3: 0 | LNW3: 0 | LNX3: 0 | LNY3: 0 | LNZ3: 0 | LOA3: 0 | LOB3: 0 | LOC3: 0 | LOD3: 0 | LOE3: 0 | LOF3: 0 | LOG3: 0 | LOH3: 0 | LOI3: 0 | LOJ3: 0 | LOK3: 0 | LOL3: 0 | LOM3: 0 | LON3: 0 | LOO3: 0 | LOP3: 0 | LOQ3: 0 | LOR3: 0 | LOS3: 0 | LOT3: 0 | LOU3: 0 | LOV3: 0 | LOW3: 0 | LOX3: 0 | LOY3: 0 | LOZ3: 0 | LPA3: 0 | LPB3: 0 | LPC3: 0 | LPD3: 0 | LPE3: 0 | LPF3: 0 | LPG3: 0 | LPH3: 0 | LPI3: 0 | LPJ3: 0 | LPK3: 0 | LPL3: 0 | LPM3: 0 | LPN3: 0 | LPO3: 0 | LPP3: 0 | LPQ3: 0 | LPR3: 0 | LPS3: 0 | LPT3: 0 | LPU3: 0 | LPV3: 0 | LPW3: 0 | LPX3: 0 | LPY3: 0 | LPZ3: 0 | LQA3: 0 | LQB3: 0 | LQC3: 0 | LQD3: 0 | LQE3: 0 | LQF3: 0 | LQG3: 0 | LQH3: 0 | LQI3: 0 | LQJ3: 0 | LQK3: 0 | LQL3: 0 | LQM3: 0 | LQN3: 0 | LQO3: 0 | LQP3: 0 | LQQ3: 0 | LQR3: 0 | LQS3: 0 | LQT3: 0 | LQU3: 0 | LQV3: 0 | LQW3: 0 | LQX3: 0 | LQY3: 0 | LQZ3: 0 | LRA3: 0 | LRB3: 0 | LRC3: 0 | LRD3: 0 | LRE3: 0 | LRF3: 0 | LRG3: 0 | LRH3: 0 | LRI3: 0 | LRJ3: 0 | LRK3: 0 | LRL3: 0 | LRM3: 0 | LRN3: 0 | LRO3: 0 | LRP3: 0 | LRQ3: 0 | LRR3: 0 | LRS3: 0 | LRT3: 0 | LRU3: 0 | LRV3: 0 | LRW3: 0 | LRX3: 0 | LRY3: 0 | LRZ3: 0 | LSA3: 0 | LSB3: 0 | LSC3: 0 | LSD3: 0 | LSE3: 0 | LSF3: 0 | LSG3: 0 | LSH3: 0 | LSI3: 0 | LSJ3: 0 | LSK3: 0 | LSL3: 0 | LSM3: 0 | LSN3: 0 | LSO3: 0 | LSP3: 0 | LSQ3: 0 | LSR3: 0 | LSS3: 0 | LST3: 0 | LSU3: 0 | LSV3: 0 | LSW3: 0 | LSX3: 0 | LSY3: 0 | LSZ3: 0 | LTA3: 0 | LTB3: 0 | LTC3: 0 | LTD3: 0 | LTE3: 0 | LTF3: 0 | LTG3: 0 | LTH3: 0 | LTI3: 0 | LTJ3: 0 | LTK3: 0 | LTL3: 0 | LTM3: 0 | LTN3: 0 | LTO3: 0 | LTP3: 0 | LTQ3: 0 | LTR3: 0 | LTS3: 0 | LTT3: 0 | LTU3: 0 | LTV3: 0 | LTW3: 0 | LTX3: 0 | LTY3: 0 | LTZ3: 0 | LUA3: 0 | LUB3: 0 | LUC3: 0 | LUD3: 0 | LUE3: 0 | LUF3: 0 | LUG3: 0 | LUH3: 0 | LUI3: 0 | LUJ3: 0 | LUK3: 0 | LUL3: 0 | LUM3: 0 | LUN3: 0 | LUO3: 0 | LUP3: 0 | LUQ3: 0 | LUR3: 0 | LUS3: 0 | LUT3: 0 | LUU3: 0 | LUV3: 0 | LUW3: 0 | LUX3: 0 | LUY3: 0 | LUZ3: 0 | LVA3: 0 | LVB3: 0 | LVC3: 0 | LVD3: 0 | LVE3: 0 | LVF3: 0 | LVG3: 0 | LVH3: 0 | LVI3: 0 | LVJ3: 0 | LVK3: 0 | LVL3: 0 | LVM3: 0 | LVN3: 0 | LVO3: 0 | LVP3: 0 | LVQ3: 0 | LVR3: 0 | LVS3: 0 | LVT3: 0 | LVU3: 0 | LVV3: 0 | LVW3: 0 | LVX3: 0 | LVY3: 0 | LVZ3: 0 | LWA3: 0 | LWB3: 0 | LWC3: 0 | LWD3: 0 | LWE3: 0 | LWF3: 0 | LWG3: 0 | LWH3: 0 | LWI3: 0 | LWJ3: 0 | LWK3: 0 | LWL3: 0 | LWM3: 0 | LWN3: 0 | LWO3: 0 | LWP3: 0 | LWQ3: 0 | LWR3: 0 | LWS3: 0 | LWT3: 0 | LWU3: 0 | LWV3: 0 | LWW3: 0 | LWX3: 0 | LWY3: 0 | LWZ3: 0 | LXA3: 0 | LXB3: 0 | LXC3: 0 | LXD3: 0 | LXE3: 0 | LXF3: 0 | LXG3: 0 | LXH3: 0 | LXI3: 0 | LXJ3: 0 | LXK3: 0 | LXL3: 0 | LXM3: 0 | LXN3: 0 | LXO3: 0 | LXP3: 0 | LXQ3: 0 | LXR3: 0 | LXS3: 0 | LXT3: 0 | LXU3: 0 | LXV3: 0 | LXW3: 0 | LXX3: 0 | LXY3: 0 | LXZ3: 0 | LYA3: 0 | LYB3: 0 | LYC3: 0 | LYD3: 0 | LYE3: 0 | LYF3: 0 | LYG3: 0 | LYH3: 0 | LYI3: 0 | LYJ3: 0 | LYK3: 0 | LYL3: 0 | LYM3: 0 | LYN3: 0 | LYO3: 0 | LYP3: 0 | LYQ3: 0 | LYR3: 0 | LYS3: 0 | LYT3: 0 | LYU3: 0 | LYV3: 0 | LYW3: 0 | LYX3: 0 | LYY3: 0 | LYZ3: 0 | LZA3: 0 | LZB3: 0 | LZC3: 0 | LZD3: 0 | LZE3: 0 | LZF3: 0 | LZG3: 0 | LZH3: 0 | LZI3: 0 | LZJ3: 0 | LZK3: 0 | LZL3: 0 | LZM3: 0 | LZN3: 0 | LZO3: 0 | LZP3: 0 | LZQ3: 0 | LZR3: 0 | LZS3: 0 | LZT3: 0 | LZU3: 0 | LZV3: 0 | LZW3: 0 | LZX3: 0 | LZY3: 0 | LZZ3: 0 | MAA3: 0 | MAB3: 0 | MAC3: 0 | MAD3: 0 | MAE3: 0 | MAF3: 0 | MAG3: 0 | MAH3: 0 | MAI3: 0 | MAJ3: 0 | MAK3: 0 | MAL3: 0 | MAM3: 0 | MAN3: 0 | MAO3: 0 | MAP3: 0 | MAQ3: 0 | MAR3: 0 | MAS3: 0 | MAT3: 0 | MAU3: 0 | MAV3: 0 | MAW3: 0 | MAX3: 0 | MAY3: 0 | MAZ3: 0 | MBA3: 0 | MBB3: 0 | MBC3: 0 | MBD3: 0 | MBE3: 0 | MBF3: 0 | MBG3: 0 | MBH3: 0 | MBI3: 0 | MBJ3: 0 | MBK3: 0 | MBL3: 0 | MBM3: 0 | MBN3: 0 | MBO3: 0 | MBP3: 0 | MBQ3: 0 | MBR3: 0 | MBS3: 0 | MBT3: 0 | MBU3: 0 | MBV3: 0 | MBW3: 0 | MBX3: 0 | MBY3: 0 | MBZ3: 0 | MCA3: 0 | MCB3: 0 | MCC3: 0 | MCD3: 0 | MCE3: 0 | MCF3: 0 | MCG3: 0 | MCH3: 0 | MCI3: 0 | MCJ3: 0 | MCK3: 0 | MCL3: 0 | MCM3: 0 | MCN3: 0 | MCO3: 0 | MCP3: 0 | MCQ3: 0 | MCR3: 0 | MCS3: 0 | MCT3: 0 | MCU3: 0 | MCV3: 0 | MCW3: 0 | MCX3: 0 | MCY3: 0 | MCZ3: 0 | MDA3: 0 | MDB3: 0 | MDC3: 0 | MDD3: 0 | MDE3: 0 | MDF3: 0 | MDG3: 0 | MDH3: 0 | MDI3: 0 | MDJ3: 0 | MDK3: 0 | MDL3: 0 | MDM3: 0 | MDN3: 0 | MDO3: 0 | MDP3: 0 | MDQ3: 0 | MDR3: 0 | MDS3: 0 | MDT3: 0 | MDU3: 0 | MDV3: 0 | MDW3: 0 | MDX3: 0 | MDY3: 0 | MDZ3: 0 | MEA3: 0 | MEB3: 0 | MEC3: 0 | MED3: 0 | MEE3: 0 | MEF3: 0 | MEG3: 0 | MEH3: 0 | MEI3: 0 | MEJ3: 0 | MEK3: 0 | MEL3: 0 | MEM3: 0 | MEN3: 0 | MEO3: 0 | MEP3: 0 | MEQ3: 0 | MER3: 0 | MES3: 0 | MET3: 0 | MEU3: 0 | MEV3: 0 | MEW3: 0 | MEX3: 0 | MEY3: 0 | MEZ3: 0 | MFA3: 0 | MFB3: 0 | MFC3: 0 | MFD3: 0 | MFE3: 0 | MFF3: 0 | MFG3: 0 | MFH3: 0 | MFI3: 0 | MFJ3: 0 | MFK3: 0 | MFL3: 0 | MFM3: 0 | MFN3: 0 | MFO3: 0 | MFP3: 0 | MFQ3: 0 | MFR3: 0 | MFS3: 0 | MFT3: 0 | MFU3: 0 | MFV3: 0 | MFW3: 0 | MFX3: 0 | MFY3: 0 | MFZ3: 0 | MGA3: 0 | MGB3: 0 | MGC3: 0 | MGD3: 0 | MGE3: 0 | MGF3: 0 | MGG3: 0 | MGH3: 0 | MGI3: 0 | MGJ3: 0 | MGK3: 0 | MGL3: 0 | MGM3: 0 | MGN3: 0 | MGO3: 0 | MGP3: 0 | MGQ3: 0 | MGR3: 0 | MGS3: 0 | MGT3: 0 | MGU3: 0 | MGV3: 0 | MGW3: 0 | MGX3: 0 | MGY3: 0 | MGZ3: 0 | MHA3: 0 | MHB3: 0 | MHC3: 0 | MHD3: 0 | MHE3: 0 | MHF3: 0 | MHG3: 0 | MHH3: 0 | MHI3: 0 | MHJ3: 0 | MHK3: 0 | MHL3: 0 | MHM3: 0 | MHN3: 0 | MHO3: 0 | MHP3: 0 | MHQ3: 0 | MHR3: 0 | MHS3: 0 | MHT3: 0 | MHU3: 0 | MHV3: 0 | MHW3: 0 | MHX3: 0 | MHY3: 0 | MHZ3: 0 | MIA3: 0 | MIB3: 0 | MIC3: 0 | MID3: 0 | MIE3: 0 | MIF3: 0 | MIG3: 0 | MIH3: 0 | MII3: 0 | MIJ3: 0 | MIK3: 0 | MIL3: 0 | MIM3: 0 | MIN3: 0 | MIO3: 0 | MIP3: 0 | MIQ3: 0 | MIR3: 0 | MIS3: 0 | MIT3: 0 | MIU3: 0 | MIV3: 0 | MIW3: 0 | MIX3: 0 | MIY3: 0 | MIZ3: 0 | MJA3: 0 | MJB3: 0 | MJC3: 0 | MJD3: 0 | MJE3: 0 | MJF3: 0 | MJG3: 0 | MJH3: 0 | MJI3: 0 | MJJ3: 0 | MJK3: 0 | MJL3: 0 | MJM3: 0 | MJN3: 0 | MJO3: 0 | MJP3: 0 | MJQ3: 0 | MJR3: 0 | MJS3: 0 | MJT3: 0 | MJU3: 0 | MJV3: 0 | MJW3: 0 | MJX3: 0 | MJY3: 0 | MJZ3: 0 | MKA3: 0 | MKB3: 0 | MKC3: 0 | MKD3: 0 | MKE3: 0 | MKF3: 0 | MKG3: 0 | MKH3: 0 | MKI3: 0 | MKJ3: 0 | MKK3: 0 | MKL3: 0 | MKM3: 0 | MKN3: 0 | MKO3: 0 | MKP3: 0 | MKQ3: 0 | MKR3: 0 | MKS3: 0 | MKT3: 0 | MKU3: 0 | MKV3: 0 | MKW3: 0 | MKX3: 0 | MKY3: 0 | MKZ3: 0 | MLA3: 0 | MLB3: 0 | MLC3: 0 | MLD3: 0 | MLE3: 0 | MLF3: 0 | MLG3: 0 | MLH3: 0 | MLI3: 0 | MLJ3: 0 | MLK3: 0 | MLL3: 0 | MLM3: 0 | MLN3: 0 | MLO3: 0 | MLP3: 0 | MLQ3: 0 | MLR3: 0 | MLS3: 0 | MLT3: 0 | MLU3: 0 | MLV3: 0 | MLW3: 0 | MLX3: 0 | MLY3: 0 | MLZ3: 0 | MMA3: 0 | MMB3: 0 | MMC3: 0 | MMD3: 0 | MME3: 0 | MMF3: 0 | MMG3: 0 | MMH3: 0 | MMI3: 0 | MMJ3: 0 | MMK3: 0 | MML3: 0 | MMM3: 0 | MMN3: 0 | MMO3: 0 | MMP3: 0 | MMQ3: 0 | MMR3: 0 | MMS3: 0 | MMT3: 0 | MMU3: 0 | MMV3: 0 | MMW3: 0 | MMX3: 0 | MMY3: 0 | MMZ3: 0 | MNA3: 0 | MNB3: 0 | MNC3: 0 | MND3: 0 | MNE3: 0 | MNF3: 0 | MNG3: 0 | MNH3: 0 | MNI3: 0 | MNJ3: 0 | MNK3: 0 | MNL3: 0 | MNM3: 0 | MNN3: 0 | MNO3: 0 | MNP3: 0 | MNQ3: 0 | MNR3: 0 | MNS3: 0 | MNT3: 0 | MNU3: 0 | MNV3: 0 | MNW3: 0 | MNX3: 0 | MNY3: 0 | MNZ3: 0 | MOA3: 0 | MOB3: 0 | MOC3: 0 | MOD3: 0 | MOE3: 0 | MOF3: 0 | MOG3: 0 | MOH3: 0 | MOI3: 0 | MOJ3: 0 | MOK3: 0 | MOL3: 0 | MOM3: 0 | MON3: 0 | MOO3: 0 | MOP3: 0 | MOQ3: 0 | MOR3: 0 | MOS3: 0 | MOT3: 0 | MOU3: 0 | MOV3: 0 | MOW3: 0 | MOX3: 0 | MOY3: 0 | MOZ3: 0 | MPA3: 0 | MPB3: 0 | MPC3: 0 | MPD3: 0 | MPE3: 0 | MPF3: 0 | MPG3: 0 | MPH3: 0 | MPI3: 0 | MPJ3: 0 | MPK3: 0 | MPL3: 0 | MPM3: 0 | MPN3: 0 | MPO3: 0 | MPP3: 0 | MPQ3: 0 | MPR3: 0 | MPS3: 0 | MPT3: 0 | MPU3: 0 | MPV3: 0 | MPW3: 0 | MPX3: 0 | MPY3: 0 | MPZ3: 0 | MQA3: 0 | MQB3: 0 | MQC3: 0 | MQD3: 0 | MQE3: 0 | MQF3: 0 | MQG3: 0 | MQH3: 0 | MQI3: 0 | MQJ3: 0 | MQK3: 0 | MQL3: 0 | MQM3: 0 | MQN3: 0 | MQO3: 0 | MQP3: 0 | MQQ3: 0 | MQR3: 0 | MQS3: 0 | MQT3: 0 | MQU3: 0 | MQV3: 0 | MQW3: 0 | MQX3: 0 | MQY3: 0 | MQZ3: 0 | MRA3: 0 | MRB3: 0 | MRC3: 0 | MRD3: 0 | MRE3: 0 | MRF3: 0 | MRG3: 0 | MRH3: 0 | MRI3: 0 | MRJ3: 0 | MRK3: 0 | MRL3: 0 | MRM3: 0 | MRN3: 0 | MRO3: 0 | MRP3: 0 | MRQ3: 0 | MRR3: 0 | MRS3: 0 | MRT3: 0 | MRU3: 0 | MRV3: 0 | MRW3: 0 | MRX3: 0 | MRY3: 0 | MRZ3: 0 | MSA3: 0 | MSB3: 0 | MSC3: 0 | MSD3: 0 | MSE3: 0 | MSF3: 0 | MSG3: 0 | MSH3: 0 | MSI3: 0 | MSJ3: 0 | MSK3: 0 | MSL3: 0 | MSM3: 0 | MSN3: 0 | MSO3: 0 | MSP3: 0 | MSQ3: 0 | MSR3: 0 | MSS3: 0 | MST3: 0 | MSU3: 0 | MSV3: 0 | MSW3: 0 | MSX3: 0 | MSY3: 0 | MSZ3: 0 | MTA3: 0 | MTB3: 0 | MTC3: 0 | MTD3: 0 | MTE3: 0 | MTF3: 0 | MTG3: 0 | MTH3: 0 | MTI3: 0 | MTJ3: 0 | MTK3: 0 | MTL3: 0 | MTM3: 0 | MTN3: 0 | MTO3: 0 | MTP3: 0 | MTQ3: 0 | MTR3: 0 | MTS3: 0 | MTT3: 0 | MTU3: 0 | MTV3: 0 | MTW3: 0 | MTX3: 0 | MTY3: 0 | MTZ3: 0 | MUA3: 0 | MUB3: 0 | MUC3: 0 | MUD3: 0 | MUE3: 0 | MUF3: 0 | MUG3: 0 | MUH3: 0 | MUI3: 0 | MUJ3: 0 | MUK3: 0 | MUL3: 0 | MUM3: 0 | MUN3: 0 | MUO3: 0 | MUP3: 0 | MUQ3: 0 | MUR3: 0 | MUS3: 0 | MUT3: 0 | MUU3: 0 | MUV3: 0 | MUW3: 0 | MUX3: 0 | MUY3: 0 | MUZ3: 0 | MVA3: 0 | MVB3: 0 | MVC3: 0 | MVD3: 0 | MVE3: 0 | MVF3: 0 | MVG3: 0 | MVH3: 0 | MVI3: 0 | MVJ3: 0 | MVK3: 0 | MVL3: 0 | MVM3: 0 | MVN3: 0 | MVO3: 0 | MVP3: 0 | MVQ3: 0 | MVR3: 0 | MVS3: 0 | MVT3: 0 | MVU3: 0 | MVV3: 0 | MVW3: 0 | MVX3: 0 | MVY3: 0 | MVZ3: 0 | MWA3: 0 | MWB3: 0 | MWC3: 0 | MWD3: 0 | MWE3: 0 | MWF3: 0 | MWG3: 0 | MWH3: 0 | MWI3: 0 | MWJ3: 0 | MWK3: 0 | MWL3: 0 | MWM3: 0 | MWN3: 0 | MWO3: 0 | MWP3: 0 | MWQ3: 0 | MWR3: 0 | MWS3: 0 | MWT3: 0 | MWU3: 0 | MWV3: 0 | MWW3: 0 | MWX3: 0 | MWY3: 0 | MWZ3: 0 | MXA3: 0 | MXB3: 0 | MXC3: 0 | MXD3: 0 | MXE3: 0 | MXF3: 0 | MXG3: 0 | MXH3: 0 | MXI3: 0 | MXJ3: 0 | MXK3: 0 | MXL3: 0 | MXM3: 0 | MXN3: 0 | MXO3: 0 | MXP3: 0 | MXQ3: 0 | MXR3: 0 | MXS3: 0 | MXT3: 0 | MXU3: 0 | MXV3: 0 | MXW3: 0 | MXX3: 0 | MXY3: 0 | MXZ3: 0 | MYA3: 0 | MYB3: 0 | MYC3: 0 | MYD3: 0 | MYE3: 0 | MYF3: 0 | MYG3: 0 | MYH3: 0 | MYI3: 0 | MYJ3: 0 | MYK3: 0 | MYL3: 0 | MYM3: 0 | MYN3: 0 | MYO3: 0 | MYP3: 0 | MYQ3: 0 | MYR3: 0 | MYS3: 0 | MYT3: 0 | MYU3: 0 | MYV3: 0 | MYW3: 0 | MYX3: 0 | MYY3: 0 | MYZ3: 0 | MZA3: 0 | MZB3: 0 | MZC3: 0 | MZD3: 0 | MZE3: 0 | MZF3: 0 | MZG3: 0 | MZH3: 0 | MZI3: 0 | MZJ3: 0 | MZK3: 0 | MZL3: 0 | MZM3: 0 | MZN3: 0 | MZO3: 0 | MZP3: 0 | MZQ3: 0 | MZR3: 0 | MZS3: 0 | MZT3: 0 | MZU3: 0 | MZV3: 0 | MZW3: 0 | MZX3: 0 | MZY3: 0 | MZZ3: 0 | NAA3: 0 | NAB3: 0 | NAC3: 0 | NAD3: 0 | NAE3: 0 | NAF3: 0 | NAG3: 0 | NAH3: 0 | NAI3: 0 | NAJ3: 0 | NAK3: 0 | NAL3: 0 | NAM3: 0 | NAN3: 0 | NAO3: 0 | NAP3: 0 | NAQ3: 0 | NAR3: 0 | NAS3: 0 | NAT3: 0 | NAU3: 0 | NAV3: 0 | NAW3: 0 | NAX3: 0 | NAY3: 0 | NAZ3: 0 | NBA3: 0 | NBB3: 0 | NBC3: 0 | NBD3: 0 | NBE3: 0 | NBF3: 0 | NBG3: 0 | NBH3: 0 | NBI3: 0 | NBJ3: 0 | NBK3: 0 | NBL3: 0 | NBM3: 0 | NBN3: 0 | NBO3: 0 | NBP3: 0 | NBQ3: 0 | NBR3: 0 | NBS3: 0 | NBT3: 0 | NBU3: 0 | NBV3: 0 | NBW3: 0 | NBX3: 0 | NBY3: 0 | NBZ3: 0 | NCA3: 0 | NCB3: 0 | NCC3: 0 | NCD3: 0 | NCE3: 0 | NCF3: 0 | NCG3: 0 | NCH3: 0 | NCI3: 0 | NCJ3: 0 | NCK3: 0 | NCL3: 0 | NCM3: 0 | NCN3: 0 | NCO3: 0 | NCP3: 0 | NCQ3: 0 | NCR3: 0 | NCS3: 0 | NCT3: 0 | NCU3: 0 | NCV3: 0 | NCW3: 0 | NCX3: 0 | NCY3: 0 | NCZ3: 0 | NDA3: 0 | NDB3: 0 | NDC3: 0 | NDD3: 0 | NDE3: 0 | NDF3: 0 | NDG3: 0 | NDH3: 0 | NDI3: 0 | NDJ3: 0 | NDK3: 0 | NDL3: 0 | NDM3: 0 | NDN3: 0 | NDO3: 0 | NDP3: 0 | NDQ3: 0 | NDR3: 0 | NDS3: 0 | NDT3: 0 | NDU3: 0 | NDV3: 0 | NDW3: 0 | NDX3: 0 | NDY3: 0 | NDZ3: 0 | NEA3: 0 | NEB3: 0 | NEC3: 0 | NED3: 0 | NEE3: 0 | NEF3: 0 | NEG3: 0 | NEH3: 0 | NEI3: 0 | NEJ3: 0 | NEK3: 0 | NEL3: 0 | NEM3: 0 | NEN3: 0 | NEO3: 0 | NEP3: 0 | NEQ3: 0 | NER3: 0 | NES3: 0 | NET3: 0 | NEU3: 0 | NEV3: 0 | NEW3: 0 | NEX3: 0 | NEY3: 0 | NEZ3: 0 | NFA3: 0 | NFB3: 0 | NFC3: 0 | NFD3: 0 | NFE3: 0 | NFF3: 0 | NFG3: 0 | NFH3: 0 | NFI3: 0 | NFJ3: 0 | NFK3: 0 | NFL3: 0 | NFM3: 0 | NFN3: 0 | NFO3: 0 | NFP3: 0 | NFQ3: 0 | NFR3: 0 | NFS3: 0 | NFT3: 0 | NFU3: 0 | NFV3: 0 | NFW3: 0 | NFX3: 0 | NFY3: 0 | NFZ3: 0 | NGA3: 0 | NGB3: 0 | NGC3: 0 | NGD3: 0 | NGE3: 0 | NGF3: 0 | NGG3: 0 | NGH3: 0 | NGI3: 0 | NGJ3: 0 | NGK3: 0 | NGL3: 0 | NGM3: 0 | NGN3: 0 | NGO3: 0 | NGP3: 0 | NGQ3: 0 | NGR3: 0 | NGS3: 0 | NGT3: 0 | NGU3: 0 | NGV3: 0 | NGW3: 0 | NGX3: 0 | NGY3: 0 | NGZ3: 0 | NHA3: 0 | NHB3: 0 | NHC3: 0 | NHD3: 0 | NHE3: 0 | NHF3: 0 | NHG3: 0 | NHH3: 0 | NHI3: 0 | NHJ3: 0 | NHK3: 0 | NHL3: 0 | NHM3: 0 | NHN3: 0 | NHO3: 0 | NHP3: 0 | NHQ3: 0 | NHR3: 0 | NHS3: 0 | NHT3: 0 | NHU3: 0 | NHV3: 0 | NHW3: 0 | NHX3: 0 | NHY3: 0 | NHZ3: 0 | NIA3: 0 | NIB3: 0 | NIC3: 0 | NID3: 0 | NIE3: 0 | NIF3: 0 | NIG3: 0 | NIH3: 0 | NII3: 0 | NIJ3: 0 | NIK3: 0 | NIL3: 0 | NIM3: 0 | NIN3: 0 | NIO3: 0 | NIP3: 0 | NIQ3: 0 | NIR3: 0 | NIS3: 0 | NIT3: 0 | NIU3: 0 | NIV3: 0 | NIW3: 0 | NIX3: 0 | NIY3: 0 | NIZ3: 0 | NJA3: 0 | NJB3: 0 | NJC3: 0 | NJD3: 0 | NJE3: 0 | NJF3: 0 | NJG3: 0 | NJH3: 0 | NJI3: 0 | NJJ3: 0 | NJK3: 0 | NJL3: 0 | NJM3: 0 | NJN3: 0 | NJO3: 0 | NJP3: 0 | NJQ3: 0 | NJR3: 0 | NJS3: 0 | NJT3: 0 | NJU3: 0 | NJV3: 0 | NJW3: 0 | NJX3: 0 | NJY3: 0 | NJZ3: 0 | NKA3: 0 | NKB3: 0 | NKC3: 0 | NKD3: 0 | NKE3: 0 | NKF3: 0 | NKG3: 0 | NKH3: 0 | NKI3: 0 | NKJ3: 0 | NKK3: 0 | NKL3: 0 | NKM3: 0 | NKN3: 0 | NKO3: 0 | NKP3: 0 | NKQ3: 0 | NKR3: 0 | NKS3: 0 | NKT3: 0 | NKU3: 0 | NKV3: 0 | NKW3: 0 | NKX3: 0 | NKY3: 0 | NKZ3: 0 | NLA3: 0 | NLB3: 0 | NLC3: 0 | NLD3: 0 | NLE3: 0 | NLF3: 0 | NLG3: 0 | NLH3: 0 | NLI3: 0 | NLJ3: 0 | NLK3: 0 | NLL3: 0 | NLM3: 0 | NLN3: 0 | NLO3: 0 | NLP3: 0 | NLQ3: 0 | NLR3: 0 | NLS3: 0 | NLT3: 0 | NLU3: 0 | NLV3: 0 | NLW3: 0 | NLX3: 0 | NLY3: 0 | NLZ3: 0 | NMA3: 0 | NMB3: 0 | NMC3: 0 | NMD3: 0 | NME3: 0 | NMF3: 0 | NMG3: 0 | NMH3: 0 | NMI3: 0 | NMJ3: 0 | NMK3: 0 | NML3: 0 | NMM3: 0 | NMN3: 0 | NMO3: 0 | NMP3: 0 | NMQ3: 0 | NMR3: 0 | NMS3: 0 | NMT3: 0 | NMU3: 0 | NMV3: 0 | NMW3: 0 | NMX3: 0 | NMY3: 0 | NMZ3: 0 | NNA3: 0 | NNB3: 0 | NNC3: 0 | NND3: 0 | NNE3: 0 | NNF3: 0 | NNG3: 0 | NNH3: 0 | NNI3: 0 | NNJ3: 0 | NNK3: 0 | NNL3: 0 | NNM3: 0 | NNN3: 0 | NNO3: 0 | NNP3: 0 | NNQ3: 0 | NNR3: 0 | NNS3: 0 | NNT3: 0 | NNU3: 0 | NNV3: 0 | NNW3: 0 | NNX3: 0 | NNY3: 0 | NNZ3: 0 | NOA3: 0 | NOB3: 0 | NOC3: 0 | NOD3: 0 | NOE3: 0 | NOF3: 0 | NOG3: 0 | NOH3: 0 | NOI3: 0 | NOJ3: 0 | NOK3: 0 | NOL3: 0 | NOM3: 0 | NON3: 0 | NOO3: 0 | NOP3: 0 | NOQ3: 0 | NOR3: 0 | NOS3: 0 | NOT3: 0 | NOU3: 0 | NOV3: 0 | NOW3: 0 | NOX3: 0 | NOY3: 0 | NOZ3: 0 | NPA3: 0 | NPB3: 0 | NPC3: 0 | NPD3: 0 | NPE3: 0 | NPF3: 0 | NPG3: 0 | NPH3: 0 | NPI3: 0 | NPJ3: 0 | NPK3: 0 | NPL3: 0 | NPM3: 0 | NPN3: 0 | NPO3: 0 | NPP3: 0 | NPQ3: 0 | NPR3: 0 | NPS3: 0 | NPT3: 0 | NPU3: 0 | NPV3: 0 | NPW3: 0 | NPX3: 0 | NPY3: 0 | NPZ3: 0 | NQA3: 0 | NQB3: 0 | NQC3: 0 | NQD3: 0 | NQE3: 0 | NQF3: 0 | NQG3: 0 | NQH3: 0 | NQI3: 0 | NQJ3: 0 | NQK3: 0 | NQL3: 0 | NQM3: 0 | NQN3: 0 | NQO3: 0 | NQP3: 0 | NQQ3: 0 | NQR3: 0 | NQS3: 0 | NQT3: 0 | NQU3: 0 | NQV3: 0 | NQW3: 0 | NQX3: 0 | NQY3: 0 | NQZ3: 0 | NRA3: 0 | NRB3: 0 | NRC3: 0 | NRD3: 0 | NRE3: 0 | NRF3: 0 | NRG3: 0 | NRH3: 0 | NRI3: 0 | NRJ3: 0 | NRK3: 0 | NRL3: 0 | NRM3: 0 | NRN3: 0 | NRO3: 0 | NRP3: 0 | NRQ3: 0 | NRR3: 0 | NRS3: 0 | NRT3: 0 | NRU3: 0 | NRV3: 0 | NRW3: 0 | NRX3: 0 | NRY3: 0 | NRZ3: 0 | NSA3: 0 | NSB3: 0 | NSC3: 0 | NSD3: 0 | NSE3: 0 | NSF3: 0 | NSG3: 0 | NSH3: 0 | NSI3: 0 | NSJ3: 0 | NSK3: 0 | NSL3: 0 | NSM3: 0 | NSN3: 0 | NSO3: 0 | NSP3: 0 | NSQ3: 0 | NSR3: 0 | NSS3: 0 | NST3: 0 | NSU3: 0 | NSV3: 0 | NSW3: 0 | NSX3: 0 | NSY3: 0 | NSZ3: 0 | NTA3: 0 | NTB3: 0 | NTC3: 0 | NTD3: 0 | NTE3: 0 | NTF3: 0 | NTG3: 0 | NTH3: 0 | NTI3: 0 | NTJ3: 0 | NTK3: 0 | NTL3: 0 | NTM3: 0 | NTN3: 0 | NTO3: 0 | NTP3: 0 | NTQ3: 0 | NTR3: 0 | NTS3: 0 | NTT3: 0 | NTU3: 0 | NTV3: 0 | NTW3: 0 | NTX3: 0 | NTY3: 0 | NTZ3: 0 | NUA3: 0 | NUB3: 0 | NUC3: 0 | NUD3: 0 | NUE3: 0 | NUF3: 0 | NUG3: 0 | NUH3: 0 | NUI3: 0 | NUJ3: 0 | NUK3: 0 | NUL3: 0 | NUM3: 0 | NUN3: 0 | NUO3: 0 | NUP3: 0 | NUQ3: 0 | NUR3: 0 | NUS3: 0 | NUT3: 0 | NUU3: 0 | NUV3: 0 | NUW3: 0 | NUX3: 0 | NUY3: 0 | NUZ3: 0 | NVA3: 0 | NVB3: 0 | NVC3: 0 | NVD3: 0 | NVE3: 0 | NVF3: 0 | NVG3: 0 | NVH3: 0 | NVI3: 0 | NVJ3: 0 | NVK3: 0 | NVL3: 0 | NVM3: 0 | NVN3: 0 | NVO3: 0 | NVP3: 0 | NVQ3: 0 | NVR3: 0 | NVS3: 0 | NVT3: 0 | NVU3: 0 | NVV3: 0 | NVW3: 0 | NVX3: 0 | NVY3: 0 | NVZ3: 0 | NWA3: 0 | NWB3: 0 | NWC3: 0 | NWD3: 0 | NWE3: 0 | NWF3: 0 | NWG3: 0 | NWH3: 0 | NWI3: 0 | NWJ3: 0 | NWK3: 0 | NWL3: 0 | NWM3: 0 | NWN3: 0 | NWO3: 0 | NWP3: 0 | NWQ3: 0 | NWR3: 0 | NWS3: 0 | NWT3: 0 | NWU3: 0 | NWV3: 0 | NWW3: 0 | NWX3: 0 | NWY3: 0 | NWZ3: 0 | NXA3: 0 | NXB3: 0 | NXC3: 0 | NXD3: 0 | NXE3: 0 | NXF3: 0 | NXG3: 0 | NXH3: 0 | NXI3: 0 | NXJ3: 0 | NXK3: 0 | NXL3: 0 | NXM3: 0 | NXN3: 0 | NXO3: 0 | NXP3: 0 | NXQ3: 0 | NXR3: 0 | NXS3: 0 | NXT3: 0 | NXU3: 0 | NXV3: 0 | NXW3: 0 | NXX3: 0 | NXY3: 0 | NXZ3: 0 | NYA3: 0 | NYB3: 0 | NYC3: 0 | NYD3: 0 | NYE3: 0 | NYF3: 0 | NYG3: 0 | NYH3: 0 | NYI3: 0 | NYJ3: 0 | NYK3: 0 | NYL3: 0 | NYM3: 0 | NYN3: 0 | NYO3: 0 | NYP3: 0 | NYQ3: 0 | NYR3: 0 | NYS3: 0 | NYT3: 0 | NYU3: 0 | NYV3: 0 | NYW3: 0 | NYX3: 0 | NYY3: 0 | NYZ3: 0 | NZA3: 0 | NZB3: 0 | NZC3: 0 | NZD3: 0 | NZE3: 0 | NZF3: 0 | NZG3: 0 | NZH3: 0 | NZI3: 0 | NZJ3: 0 | NZK3: 0 | NZL3: 0 | NZM3: 0 | NZN3: 0 | NZO3: 0 | NZP3: 0 | NZQ3: 0 | NZR3: 0 | NZS3: 0 | NZT3: 0 | NZU3: 0 | NZV3: 0 | NZW3: 0 | NZX3: 0 | NZY3: 0 | NZZ3: 0 | OAA3: 0 | OAB3: 0 | OAC3: 0 | OAD3: 0 | OAE3: 0 | OAF3: 0 | OAG3: 0 | OAH3: 0 | OAI3: 0 | OAJ3: 0 | OAK3: 0 | OAL3: 0 | OAM3: 0 | OAN3: 0 | OAO3: 0 | OAP3: 0 | OAQ3: 0 | OAR3: 0 | OAS3: 0 | OAT3: 0 | OAU3: 0 | OAV3: 0 | OAW3: 0 | OAX3: 0 | OAY3: 0 | OAZ3: 0 | OBA3: 0 | OBB3: 0 | OBC3: 0 | OBD3: 0 | OBE3: 0 | OBF3: 0 | OBG3: 0 | OBH3: 0 | OBI3: 0 | OBJ3: 0 | OBK3: 0 | OBL3: 0 | OBM3: 0 | OBN3: 0 | OBO3: 0 | OBP3: 0 | OBQ3: 0 | OBR3: 0 | OBS3: 0 | OBT3: 0 | OBU3: 0 | OBV3: 0 | OBW3: 0 | OBX3: 0 | OBY3: 0 | OBZ3: 0 | OCA3: 0 | OCB3: 0 | OCC3: 0 | OCD3: 0 | OCE3: 0 | OCF3: 0 | OCG3: 0 | OCH3: 0 | OCI3: 0 | OCJ3: 0 | OCK3: 0 | OCL3: 0 | OCM3: 0 | OCN3: 0 | OCO3: 0 | OCP3: 0 | OCQ3: 0 | OCR3: 0 | OCS3: 0 | OCT3: 0 | OCU3: 0 | OCV3: 0 | OCW3: 0 | OCX3: 0 | OCY3: 0 | OCZ3: 0 | ODA3: 0 | ODB3: 0 | ODC3: 0 | ODD3: 0 | ODE3: 0 | ODF3: 0 | ODG3: 0 | ODH3: 0 | ODI3: 0 | ODJ3: 0 | ODK3: 0 | ODL3: 0 | ODM3: 0 | ODN3: 0 | ODO3: 0 | ODP3: 0 | ODQ3: 0 | ODR3: 0 | ODS3: 0 | ODT3: 0 | ODU3: 0 | ODV3: 0 | ODW3: 0 | ODX3: 0 | ODY3: 0 | ODZ3: 0 | OEA3: 0 | OEB3: 0 | OEC3: 0 | OED3: 0 | OEE3: 0 | OEF3: 0 | OEG3: 0 | OEH3: 0 | OEI3: 0 | OEJ3: 0 | OEK3: 0 | OEL3: 0 | OEM3: 0 | OEN3: 0 | OEO3: 0 | OEP3: 0 | OEQ3: 0 | OER3: 0 | OES3: 0 | OET3: 0 | OEU3: 0 | OEV3: 0 | OEW3: 0 | OEX3: 0 | OEY3: 0 | OEZ3: 0 | OFA3: 0 | OFB3: 0 | OFC3: 0 | OFD3: 0 | OFE3: 0 | OFF3: 0 | OFG3: 0 | OFH3: 0 | OFI3: 0 | OFJ3: 0 | OFK3: 0 | OFL3: 0 | OFM3: 0 | OFN3: 0 | OFO3: 0 | OFP3: 0 | OFQ3: 0 | OFR3: 0 | OFS3: 0 | OFT3: 0 | OFU3: 0 | OFV3: 0 | OFW3: 0 | OFX3: 0 | OFY3: 0 | OFZ3: 0 | OGA3: 0 | OGB3: 0 | OGC3: 0 | OGD3: 0 | OGE3: 0 | OGF3: 0 | OGG3: 0 | OGH3: 0 | OGI3: 0 | OGJ3: 0 | OGK3: 0 | OGL3: 0 | OGM3: 0 | OGN3: 0 | OGO3: 0 | OGP3: 0 | OGQ3: 0 | OGR3: 0 | OGS3: 0 | OGT3: 0 | OGU3: 0 | OGV3: 0 | OGW3: 0 | OGX3: 0 | OGY3: 0 | OGZ3: 0 | OHA3: 0 | OHB3: 0 | OHC3: 0 | OHD3: 0 | OHE3: 0 | OHF3: 0 | OHG3: 0 | OHH3: 0 | OHI3: 0 | OHJ3: 0 | OHK3: 0 | OHL3: 0 | OHM3: 0 | OHN3: 0 | OHO3: 0 | OHP3: 0 | OHQ3: 0 | OHR3: 0 | OHS3: 0 | OHT3: 0 | OHU3: 0 | OHV3: 0 | OHW3: 0 | OHX3: 0 | OHY3: 0 | OHZ3: 0 | OIA3: 0 | OIB3: 0 | OIC3: 0 | OID3: 0 | OIE3: 0 | OIF3: 0 | OIG3: 0 | OIH3: 0 | OII3: 0 | OIJ3: 0 | OIK3: 0 | OIL3: 0 | OIM3: 0 | OIN3: 0 | OIO3: 0 | OIP3: 0 | OIQ3: 0 | OIR3: 0 | OIS3: 0 | OIT3: 0 | OIU3: 0 | OIV3: 0 | OIW3: 0 | OIX3: 0 | OIY3: 0 | OIZ3: 0 | OJA3: 0 | OJB3: 0 | OJC3: 0 | OJD3: 0 | OJE3: 0 | OJF3: 0 | OJG3: 0 | OJH3: 0 | OJI3: 0 | OJJ3: 0 | OJK3: 0 | OJL3: 0 | OJM3: 0 | OJN3: 0 | OJO3: 0 | OJP3: 0 | OJQ3: 0 | OJR3: 0 | OJS3: 0 | OJT3: 0 | OJU3: 0 | OJV3: 0 | OJW3: 0 | OJX3: 0 | OJY3: 0 | OJZ3: 0 | OKA3: 0 | OKB3: 0 | OKC3: 0 | OKD3: 0 | OKE3: 0 | OKF3: 0 | OKG3: 0 | OKH3: 0 | OKI3: 0 | OKJ3: 0 | OKK3: 0 | OKL3: 0 | OKM3: 0 | OKN3: 0 | OKO3: 0 | OKP3: 0 | OKQ3: 0 | OKR3: 0 | OKS3: 0 | OKT3: 0 | OKU3: 0 | OKV3: 0 | OKW3: 0 | OKX3: 0 | OKY3: 0 | OKZ3: 0 | OLA3: 0 | OLB3: 0 | OLC3: 0 | OLD3: 0 | OLE3: 0 | OLF3: 0 | OLG3: 0 | OLH3: 0 | OLI3: 0 | OLJ3: 0 | OLK3: 0 | OLL3: 0 | OLM3: 0 | OLN3: 0 | OLO3: 0 | OLP3: 0 | OLQ3: 0 | OLR3: 0 | OLS3: 0 | OLT3: 0 | OLU3: 0 | OLV3: 0 | OLW3: 0 | OLX3: 0 | OLY3: 0 | OLZ3: 0 | OMA3: 0 | OMB3: 0 | OMC3: 0 | OMD3: 0 | OME3: 0 | OMF3: 0 | OMG3: 0 | OMH3: 0 | OMI3: 0 | OMJ3: 0 | OMK3: 0 | OML3: 0 | OMM3: 0 | OMN3: 0 | OMO3: 0 | OMP3: 0 | OMQ3: 0 | OMR3: 0 | OMS3: 0 | OMT3: 0 | OMU3: 0 | OMV3: 0 | OMW3: 0 | OMX3: 0 | OMY3: 0 | OMZ3: 0 | ONA3: 0 | ONB3: 0 | ONC3: 0 | OND3: 0 | ONE3: 0 | ONF3: 0 | ONG3: 0 | ONH3: 0 | ONI3: 0 | ONJ3: 0 | ONK3: 0 | ONL3: 0 | ONM3: 0 | ONN3: 0 | ONO3: 0 | ONP3: 0 | ONQ3: 0 | ONR3: 0 | ONS3: 0 | ONT3: 0 | ONU3: 0 | ONV3: 0 | ONW3: 0 | ONX3: 0 | ONY3: 0 | ONZ3: 0 | OOA3: 0 | OOB3: 0 | OOC3: 0 | OOD3: 0 | OOE3: 0 | OOF3: 0 | OOG3: 0 | OOH3: 0 | OOI3: 0 | OOJ3: 0 | OOK3: 0 | OOL3: 0 | OOM3: 0 | OON3: 0 | OOO3: 0 | OOP3: 0 | OOQ3: 0 | OOR3: 0 | OOS3: 0 | OOT3: 0 | OOU3: 0 | OOV3: 0 | OOW3: 0 | OOX3: 0 | OOY3: 0 | OOZ3: 0 | OPA3: 0 | OPB3: 0 | OPC3: 0 | OPD3: 0 | OPE3: 0 | OPF3: 0 | OPG3: 0 | OPH3: 0 | OPI3: 0 | OPJ3: 0 | OPK3: 0 | OPL3: 0 | OPM3: 0 | OPN3: 0 | OPO3: 0 | OPP3: 0 | OPQ3: 0 | OPR3: 0 | OPS3: 0 | OPT3: 0 | OPU3: 0 | OPV3: 0 | OPW3: 0 | OPX3: 0 | OPY3: 0 | OPZ3: 0 | OQA3: 0 | OQB3: 0 | OQC3: 0 | OQD3: 0 | OQE3: 0 | OQF3: 0 | OQG3: 0 | OQH3: 0 | OQI3: 0 | OQJ3: 0 | OQK3: 0 | OQL3: 0 | OQM3: 0 | OQN3: 0 | OQO3: 0 | OQP3: 0 | OQQ3: 0 | OQR3: 0 | OQS3: 0 | OQT3: 0 | OQU3: 0 | OQV3: 0 | OQW3: 0 | OQX3: 0 | OQY3: 0 | OQZ3: 0 | ORA3: 0 | ORB3: 0 | ORC3: 0 | ORD3: 0 | ORE3: 0 | ORF3: 0 | ORG3: 0 | ORH3: 0 | ORI3: 0 | ORJ3: 0 | ORK3: 0 | ORL3: 0 | ORM3: 0 | ORN3: 0 | ORO3: 0 | ORP3: 0 | ORQ3: 0 | ORR3: 0 | ORS3: 0 | ORT3: 0 | ORU3: 0 | ORV3: 0 | ORW3: 0 | ORX3: 0 | ORY3: 0 | ORZ3: 0 | OSA3: 0 | OSB3: 0 | OSC3: 0 | OSD3: 0 | OSE3: 0 | OSF3: 0 | OSG3: 0 | OSH3: 0 | OSI3: 0 | OSJ3: 0 | OSK3: 0 | OSL3: 0 | OSM3: 0 | OSN3: 0 | OSO3: 0 | OSP3: 0 | OSQ3: 0 | OSR3: 0 | OSS3: 0 | OST3: 0 | OSU3: 0 | OSV3: 0 | OSW3: 0 | OSX3: 0 | OSY3: 0 | OSZ3: 0 | OTA3: 0 | OTB3: 0 | OTC3: 0 | OTD3: 0 | OTE3: 0 | OTF3: 0 | OTG3: 0 | OTH3: 0 | OTI3: 0 | OTJ3: 0 | OTK3: 0 | OTL3: 0 | OTM3: 0 | OTN3: 0 | OTO3: 0 | OTP3: 0 | OTQ3: 0 | OTR3: 0 | OTS3: 0 | OTT3: 0 | OTU3: 0 | OTV3: 0 | OTW3: 0 | OTX3: 0 | OTY3: 0 | OTZ3: 0 | OUA3: 0 | OUB3: 0 | OUC3: 0 | OUD3: 0 | OUE3: 0 | OUF3: 0 | OUG3: 0 | OUH3: 0 | OUI3: 0 | OUJ3: 0 | OUK3: 0 | OUL3: 0 | OUM3: 0 | OUN3: 0 | OUO3: 0 | OUP3: 0 | OUQ3: 0 | OUR3: 0 | OUS3: 0 | OUT3: 0 | OUU3: 0 | OUV3: 0 | OUW3: 0 | OUX3: 0 | OUY3: 0 | OUZ3: 0 | OVA3: 0 | OVB3: 0 | OVC3: 0 | OVD3: 0 | OVE3: 0 | OVF3: 0 | OVG3: 0 | OVH3: 0 | OVI3: 0 | OVJ3: 0 | OVK3: 0 | OVL3: 0 | OVM3: 0 | OVN3: 0 | OVO3: 0 | OVP3: 0 | OVQ3: 0 | OVR3: 0 | OVS3: 0 | OVT3: 0 | OVU3: 0 | OVV3: 0 | OVW3: 0 | OVX3: 0 | OVY3: 0 | OVZ3: 0 | OWA3: 0 | OWB3: 0 | OWC3: 0 | OWD3: 0 | OWE3: 0 | OWF3: 0 | OWG3: 0 | OWH3: 0 | OWI3: 0 | OWJ3: 0 | OWK3: 0 | OWL3: 0 | OWM3: 0 | OWN3: 0 | OWO3: 0 | OWP3: 0 | OWQ3: 0 | OWR3: 0 | OWS3: 0 | OWT3: 0 | OWU3: 0 | OWV3: 0 | OWW3: 0 | OWX3: 0 | OWY3: 0 | OWZ3: 0 | OXA3: 0 | OXB3: 0 | OXC3: 0 | OXD3: 0 | OXE3: 0 | OXF3: 0 | OXG3: 0 | OXH3: 0 | OXI3: 0 | OXJ3: 0 | OXK3: 0 | OXL3: 0 | OXM3: 0 | OXN3: 0 | OXO3: 0 | OXP3: 0 | OXQ3: 0 | OXR3: 0 | OXS3: 0 | OXT3: 0 | OXU3: 0 | OXV3: 0 | OXW3: 0 | OXX3: 0 | OXY3: 0 | OXZ3: 0 | OYA3: 0 | OYB3: 0 | OYC3: 0 | OYD3: 0 | OYE3: 0 | OYF3: 0 | OYG3: 0 | OYH3: 0 | OYI3: 0 | OYJ3: 0 | OYK3: 0 | OYL3: 0 | OYM3: 0 | OYN3: 0 | OYO3: 0 | OYP3: 0 | OYQ3: 0 | OYR3: 0 | OYS3: 0 | OYT3: 0 | OYU3: 0 | OYV3: 0 | OYW3: 0 | OYX3: 0 | OYY3: 0 | OYZ3: 0 | OZA3: 0 | OZB3: 0 | OZC3: 0 | OZD3: 0 | OZE3: 0 | OZF3: 0 | OZG3: 0 | OZH3: 0 | OZI3: 0 | OZJ3: 0 | OZK3: 0 | OZL3: 0 | OZM3: 0 | OZN3: 0 | OZO3: 0 | OZP3: 0 | OZQ3: 0 | OZR3: 0 | OZS3: 0 | OZT3: 0 | OZU3: 0 | OZV3: 0 | OZW3: 0 | OZX3: 0 | OZY3: 0 | OZZ3: 0 | PAA3: 0 | PAB3: 0 | PAC3: 0 | PAD3: 0 | PAE3: 0 | PAF3: 0 | PAG3: 0 | PAH3: 0 | PAI3: 0 | PAJ3: 0 | PAK3: 0 | PAL3: 0 | PAM3: 0 | PAN3: 0 | PAO3: 0 | PAP3: 0 | PAQ3: 0 | PAR3: 0 | PAS3: 0 | PAT3: 0 | PAU3: 0 | PAV3: 0 | PAW3: 0 | PAX3: 0 | PAY3: 0 | PAZ3: 0 | PBA3: 0 | PBB3: 0 | PBC3: 0 | PBD3: 0 | PBE3: 0 | PBF3: 0 | PBG3: 0 | PBH3: 0 | PBI3: 0 | PBJ3: 0 | PBK3: 0 | PBL3: 0 | PBM3: 0 | PBN3: 0 | PBO3: 0 | PBP3: 0 | PBQ3: 0 | PBR3: 0 | PBS3: 0 | PBT3: 0 | PBU3: 0 | PBV3: 0 | PBW3: 0 | PBX3: 0 | PBY3: 0 | PBZ3: 0 | PCA3: 0 | PCB3: 0 | PCC3: 0 | PCD3: 0 | PCE3: 0 | PCF3: 0 | PCG3: 0 | PCH3: 0 | PCI3: 0 | PCJ3: 0 | PCK3: 0 | PCL3: 0 | PCM3: 0 | PCN3: 0 | PCO3: 0 | PCP3: 0 | PCQ3: 0 | PCR3: 0 | PCS3: 0 | PCT3: 0 | PCU3: 0 | PCV3: 0 | PCW3: 0 | PCX3: 0 | PCY3: 0 | PCZ3: 0 | PDA3: 0 | PDB3: 0 | PDC3: 0 | PDD3: 0 | PDE3: 0 | PDF3: 0 | PDG3: 0 | PDH3: 0 | PDI3: 0 | PDJ3: 0 | PDK3: 0 | PDL3: 0 | PDM3: 0 | PDN3: 0 | PDO3: 0 | PDP3: 0 | PDQ3: 0 | PDR3: 0 | PDS3: 0 | PDT3: 0 | PDU3: 0 | PDV3: 0 | PDW3: 0 | PDX3: 0 | PDY3: 0 | PDZ3: 0 | PEA3: 0 | PEB3: 0 | PEC3: 0 | PED3: 0 | PEE3: 0 | PEF3: 0 | PEG3: 0 | PEH3: 0 | PEI3: 0 | PEJ3: 0 | PEK3: 0 | PEL3: 0 | PEM3: 0 | PEN3: 0 | PEO3: 0 | PEP3: 0 | PEQ3: 0 | PER3: 0 | PES3: 0 | PET3: 0 | PEU3: 0 | PEV3: 0 | PEW3: 0 | PEX3: 0 | PEY3: 0 | PEZ3: 0 | PFA3: 0 | PFB3: 0 | PFC3: 0 | PFD3: 0 | PFE3: 0 | PFF3: 0 | PFG3: 0 | PFH3: 0 | PFI3: 0 | PFJ3: 0 | PFK3: 0 | PFL3: 0 | PFM3: 0 | PFN3: 0 | PFO3: 0 | PFP3: 0 | PFQ3: 0 | PFR3: 0 | PFS3: 0 | PFT3: 0 | PFU3: 0 | PFV3: 0 | PFW3: 0 | PFX3: 0 | PFY3: 0 | PFZ3: 0 | PGA3: 0 | PGB3: 0 | PGC3: 0 | PGD3: 0 | PGE3: 0 | PGF3: 0 | PGG3: 0 | PGH3: 0 | PGI3: 0 | PGJ3: 0 | PGK3: 0 | PGL3: 0 | PGM3: 0 | PGN3: 0 | PGO3: 0 | PGP3: 0 | PGQ3: 0 | PGR3: 0 | PGS3: 0 | PGT3: 0 | PGU3: 0 | PGV3: 0 | PGW3: 0 | PGX3: 0 | PGY3: 0 | PGZ3: 0 | PHA3: 0 | PHB3: 0 | PHC3: 0 | PHD3: 0 | PHE3: 0 | PHF3: 0 | PHG3: 0 | PHH3: 0 | PHI3: 0 | PHJ3: 0 | PHK3: 0 | PHL3: 0 | PHM3: 0 | PHN3: 0 | PHO3: 0 | PHP3: 0 | PHQ3: 0 | PHR3: 0 | PHS3: 0 | PHT3: 0 | PHU3: 0 | PHV3: 0 | PHW3: 0 | PHX3: 0 | PHY3: 0 | PHZ3: 0 | PIA3: 0 | PIB3: 0 | PIC3: 0 | PID3: 0 | PIE3: 0 | PIF3: 0 | PIG3: 0 | PIH3: 0 | PII3: 0 | PIJ3: 0 | PIK3: 0 | PIL3: 0 | PIM3: 0 | PIN3: 0 | PIO3: 0 | PIP3: 0 | PIQ3: 0 | PIR3: 0 | PIS3: 0 | PIT3: 0 | PIU3: 0 | PIV3: 0 | PIW3: 0 | PIX3: 0 | PIY3: 0 | PIZ3: 0 | PJA3: 0 | PJB3: 0 | PJC3: 0 | PJD3: 0 | PJE3: 0 | PJF3: 0 | PJG3: 0 | PJH3: 0 | PJI3: 0 | PJJ3: 0 | PJK3: 0 | PJL3: 0 | PJM3: 0 | PJN3: 0 | PJO3: 0 | PJP3: 0 | PJQ3: 0 | PJR3: 0 | PJS3: 0 | PJT3: 0 | PJU3: 0 | PJV3: 0 | PJW3: 0 | PJX3: 0 | PJY3: 0 | PJZ3: 0 | PKA3: 0 | PKB3: 0 | PKC3: 0 | PKD3: 0 | PKE3: 0 | PKF3: 0 | PKG3: 0 | PKH3: 0 | PKI3: 0 | PKJ3: 0 | PKK3: 0 | PKL3: 0 | PKM3: 0 | PKN3: 0 | PKO3: 0 | PKP3: 0 | PKQ3: 0 | PKR3: 0 | PKS3: 0 | PKT3: 0 | PKU3: 0 | PKV3: 0 | PKW3: 0 | PKX3: 0 | PKY3: 0 | PKZ3: 0 | PLA3: 0 | PLB3: 0 | PLC3: 0 | PLD3: 0 | PLE3: 0 | PLF3: 0 | PLG3: 0 | PLH3: 0 | PLI3: 0 | PLJ3: 0 | PLK3: 0 | PLL3: 0 | PLM3: 0 | PLN3: 0 | PLO3: 0 | PLP3: 0 | PLQ3: 0 | PLR3: 0 | PLS3: 0 | PLT3: 0 | PLU3: 0 | PLV3: 0 | PLW3: 0 | PLX3: 0 | PLY3: 0 | PLZ3: 0 | PMA3: 0 | PMB3: 0 | PMC3: 0 | PMD3: 0 | PME3: 0 | PMF3: 0 | PMG3: 0 | PMH3: 0 | PMI3: 0 | PMJ3: 0 | PMK3: 0 | PML3: 0 | PMM3: 0 | PMN3: 0 | PMO3: 0 | PMP3: 0 | PMQ3: 0 | PMR3: 0 | PMS3: 0 | PMT3: 0 | PMU3: 0 | PMV3: 0 | PMW3: 0 | PMX3: 0 | PMY3: 0 | PMZ3: 0 | PNA3: 0 | PNB3: 0 | PNC3: 0 | PND3: 0 | PNE3: 0 | PNF3: 0 | PNG3: 0 | PNH3: 0 | PNI3: 0 | PNJ3: 0 | PNK3: 0 | PNL3: 0 | PNM3: 0 | PNN3: 0 | PNO3: 0 | PNP3: 0 | PNQ3: 0 | PNR3: 0 | PNS3: 0 | PNT3: 0 | PNU3: 0 | PNV3: 0 | PNW3: 0 | PNX3: 0 | PNY3: 0 | PNZ3: 0 | POA3: 0 | POB3: 0 | POC3: 0 | POD3: 0 | POE3: 0 | POF3: 0 | POG3: 0 | POH3: 0 | POI3: 0 | POJ3: 0 | POK3: 0 | POL3: 0 | POM3: 0 | PON3: 0 | POO3: 0 | POP3: 0 | POQ3: 0 | POR3: 0 | POS3: 0 | POT3: 0 | POU3: 0 | POV3: 0 | POW3: 0 | POX3: 0 | POY3: 0 | POZ3: 0 | PPA3: 0 | PPB3: 0 | PPC3: 0 | PPD3: 0 | PPE3: 0 | PPF3: 0 | PPG3: 0 | PPH3: 0 | PPI3: 0 | PPJ3: 0 | PPK3: 0 | PPL3: 0 | PPM3: 0 | PPN3: 0 | PPO3: 0 | PPP3: 0 | PPQ3: 0 | PPR3: 0 | PPS3: 0 | PPT3: 0 | PPU3: 0 | PPV3: 0 | PPW3: 0 | PPX3: 0 | PPY3: 0 | PPZ3: 0 | PQA3: 0 | PQB3: 0 | PQC3: 0 | PQD3: 0 | PQE3: 0 | PQF3: 0 | PQG3: 0 | PQH3: 0 | PQI3: 0 | PQJ3: 0 | PQK3: 0 | PQL3: 0 | PQM3: 0 | PQN3: 0 | PQO3: 0 | PQP3: 0 | PQQ3: 0 | PQR3: 0 | PQS3: 0 | PQT3: 0 | PQU3: 0 | PQV3: 0 | PQW3: 0 | PQX3: 0 | PQY3: 0 | PQZ3: 0 | PRA3: 0 | PRB3: 0 | PRC3: 0 | PRD3: 0 | PRE3: 0 | PRF3: 0 | PRG3: 0 | PRH3: 0 | PRI3: 0 | PRJ3: 0 | PRK3: 0 | PRL3: 0 | PRM3: 0 | PRN3: 0 | PRO3: 0 | PRP3: 0 | PRQ3: 0 | PRR3: 0 | PRS3: 0 | PRT3: 0 | PRU3: 0 | PRV3: 0 | PRW3: 0 | PRX3: 0 | PRY3: 0 | PRZ3: 0 | PSA3: 0 | PSB3: 0 | PSC3: 0 | PSD3: 0 | PSE3: 0 | PSF3: 0 | PSG3: 0 | PSH3: 0 | PSI3: 0 | PSJ3: 0 | PSK3: 0 | PSL3: 0 | PSM3: 0 | PSN3: 0 | PSO3: 0 | PSP3: 0 | PSQ3: 0 | PSR3: 0 | PSS3: 0 | PST3: 0 | PSU3: 0 | PSV3: 0 | PSW3: 0 | PSX3: 0 | PSY3: 0 | PSZ3: 0 | PTA3: 0 | PTB3: 0 | PTC3: 0 | PTD3: 0 | PTE3: 0 | PTF3: 0 | PTG3: 0 | PTH3: 0 | PTI3: 0 | PTJ3: 0 | PTK3: 0 | PTL3: 0 | PTM3: 0 | PTN3: 0 | PTO3: 0 | PTP3: 0 | PTQ3: 0 | PTR3: 0 | PTS3: 0 | PTT3: 0 | PTU3: 0 | PTV3: 0 | PTW3: 0 | PTX3: 0 | PTY3: 0 | PTZ3: 0 | PUA3: 0 | PUB3: 0 | PUC3: 0 | PUD3: 0 | PUE3: 0 | PUF3: 0 | PUG3: 0 | PUH3: 0 | PUI3: 0 | PUJ3: 0 | PUK3: 0 | PUL3: 0 | PUM3: 0 | PUN3: 0 | PUO3: 0 | PUP3: 0 | PUQ3: 0 | PUR3: 0 | PUS3: 0 | PUT3: 0 | PUU3: 0 | PUV3: 0 | PUW3: 0 | PUX3: 0 | PUY3: 0 | PUZ3: 0 | PVA3: 0 | PVB3: 0 | PVC3: 0 | PVD3: 0 | PVE3: 0 | PVF3: 0 | PVG3: 0 | PVH3: 0 | PVI3: 0 | PVJ3: 0 | PVK3: 0 | PVL3: 0 | PVM3: 0 | PVN3: 0 | PVO3: 0 | PVP3: 0 | PVQ3: 0 | PVR3: 0 | PVS3: 0 | PVT3: 0 | PVU3: 0 | PVV3: 0 | PVW3: 0 | PVX3: 0 | PVY3: 0 | PVZ3: 0 | PWA3: 0 | PWB3: 0 | PWC3: 0 | PWD3: 0 | PWE3: 0 | PWF3: 0 | PWG3: 0 | PWH3: 0 | PWI3: 0 | PWJ3: 0 | PWK3: 0 | PWL3: 0 | PWM3: 0 | PWN3: 0 | PWO3: 0 | PWP3: 0 | PWQ3: 0 | PWR3: 0 | PWS3: 0 | PWT3: 0 | PWU3: 0 | PWV3: 0 | PWW3: 0 | PWX3: 0 | PWY3: 0 | PWZ3: 0 | PXA3: 0 | PXB3: 0 | PXC3: 0 | PXD3: 0 | PXE3: 0 | PXF3: 0 | PXG3: 0 | PXH3: 0 | PXI3: 0 | PXJ3: 0 | PXK3: 0 | PXL3: 0 | PXM3: 0 | PXN3: 0 | PXO3: 0 | PXP3: 0 | PXQ3: 0 | PXR3: 0 | PXS3: 0 | PXT3: 0 | PXU3: 0 | PXV3: 0 | PXW3: 0 | PXX3: 0 | PXY3: 0 | PXZ3: 0 | PYA3: 0 | PYB3: 0 | PYC3: 0 | PYD3: 0 | PYE3: 0 | PYF3: 0 | PYG3: 0 | PYH3: 0 | PYI3: 0 | PYJ3: 0 | PYK3: 0 | PYL3: 0 | PYM3: 0 | PYN3: 0 | PYO3: 0 | PYP3: 0 | PYQ3: 0 | PYR3: 0 | PYS3: 0 | PYT3: 0 | PYU3: 0 | PYV3: 0 | PYW3: 0 | PYX3: 0 | PYY3: 0 | PYZ3: 0 | PZA3: 0 | PZB3: 0 | PZC3: 0 | PZD3: 0 | PZE3: 0 | PZF3: 0 | PZG3: 0 | PZH3: 0 | PZI3: 0 | PZJ3: 0 | PZK3: 0 | PZL3: 0 | PZM3: 0 | PZN3: 0 | PZO3: 0 | PZP3: 0 | PZQ3: 0 | PZR3: 0 | PZS3: 0 | PZT3: 0 | PZU3: 0 | PZV3: 0 | PZW3: 0 | PZX3: 0 | PZY3: 0 | PZZ3: 0 | QAA3: 0 | QAB3: 0 | QAC3: 0 | QAD3: 0 | QAE3: 0 | QAF3: 0 | QAG3: 0 | QAH3: 0 | QAI3: 0 | QAJ3: 0 | QAK3: 0 | QAL3: 0 | QAM3: 0 | QAN3: 0 | QAO3: 0 | QAP3: 0 | QAQ3: 0 | QAR3: 0 | QAS3: 0 | QAT3: 0 | QAU3: 0 | QAV3: 0 | QAW3: 0 | QAX3: 0 | QAY3: 0 | QAZ3: 0 | QBA3: 0 | QBB3: 0 | QBC3: 0 | QBD3: 0 | QBE3: 0 | QBF3: 0 | QBG3: 0 | QBH3: 0 | QBI3: 0 | QBJ3: 0 | QBK3: 0 | QBL3: 0 | QBM3: 0 | QBN3: 0 | QBO3: 0 | QBP3: 0 | QBQ3: 0 | QBR3: 0 | QBS3: 0 | QBT3: 0 | QBU3: 0 | QBV3: 0 | QBW3: 0 | QBX3: 0 | QBY3: 0 | QBZ3: 0 | QCA3: 0 | QCB3: 0 | QCC3: 0 | QCD3: 0 | QCE3: 0 | QCF3: 0 | QCG3: 0 | QCH3: 0 | QCI3: 0 | QCJ3: 0 | QCK3: 0 | QCL3: 0 | QCM3: 0 | QCN3: 0 | QCO3: 0 | QCP3: 0 | QCQ3: 0 | QCR3: 0 | QCS3: 0 | QCT3: 0 | QCU3: 0 | QCV3: 0 | QCW3: 0 | QCX3: 0 | QCY3: 0 | QCZ3: 0 | QDA3: 0 | QDB3: 0 | QDC3: 0 | QDD3: 0 | QDE3: 0 | QDF3: 0 | QDG3: 0 | QDH3: 0 | QDI3: 0 | QDJ3: 0 | QDK3: 0 | QDL3: 0 | QDM3: 0 | QDN3: 0 | QDO3: 0 | QDP3: 0 | QDQ3: 0 | QDR3: 0 | QDS3: 0 | QDT3: 0 | QDU3: 0 | QDV3: 0 | QDW3: 0 | QDX3: 0 | QDY3: 0 | QDZ3: 0 | QEA3: 0 | QEB3: 0 | QEC3: 0 | QED3: 0 | QEE3: 0 | QEF3: 0 | QEG3: 0 | QEH3: 0 | QEI3: 0 | QEJ3: 0 | QEK3: 0 | QEL3: 0 | QEM3: 0 | QEN3: 0 | QEO3: 0 | QEP3: 0 | QEQ3: 0 | QER3: 0 | QES3: 0 | QET3: 0 | QEU3: 0 | QEV3: 0 | QEW3: 0 | QEX3: 0 | QEY3: 0 | QEZ3: 0 | QFA3: 0 | QFB3: 0 | QFC3: 0 | QFD3: 0 | QFE3: 0 | QFF3: 0 | QFG3: 0 | QFH3: 0 | QFI3: 0 | QFJ3: 0 | QFK3: 0 | QFL3: 0 | QFM3: 0 | QFN3: 0 | QFO3: 0 | QFP3: 0 | QFQ3: 0 | QFR3: 0 | QFS3: 0 | QFT3: 0 | QFU3: 0 | QFV3: 0 | QFW3: 0 | QFX3: 0 | QFY3: 0 | QFZ3: 0 | QGA3: 0 | QGB3: 0 | QGC3: 0 | QGD3: 0 | QGE3: 0 | QGF3: 0 | QGG3: 0 | QGH3: 0 | QGI3: 0 | QGJ3: 0 | QGK3: 0 | QGL3: 0 | QGM3: 0 | QGN3: 0 | QGO3: 0 | QGP3: 0 | QGQ3: 0 | QGR3: 0 | QGS3: 0 | QGT3: 0 | QGU3: 0 | QGV3: 0 | QGW3: 0 | QGX3: 0 | QGY3: 0 | QGZ3: 0 | QHA3: 0 | QHB3: 0 | QHC3: 0 | QHD3: 0 | QHE3: 0 | QHF3: 0 | QHG3: 0 | QHH3: 0 | QHI3: 0 | QHJ3: 0 | QHK3: 0 | QHL3: 0 | QHM3: 0 | QHN3: 0 | QHO3: 0 | QHP3: 0 | QHQ3: 0 | QHR3: 0 | QHS3: 0 | QHT3: 0 | QHU3: 0 | QHV3: 0 | QHW3: 0 | QHX3: 0 | QHY3: 0 | QHZ3: 0 | QIA3: 0 | QIB3: 0 | QIC3: 0 | QID3: 0 | QIE3: 0 | QIF3: 0 | QIG3: 0 | QIH3: 0 | QII3: 0 | QIJ3: 0 | QIK3: 0 | QIL3: 0 | QIM3: 0 | QIN3: 0 | QIO3: 0 | QIP3: 0 | QIQ3: 0 | QIR3: 0 | QIS3: 0 | QIT3: 0 | QIU3: 0 | QIV3: 0 | QIW3: 0 | QIX3: 0 | QIY3: 0 | QIZ3: 0 | QJA3: 0 | QJB3: 0 | QJC3: 0 | QJD3: 0 | QJE3: 0 | QJF3: 0 | QJG3: 0 | QJH3: 0 | QJI3: 0 | QJJ3: 0 | QJK3: 0 | QJL3: 0 | QJM3: 0 | QJN3: 0 | QJO3: 0 | QJP3: 0 | QJQ3: 0 | QJR3: 0 | QJS3: 0 | QJT3: 0 | QJU3: 0 | QJV3: 0 | QJW3: 0 | QJX3: 0 | QJY3: 0 | QJZ3: 0 | QKA3: 0 | QKB3: 0 | QKC3: 0 | QKD3: 0 | QKE3: 0 | QKF3: 0 | QKG3: 0 | QKH3: 0 | QKI3: 0 | QKJ3: 0 | QKK3: 0 | QKL3: 0 | QKM3: 0 | QKN3: 0 | QKO3: 0 | QKP3: 0 | QKQ3: 0 | QKR3: 0 | QKS3: 0 | QKT3: 0 | QKU3: 0 | QKV3: 0 | QKW3: 0 | QKX3: 0 | QKY3: 0 | QKZ3: 0 | QLA3: 0 | QLB3: 0 | QLC3: 0 | QLD3: 0 | QLE3: 0 | QLF3: 0 | QLG3: 0 | QLH3: 0 | QLI3: 0 | QLJ3: 0 | QLK3: 0 | QLL3: 0 | QLM3: 0 | QLN3: 0 | QLO3: 0 | QLP3: 0 | QLQ3: 0 | QLR3: 0 | QLS3: 0 | QLT3: 0 | QLU3: 0 | QLV3: 0 | QLW3: 0 | QLX3: 0 | QLY3: 0 | QLZ3: 0 | QMA3: 0 | QMB3: 0 | QMC3: 0 | QMD3: 0 | QME3: 0 | QMF3: 0 | QMG3: 0 | QMH3: 0 | QMI3: 0 | QMJ3: 0 | QMK3: 0 | QML3: 0 | QMM3: 0 | QMN3: 0 | QMO3: 0 | QMP3: 0 | QMQ3: 0 | QMR3: 0 | QMS3: 0 | QMT3: 0 | QMU3: 0 | QMV3: 0 | QMW3: 0 | QMX3: 0 | QMY3: 0 | QMZ3: 0 | QNA3: 0 | QNB3: 0 | QNC3: 0 | QND3: 0 | QNE3: 0 | QNF3: 0 | QNG3: 0 | QNH3: 0 | QNI3: 0 | QNJ3: 0 | QNK3: 0 | QNL3: 0 | QNM3: 0 | QNN3: 0 | QNO3: 0 | QNP3: 0 | QNQ3: 0 | QNR3: 0 | QNS3: 0 | QNT3: 0 | QNU3: 0 | QNV3: 0 | QNW3: 0 | QNX3: 0 | QNY3: 0 | QNZ3: 0 | QOA3: 0 | QOB3: 0 | QOC3: 0 | QOD3: 0 | QOE3: 0 | QOF3: 0 | QOG3: 0 | QOH3: 0 | QOI3: 0 | QOJ3: 0 | QOK3: 0 | QOL3: 0 | QOM3: 0 | QON3: 0 | QOO3: 0 | QOP3: 0 | QOQ3: 0 | QOR3: 0 | QOS3: 0 | QOT3: 0 | QOU3: 0 | QOV3: 0 | QOW3: 0 | QOX3: 0 | QOY3: 0 | QOZ3: 0 | QPA3: 0 | QPB3: 0 | QPC3: 0 | QPD3: 0 | QPE3: 0 | QPF3: 0 | QPG3: 0 | QPH3: 0 | QPI3: 0 | QPJ3: 0 | QPK3: 0 | QPL3: 0 | QPM3: 0 | QPN3: 0 | QPO3: 0 | QPP3: 0 | QPQ3: 0 | QPR3: 0 | QPS3: 0 | QPT3: 0 | QPU3: 0 | QPV3: 0 | QPW3: 0 | QPX3: 0 | QPY3: 0 | QPZ3: 0 | QQA3: 0 | QQB3: 0 | QQC3: 0 | QQD3: 0 | QQE3: 0 | QQF3: 0 | QQG3: 0 | QQH3: 0 | QQI3: 0 | QQJ3: 0 | QQK3: 0 | QQL3: 0 | QQM3: 0 | QQN3: 0 | QQO3: 0 | QQP3: 0 | QQQ3: 0 | QQR3: 0 | QQS3: 0 | QQT3: 0 | QQU3: 0 | QQV3: 0 | QQW3: 0 | QQX3: 0 | QQY3: 0 | QQZ3: 0 | QRA3: 0 | QRB3: 0 | QRC3: 0 | QRD3: 0 | QRE3: 0 | QRF3: 0 | QRG3: 0 | QRH3: 0 | QRI3: 0 | QRJ3: 0 | QRK3: 0 | QRL3: 0 | QRM3: 0 | QRN3: 0 | QRO3: 0 | QRP3: 0 | QRQ3: 0 | QRR3: 0 | QRS3: 0 | QRT3: 0 | QRU3: 0 | QRV3: 0 | QRW3: 0 | QRX3: 0 | QRY3: 0 | QRZ3: 0 | QSA3: 0 | QSB3: 0 | QSC3: 0 | QSD3: 0 | QSE3: 0 | QSF3: 0 | QSG3: 0 | QSH3: 0 | QSI3: 0 | QSJ3: 0 | QSK3: 0 | QSL3: 0 | QSM3: 0 | QSN3: 0 | QSO3: 0 | QSP3: 0 | QSQ3: 0 | QSR3: 0 | QSS3: 0 | QST3: 0 | QSU3: 0 | QSV3: 0 | QSW3: 0 | QSX3: 0 | QSY3: 0 | QSZ3: 0 | QTA3: 0 | QTB3: 0 | QTC3: 0 | QTD3: 0 | QTE3: 0 | QTF3: 0 | QTG3: 0 | QTH3: 0 | QTI3: 0 | QTJ3: 0 | QTK3: 0 | QTL3: 0 | QTM3: 0 | QTN3: 0 | QTO3: 0 | QTP3: 0 | QTQ3: 0 | QTR3: 0 | QTS3: 0 | QTT3: 0 | QTU3: 0 | QTV3: 0 | QTW3: 0 | QTX3: 0 | QTY3: 0 | QTZ3: 0 | QUA3: 0 | QUB3: 0 | QUC3: 0 | QUD3: 0 | QUE3: 0 | QUF3: 0 | QUG3: 0 | QUH3: 0 | QUI3: 0 | QUJ3: 0 | QUK3: 0 | QUL3: 0 | QUM3: 0 | QUN3: 0 | QUO3: 0 | QUP3: 0 | QUQ3: 0 | QUR3: 0 | QUS3: 0 | QUT3: 0 | QUU3: 0 | QUV3: 0 | QUW3: 0 | QUX3: 0 | QUY3: 0 | QUZ3: 0 | QVA3: 0 | QVB3: 0 | QVC3: 0 | QVD3: 0 | QVE3: 0 | QVF3: 0 | QVG3: 0 | QVH3: 0 | QVI3: 0 | QVJ3: 0 | QVK3: 0 | QVL3: 0 | QVM3: 0 | QVN3: 0 | QVO3: 0 | QVP3: 0 | QVQ3: 0 | QVR3: 0 | QVS3: 0 | QVT3: 0 | QVU3: 0 | QVV3: 0 | QVW3: 0 | QVX3: 0 | QVY3: 0 | QVZ3: 0 | QWA3: 0 | QWB3: 0 | QWC3: 0 | QWD3: 0 | QWE3: 0 | QWF3: 0 | QWG3: 0 | QWH3: 0 | QWI3: 0 | QWJ3: 0 | QWK3: 0 | QWL3: 0 | QWM3: 0 | QWN3: 0 | QWO3: 0 | QWP3: 0 | QWQ3: 0 | QWR3: 0 | QWS3: 0 | QWT3: 0 | QWU3: 0 | QWV3: 0 | QWW3: 0 | QWX3: 0 | QWY3: 0 | QWZ3: 0 | QXA3: 0 | QXB3: 0 | QXC3: 0 | QXD3: 0 | QXE3: 0 | QXF3: 0 | QXG3: 0 | QXH3: 0 | QXI3: 0 | QXJ3: 0 | QXK3: 0 | QXL3: 0 | QXM3: 0 | QXN3: 0 | QXO3: 0 | QXP3: 0 | QXQ3: 0 | QXR3: 0 | QXS3: 0 | QXT3: 0 | QXU3: 0 | QXV3: 0 | QXW3: 0 | QXX3: 0 | QXY3: 0 | QXZ3: 0 | QYA3: 0 | QYB3: 0 | QYC3: 0 | QYD3: 0 | QYE3: 0 | QYF3: 0 | QYG3: 0 | QYH3: 0 | QYI3: 0 | QYJ3: 0 | QYK3: 0 | QYL3: 0 | QYM3: 0 | QYN3: 0 | QYO3: 0 | QYP3: 0 | QYQ3: 0 | QYR3: 0 | QYS3: 0 | QYT3: 0 | QYU3: 0 | QYV3: 0 | QYW3: 0 | QYX3: 0 | QYY3: 0 | QYZ3: 0 | QZA3: 0 | QZB3: 0 | QZC3: 0 | QZD3: 0 | QZE3: 0 | QZF3: 0 | QZG3: 0 | QZH3: 0 | QZI3: 0 | QZJ3: 0 | QZK3: 0 | QZL3: 0 | QZM3: 0 | QZN3: 0 | QZO3: 0 | QZP3: 0 | QZQ3: 0 | QZR3: 0 | QZS3: 0 | QZT3: 0 | QZU3: 0 | QZV3: 0 | QZW3: 0 | QZX3: 0 | QZY3: 0 | QZZ3: 0 | RAA3: 0 | RAB3: 0 | RAC3: 0 | RAD3: 0 | RAE3: 0 | RAF3: 0 | RAG3: 0 | RAH3: 0 | RAI3: 0 | RAJ3: 0 | RAK3: 0 | RAL3: 0 | RAM3: 0 | RAN3: 0 | RAO3: 0 | RAP3: 0 | RAQ3: 0 | RAR3: 0 | RAS3: 0 | RAT3: 0 | RAU3: 0 | RAV3: 0 | RAW3: 0 | RAX3: 0 | RAY3: 0 | RAZ3: 0 | RBA3: 0 | RBB3: 0 | RBC3: 0 | RBD3: 0 | RBE3: 0 | RBF3: 0 | RBG3: 0 | RBH3: 0 | RBI3: 0 | RBJ3: 0 | RBK3: 0 | RBL3: 0 | RBM3: 0 | RBN3: 0 | RBO3: 0 | RBP3: 0 | RBQ3: 0 | RBR3: 0 | RBS3: 0 | RBT3: 0 | RBU3: 0 | RBV3: 0 | RBW3: 0 | RBX3: 0 | RBY3: 0 | RBZ3: 0 | RCA3: 0 | RCB3: 0 | RCC3: 0 | RCD3: 0 | RCE3: 0 | RCF3: 0 | RCG3: 0 | RCH3: 0 | RCI3: 0 | RCJ3: 0 | RCK3: 0 | RCL3: 0 | RCM3: 0 | RCN3: 0 | RCO3: 0 | RCP3: 0 | RCQ3: 0 | RCR3: 0 | RCS3: 0 | RCT3: 0 | RCU3: 0 | RCV3: 0 | RCW3: 0 | RCX3: 0 | RCY3: 0 | RCZ3: 0 | RDA3: 0 | RDB3: 0 | RDC3: 0 | RDD3: 0 | RDE3: 0 | RDF3: 0 | RDG3: 0 | RDH3: 0 | RDI3: 0 | RDJ3: 0 | RDK3: 0 | RDL3: 0 | RDM3: 0 | RDN3: 0 | RDO3: 0 | RDP3: 0 | RDQ3: 0 | RDR3: 0 | RDS3: 0 | RDT3: 0 | RDU3: 0 | RDV3: 0 | RDW3: 0 | RDX3: 0 | RDY3: 0 | RDZ3: 0 | REA3: 0 | REB3: 0 | REC3: 0 | RED3: 0 | REE3: 0 | REF3: 0 | REG3: 0 | REH3: 0 | REI3: 0 | REJ3: 0 | REK3: 0 | REL3: 0 | REM3: 0 | REN3: 0 | REO3: 0 | REP3: 0 | REQ3: 0 | RER3: 0 | RES3: 0 | RET3: 0 | REU3: 0 | REV3: 0 | REW3: 0 | REX3: 0 | REY3: 0 | REZ3: 0 | RFA3: 0 | RFB3: 0 | RFC3: 0 | RFD3: 0 | RFE3: 0 | RFF3: 0 | RFG3: 0 | RFH3: 0 | RFI3: 0 | RFJ3: 0 | RFK3: 0 | RFL3: 0 | RFM3: 0 | RFN3: 0 | RFO3: 0 | RFP3: 0 | RFQ3: 0 | RFR3: 0 | RFS3: 0 | RFT3: 0 | RFU3: 0 | RFV3: 0 | RFW3: 0 | RFX3: 0 | RFY3: 0 | RFZ3: 0 | RGA3: 0 | RGB3: 0 | RGC3: 0 | RGD3: 0 | RGE3: 0 | RGF3: 0 | RGG3: 0 | RGH3: 0 | RGI3: 0 | RGJ3: 0 | RGK3: 0 | RGL3: 0 | RGM3: 0 | RGN3: 0 | RGO3: 0 | RGP3: 0 | RGQ3: 0 | RGR3: 0 | RGS3: 0 | RGT3: 0 | RGU3: 0 | RGV3: 0 | RGW3: 0 | RGX3: 0 | RGY3: 0 | RGZ3: 0 | RHA3: 0 | RHB3: 0 | RHC3: 0 | RHD3: 0 | RHE3: 0 | RHF3: 0 | RHG3: 0 | RHH3: 0 | RHI3: 0 | RHJ3: 0 | RHK3: 0 | RHL3: 0 | RHM3: 0 | RHN3: 0 | RHO3: 0 | RHP3: 0 | RHQ3: 0 | RHR3: 0 | RHS3: 0 | RHT3: 0 | RHU3: 0 | RHV3: 0 | RHW3: 0 | RHX3: 0 | RHY3: 0 | RHZ3: 0 | RIA3: 0 | RIB3: 0 | RIC3: 0 | RID3: 0 | RIE3: 0 | RIF3: 0 | RIG3: 0 | RIH3: 0 | RII3: 0 | RIJ3: 0 | RIK3: 0 | RIL3: 0 | RIM3: 0 | RIN3: 0 | RIO3: 0 | RIP3: 0 | RIQ3: 0 | RIR3: 0 | RIS3: 0 | RIT3: 0 | RIU3: 0 | RIV3: 0 | RIW3: 0 | RIX3: 0 | RIY3: 0 | RIZ3: 0 | RJA3: 0 | RJB3: 0 | RJC3: 0 | RJD3: 0 | RJE3: 0 | RJF3: 0 | RJG3: 0 | RJH3: 0 | RJI3: 0 | RJJ3: 0 | RJK3: 0 | RJL3: 0 | RJM3: 0 | RJN3: 0 | RJO3: 0 | RJP3: 0 | RJQ3: 0 | RJR3: 0 | RJS3: 0 | RJT3: 0 | RJU3: 0 | RJV3: 0 | RJW3: 0 | RJX3: 0 | RJY3: 0 | RJZ3: 0 | RKA3: 0 | RKB3: 0 | RKC3: 0 | RKD3: 0 | RKE3: 0 | RKF3: 0 | RKG3: 0 | RKH3: 0 | RKI3: 0 | RKJ3: 0 | RKK3: 0 | RKL3: 0 | RKM3: 0 | RKN3: 0 | RKO3: 0 | RKP3: 0 | RKQ3: 0 | RKR3: 0 | RKS3: 0 | RKT3: 0 | RKU3: 0 | RKV3: 0 | RKW3: 0 | RKX3: 0 | RKY3: 0 | RKZ3: 0 | RLA3: 0 | RLB3: 0 | RLC3: 0 | RLD3: 0 | RLE3: 0 | RLF3: 0 | RLG3: 0 | RLH3: 0 | RLI3: 0 | RLJ3: 0 | RLK3: 0 | RLL3: 0 | RLM3: 0 | RLN3: 0 | RLO3: 0 | RLP3: 0 | RLQ3: 0 | RLR3: 0 | RLS3: 0 | RLT3: 0 | RLU3: 0 | RLV3: 0 | RLW3: 0 | RLX3: 0 | RLY3: 0 | RLZ3: 0 | RMA3: 0 | RMB3: 0 | RMC3: 0 | RMD3: 0 | RME3: 0 | RMF3: 0 | RMG3: 0 | RMH3: 0 | RMI3: 0 | RMJ3: 0 | RMK3: 0 | RML3: 0 | RMM3: 0 | RMN3: 0 | RMO3: 0 | RMP3: 0 | RMQ3: 0 | RMR3: 0 | RMS3: 0 | RMT3: 0 | RMU3: 0 | RMV3: 0 | RMW3: 0 | RMX3: 0 | RMY3: 0 | RMZ3: 0 | RNA3: 0 | RNB3: 0 | RNC3: 0 | RND3: 0 | RNE3: 0 | RNF3: 0 | RNG3: 0 | RNH3: 0 | RNI3: 0 | RNJ3: 0 | RNK3: 0 | RNL3: 0 | RNM3: 0 | RNN3: 0 | RNO3: 0 | RNP3: 0 | RNQ3: 0 | RNR3: 0 | RNS3: 0 | RNT3: 0 | RNU3: 0 | RNV3: 0 | RNW3: 0 | RNX3: 0 | RNY3: 0 | RNZ3: 0 | ROA3: 0 | ROB3: 0 | ROC3: 0 | ROD3: 0 | ROE3: 0 | ROF3: 0 | ROG3: 0 | ROH3: 0 | ROI3: 0 | ROJ3: 0 | ROK3: 0 | ROL3: 0 | ROM3: 0 | RON3: 0 | ROO3: 0 | ROP3: 0 | ROQ3: 0 | ROR3: 0 | ROS3: 0 | ROT3: 0 | ROU3: 0 | ROV3: 0 | ROW3: 0 | ROX3: 0 | ROY3: 0 | ROZ3: 0 | RPA3: 0 | RPB3: 0 | RPC3: 0 | RPD3: 0 | RPE3: 0 | RPF3: 0 | RPG3: 0 | RPH3: 0 | RPI3: 0 | RPJ3: 0 | RPK3: 0 | RPL3: 0 | RPM3: 0 | RPN3: 0 | RPO3: 0 | RPP3: 0 | RPQ3: 0 | RPR3: 0 | RPS3: 0 | RPT3: 0 | RPU3: 0 | RPV3: 0 | RPW3: 0 | RPX3: 0 | RPY3: 0 | RPZ3: 0 | RQA3: 0 | RQB3: 0 | RQC3: 0 | RQD3: 0 | RQE3: 0 | RQF3: 0 | RQG3: 0 | RQH3: 0 | RQI3: 0 | RQJ3: 0 | RQK3: 0 | RQL3: 0 | RQM3: 0 | RQN3: 0 | RQO3: 0 | RQP3: 0 | RQQ3: 0 | RQR3: 0 | RQS3: 0 | RQT3: 0 | RQU3: 0 | RQV3: 0 | RQW3: 0 | RQX3: 0 | RQY3: 0 | RQZ3: 0 | RRA3: 0 | RRB3: 0 | RRC3: 0 | RRD3: 0 | RRE3: 0 | RRF3: 0 | RRG3: 0 | RRH3: 0 | RRI3: 0 | RRJ3: 0 | RRK3: 0 | RRL3: 0 | RRM3: 0 | RRN3: 0 | RRO3: 0 | RRP3: 0 | RRQ3: 0 | RRR3: 0 | RRS3: 0 | RRT3: 0 | RRU3: 0 | RRV3: 0 | RRW3: 0 | RRX3: 0 | RRY3: 0 | RRZ3: 0 | RSA3: 0 | RSB3: 0 | RSC3: 0 | RSD3: 0 | RSE3: 0 | RSF3: 0 | RSG3: 0 | RSH3: 0 | RSI3: 0 | RSJ3: 0 | RSK3: 0 | RSL3: 0 | RSM3: 0 | RSN3: 0 | RSO3: 0 | RSP3: 0 | RSQ3: 0 | RSR3: 0 | RSS3: 0 | RST3: 0 | RSU3: 0 | RSV3: 0 | RSW3: 0 | RSX3: 0 | RSY3: 0 | RSZ3: 0 | RTA3: 0 | RTB3: 0 | RTC3: 0 | RTD3: 0 | RTE3: 0 | RTF3: 0 | RTG3: 0 | RTH3: 0 | RTI3: 0 | RTJ3: 0 | RTK3: 0 | RTL3: 0 | RTM3: 0 | RTN3: 0 | RTO3: 0 | RTP3: 0 | RTQ3: 0 | RTR3: 0 | RTS3: 0 | RTT3: 0 | RTU3: 0 | RTV3: 0 | RTW3: 0 | RTX3: 0 | RTY3: 0 | RTZ3: 0 | RUA3: 0 | RUB3: 0 | RUC3: 0 | RUD3: 0 | RUE3: 0 | RUF3: 0 | RUG3: 0 | RUH3: 0 | RUI3: 0 | RUJ3: 0 | RUK3: 0 | RUL3: 0 | RUM3: 0 | RUN3: 0 | RUO3: 0 | RUP3: 0 | RUQ3: 0 | RUR3: 0 | RUS3: 0 | RUT3: 0 | RUU3: 0 | RUV3: 0 | RUW3: 0 | RUX3: 0 | RUY3: 0 | RUZ3: 0 | RVA3: 0 | RVB3: 0 | RVC3: 0 | RVD3: 0 | RVE3: 0 | RVF3: 0 | RVG3: 0 | RVH3: 0 | RVI3: 0 | RVJ3: 0 | RVK3: 0 | RVL3: 0 | RVM3: 0 | RVN3: 0 | RVO3: 0 | RVP3: 0 | RVQ3: 0 | RVR3: 0 | RVS3: 0 | RVT3: 0 | RVU3: 0 | RVV3: 0 | RVW3: 0 | RVX3: 0 | RVY3: 0 | RVZ3: 0 | RWA3: 0 | RWB3: 0 | RWC3: 0 | RWD3: 0 | RWE3: 0 | RWF3: 0 | RWG3: 0 | RWH3: 0 | RWI3: 0 | RWJ3: 0 | RWK3: 0 | RWL3: 0 | RWM3: 0 | RWN3: 0 | RWO3: 0 | RWP3: 0 | RWQ3: 0 | RWR3: 0 | RWS3: 0 | RWT3: 0 | RWU3: 0 | RWV3: 0 | RWW3: 0 | RWX3: 0 | RWY3: 0 | RWZ3: 0 | RXA3: 0 | RXB3: 0 | RXC3: 0 | RXD3: 0 | RXE3: 0 | RXF3: 0 | RXG3: 0 | RXH3: 0 | RXI3: 0 | RXJ3: 0 | RXK3: 0 | RXL3: 0 | RXM3: 0 | RXN3: 0 | RXO3: 0 | RXP3: 0 | RXQ3: 0 | RXR3: 0 | RXS3: 0 | RXT3: 0 | RXU3: 0 | RXV3: 0 | RXW3: 0 | RXX3: 0 | RXY3: 0 | RXZ3: 0 | RYA3: 0 | RYB3: 0 | RYC3: 0 | RYD3: 0 | RYE3: 0 | RYF3: 0 | RYG3: 0 | RYH3: 0 | RYI3: 0 | RYJ3: 0 | RYK3: 0 | RYL3: 0 | RYM3: 0 | RYN3: 0 | RYO3: 0 | RYP3: 0 | RYQ3: 0 | RYR3: 0 | RYS3: 0 | RYT3: 0 | RYU3: 0 | RYV3: 0 | RYW3: 0 | RYX3: 0 | RYY3: 0 | RYZ3: 0 | RZA3: 0 | RZB3: 0 | RZC3: 0 | RZD3: 0 | RZE3: 0 | RZF3: 0 | RZG3: 0 | RZH3: 0 | RZI3: 0 | RZJ3: 0 | RZK3: 0 | RZL3: 0 | RZM3: 0 | RZN3: 0 | RZO3: 0 | RZP3: 0 | RZQ3: 0 | RZR3: 0 | RZS3: 0 | RZT3: 0 | RZU3: 0 | RZV3: 0 | RZW3: 0 | RZX3: 0 | RZY3: 0 | RZZ3: 0 | SAA3: 0 | SAB3: 0 | SAC3: 0 | SAD3: 0 | SAE3: 0 | SAF3: 0 | SAG3: 0 | SAH3: 0 | SAI3: 0 | SAJ3: 0 | SAK3: 0 | SAL3: 0 | SAM3: 0 | SAN3: 0 | SAO3: 0 | SAP3: 0 | SAQ3: 0 | SAR3: 0 | SAS3: 0 | SAT3: 0 | SAU3: 0 | SAV3: 0 | SAW3: 0 | SAX3: 0 | SAY3: 0 | SAZ3: 0 | SBA3: 0 | SBB3: 0 | SBC3: 0 | SBD3: 0 | SBE3: 0 | SBF3: 0 | SBG3: 0 | SBH3: 0 | SBI3: 0 | SBJ3: 0 | SBK3: 0 | SBL3: 0 | SBM3: 0 | SBN3: 0 | SBO3: 0 | SBP3: 0 | SBQ3: 0 | SBR3: 0 | SBS3: 0 | SBT3: 0 | SBU3: 0 | SBV3: 0 | SBW3: 0 | SBX3: 0 | SBY3: 0 | SBZ3: 0 | SCA3: 0 | SCB3: 0 | SCC3: 0 | SCD3: 0 | SCE3: 0 | SCF3: 0 | SCG3: 0 | SCH3: 0 | SCI3: 0 | SCJ3: 0 | SCK3: 0 | SCL3: 0 | SCM3: 0 | SCN3: 0 | SCO3: 0 | SCP3: 0 | SCQ3: 0 | SCR3: 0 | SCS3: 0 | SCT3: 0 | SCU3: 0 | SCV3: 0 | SCW3: 0 | SCX3: 0 | SCY3: 0 | SCZ3: 0 | SDA3: 0 | SDB3: 0 | SDC3: 0 | SDD3: 0 | SDE3: 0 | SDF3: 0 | SDG3: 0 | SDH3: 0 | SDI3: 0 | SDJ3: 0 | SDK3: 0 | SDL3: 0 | SDM3: 0 | SDN3: 0 | SDO3: 0 | SDP3: 0 | SDQ3: 0 | SDR3: 0 | SDS3: 0 | SDT3: 0 | SDU3: 0 | SDV3: 0 | SDW3: 0 | SDX3: 0 | SDY3: 0 | SDZ3: 0 | SEA3: 0 | SEB3: 0 | SEC3: 0 | SED3: 0 | SEE3: 0 | SEF3: 0 | SEG3: 0 | SEH3: 0 | SEI3: 0 | SEJ3: 0 | SEK3: 0 | SEL3: 0 | SEM3: 0 | SEN3: 0 | SEO3: 0 | SEP3: 0 | SEQ3: 0 | SER3: 0 | SES3: 0 | SET3: 0 | SEU3: 0 | SEV3: 0 | SEW3: 0 | SEX3: 0 | SEY3: 0 | SEZ3: 0 | SFA3: 0 | SFB3: 0 | SFC3: 0 | SFD3: 0 | SFE3: 0 | SFF3: 0 | SFG3: 0 | SFH3: 0 | SFI3: 0 | SFJ3: 0 | SFK3: 0 | SFL3: 0 | SFM3: 0 | SFN3: 0 | SFO3: 0 | SFP3: 0 | SFQ3: 0 | SFR3: 0 | SFS3: 0 | SFT3: 0 | SFU3: 0 | SFV3: 0 | SFW3: 0 | SFX3: 0 | SFY3: 0 | SFZ3: 0 | SGA3: 0 | SGB3: 0 | SGC3: 0 | SGD3: 0 | SGE3: 0 | SGF3: 0 | SGG3: 0 | SGH3: 0 | SGI3: 0 | SGJ3: 0 | SGK3: 0 | SGL3: 0 | SGM3: 0 | SGN3: 0 | SGO3: 0 | SGP3: 0 | SGQ3: 0 | SGR3: 0 | SGS3: 0 | SGT3: 0 | SGU3: 0 | SGV3: 0 | SGW3: 0 | SGX3: 0 | SGY3: 0 | SGZ3: 0 | SHA3: 0 | SHB3: 0 | SHC3: 0 | SHD3: 0 | SHE3: 0 | SHF3: 0 | SHG3: 0 | SHH3: 0 | SHI3: 0 | SHJ3: 0 | SHK3: 0 | SHL3: 0 | SHM3: 0 | SHN3: 0 | SHO3: 0 | SHP3: 0 | SHQ3: 0 | SHR3: 0 | SHS3: 0 | SHT3: 0 | SHU3: 0 | SHV3: 0 | SHW3: 0 | SHX3: 0 | SHY3: 0 | SHZ3: 0 | SIA3: 0 | SIB3: 0 | SIC3: 0 | SID3: 0 | SIE3: 0 | SIF3: 0 | SIG3: 0 | SIH3: 0 | SII3: 0 | SIJ3: 0 | SIK3: 0 | SIL3: 0 | SIM3: 0 | SIN3: 0 | SIO3: 0 | SIP3: 0 | SIQ3: 0 | SIR3: 0 | SIS3: 0 | SIT3: 0 | SIU3: 0 | SIV3: 0 | SIW3: 0 | SIX3: 0 | SIY3: 0 | SIZ3: 0 | SJA3: 0 | SJB3: 0 | SJC3: 0 | SJD3: 0 | SJE3: 0 | SJF3: 0 | SJG3: 0 | SJH3: 0 | SJI3: 0 | SJJ3: 0 | SJK3: 0 | SJL3: 0 | SJM3: 0 | SJN3: 0 | SJO3: 0 | SJP3: 0 | SJQ3: 0 | SJR3: 0 | SJS3: 0 | SJT3: 0 | SJU3: 0 | SJV3: 0 | SJW3: 0 | SJX3: 0 | SJY3: 0 | SJZ3: 0 | SKA3: 0 | SKB3: 0 | SKC3: 0 | SKD3: 0 | SKE3: 0 | SKF3: 0 | SKG3: 0 | SKH3: 0 | SKI3: 0 | SKJ3: 0 | SKK3: 0 | SKL3: 0 | SKM3: 0 | SKN3: 0 | SKO3: 0 | SKP3: 0 | SKQ3: 0 | SKR3: 0 | SKS3: 0 | SKT3: 0 | SKU3: 0 | SKV3: 0 | SKW3: 0 | SKX3: 0 | SKY3: 0 | SKZ3: 0 | SLA3: 0 | SLB3: 0 | SLC3: 0 | SLD3: 0 | SLE3: 0 | SLF3: 0 | SLG3: 0 | SLH3: 0 | SLI3: 0 | SLJ3: 0 | SLK3: 0 | SLL3: 0 | SLM3: 0 | SLN3: 0 | SLO3: 0 | SLP3: 0 | SLQ3: 0 | SLR3: 0 | SLS3: 0 | SLT3: 0 | SLU3: 0 | SLV3: 0 | SLW3: 0 | SLX3: 0 | SLY3: 0 | SLZ3: 0 | SMA3: 0 | SMB3: 0 | SMC3: 0 | SMD3: 0 | SME3: 0 | SMF3: 0 | SMG3: 0 | SMH3: 0 | SMI3: 0 | SMJ3: 0 | SMK3: 0 | SML3: 0 | SMM3: 0 | SMN3: 0 | SMO3: 0 | SMP3: 0 | SMQ3: 0 | SMR3: 0 | SMS3: 0 | SMT3: 0 | SMU3: 0 | SMV3: 0 | SMW3: 0 | SMX3: 0 | SMY3: 0 | SMZ3: 0 | SNA3: 0 | SNB3: 0 | SNC3: 0 | SND3: 0 | SNE3: 0 | SNF3: 0 | SNG3: 0 | SNH3: 0 | SNI3: 0 | SNJ3: 0 | SNK3: 0 | SNL3: 0 | SNM3: 0 | SNN3: 0 | SNO3: 0 | SNP3: 0 | SNQ3: 0 | SNR3: 0 | SNS3: 0 | SNT3: 0 | SNU3: 0 | SNV3: 0 | SNW3: 0 | SNX3: 0 | SNY3: 0 | SNZ3: 0 | SOA3: 0 | SOB3: 0 | SOC3: 0 | SOD3: 0 | SOE3: 0 | SOF3: 0 | SOG3: 0 | SOH3: 0 | SOI3: 0 | SOJ3: 0 | SOK3: 0 | SOL3: 0 | SOM3: 0 | SON3: 0 | SOO3: 0 | SOP3: 0 | SOQ3: 0 | SOR3: 0 | SOS3: 0 | SOT3: 0 | SOU3: 0 | SOV3: 0 | SOW3: 0 | SOX3: 0 | SOY3: 0 | SOZ3: 0 | SPA3: 0 | SPB3: 0 | SPC3: 0 | SPD3: 0 | SPE3: 0 | SPF3: 0 | SPG3: 0 | SPH3: 0 | SPI3: 0 | SPJ3: 0 | SPK3: 0 | SPL3: 0 | SPM3: 0 | SPN3: 0 | SPO3: 0 | SPP3: 0 | SPQ3: 0 | SPR3: 0 | SPS3: 0 | SPT3: 0 | SPU3: 0 | SPV3: 0 | SPW3: 0 | SPX3: 0 | SPY3: 0 | SPZ3: 0 | SQA3: 0 | SQB3: 0 | SQC3: 0 | SQD3: 0 | SQE3: 0 | SQF3: 0 | SQG3: 0 | SQH3: 0 | SQI3: 0 | SQJ3: 0 | SQK3: 0 | SQL3: 0 | SQM3: 0 | SQN3: 0 | SQO3: 0 | SQP3: 0 | SQQ3: 0 | SQR3: 0 | SQS3: 0 | SQT3: 0 | SQU3: 0 | SQV3: 0 | SQW3: 0 | SQX3: 0 | SQY3: 0 | SQZ3: 0 | SRA3: 0 | SRB3: 0 | SRC3: 0 | SRD3: 0 | SRE3: 0 | SRF3: 0 | SRG3: 0 | SRH3: 0 | SRI3: 0 | SRJ3: 0 | SRK3: 0 | SRL3: 0 | SRM3: 0 | SRN3: 0 | SRO3: 0 | SRP3: 0 | SRQ3: 0 | SRR3: 0 | SRS3: 0 | SRT3: 0 | SRU3: 0 | SRV3: 0 | SRW3: 0 | SRX3: 0 | SRY3: 0 | SRZ3: 0 | SSA3: 0 | SSB3: 0 | SSC3: 0 | SSD3: 0 | SSE3: 0 | SSF3: 0 | SSG3: 0 | SSH3: 0 | SSI3: 0 | SSJ3: 0 | SSK3: 0 | SSL3: 0 | SSM3: 0 | SSN3: 0 | SSO3: 0 | SSP3: 0 | SSQ3: 0 | SSR3: 0 | SSS3: 0 | SST3: 0 | SSU3: 0 | SSV3: 0 | SSW3: 0 | SSX3: 0 | SSY3: 0 | SSZ3: 0 | STA3: 0 | STB3: 0 | STC3: 0 | STD3: 0 | STE3: 0 | STF3: 0 | STG3: 0 | STH3: 0 | STI3: 0 | STJ3: 0 | STK3: 0 | STL3: 0 | STM3: 0 | STN3: 0 | STO3: 0 | STP3: 0 | STQ3: 0 | STR3: 0 | STS3: 0 | STT3: 0 | STU3: 0 | STV3: 0 | STW3: 0 | STX3: 0 | STY3: 0 | STZ3: 0 | SUA3: 0 | SUB3: 0 | SUC3: 0 | SUD3: 0 | SUE3: 0 | SUF3: 0 | SUG3: 0 | SUH3: 0 | SUI3: 0 | SUJ3: 0 | SUK3: 0 | SUL3: 0 | SUM3: 0 | SUN3: 0 | SUO3: 0 | SUP3: 0 | SUQ3: 0 | SUR3: 0 | SUS3: 0 | SUT3: 0 | SUU3: 0 | SUV3: 0 | SUW3: 0 | SUX3: 0 | SUY3: 0 | SUZ3: 0 | SVA3: 0 | SVB3: 0 | SVC3: 0 | SVD3: 0 | SVE3: 0 | SVF3: 0 | SVG3: 0 | SVH3: 0 | SVI3: 0 | SVJ3: 0 | SVK3: 0 | SVL3: 0 | SVM3: 0 | SVN3: 0 | SVO3: 0 | SVP3: 0 | SVQ3: 0 | SVR3: 0 | SVS3: 0 | SVT3: 0 | SVU3: 0 | SVV3: 0 | SVW3: 0 | SVX3: 0 | SVY3: 0 | SVZ3: 0 | SWA3: 0 | SWB3: 0 | SWC3: 0 | SWD3: 0 | SWE3: 0 | SWF3: 0 | SWG3: 0 | SWH3: 0 | SWI3: 0 | SWJ3: 0 | SWK3: 0 | SWL3: 0 | SWM3: 0 | SWN3: 0 | SWO3: 0 | SWP3: 0 | SWQ3: 0 | SWR3: 0 | SWS3: 0 | SWT3: 0 | SWU3: 0 | SWV3: 0 | SWW3: 0 | SWX3: 0 | SWY3: 0 | SWZ3: 0 | SXA3: 0 | SXB3: 0 | SXC3: 0 | SXD3: 0 | SXE3: 0 | SXF3: 0 | SXG3: 0 | SXH3: 0 | SXI3: 0 | SXJ3: 0 | SXK3: 0 | SXL3: 0 | SXM3: 0 | SXN3: 0 | SXO3: 0 | SXP3: 0 | SXQ3: 0 | SXR3: 0 | SXS3: 0 | SXT3: 0 | SXU3: 0 | SXV3: 0 | SXW3: 0 | SXX3: 0 | SXY3: 0 | SXZ3: 0 | SYA3: 0 | SYB3: 0 | SYC3: 0 | SYD3: 0 | SYE3: 0 | SYF3: 0 | SYG3: 0 | SYH3: 0 | SYI3: 0 | SYJ3: 0 | SYK3: 0 | SYL3: 0 | SYM3: 0 | SYN3: 0 | SYO3: 0 | SYP3: 0 | SYQ3: 0 | SYR3: 0 | SYS3: 0 | SYT3: 0 | SYU3: 0 | SYV3: 0 | SYW3: 0 | SYX3: 0 | SYY3: 0 | SYZ3: 0 | SZA3: 0 | SZB3: 0 | SZC3: 0 | SZD3: 0 | SZE3: 0 | SZF3: 0 | SZG3: 0 | SZH3: 0 | SZI3: 0 | SZJ3: 0 | SZK3: 0 | SZL3: 0 | SZM3: 0 | SZN3: 0 | SZO3: 0 | SZP3: 0 | SZQ3: 0 | SZR3: 0 | SZS3: 0 | SZT3: 0 | SZU3: 0 | SZV3: 0 | SZW3: 0 | SZX3: 0 | SZY3: 0 | SZZ3: 0 | TAA3: 0 | TAB3: 0 | TAC3: 0 | TAD3: 0 | TAE3: 0 | TAF3: 0 | TAG3: 0 | TAH3: 0 | TAI3: 0 | TAJ3: 0 | TAK3: 0 | TAL3: 0 | TAM3: 0 | TAN3: 0 | TAO3: 0 | TAP3: 0 | TAQ3: 0 | TAR3: 0 | TAS3: 0 | TAT3: 0 | TAU3: 0 | TAV3: 0 | TAW3: 0 | TAX3: 0 | TAY3: 0 | TAZ3: 0 | TBA3: 0 | TBB3: 0 | TBC3: 0 | TBD3: 0 | TBE3: 0 | TBF3: 0 | TBG3: 0 | TBH3: 0 | TBI3: 0 | TBJ3: 0 | TBK3: 0 | TBL3: 0 | TBM3: 0 | TBN3: 0 | TBO3: 0 | TBP3: 0 | TBQ3: 0 | TBR3: 0 | TBS3: 0 | TBT3: 0 | TBU3: 0 | TBV3: 0 | TBW3: 0 | TBX3: 0 | TBY3: 0 | TBZ3: 0 | TCA3: 0 | TCB3: 0 | TCC3: 0 | TCD3: 0 | TCE3: 0 | TCF3: 0 | TCG3: 0 | TCH3: 0 | TCI3: 0 | TCJ3: 0 | TCK3: 0 | TCL3: 0 | TCM3: 0 | TCN3: 0 | TCO3: 0 | TCP3: 0 | TCQ3: 0 | TCR3: 0 | TCS3: 0 | TCT3: 0 | TCU3: 0 | TCV3: 0 | TCW3: 0 | TCX3: 0 | TCY3: 0 | TCZ3: 0 | TDA3: 0 | TDB3: 0 | TDC3: 0 | TDD3: 0 | TDE3: 0 | TDF3: 0 | TDG3: 0 | TDH3: 0 | TDI3: 0 | TDJ3: 0 | TDK3: 0 | TDL3: 0 | TDM3: 0 | TDN3: 0 | TDO3: 0 | TDP3: 0 | TDQ3: 0 | TDR3: 0 | TDS3: 0 | TDT3: 0 | TDU3: 0 | TDV3: 0 | TDW3: 0 | TDX3: 0 | TDY3: 0 | TDZ3: 0 | TEA3: 0 | TEB3: 0 | TEC3: 0 | TED3: 0 | TEE3: 0 | TEF3: 0 | TEG3: 0 | TEH3: 0 | TEI3: 0 | TEJ3: 0 | TEK3: 0 | TEL3: 0 | TEM3: 0 | TEN3: 0 | TEO3: 0 | TEP3: 0 | TEQ3: 0 | TER3: 0 | TES3: 0 | TET3: 0 | TEU3: 0 | TEV3: 0 | TEW3: 0 | TEX3: 0 | TEY3: 0 | TEZ3: 0 | TFA3: 0 | TFB3: 0 | TFC3: 0 | TFD3: 0 | TFE3: 0 | TFF3: 0 | TFG3: 0 | TFH3: 0 | TFI3: 0 | TFJ3: 0 | TFK3: 0 | TFL3: 0 | TFM3: 0 | TFN3: 0 | TFO3: 0 | TFP3: 0 | TFQ3: 0 | TFR3: 0 | TFS3: 0 | TFT3: 0 | TFU3: 0 | TFV3: 0 | TFW3: 0 | TFX3: 0 | TFY3: 0 | TFZ3: 0 | TGA3: 0 | TGB3: 0 | TGC3: 0 | TGD3: 0 | TGE3: 0 | TGF3: 0 | TGG3: 0 | TGH3: 0 | TGI3: 0 | TGJ3: 0 | TGK3: 0 | TGL3: 0 | TGM3: 0 | TGN3: 0 | TGO3: 0 | TGP3: 0 | TGQ3: 0 | TGR3: 0 | TGS3: 0 | TGT3: 0 | TGU3: 0 | TGV3: 0 | TGW3: 0 | TGX3: 0 | TGY3: 0 | TGZ3: 0 | THA3: 0 | THB3: 0 | THC3: 0 | THD3: 0 | THE3: 0 | THF3: 0 | THG3: 0 | THH3: 0 | THI3: 0 | THJ3: 0 | THK3: 0 | THL3: 0 | THM3: 0 | THN3: 0 | THO3: 0 | THP3: 0 | THQ3: 0 | THR3: 0 | THS3: 0 | THT3: 0 | THU3: 0 | THV3: 0 | THW3: 0 | THX3: 0 | THY3: 0 | THZ3: 0 | TIA3: 0 | TIB3: 0 | TIC3: 0 | TID3: 0 | TIE3: 0 | TIF3: 0 | TIG3: 0 | TIH3: 0 | TII3: 0 | TIJ3: 0 | TIK3: 0 | TIL3: 0 | TIM3: 0 | TIN3: 0 | TIO3: 0 | TIP3: 0 | TIQ3: 0 | TIR3: 0 | TIS3: 0 | TIT3: 0 | TIU3: 0 | TIV3: 0 | TIW3: 0 | TIX3: 0 | TIY3: 0 | TIZ3: 0 | TJA3: 0 | TJB3: 0 | TJC3: 0 | TJD3: 0 | TJE3: 0 | TJF3: 0 | TJG3: 0 | TJH3: 0 | TJI3: 0 | TJJ3: 0 | TJK3: 0 | TJL3: 0 | TJM3: 0 | TJN3: 0 | TJO3: 0 | TJP3: 0 | TJQ3: 0 | TJR3: 0 | TJS3: 0 | TJT3: 0 | TJU3: 0 | TJV3: 0 | TJW3: 0 | TJX3: 0 | TJY3: 0 | TJZ3: 0 | TKA3: 0 | TKB3: 0 | TKC3: 0 | TKD3: 0 | TKE3: 0 | TKF3: 0 | TKG3: 0 | TKH3: 0 | TKI3: 0 | TKJ3: 0 | TKK3: 0 | TKL3: 0 | TKM3: 0 | TKN3: 0 | TKO3: 0 | TKP3: 0 | TKQ3: 0 | TKR3: 0 | TKS3: 0 | TKT3: 0 | TKU3: 0 | TKV3: 0 | TKW3: 0 | TKX3: 0 | TKY3: 0 | TKZ3: 0 | TLA3: 0 | TLB3: 0 | TLC3: 0 | TLD3: 0 | TLE3: 0 | TLF3: 0 | TLG3: 0 | TLH3: 0 | TLI3: 0 | TLJ3: 0 | TLK3: 0 | TLL3: 0 | TLM3: 0 | TLN3: 0 | TLO3: 0 | TLP3: 0 | TLQ3: 0 | TLR3: 0 | TLS3: 0 | TLT3: 0 | TLU3: 0 | TLV3: 0 | TLW3: 0 | TLX3: 0 | TLY3: 0 | TLZ3: 0 | TMA3: 0 | TMB3: 0 | TMC3: 0 | TMD3: 0 | TME3: 0 | TMF3: 0 | TMG3: 0 | TMH3: 0 | TMI3: 0 | TMJ3: 0 | TMK3: 0 | TML3: 0 | TMM3: 0 | TMN3: 0 | TMO3: 0 | TMP3: 0 | TMQ3: 0 | TMR3: 0 | TMS3: 0 | TMT3: 0 | TMU3: 0 | TMV3: 0 | TMW3: 0 | TMX3: 0 | TMY3: 0 | TMZ3: 0 | TNA3: 0 | TNB3: 0 | TNC3: 0 | TND3: 0 | TNE3: 0 | TNF3: 0 | TNG3: 0 | TNH3: 0 | TNI3: 0 | TNJ3: 0 | TNK3: 0 | TNL3: 0 | TNM3: 0 | TNN3: 0 | TNO3: 0 | TNP3: 0 | TNQ3: 0 | TNR3: 0 | TNS3: 0 | TNT3: 0 | TNU3: 0 | TNV3: 0 | TNW3: 0 | TNX3: 0 | TNY3: 0 | TNZ3: 0 | TOA3: 0 | TOB3: 0 | TOC3: 0 | TOD3: 0 | TOE3: 0 | TOF3: 0 | TOG3: 0 | TOH3: 0 | TOI3: 0 | TOJ3: 0 | TOK3: 0 | TOL3: 0 | TOM3: 0 | TON3: 0 | TOO3: 0 | TOP3: 0 | TOQ3: 0 | TOR3: 0 | TOS3: 0 | TOT3: 0 | TOU3: 0 | TOV3: 0 | TOW3: 0 | TOX3: 0 | TOY3: 0 | TOZ3: 0 | TPA3: 0 | TPB3: 0 | TPC3: 0 | TPD3: 0 | TPE3: 0 | TPF3: 0 | TPG3: 0 | TPH3: 0 | TPI3: 0 | TPJ3: 0 | TPK3: 0 | TPL3: 0 | TPM3: 0 | TPN3: 0 | TPO3: 0 | TPP3: 0 | TPQ3: 0 | TPR3: 0 | TPS3: 0 | TPT3: 0 | TPU3: 0 | TPV3: 0 | TPW3: 0 | TPX3: 0 | TPY3: 0 | TPZ3: 0 | TQA3: 0 | TQB3: 0 | TQC3: 0 | TQD3: 0 | TQE3: 0 | TQF3: 0 | TQG3: 0 | TQH3: 0 | TQI3: 0 | TQJ3: 0 | TQK3: 0 | TQL3: 0 | TQM3: 0 | TQN3: 0 | TQO3: 0 | TQP3: 0 | TQQ3: 0 | TQR3: 0 | TQS3: 0 | TQT3: 0 | TQU3: 0 | TQV3: 0 | TQW3: 0 | TQX3: 0 | TQY3: 0 | TQZ3: 0 | TRA3: 0 | TRB3: 0 | TRC3: 0 | TRD3: 0 | TRE3: 0 | TRF3: 0 | TRG3: 0 | TRH3: 0 | TRI3: 0 | TRJ3: 0 | TRK3: 0 | TRL3: 0 | TRM3: 0 | TRN3: 0 | TRO3: 0 | TRP3: 0 | TRQ3: 0 | TRR3: 0 | TRS3: 0 | TRT3: 0 | TRU3: 0 | TRV3: 0 | TRW3: 0 | TRX3: 0 | TRY3: 0 | TRZ3: 0 | TSA3: 0 | TSB3: 0 | TSC3: 0 | TSD3: 0 | TSE3: 0 | TSF3: 0 | TSG3: 0 | TSH3: 0 | TSI3: 0 | TSJ3: 0 | TSK3: 0 | TSL3: 0 | TSM3: 0 | TSN3: 0 | TSO3: 0 | TSP3: 0 | TSQ3: 0 | TSR3: 0 | TSS3: 0 | TST3: 0 | TSU3: 0 | TSV3: 0 | TSW3: 0 | TSX3: 0 | TSY3: 0 | TSZ3: 0 | TTA3: 0 | TTB3: 0 | TTC3: 0 | TTD3: 0 | TTE3: 0 | TTF3: 0 | TTG3: 0 | TTH3: 0 | TTI3: 0 | TTJ3: 0 | TTK3: 0 | TTL3: 0 | TTM3: 0 | TTN3: 0 | TTO3: 0 | TTP3: 0 | TTQ3: 0 | TTR3: 0 | TTS3: 0 | TTT3: 0 | TTU3: 0 | TTV3: 0 | TTW3: 0 | TTX3: 0 | TTY3: 0 | TTZ3: 0 | TUA3: 0 | TUB3: 0 | TUC3: 0 | TUD3: 0 | TUE3: 0 | TUF3: 0 | TUG3: 0 | TUH3: 0 | TUI3: 0 | TUJ3: 0 | TUK3: 0 | TUL3: 0 | TUM3: 0 | TUN3: 0 | TUO3: 0 | TUP3: 0 | TUQ3: 0 | TUR3: 0 | TUS3: 0 | TUT3: 0 | TUU3: 0 | TUV3: 0 | TUW3: 0 | TUX3: 0 | TUY3: 0 | TUZ3: 0 | TVA3: 0 | TVB3: 0 | TVC3: 0 | TVD3: 0 | TVE3: 0 | TVF3: 0 | TVG3: 0 | TVH3: 0 | TVI3: 0 | TVJ3: 0 | TVK3: 0 | TVL3: 0 | TVM3: 0 | TVN3: 0 | TVO3: 0 | TVP3: 0 | TVQ3: 0 | TVR3: 0 | TVS3: 0 | TVT3: 0 | TVU3: 0 | TVV3: 0 | TVW3: 0 | TVX3: 0 | TVY3: 0 | TVZ3: 0 | TWA3: 0 | TWB3: 0 | TWC3: 0 | TWD3: 0 | TWE3: 0 | TWF3: 0 | TWG3: 0 | TWH3: 0 | TWI3: 0 | TWJ3: 0 | TWK3: 0 | TWL3: 0 | TWM3: 0 | TWN3: 0 | TWO3: 0 | TWP3: 0 | TWQ3: 0 | TWR3: 0 | TWS3: 0 | TWT3: 0 | TWU3: 0 | TWV3: 0 | TWW3: 0 | TWX3: 0 | TWY3: 0 | TWZ3: 0 | TXA3: 0 | TXB3: 0 | TXC3: 0 | TXD3: 0 | TXE3: 0 | TXF3: 0 | TXG3: 0 | TXH3: 0 | TXI3: 0 | TXJ3: 0 | TXK3: 0 | TXL3: 0 | TXM3: 0 | TXN3: 0 | TXO3: 0 | TXP3: 0 | TXQ3: 0 | TXR3: 0 | TXS3: 0 | TXT3: 0 | TXU3: 0 | TXV3: 0 | TXW3: 0 | TXX3: 0 | TXY3: 0 | TXZ3: 0 | TYA3: 0 | TYB3: 0 | TYC3: 0 | TYD3: 0 | TYE3: 0 | TYF3: 0 | TYG3: 0 | TYH3: 0 | TYI3: 0 | TYJ3: 0 | TYK3: 0 | TYL3: 0 | TYM3: 0 | TYN3: 0 | TYO3: 0 | TYP3: 0 | TYQ3: 0 | TYR3: 0 | TYS3: 0 | TYT3: 0 | TYU3: 0 | TYV3: 0 | TYW3: 0 | TYX3: 0 | TYY3: 0 | TYZ3: 0 | TZA3: 0 | TZB3: 0 | TZC3: 0 | TZD3: 0 | TZE3: 0 | TZF3: 0 | TZG3: 0 | TZH3: 0 | TZI3: 0 | TZJ3: 0 | TZK3: 0 | TZL3: 0 | TZM3: 0 | TZN3: 0 | TZO3: 0 | TZP3: 0 | TZQ3: 0 | TZR3: 0 | TZS3: 0 | TZT3: 0 | TZU3: 0 | TZV3: 0 | TZW3: 0 | TZX3: 0 | TZY3: 0 | TZZ3: 0 | UAA3: 0 | UAB3: 0 | UAC3: 0 | UAD3: 0 | UAE3: 0 | UAF3: 0 | UAG3: 0 | UAH3: 0 | UAI3: 0 | UAJ3: 0 | UAK3: 0 | UAL3: 0 | UAM3: 0 | UAN3: 0 | UAO3: 0 | UAP3: 0 | UAQ3: 0 | UAR3: 0 | UAS3: 0 | UAT3: 0 | UAU3: 0 | UAV3: 0 | UAW3: 0 | UAX3: 0 | UAY3: 0 | UAZ3: 0 | UBA3: 0 | UBB3: 0 | UBC3: 0 | UBD3: 0 | UBE3: 0 | UBF3: 0 | UBG3: 0 | UBH3: 0 | UBI3: 0 | UBJ3: 0 | UBK3: 0 | UBL3: 0 | UBM3: 0 | UBN3: 0 | UBO3: 0 | UBP3: 0 | UBQ3: 0 | UBR3: 0 | UBS3: 0 | UBT3: 0 | UBU3: 0 | UBV3: 0 | UBW3: 0 | UBX3: 0 | UBY3: 0 | UBZ3: 0 | UCA3: 0 | UCB3: 0 | UCC3: 0 | UCD3: 0 | UCE3: 0 | UCF3: 0 | UCG3: 0 | UCH3: 0 | UCI3: 0 | UCJ3: 0 | UCK3: 0 | UCL3: 0 | UCM3: 0 | UCN3: 0 | UCO3: 0 | UCP3: 0 | UCQ3: 0 | UCR3: 0 | UCS3: 0 | UCT3: 0 | UCU3: 0 | UCV3: 0 | UCW3: 0 | UCX3: 0 | UCY3: 0 | UCZ3: 0 | UDA3: 0 | UDB3: 0 | UDC3: 0 | UDD3: 0 | UDE3: 0 | UDF3: 0 | UDG3: 0 | UDH3: 0 | UDI3: 0 | UDJ3: 0 | UDK3: 0 | UDL3: 0 | UDM3: 0 | UDN3: 0 | UDO3: 0 | UDP3: 0 | UDQ3: 0 | UDR3: 0 | UDS3: 0 | UDT3: 0 | UDU3: 0 | UDV3: 0 | UDW3: 0 | UDX3: 0 | UDY3: 0 | UDZ3: 0 | UEA3: 0 | UEB3: 0 | UEC3: 0 | UED3: 0 | UEE3: 0 | UEF3: 0 | UEG3: 0 | UEH3: 0 | UEI3: 0 | UEJ3: 0 | UEK3: 0 | UEL3: 0 | UEM3: 0 | UEN3: 0 | UEO3: 0 | UEP3: 0 | UEQ3: 0 | UER3: 0 | UES3: 0 | UET3: 0 | UEU3: 0 | UEV3: 0 | UEW3: 0 | UEX3: 0 | UEY3: 0 | UEZ3: 0 | UFA3: 0 | UFB3: 0 | UFC3: 0 | UFD3: 0 | UFE3: 0 | UFF3: 0 | UFG3: 0 | UFH3: 0 | UFI3: 0 | UFJ3: 0 | UFK3: 0 | UFL3: 0 | UFM3: 0 | UFN3: 0 | UFO3: 0 | UFP3: 0 | UFQ3: 0 | UFR3: 0 | UFS3: 0 | UFT3: 0 | UFU3: 0 | UFV3: 0 | UFW3: 0 | UFX3: 0 | UFY3: 0 | UFZ3: 0 | UGA3: 0 | UGB3: 0 | UGC3: 0 | UGD3: 0 | UGE3: 0 | UGF3: 0 | UGG3: 0 | UGH3: 0 | UGI3: 0 | UGJ3: 0 | UGK3: 0 | UGL3: 0 | UGM3: 0 | UGN3: 0 | UGO3: 0 | UGP3: 0 | UGQ3: 0 | UGR3: 0 | UGS3: 0 | UGT3: 0 | UGU3: 0 | UGV3: 0 | UGW3: 0 | UGX3: 0 | UGY3: 0 | UGZ3: 0 | UHA3: 0 | UHB3: 0 | UHC3: 0 | UHD3: 0 | UHE3: 0 | UHF3: 0 | UHG3: 0 | UHH3: 0 | UHI3: 0 | UHJ3: 0 | UHK3: 0 | UHL3: 0 | UHM3: 0 | UHN3: 0 | UHO3: 0 | UHP3: 0 | UHQ3: 0 | UHR3: 0 | UHS3: 0 | UHT3: 0 | UHU3: 0 | UHV3: 0 | UHW3: 0 | UHX3: 0 | UHY3: 0 | UHZ3: 0 | UIA3: 0 | UIB3: 0 | UIC3: 0 | UID3: 0 | UIE3: 0 | UIF3: 0 | UIG3: 0 | UIH3: 0 | UII3: 0 | UIJ3: 0 | UIK3: 0 | UIL3: 0 | UIM3: 0 | UIN3: 0 | UIO3: 0 | UIP3: 0 | UIQ3: 0 | UIR3: 0 | UIS3: 0 | UIT3: 0 | UIU3: 0 | UIV3: 0 | UIW3: 0 | UIX3: 0 | UIY3: 0 | UIZ3: 0 | UJA3: 0 | UJB3: 0 | UJC3: 0 | UJD3: 0 | UJE3: 0 | UJF3: 0 | UJG3: 0 | UJH3: 0 | UJI3: 0 | UJJ3: 0 | UJK3: 0 | UJL3: 0 | UJM3: 0 | UJN3: 0 | UJO3: 0 | UJP3: 0 | UJQ3: 0 | UJR3: 0 | UJS3: 0 | UJT3: 0 | UJU3: 0 | UJV3: 0 | UJW3: 0 | UJX3: 0 | UJY3: 0 | UJZ3: 0 | UKA3: 0 | UKB3: 0 | UKC3: 0 | UKD3: 0 | UKE3: 0 | UKF3: 0 | UKG3: 0 | UKH3: 0 | UKI3: 0 | UKJ3: 0 | UKK3: 0 | UKL3: 0 | UKM3: 0 | UKN3: 0 | UKO3: 0 | UKP3: 0 | UKQ3: 0 | UKR3: 0 | UKS3: 0 | UKT3: 0 | UKU3: 0 | UKV3: 0 | UKW3: 0 | UKX3: 0 | UKY3: 0 | UKZ3: 0 | ULA3: 0 | ULB3: 0 | ULC3: 0 | ULD3: 0 | ULE3: 0 | ULF3: 0 | ULG3: 0 | ULH3: 0 | ULI3: 0 | ULJ3: 0 | ULK3: 0 | ULL3: 0 | ULM3: 0 | ULN3: 0 | ULO3: 0 | ULP3: 0 | ULQ3: 0 | ULR3: 0 | ULS3: 0 | ULT3: 0 | ULU3: 0 | ULV3: 0 | ULW3: 0 | ULX3: 0 | ULY3: 0 | ULZ3: 0 | UMA3: 0 | UMB3: 0 | UMC3: 0 | UMD3: 0 | UME3: 0 | UMF3: 0 | UMG3: 0 | UMH3: 0 | UMI3: 0 | UMJ3: 0 | UMK3: 0 | UML3: 0 | UMM3: 0 | UMN3: 0 | UMO3: 0 | UMP3: 0 | UMQ3: 0 | UMR3: 0 | UMS3: 0 | UMT3: 0 | UMU3: 0 | UMV3: 0 | UMW3: 0 | UMX3: 0 | UMY3: 0 | UMZ3: 0 | UNA3: 0 | UNB3: 0 | UNC3: 0 | UND3: 0 | UNE3: 0 | UNF3: 0 | UNG3: 0 | UNH3: 0 | UNI3: 0 | UNJ3: 0 | UNK3: 0 | UNL3: 0 | UNM3: 0 | UNN3: 0 | UNO3: 0 | UNP3: 0 | UNQ3: 0 | UNR3: 0 | UNS3: 0 | UNT3: 0 | UNU3: 0 | UNV3: 0 | UNW3: 0 | UNX3: 0 | UNY3: 0 | UNZ3: 0 | UOA3: 0 | UOB3: 0 | UOC3: 0 | UOD3: 0 | UOE3: 0 | UOF3: 0 | UOG3: 0 | UOH3: 0 | UOI3: 0 | UOJ3: 0 | UOK3: 0 | UOL3: 0 | UOM3: 0 | UON3: 0 | UOO3: 0 | UOP3: 0 | UOQ3: 0 | UOR3: 0 | UOS3: 0 | UOT3: 0 | UOU3: 0 | UOV3: 0 | UOW3: 0 | UOX3: 0 | UOY3: 0 | UOZ3: 0 | UPA3: 0 | UPB3: 0 | UPC3: 0 | UPD3: 0 | UPE3: 0 | UPF3: 0 | UPG3: 0 | UPH3: 0 | UPI3: 0 | UPJ3: 0 | UPK3: 0 | UPL3: 0 | UPM3: 0 | UPN3: 0 | UPO3: 0 | UPP3: 0 | UPQ3: 0 | UPR3: 0 | UPS3: 0 | UPT3: 0 | UPU3: 0 | UPV3: 0 | UPW3: 0 | UPX3: 0 | UPY3: 0 | UPZ3: 0 | UQA3: 0 | UQB3: 0 | UQC3: 0 | UQD3: 0 | UQE3: 0 | UQF3: 0 | UQG3: 0 | UQH3: 0 | UQI3: 0 | UQJ3: 0 | UQK3: 0 | UQL3: 0 | UQM3: 0 | UQN3: 0 | UQO3: 0 | UQP3: 0 | UQQ3: 0 | UQR3: 0 | UQS3: 0 | UQT3: 0 | UQU3: 0 | UQV3: 0 | UQW3: 0 | UQX3: 0 | UQY3: 0 | UQZ3: 0 | URA3: 0 | URB3: 0 | URC3: 0 | URD3: 0 | URE3: 0 | URF3: 0 | URG3: 0 | URH3: 0 | URI3: 0 | URJ3: 0 | URK3: 0 | URL3: 0 | URM3: 0 | URN3: 0 | URO3: 0 | URP3: 0 | URQ3: 0 | URR3: 0 | URS3: 0 | URT3: 0 | URU3: 0 | URV3: 0 | URW3: 0 | URX3: 0 | URY3: 0 | URZ3: 0 | USA3: 0 | USB3: 0 | USC3: 0 | USD3: 0 | USE3: 0 | USF3: 0 | USG3: 0 | USH3: 0 | USI3: 0 | USJ3: 0 | USK3: 0 | USL3: 0 | USM3: 0 | USN3: 0 | USO3: 0 | USP3: 0 | USQ3: 0 | USR3: 0 | USS3: 0 | UST3: 0 | USU3: 0 | USV3: 0 | USW3: 0 | USX3: 0 | USY3: 0 | USZ3: 0 | UTA3: 0 | UTB3: 0 | UTC3: 0 | UTD3: 0 | UTE3: 0 | UTF3: 0 | UTG3: 0 | UTH3: 0 | UTI3: 0 | UTJ3: 0 | UTK3: 0 | UTL3: 0 | UTM3: 0 | UTN3: 0 | UTO3: 0 | UTP3: 0 | UTQ3: 0 | UTR3: 0 | UTS3: 0 | UTT3: 0 | UTU3: 0 | UTV3: 0 | UTW3: 0 | UTX3: 0 | UTY3: 0 | UTZ3: 0 | UUA3: 0 | UUB3: 0 | UUC3: 0 | UUD3: 0 | UUE3: 0 | UUF3: 0 | UUG3: 0 | UUH3: 0 | UUI3: 0 | UUJ3: 0 | UUK3: 0 | UUL3: 0 | UUM3: 0 | UUN3: 0 | UUO3: 0 | UUP3: 0 | UUQ3: 0 | UUR3: 0 | UUS3: 0 | UUT3: 0 | UUU3: 0 | UUV3: 0 | UUW3: 0 | UUX3: 0 | UUY3: 0 | UUZ3: 0 | UVA3: 0 | UVB3: 0 | UVC3: 0 | UVD3: 0 | UVE3: 0 | UVF3: 0 | UVG3: 0 | UVH3: 0 | UVI3: 0 | UVJ3: 0 | UVK3: 0 | UVL3: 0 | UVM3: 0 | UVN3: 0 | UVO3: 0 | UVP3: 0 | UVQ3: 0 | UVR3: 0 | UVS3: 0 | UVT3: 0 | UVU3: 0 | UVV3: 0 | UVW3: 0 | UVX3: 0 | UVY3: 0 | UVZ3: 0 | UWA3: 0 | UWB3: 0 | UWC3: 0 | UWD3: 0 | UWE3: 0 | UWF3: 0 | UWG3: 0 | UWH3: 0 | UWI3: 0 | UWJ3: 0 | UWK3: 0 | UWL3: 0 | UWM3: 0 | UWN3: 0 | UWO3: 0 | UWP3: 0 | UWQ3: 0 | UWR3: 0 | UWS3: 0 | UWT3: 0 | UWU3: 0 | UWV3: 0 | UWW3: 0 | UWX3: 0 | UWY3: 0 | UWZ3: 0 | UXA3: 0 | UXB3: 0 | UXC3: 0 | UXD3: 0 | UXE3: 0 | UXF3: 0 | UXG3: 0 | UXH3: 0 | UXI3: 0 | UXJ3: 0 | UXK3: 0 | UXL3: 0 | UXM3: 0 | UXN3: 0 | UXO3: 0 | UXP3: 0 | UXQ3: 0 | UXR3: 0 | UXS3: 0 | UXT3: 0 | UXU3: 0 | UXV3: 0 | UXW3: 0 | UXX3: 0 | UXY3: 0 | UXZ3: 0 | UYA3: 0 | UYB3: 0 | UYC3: 0 | UYD3: 0 | UYE3: 0 | UYF3: 0 | UYG3: 0 | UYH3: 0 | UYI3: 0 | UYJ3: 0 | UYK3: 0 | UYL3: 0 | UYM3: 0 | UYN3: 0 | UYO3: 0 | UYP3: 0 | UYQ3: 0 | UYR3: 0 | UYS3: 0 | UYT3: 0 | UYU3: 0 | UYV3: 0 | UYW3: 0 | UYX3: 0 | UYY3: 0 | UYZ3: 0 | UZA3: 0 | UZB3: 0 | UZC3: 0 | UZD3: 0 | UZE3: 0 | UZF3: 0 | UZG3: 0 | UZH3: 0 | UZI3: 0 | UZJ3: 0 | UZK3: 0 | UZL3: 0 | UZM3: 0 | UZN3: 0 | UZO3: 0 | UZP3: 0 | UZQ3: 0 | UZR3: 0 | UZS3: 0 | UZT3: 0 | UZU3: 0 | UZV3: 0 | UZW3: 0 | UZX3: 0 | UZY3: 0 | UZZ3: 0 | VAA3: 0 | VAB3: 0 | VAC3: 0 | VAD3: 0 | VAE3: 0 | VAF3: 0 | VAG3: 0 | VAH3: 0 | VAI3: 0 | VAJ3: 0 | VAK3: 0 | VAL3: 0 | VAM3: 0 | VAN3: 0 | VAO3: 0 | VAP3: 0 | VAQ3: 0 | VAR3: 0 | VAS3: 0 | VAT3: 0 | VAU3: 0 | VAV3: 0 | VAW3: 0 | VAX3: 0 | VAY3: 0 | VAZ3: 0 | VBA3: 0 | VBB3: 0 | VBC3: 0 | VBD3: 0 | VBE3: 0 | VBF3: 0 | VBG3: 0 | VBH3: 0 | VBI3: 0 | VBJ3: 0 | VBK3: 0 | VBL3: 0 | VBM3: 0 | VBN3: 0 | VBO3: 0 | VBP3: 0 | VBQ3: 0 | VBR3: 0 | VBS3: 0 | VBT3: 0 | VBU3: 0 | VBV3: 0 | VBW3: 0 | VBX3: 0 | VBY3: 0 | VBZ3: 0 | VCA3: 0 | VCB3: 0 | VCC3: 0 | VCD3: 0 | VCE3: 0 | VCF3: 0 | VCG3: 0 | VCH3: 0 | VCI3: 0 | VCJ3: 0 | VCK3: 0 | VCL3: 0 | VCM3: 0 | VCN3: 0 | VCO3: 0 | VCP3: 0 | VCQ3: 0 | VCR3: 0 | VCS3: 0 | VCT3: 0 | VCU3: 0 | VCV3: 0 | VCW3: 0 | VCX3: 0 | VCY3: 0 | VCZ3: 0 | VDA3: 0 | VDB3: 0 | VDC3: 0 | VDD3: 0 | VDE3: 0 | VDF3: 0 | VDG3: 0 | VDH3: 0 | VDI3: 0 | VDJ3: 0 | VDK3: 0 | VDL3: 0 | VDM3: 0 | VDN3: 0 | VDO3: 0 | VDP3: 0 | VDQ3: 0 | VDR3: 0 | VDS3: 0 | VDT3: 0 | VDU3: 0 | VDV3: 0 | VDW3: 0 | VDX3: 0 | VDY3: 0 | VDZ3: 0 | VEA3: 0 | VEB3: 0 | VEC3: 0 | VED3: 0 | VEE3: 0 | VEF3: 0 | VEG3: 0 | VEH3: 0 | VEI3: 0 | VEJ3: 0 | VEK3: 0 | VEL3: 0 | VEM3: 0 | VEN3: 0 | VEO3: 0 | VEP3: 0 | VEQ3: 0 | VER3: 0 | VES3: 0 | VET3: 0 | VEU3: 0 | VEV3: 0 | VEW3: 0 | VEX3: 0 | VEY3: 0 | VEZ3: 0 | VFA3: 0 | VFB3: 0 | VFC3: 0 | VFD3: 0 | VFE3: 0 | VFF3: 0 | VFG3: 0 | VFH3: 0 | VFI3: 0 | VFJ3: 0 | VFK3: 0 | VFL3: 0 | VFM3: 0 | VFN3: 0 | VFO3: 0 | VFP3: 0 | VFQ3: 0 | VFR3: 0 | VFS3: 0 | VFT3: 0 | VFU3: 0 | VFV3: 0 | VFW3: 0 | VFX3: 0 | VFY3: 0 | VFZ3: 0 | VGA3: 0 | VGB3: 0 | VGC3: 0 | VGD3: 0 | VGE3: 0 | VGF3: 0 | VGG3: 0 | VGH3: 0 | VGI3: 0 | VGJ3: 0 | VGK3: 0 | VGL3: 0 | VGM3: 0 | VGN3: 0 | VGO3: 0 | VGP3: 0 | VGQ3: 0 | VGR3: 0 | VGS3: 0 | VGT3: 0 | VGU3: 0 | VGV3: 0 | VGW3: 0 | VGX3: 0 | VGY3: 0 | VGZ3: 0 | VHA3: 0 | VHB3: 0 | VHC3: 0 | VHD3: 0 | VHE3: 0 | VHF3: 0 | VHG3: 0 | VHH3: 0 | VHI3: 0 | VHJ3: 0 | VHK3: 0 | VHL3: 0 | VHM3: 0 | VHN3: 0 | VHO3: 0 | VHP3: 0 | VHQ3: 0 | VHR3: 0 | VHS3: 0 | VHT3: 0 | VHU3: 0 | VHV3: 0 | VHW3: 0 | VHX3: 0 | VHY3: 0 | VHZ3: 0 | VIA3: 0 | VIB3: 0 | VIC3: 0 | VID3: 0 | VIE3: 0 | VIF3: 0 | VIG3: 0 | VIH3: 0 | VII3: 0 | VIJ3: 0 | VIK3: 0 | VIL3: 0 | VIM3: 0 | VIN3: 0 | VIO3: 0 | VIP3: 0 | VIQ3: 0 | VIR3: 0 | VIS3: 0 | VIT3: 0 | VIU3: 0 | VIV3: 0 | VIW3: 0 | VIX3: 0 | VIY3: 0 | VIZ3: 0 | VJA3: 0 | VJB3: 0 | VJC3: 0 | VJD3: 0 | VJE3: 0 | VJF3: 0 | VJG3: 0 | VJH3: 0 | VJI3: 0 | VJJ3: 0 | VJK3: 0 | VJL3: 0 | VJM3: 0 | VJN3: 0 | VJO3: 0 | VJP3: 0 | VJQ3: 0 | VJR3: 0 | VJS3: 0 | VJT3: 0 | VJU3: 0 | VJV3: 0 | VJW3: 0 | VJX3: 0 | VJY3: 0 | VJZ3: 0 | VKA3: 0 | VKB3: 0 | VKC3: 0 | VKD3: 0 | VKE3: 0 | VKF3: 0 | VKG3: 0 | VKH3: 0 | VKI3: 0 | VKJ3: 0 | VKK3: 0 | VKL3: 0 | VKM3: 0 | VKN3: 0 | VKO3: 0 | VKP3: 0 | VKQ3: 0 | VKR3: 0 | VKS3: 0 | VKT3: 0 | VKU3: 0 | VKV3: 0 | VKW3: 0 | VKX3: 0 | VKY3: 0 | VKZ3: 0 | VLA3: 0 | VLB3: 0 | VLC3: 0 | VLD3: 0 | VLE3: 0 | VLF3: 0 | VLG3: 0 | VLH3: 0 | VLI3: 0 | VLJ3: 0 | VLK3: 0 | VLL3: 0 | VLM3: 0 | VLN3: 0 | VLO3: 0 | VLP3: 0 | VLQ3: 0 | VLR3: 0 | VLS3: 0 | VLT3: 0 | VLU3: 0 | VLV3: 0 | VLW3: 0 | VLX3: 0 | VLY3: 0 | VLZ3: 0 | VMA3: 0 | VMB3: 0 | VMC3: 0 | VMD3: 0 | VME3: 0 | VMF3: 0 | VMG3: 0 | VMH3: 0 | VMI3: 0 | VMJ3: 0 | VMK3: 0 | VML3: 0 | VMM3: 0 | VMN3: 0 | VMO3: 0 | VMP3: 0 | VMQ3: 0 | VMR3: 0 | VMS3: 0 | VMT3: 0 | VMU3: 0 | VMV3: 0 | VMW3: 0 | VMX3: 0 | VMY3: 0 | VMZ3: 0 | VNA3: 0 | VNB3: 0 | VNC3: 0 | VND3: 0 | VNE3: 0 | VNF3: 0 | VNG3: 0 | VNH3: 0 | VNI3: 0 | VNJ3: 0 | VNK3: 0 | VNL3: 0 | VNM3: 0 | VNN3: 0 | VNO3: 0 | VNP3: 0 | VNQ3: 0 | VNR3: 0 | VNS3: 0 | VNT3: 0 | VNU3: 0 | VNV3: 0 | VNW3: 0 | VNX3: 0 | VNY3: 0 | VNZ3: 0 | VOA3: 0 | VOB3: 0 | VOC3: 0 | VOD3: 0 | VOE3: 0 | VOF3: 0 | VOG3: 0 | VOH3: 0 | VOI3: 0 | VOJ3: 0 | VOK3: 0 | VOL3: 0 | VOM3: 0 | VON3: 0 | VOO3: 0 | VOP3: 0 | VOQ3: 0 | VOR3: 0 | VOS3: 0 | VOT3: 0 | VOU3: 0 | VOV3: 0 | VOW3: 0 | VOX3: 0 | VOY3: 0 | VOZ3: 0 | VPA3: 0 | VPB3: 0 | VPC3: 0 | VPD3: 0 | VPE3: 0 | VPF3: 0 | VPG3: 0 | VPH3: 0 | VPI3: 0 | VPJ3: 0 | VPK3: 0 | VPL3: 0 | VPM3: 0 | VPN3: 0 | VPO3: 0 | VPP3: 0 | VPQ3: 0 | VPR3: 0 | VPS3: 0 | VPT3: 0 | VPU3: 0 | VPV3: 0 | VPW3: 0 | VPX3: 0 | VPY3: 0 | VPZ3: 0 | VQA3: 0 | VQB3: 0 | VQC3: 0 | VQD3: 0 | VQE3: 0 | VQF3: 0 | VQG3: 0 | VQH3: 0 | VQI3: 0 | VQJ3: 0 | VQK3: 0 | VQL3: 0 | VQM3: 0 | VQN3: 0 | VQO3: 0 | VQP3: 0 | VQQ3: 0 | VQR3: 0 | VQS3: 0 | VQT3: 0 | VQU3: 0 | VQV3: 0 | VQW3: 0 | VQX3: 0 | VQY3: 0 | VQZ3: 0 | VRA3: 0 | VRB3: 0 | VRC3: 0 | VRD3: 0 | VRE3: 0 | VRF3: 0 | VRG3: 0 | VRH3: 0 | VRI3: 0 | VRJ3: 0 | VRK3: 0 | VRL3: 0 | VRM3: 0 | VRN3: 0 | VRO3: 0 | VRP3: 0 | VRQ3: 0 | VRR3: 0 | VRS3: 0 | VRT3: 0 | VRU3: 0 | VRV3: 0 | VRW3: 0 | VRX3: 0 | VRY3: 0 | VRZ3: 0 | VSA3: 0 | VSB3: 0 | VSC3: 0 | VSD3: 0 | VSE3: 0 | VSF3: 0 | VSG3: 0 | VSH3: 0 | VSI3: 0 | VSJ3: 0 | VSK3: 0 | VSL3: 0 | VSM3: 0 | VSN3: 0 | VSO3: 0 | VSP3: 0 | VSQ3: 0 | VSR3: 0 | VSS3: 0 | VST3: 0 | VSU3: 0 | VSV3: 0 | VSW3: 0 | VSX3: 0 | VSY3: 0 | VSZ3: 0 | VTA3: 0 | VTB3: 0 | VTC3: 0 | VTD3: 0 | VTE3: 0 | VTF3: 0 | VTG3: 0 | VTH3: 0 | VTI3: 0 | VTJ3: 0 | VTK3: 0 | VTL3: 0 | VTM3: 0 | VTN3: 0 | VTO3: 0 | VTP3: 0 | VTQ3: 0 | VTR3: 0 | VTS3: 0 | VTT3: 0 | VTU3: 0 | VTV3: 0 | VTW3: 0 | VTX3: 0 | VTY3: 0 | VTZ3: 0 | VUA3: 0 | VUB3: 0 | VUC3: 0 | VUD3: 0 | VUE3: 0 | VUF3: 0 | VUG3: 0 | VUH3: 0 | VUI3: 0 | VUJ3: 0 | VUK3: 0 | VUL3: 0 | VUM3: 0 | VUN3: 0 | VUO3: 0 | VUP3: 0 | VUQ3: 0 | VUR3: 0 | VUS3: 0 | VUT3: 0 | VUU3: 0 | VUV3: 0 | VUW3: 0 | VUX3: 0 | VUY3: 0 | VUZ3: 0 | VVA3: 0 | VVB3: 0 | VVC3: 0 | VVD3: 0 | VVE3: 0 | VVF3: 0 | VVG3: 0 | VVH3: 0 | VVI3: 0 | VVJ3: 0 | VVK3: 0 | VVL3: 0 | VVM3: 0 | VVN3: 0 | VVO3: 0 | VVP3: 0 | VVQ3: 0 | VVR3: 0 | VVS3: 0 | VVT3: 0 | VVU3: 0 | VVV3: 0 | VVW3: 0 | VVX3: 0 | VVY3: 0 | VVZ3: 0 | VWA3: 0 | VWB3: 0 | VWC3: 0 | VWD3: 0 | VWE3: 0 | VWF3: 0 | VWG3: 0 | VWH3: 0 | VWI3: 0 | VWJ3: 0 | VWK3: 0 | VWL3: 0 | VWM3: 0 | VWN3: 0 | VWO3: 0 | VWP3: 0 | VWQ3: 0 | VWR3: 0 | VWS3: 0 | VWT3: 0 | VWU3: 0 | VWV3: 0 | VWW3: 0 | VWX3: 0 | VWY3: 0 | VWZ3: 0 | VXA3: 0 | VXB3: 0 | VXC3: 0 | VXD3: 0 | VXE3: 0 | VXF3: 0 | VXG3: 0 | VXH3: 0 | VXI3: 0 | VXJ3: 0 | VXK3: 0 | VXL3: 0 | VXM3: 0 | VXN3: 0 | VXO3: 0 | VXP3: 0 | VXQ3: 0 | VXR3: 0 | VXS3: 0 | VXT3: 0 | VXU3: 0 | VXV3: 0 | VXW3: 0 | VXX3: 0 | VXY3: 0 | VXZ3: 0 | VYA3: 0 | VYB3: 0 | VYC3: 0 | VYD3: 0 | VYE3: 0 | VYF3: 0 | VYG3: 0 | VYH3: 0 | VYI3: 0 | VYJ3: 0 | VYK3: 0 | VYL3: 0 | VYM3: 0 | VYN3: 0 | VYO3: 0 | VYP3: 0 | VYQ3: 0 | VYR3: 0 | VYS3: 0 | VYT3: 0 | VYU3: 0 | VYV3: 0 | VYW3: 0 | VYX3: 0 | VYY3: 0 | VYZ3: 0 | VZA3: 0 | VZB3: 0 | VZC3: 0 | VZD3: 0 | VZE3: 0 | VZF3: 0 | VZG3: 0 | VZH3: 0 | VZI3: 0 | VZJ3: 0 | VZK3: 0 | VZL3: 0 | VZM3: 0 | VZN3: 0 | VZO3: 0 | VZP3: 0 | VZQ3: 0 | VZR3: 0 | VZS3: 0 | VZT3: 0 | VZU3: 0 | VZV3: 0 | VZW3: 0 | VZX3: 0 | VZY3: 0 | VZZ3: 0 | WAA3: 0 | WAB3: 0 | WAC3: 0 | WAD3: 0 | WAE3: 0 | WAF3: 0 | WAG3: 0 | WAH3: 0 | WAI3: 0 | WAJ3: 0 | WAK3: 0 | WAL3: 0 | WAM3: 0 | WAN3: 0 | WAO3: 0 | WAP3: 0 | WAQ3: 0 | WAR3: 0 | WAS3: 0 | WAT3: 0 | WAU3: 0 | WAV3: 0 | WAW3: 0 | WAX3: 0 | WAY3: 0 | WAZ3: 0 | WBA3: 0 | WBB3: 0 | WBC3: 0 | WBD3: 0 | WBE3: 0 | WBF3: 0 | WBG3: 0 | WBH3: 0 | WBI3: 0 | WBJ3: 0 | WBK3: 0 | WBL3: 0 | WBM3: 0 | WBN3: 0 | WBO3: 0 | WBP3: 0 | WBQ3: 0 | WBR3: 0 | WBS3: 0 | WBT3: 0 | WBU3: 0 | WBV3: 0 | WBW3: 0 | WBX3: 0 | WBY3: 0 | WBZ3: 0 | WCA3: 0 | WCB3: 0 | WCC3: 0 | WCD3: 0 | WCE3: 0 | WCF3: 0 | WCG3: 0 | WCH3: 0 | WCI3: 0 | WCJ3: 0 | WCK3: 0 | WCL3: 0 | WCM3: 0 | WCN3: 0 | WCO3: 0 | WCP3: 0 | WCQ3: 0 | WCR3: 0 | WCS3: 0 | WCT3: 0 | WCU3: 0 | WCV3: 0 | WCW3: 0 | WCX3: 0 | WCY3: 0 | WCZ3: 0 | WDA3: 0 | WDB3: 0 | WDC3: 0 | WDD3: 0 | WDE3: 0 | WDF3: 0 | WDG3: 0 | WDH3: 0 | WDI3: 0 | WDJ3: 0 | WDK3: 0 | WDL3: 0 | WDM3: 0 | WDN3: 0 | WDO3: 0 | WDP3: 0 | WDQ3: 0 | WDR3: 0 | WDS3: 0 | WDT3: 0 | WDU3: 0 | WDV3: 0 | WDW3: 0 | WDX3: 0 | WDY3: 0 | WDZ3: 0 | WEA3: 0 | WEB3: 0 | WEC3: 0 | WED3: 0 | WEE3: 0 | WEF3: 0 | WEG3: 0 | WEH3: 0 | WEI3: 0 | WEJ3: 0 | WEK3: 0 | WEL3: 0 | WEM3: 0 | WEN3: 0 | WEO3: 0 | WEP3: 0 | WEQ3: 0 | WER3: 0 | WES3: 0 | WET3: 0 | WEU3: 0 | WEV3: 0 | WEW3: 0 | WEX3: 0 | WEY3: 0 | WEZ3: 0 | WFA3: 0 | WFB3: 0 | WFC3: 0 | WFD3: 0 | WFE3: 0 | WFF3: 0 | WFG3: 0 | WFH3: 0 | WFI3: 0 | WFJ3: 0 | WFK3: 0 | WFL3: 0 | WFM3: 0 | WFN3: 0 | WFO3: 0 | WFP3: 0 | WFQ3: 0 | WFR3: 0 | WFS3: 0 | WFT3: 0 | WFU3: 0 | WFV3: 0 | WFW3: 0 | WFX3: 0 | WFY3: 0 | WFZ3: 0 | WGA3: 0 | WGB3: 0 | WGC3: 0 | WGD3: 0 | WGE3: 0 | WGF3: 0 | WGG3: 0 | WGH3: 0 | WGI3: 0 | WGJ3: 0 | WGK3: 0 | WGL3: 0 | WGM3: 0 | WGN3: 0 | WGO3: 0 | WGP3: 0 | WGQ3: 0 | WGR3: 0 | WGS3: 0 | WGT3: 0 | WGU3: 0 | WGV3: 0 | WGW3: 0 | WGX3: 0 | WGY3: 0 | WGZ3: 0 | WHA3: 0 | WHB3: 0 | WHC3: 0 | WHD3: 0 | WHE3: 0 | WHF3: 0 | WHG3: 0 | WHH3: 0 | WHI3: 0 | WHJ3: 0 | WHK3: 0 | WHL3: 0 | WHM3: 0 | WHN3: 0 | WHO3: 0 | WHP3: 0 | WHQ3: 0 | WHR3: 0 | WHS3: 0 | WHT3: 0 | WHU3: 0 | WHV3: 0 | WHW3: 0 | WHX3: 0 | WHY3: 0 | WHZ3: 0 | WIA3: 0 | WIB3: 0 | WIC3: 0 | WID3: 0 | WIE3: 0 | WIF3: 0 | WIG3: 0 | WIH3: 0 | WII3: 0 | WIJ3: 0 | WIK3: 0 | WIL3: 0 | WIM3: 0 | WIN3: 0 | WIO3: 0 | WIP3: 0 | WIQ3: 0 | WIR3: 0 | WIS3: 0 | WIT3: 0 | WIU3: 0 | WIV3: 0 | WIW3: 0 | WIX3: 0 | WIY3: 0 | WIZ3: 0 | WJA3: 0 | WJB3: 0 | WJC3: 0 | WJD3: 0 | WJE3: 0 | WJF3: 0 | WJG3: 0 | WJH3: 0 | WJI3: 0 | WJJ3: 0 | WJK3: 0 | WJL3: 0 | WJM3: 0 | WJN3: 0 | WJO3: 0 | WJP3: 0 | WJQ3: 0 | WJR3: 0 | WJS3: 0 | WJT3: 0 | WJU3: 0 | WJV3: 0 | WJW3: 0 | WJX3: 0 | WJY3: 0 | WJZ3: 0 | WKA3: 0 | WKB3: 0 | WKC3: 0 | WKD3: 0 | WKE3: 0 | WKF3: 0 | WKG3: 0 | WKH3: 0 | WKI3: 0 | WKJ3: 0 | WKK3: 0 | WKL3: 0 | WKM3: 0 | WKN3: 0 | WKO3: 0 | WKP3: 0 | WKQ3: 0 | WKR3: 0 | WKS3: 0 | WKT3: 0 | WKU3: 0 | WKV3: 0 | WKW3: 0 | WKX3: 0 | WKY3: 0 | WKZ3: 0 | WLA3: 0 | WLB3: 0 | WLC3: 0 | WLD3: 0 | WLE3: 0 | WLF3: 0 | WLG3: 0 | WLH3: 0 | WLI3: 0 | WLJ3: 0 | WLK3: 0 | WLL3: 0 | WLM3: 0 | WLN3: 0 | WLO3: 0 | WLP3: 0 | WLQ3: 0 | WLR3: 0 | WLS3: 0 | WLT3: 0 | WLU3: 0 | WLV3: 0 | WLW3: 0 | WLX3: 0 | WLY3: 0 | WLZ3: 0 | WMA3: 0 | WMB3: 0 | WMC3: 0 | WMD3: 0 | WME3: 0 | WMF3: 0 | WMG3: 0 | WMH3: 0 | WMI3: 0 | WMJ3: 0 | WMK3: 0 | WML3: 0 | WMM3: 0 | WMN3: 0 | WMO3: 0 | WMP3: 0 | WMQ3: 0 | WMR3: 0 | WMS3: 0 | WMT3: 0 | WMU3: 0 | WMV3: 0 | WMW3: 0 | WMX3: 0 | WMY3: 0 | WMZ3: 0 | WNA3: 0 | WNB3: 0 | WNC3: 0 | WND3: 0 | WNE3: 0 | WNF3: 0 | WNG3: 0 | WNH3: 0 | WNI3: 0 | WNJ3: 0 | WNK3: 0 | WNL3: 0 | WNM3: 0 | WNN3: 0 | WNO3: 0 | WNP3: 0 | WNQ3: 0 | WNR3: 0 | WNS3: 0 | WNT3: 0 | WNU3: 0 | WNV3: 0 | WNW3: 0 | WNX3: 0 | WNY3: 0 | WNZ3: 0 | WOA3: 0 | WOB3: 0 | WOC3: 0 | WOD3: 0 | WOE3: 0 | WOF3: 0 | WOG3: 0 | WOH3: 0 | WOI3: 0 | WOJ3: 0 | WOK3: 0 | WOL3: 0 | WOM3: 0 | WON3: 0 | WOO3: 0 | WOP3: 0 | WOQ3: 0 | WOR3: 0 | WOS3: 0 | WOT3: 0 | WOU3: 0 | WOV3: 0 | WOW3: 0 | WOX3: 0 | WOY3: 0 | WOZ3: 0 | WPA3: 0 | WPB3: 0 | WPC3: 0 | WPD3: 0 | WPE3: 0 | WPF3: 0 | WPG3: 0 | WPH3: 0 | WPI3: 0 | WPJ3: 0 | WPK3: 0 | WPL3: 0 | WPM3: 0 | WPN3: 0 | WPO3: 0 | WPP3: 0 | WPQ3: 0 | WPR3: 0 | WPS3: 0 | WPT3: 0 | WPU3: 0 | WPV3: 0 | WPW3: 0 | WPX3: 0 | WPY3: 0 | WPZ3: 0 | WQA3: 0 | WQB3: 0 | WQC3: 0 | WQD3: 0 | WQE3: 0 | WQF3: 0 | WQG3: 0 | WQH3: 0 | WQI3: 0 | WQJ3: 0 | WQK3: 0 | WQL3: 0 | WQM3: 0 | WQN3: 0 | WQO3: 0 | WQP3: 0 | WQQ3: 0 | WQR3: 0 | WQS3: 0 | WQT3: 0 | WQU3: 0 | WQV3: 0 | WQW3: 0 | WQX3: 0 | WQY3: 0 | WQZ3: 0 | WRA3: 0 | WRB3: 0 | WRC3: 0 | WRD3: 0 | WRE3: 0 | WRF3: 0 | WRG3: 0 | WRH3: 0 | WRI3: 0 | WRJ3: 0 | WRK3: 0 | WRL3: 0 | WRM3: 0 | WRN3: 0 | WRO3: 0 | WRP3: 0 | WRQ3: 0 | WRR3: 0 | WRS3: 0 | WRT3: 0 | WRU3: 0 | WRV3: 0 | WRW3: 0 | WRX3: 0 | WRY3: 0 | WRZ3: 0 | WSA3: 0 | WSB3: 0 | WSC3: 0 | WSD3: 0 | WSE3: 0 | WSF3: 0 | WSG3: 0 | WSH3: 0 | WSI3: 0 | WSJ3: 0 | WSK3: 0 | WSL3: 0 | WSM3: 0 | WSN3: 0 | WSO3: 0 | WSP3: 0 | WSQ3: 0 | WSR3: 0 | WSS3: 0 | WST3: 0 | WSU3: 0 | WSV3: 0 | WSW3: 0 | WSX3: 0 | WSY3: 0 | WSZ3: 0 | WTA3: 0 | WTB3: 0 | WTC3: 0 | WTD3: 0 | WTE3: 0 | WTF3: 0 | WTG3: 0 | WTH3: 0 | WTI3: 0 | WTJ3: 0 | WTK3: 0 | WTL3: 0 | WTM3: 0 | WTN3: 0 | WTO3: 0 | WTP3: 0 | WTQ3: 0 | WTR3: 0 | WTS3: 0 | WTT3: 0 | WTU3: 0 | WTV3: 0 | WTW3: 0 | WTX3: 0 | WTY3: 0 | WTZ3: 0 | WUA3: 0 | WUB3: 0 | WUC3: 0 | WUD3: 0 | WUE3: 0 | WUF3: 0 | WUG3: 0 | WUH3: 0 | WUI3: 0 | WUJ3: 0 | WUK3: 0 | WUL3: 0 | WUM3: 0 | WUN3: 0 | WUO3: 0 | WUP3: 0 | WUQ3: 0 | WUR3: 0 | WUS3: 0 | WUT3: 0 | WUU3: 0 | WUV3: 0 | WUW3: 0 | WUX3: 0 | WUY3: 0 | WUZ3: 0 | WVA3: 0 | WVB3: 0 | WVC3: 0 | WVD3: 0 | WVE3: 0 | WVF3: 0 | WVG3: 0 | WVH3: 0 | WVI3: 0 | WVJ3: 0 | WVK3: 0 | WVL3: 0 | WVM3: 0 | WVN3: 0 | WVO3: 0 | WVP3: 0 | WVQ3: 0 | WVR3: 0 | WVS3: 0 | WVT3: 0 | WVU3: 0 | WVV3: 0 | WVW3: 0 | WVX3: 0 | WVY3: 0 | WVZ3: 0 | WWA3: 0 | WWB3: 0 | WWC3: 0 | WWD3: 0 | WWE3: 0 | WWF3: 0 | WWG3: 0 | WWH3: 0 | WWI3: 0 | WWJ3: 0 | WWK3: 0 | WWL3: 0 | WWM3: 0 | WWN3: 0 | WWO3: 0 | WWP3: 0 | WWQ3: 0 | WWR3: 0 | WWS3: 0 | WWT3: 0 | WWU3: 0 | WWV3: 0 | WWW3: 0 | WWX3: 0 | WWY3: 0 | WWZ3: 0 | WXA3: 0 | WXB3: 0 | WXC3: 0 | WXD3: 0 | WXE3: 0 | WXF3: 0 | WXG3: 0 | WXH3: 0 | WXI3: 0 | WXJ3: 0 | WXK3: 0 | WXL3: 0 | WXM3: 0 | WXN3: 0 | WXO3: 0 | WXP3: 0 | WXQ3: 0 | WXR3: 0 | WXS3: 0 | WXT3: 0 | WXU3: 0 | WXV3: 0 | WXW3: 0 | WXX3: 0 | WXY3: 0 | WXZ3: 0 | WYA3: 0 | WYB3: 0 | WYC3: 0 | WYD3: 0 | WYE3: 0 | WYF3: 0 | WYG3: 0 | WYH3: 0 | WYI3: 0 | WYJ3: 0 | WYK3: 0 | WYL3: 0 | WYM3: 0 | WYN3: 0 | WYO3: 0 | WYP3: 0 | WYQ3: 0 | WYR3: 0 | WYS3: 0 | WYT3: 0 | WYU3: 0 | WYV3: 0 | WYW3: 0 | WYX3: 0 | WYY3: 0 | WYZ3: 0 | WZA3: 0 | WZB3: 0 | WZC3: 0 | WZD3: 0 | WZE3: 0 | WZF3: 0 | WZG3: 0 | WZH3: 0 | WZI3: 0 | WZJ3: 0 | WZK3: 0 | WZL3: 0 | WZM3: 0 | WZN3: 0 | WZO3: 0 | WZP3: 0 | WZQ3: 0 | WZR3: 0 | WZS3: 0 | WZT3: 0 | WZU3: 0 | WZV3: 0 | WZW3: 0 | WZX3: 0 | WZY3: 0 | WZZ3: 0 | XAA3: 0 | XAB3: 0 | XAC3: 0 | XAD3: 0 | XAE3: 0 | XAF3: 0 | XAG3: 0 | XAH3: 0 | XAI3: 0 | XAJ3: 0 | XAK3: 0 | XAL3: 0 | XAM3: 0 | XAN3: 0 | XAO3: 0 | XAP3: 0 | XAQ3: 0 | XAR3: 0 | XAS3: 0 | XAT3: 0 | XAU3: 0 | XAV3: 0 | XAW3: 0 | XAX3: 0 | XAY3: 0 | XAZ3: 0 | XBA3: 0 | XBB3: 0 | XBC3: 0 | XBD3: 0 | XBE3: 0 | XBF3: 0 | XBG3: 0 | XBH3: 0 | XBI3: 0 | XBJ3: 0 | XBK3: 0 | XBL3: 0 | XBM3: 0 | XBN3: 0 | XBO3: 0 | XBP3: 0 | XBQ3: 0 | XBR3: 0 | XBS3: 0 | XBT3: 0 | XBU3: 0 | XBV3: 0 | XBW3: 0 | XBX3: 0 | XBY3: 0 | XBZ3: 0 | XCA3: 0 | XCB3: 0 | XCC3: 0 | XCD3: 0 | XCE3: 0 | XCF3: 0 | XCG3: 0 | XCH3: 0 | XCI3: 0 | XCJ3: 0 | XCK3: 0 | XCL3: 0 | XCM3: 0 | XCN3: 0 | XCO3: 0 | XCP3: 0 | XCQ3: 0 | XCR3: 0 | XCS3: 0 | XCT3: 0 | XCU3: 0 | XCV3: 0 | XCW3: 0 | XCX3: 0 | XCY3: 0 | XCZ3: 0 | XDA3: 0 | XDB3: 0 | XDC3: 0 | XDD3: 0 | XDE3: 0 | XDF3: 0 | XDG3: 0 | XDH3: 0 | XDI3: 0 | XDJ3: 0 | XDK3: 0 | XDL3: 0 | XDM3: 0 | XDN3: 0 | XDO3: 0 | XDP3: 0 | XDQ3: 0 | XDR3: 0 | XDS3: 0 | XDT3: 0 | XDU3: 0 | XDV3: 0 | XDW3: 0 | XDX3: 0 | XDY3: 0 | XDZ3: 0 | XEA3: 0 | XEB3: 0 | XEC3: 0 | XED3: 0 | XEE3: 0 | XEF3: 0 | XEG3: 0 | XEH3: 0 | XEI3: 0 | XEJ3: 0 | XEK3: 0 | XEL3: 0 | XEM3: 0 | XEN3: 0 | XEO3: 0 | XEP3: 0 | XEQ3: 0 | XER3: 0 | XES3: 0 | XET3: 0 | XEU3: 0 | XEV3: 0 | XEW3: 0 | XEX3: 0 | XEY3: 0 | XEZ3: 0 | XFA3: 0 | XFB3: 0 | XFC3: 0 | XFD3: 0
